Workbook
Name _?: #REF!
Name _?춑_TOTAL: #REF!
Name _?춮t2: #REF!
Name _?춮ta: #REF!
Name _?춮tb: #REF!
Name __: #REF!
Name __?: #REF!
Name __?춑_TOTAL: #REF!
Name __?춮t2: #REF!
Name __?춮ta: #REF!
Name __?춮tb: #REF!
Name ___: #REF!
Name ___?: #REF!
Name ___?춑_TOTAL: #REF!
Name ____: #REF!
Name ____?: #REF!
Name ____?춑_TOTAL: #REF!
Name ____?춮t2: #REF!
Name ____?춮ta: #REF!
Name ____?춮tb: #REF!
Name _____: #REF!
Name _____?: #REF!
Name _____?춑_TOTAL: #REF!
Name ______: #REF!
Name ______?: #REF!
Name ______?춑_TOTAL: #REF!
Name _______: #REF!
Name _______?: #REF!
Name _______?춑_TOTAL: #REF!
Name ________: #REF!
Name ________?: #REF!
Name ________?춑_TOTAL: #REF!
Name _________: #REF!
Name _________?: #REF!
Name _________?춑_TOTAL: #REF!
Name __________: #REF!
Name __________?: #REF!
Name __________?춑_TOTAL: #REF!
Name ___________: #REF!
Name ___________?: #REF!
Name ___________?춑_TOTAL: #REF!
Name ____________?: #REF!
Name ____________?춑_TOTAL: #REF!
Name _____________?: #REF!
Name ____________________C332897: #REF!
Name ____________________E65954: #REF!
Name ___________________C332897: #REF!
Name ___________________E65954: #REF!
Name __________________C332897: #REF!
Name __________________E65954: #REF!
Name _________________C332897: #REF!
Name _________________E65954: #REF!
Name ________________C332897: #REF!
Name ________________E65954: #REF!
Name _______________C332897: #REF!
Name _______________E65954: #REF!
Name ______________C332897: #REF!
Name ______________E65954: #REF!
Name _____________Ａ４: #REF!
Name _____________C1244ㅁ1430: #REF!

Sheet 11월
E5: 45962
E7: Date | F7: =EDATE($E$5,-12) -> 45597 | H7: =F7 -> 45597 | J7: =H7 -> 45597 | L7: =J7 -> 45597 | N7: =L7 -> 45597 | P7: =L7 -> 45597 | T7: =EDATE($E$5,0) -> 45962 | V7: =T7 -> 45962 | X7: =V7 -> 45962 | Z7: =X7 -> 45962 | AB7: =Z7 -> 45962 | AD7: =Z7 -> 45962 | AH7: =EDATE($E$5,0) -> 45962 | AJ7: =AH7 -> 45962 | AL7: =AJ7 -> 45962 | AN7: =AL7 -> 45962 | AP7: =AN7 -> 45962 | AR7: =AN7 -> 45962 | AV7: =EDATE($E$5,0) -> 45962 | AX7: =AV7 -> 45962 | AZ7: =AX7 -> 45962 | BD7: =BB7 -> 0 | BF7: =BB7 -> 0
E8: Category | F8: Wholesale | H8: Ecommerce (US) | J8: Ecommerce (EU) | L8: License | N8: Other Income | T8: Wholesale | V8: Ecommerce (US) | X8: Ecommerce (EU) | Z8: License | AB8: Other Income | AH8: Wholesale | AJ8: Ecommerce (US) | AL8: Ecommerce (EU) | AN8: License | AP8: Other Income | AV8: Wholesale | AX8: Ecommerce (US) | AZ8: Ecommerce (EU) | BD8: Other Income
E9: M | F9: =MONTH(F7) -> 11 | T9: =MONTH(T7) -> 11 | AH9: =MONTH(AH7) -> 11 | AV9: =MONTH(AV7) -> 11
E10: Q | F10: ="Q"&ROUNDUP(MONTH(F7)/3,0)&"'"&TEXT(F7,"yy") -> Q4'24 | T10: ="Q"&ROUNDUP(MONTH(T7)/3,0)&"'"&TEXT(T7,"yy") -> Q4'25 | AH10: ="Q"&ROUNDUP(MONTH(AH7)/3,0)&"'"&TEXT(AH7,"yy") -> Q4'25 | AV10: ="Q"&ROUNDUP(MONTH(AV7)/3,0)&"'"&TEXT(AV7,"yy") -> Q4'25
E11: H | F11: ="H"&ROUNDUP(MONTH(F7)/6,0)&"'"&TEXT(F7,"yy") -> H2'24 | T11: ="H"&ROUNDUP(MONTH(T7)/6,0)&"'"&TEXT(T7,"yy") -> H2'25 | AH11: ="H"&ROUNDUP(MONTH(AH7)/6,0)&"'"&TEXT(AH7,"yy") -> H2'25 | AV11: ="H"&ROUNDUP(MONTH(AV7)/6,0)&"'"&TEXT(AV7,"yy") -> H2'25
E12: Y | F12: =YEAR(F7) -> 2024 | T12: =YEAR(T7) -> 2025 | AH12: =YEAR(AH7) -> 2025 | AV12: =YEAR(AV7) -> 2025
E13: Actual / Forecast | F13: Actual | T13: Forecast | AH13: Actual | AV13: Actual
F15: Last Year - Current Month | T15: Budget - Current Month | AH15: Actual - Current Month | AV15: vs Plan
F17: ="STO"&" "&RIGHT(YEAR($E$5)-1,2)&"년"&" "&MONTH($E$5)&"월 전년 실적" -> STO 24년 11월 전년 실적 | P17: ="STO"&" "&RIGHT(YEAR($E$5)-1,2)&"년"&" "&MONTH($E$5)&"월 전년 실적" -> STO 24년 11월 전년 실적 | T17: ="STO"&" "&RIGHT(YEAR($E$5),2)&"년"&" "&MONTH($E$5)&"월 당월 계획" -> STO 25년 11월 당월 계획 | AD17: ="STO"&" "&RIGHT(YEAR($E$5),2)&"년"&" "&MONTH($E$5)&"월 당월 계획" -> STO 25년 11월 당월 계획 | AH17: ="STO"&" "&RIGHT(YEAR($E$5),2)&"년"&" "&MONTH($E$5)&"월 당월 실적" -> STO 25년 11월 당월 실적 | AR17: ="STO"&" "&RIGHT(YEAR($E$5),2)&"년"&" "&MONTH($E$5)&"월 당월 실적" -> STO 25년 11월 당월 실적 | AV17: ="STO"&" "&RIGHT(YEAR($E$5),2)&"년"&" "&MONTH($E$5)&"월 계획대비" -> STO 25년 11월 계획대비 | BF17: ="STO"&" "&RIGHT(YEAR($E$5),2)&"년"&" "&MONTH($E$5)&"월 당월 실적" -> STO 25년 11월 당월 실적
F18: 홀세일(미국) | H18: 온라인(미국) | J18: 온라인(유럽) | L18: 라이선스 | N18: 기타 | P18: STO 합계 | T18: 홀세일(미국) | V18: 온라인(미국) | X18: 온라인(유럽) | Z18: 라이선스 | AB18: 기타 | AD18: STO 합계 | AH18: 홀세일(미국) | AJ18: 온라인(미국) | AL18: 온라인(유럽) | AN18: 라이선스 | AP18: 기타 | AR18: STO 합계 | AV18: 홀세일(미국) | AX18: 온라인(미국) | AZ18: 온라인(유럽) | BB18: 라이선스 | BD18: 기타 | BF18: STO 합계
E19: STO/STIP
E20: 라이선스
E21: 홀세일(미국)
E22: 온라인(미국)
E23: 할인율(%)
E24: 생산원가율(%)
E25: 온라인(유럽)
E26: 매출액(할인전) 계
E27: 총매출 (MSRP) | F27: 113185 | H27: 2828446 | J27: 199692 | L27: =L29 -> 61306.95 | N27: =N29 -> 0 | P27: =SUM(F27,H27,J27,L27,N27) -> 3202630 | T27: 69195.23 | V27: 4428667.2 | X27: 140715.17 | Z27: =Z29 -> 71618.645 | AB27: =AB29 -> 0 | AD27: =SUM(T27,V27,X27,Z27,AB27) -> 4710196.2 | AH27: 119067 | AJ27: 7276141 | AL27: 145950 | AN27: =AN29 -> 62076.42 | AP27: =AP29 -> 14497.69 | AR27: =SUM(AH27,AJ27,AL27,AN27,AP27) -> 7617732.1 | AV27: =AH27-T27 -> 49871.77 | AX27: =AJ27-V27 -> 2847473.8 | AZ27: =AL27-X27 -> 5234.8275 | BB27: =AN27-Z27 -> -9542.225 | BD27: =AP27-AB27 -> 14497.69 | BF27: =AR27-AD27 -> 2907535.9
E28: 할인액 | F28: =F27-F29 -> 72650.65 | H28: =H27-H29 -> 1194745.8 | J28: =J27-J29 -> 42705.53 | L28: =L27-L29 -> 0 | N28: =N27-N29 -> 0 | P28: =SUM(F28,H28,J28,L28,N28) -> 1310102 | T28: =T27-T29 -> 43938.971 | V28: =V27-V29 -> 1969571.5 | X28: =X27-X29 -> 64660.668 | Z28: =Z27-Z29 -> 0 | AB28: =AB27-AB29 -> 0 | AD28: =SUM(T28,V28,X28,Z28,AB28) -> 2078171.2 | AH28: =AH27-AH29 -> 84720.1 | AJ28: =AJ27-AJ29 -> 4437529.9 | AL28: =AL27-AL29 -> 92019.25 | AN28: =AN27-AN29 -> 0 | AP28: =AP27-AP29 -> 0 | AR28: =SUM(AH28,AJ28,AL28,AN28,AP28) -> 4614269.2 | AV28: =AH28-T28 -> 40781.129 | AX28: =AJ28-V28 -> 2467958.3 | AZ28: =AL28-X28 -> 27358.582 | BB28: =AN28-Z28 -> 0 | BD28: =AP28-AB28 -> 0 | BF28: =AR28-AD28 -> 2536098
C29: Revenue | E29: 실판매 | F29: 40534.35 | G29: =IFERROR(1-F29/F27,0) -> 0.64187525 | H29: 1633700.2 | I29: =IFERROR(1-H29/H27,0) -> 0.42240361 | J29: 156986.47 | K29: =IFERROR(1-J29/J27,0) -> 0.21385699 | L29: 61306.95 | M29: =IFERROR(1-L29/L27,0) -> 0 | N29: 0 | O29: =IFERROR(1-N29/N27,0) -> 0 | P29: =SUM(F29,H29,J29,L29,N29) -> 1892528 | Q29: =IFERROR(1-P29/P27,0) -> 0.40907067 | T29: 25256.259 | U29: =IFERROR(1-T29/T27,0) -> 0.635 | V29: 2459095.6 | W29: =IFERROR(1-V29/V27,0) -> 0.44473235 | X29: 76054.504 | Y29: =IFERROR(1-X29/X27,0) -> 0.45951454 | Z29: 71618.645 | AA29: =IFERROR(1-Z29/Z27,0) -> 0 | AB29: 0 | AC29: =IFERROR(1-AB29/AB27,0) -> 0 | AD29: =SUM(T29,V29,X29,Z29,AB29) -> 2632025.1 | AE29: =IFERROR(1-AD29/AD27,0) -> 0.44120692 | AH29: 34346.9 | AI29: =IFERROR(1-AH29/AH27,0) -> 0.711533 | AJ29: 2838611.1 | AK29: =IFERROR(1-AJ29/AJ27,0) -> 0.60987409 | AL29: 53930.75 | AM29: =IFERROR(1-AL29/AL27,0) -> 0.63048476 | AN29: 62076.42 | AO29: =IFERROR(1-AN29/AN27,0) -> 0 | AP29: 14497.69 | AQ29: =IFERROR(1-AP29/AP27,0) -> 0 | AR29: =SUM(AH29,AJ29,AL29,AN29,AP29) -> 3003462.9 | AS29: =IFERROR(1-AR29/AR27,0) -> 0.60572742 | AV29: =AH29-T29 -> 9090.6409 | AW29: =(AI29-U29)*100 -> 7.6533002 | AX29: =AJ29-V29 -> 379515.51 | AY29: =(AK29-W29)*100 -> 16.514174 | AZ29: =AL29-X29 -> -22123.754 | BA29: =(AM29-Y29)*100 -> 17.097021 | BB29: =AN29-Z29 -> -9542.225 | BC29: =(AO29-AA29)*100 -> 0 | BD29: =AP29-AB29 -> 14497.69 | BE29: =(AQ29-AC29)*100 -> 0 | BF29: =AR29-AD29 -> 371437.86 | BG29: =(AS29-AE29)*100 -> 16.45205
E30: 제품매출
E31: 기타매출
E33: 계획대비 | F33: n/a | G33: n/a | H33: n/a | I33: n/a | J33: n/a | K33: n/a | L33: n/a | M33: n/a | N33: n/a | O33: n/a | P33: n/a | Q33: n/a | AH33: =AH29-T29 -> 9090.6409 | AI33: =IFERROR(AH29/T29-1,0) -> 0.35993616 | AJ33: =AJ29-V29 -> 379515.51 | AK33: =IFERROR(AJ29/V29-1,0) -> 0.15433133 | AL33: =AL29-X29 -> -22123.754 | AM33: =IFERROR(AL29/X29-1,0) -> -0.29089341 | AN33: =AN29-Z29 -> -9542.225 | AO33: =IFERROR(AN29/Z29-1,0) -> -0.1332366 | AP33: =AP29-AB29 -> 14497.69 | AQ33: =IFERROR(AP29/AB29-1,0) -> 0 | AR33: =AR29-AD29 -> 371437.86 | AS33: =IFERROR(AR29/AD29-1,0) -> 0.14112246
E34: 전년대비 | F34: n/a | G34: n/a | H34: n/a | I34: n/a | J34: n/a | K34: n/a | L34: n/a | M34: n/a | N34: n/a | O34: n/a | P34: n/a | Q34: n/a | T34: =T29-F29 -> -15278.091 | U34: =IFERROR(T29/F29-1,0) -> -0.37691713 | V34: =V29-H29 -> 825395.44 | W34: =IFERROR(V29/H29-1,0) -> 0.50523067 | X34: =X29-J29 -> -80931.966 | Y34: =IFERROR(X29/J29-1,0) -> -0.51553465 | Z34: =Z29-L29 -> 10311.695 | AA34: =IFERROR(Z29/L29-1,0) -> 0.16819781 | AB34: =AB29-N29 -> 0 | AC34: =IFERROR(AB29/N29-1,0) -> 0 | AD34: =AD29-P29 -> 739497.08 | AE34: =IFERROR(AD29/P29-1,0) -> 0.39074565 | AH34: =AH29-F29 -> -6187.45 | AI34: =IFERROR(AH29/F29-1,0) -> -0.15264708 | AJ34: =AJ29-H29 -> 1204910.9 | AK34: =IFERROR(AJ29/H29-1,0) -> 0.73753492 | AL34: =AL29-J29 -> -103055.72 | AM34: =IFERROR(AL29/J29-1,0) -> -0.65646243 | AN34: =AN29-L29 -> 769.47 | AO34: =IFERROR(AN29/L29-1,0) -> 0.012551106 | AP34: =AP29-N29 -> 14497.69 | AQ34: =IFERROR(AP29/N29-1,0) -> 0 | AR34: =AR29-P29 -> 1110934.9 | AS34: =IFERROR(AR29/P29-1,0) -> 0.58701111
C36: COGS | E36: 매출원가 | F36: 22110.17 | G36: =IFERROR(F36/F$29,0) -> 0.54546749 | H36: 549409.54 | I36: =IFERROR(H36/H$29,0) -> 0.33629765 | J36: 38331.98 | K36: =IFERROR(J36/J$29,0) -> 0.24417378 | L36: 0 | M36: =IFERROR(L36/L$29,0) -> 0 | N36: 53018.25 | O36: =IFERROR(N36/N$29,0) -> 0 | P36: =SUM(F36,H36,J36,L36,N36) -> 662869.94 | Q36: =IFERROR(P36/P$29,0) -> 0.35025635 | T36: 12144.875 | U36: =IFERROR(T36/T$29,0) -> 0.48086595 | V36: 885593.37 | W36: =IFERROR(V36/V$29,0) -> 0.3601297 | X36: 27389.486 | Y36: =IFERROR(X36/X$29,0) -> 0.3601297 | Z36: 0 | AA36: =IFERROR(Z36/Z$29,0) -> 0 | AB36: 0 | AC36: =IFERROR(AB36/AB$29,0) -> 0 | AD36: =SUM(T36,V36,X36,Z36,AB36) -> 925127.73 | AE36: =IFERROR(AD36/AD$29,0) -> 0.35148895 | AH36: 26318.46 | AI36: =IFERROR(AH36/AH$29,0) -> 0.76625431 | AJ36: 1507965.7 | AK36: =IFERROR(AJ36/AJ$29,0) -> 0.53123364 | AL36: 38304.63 | AM36: =IFERROR(AL36/AL$29,0) -> 0.71025584 | AN36: 0 | AO36: =IFERROR(AN36/AN$29,0) -> 0 | AP36: 0 | AQ36: =IFERROR(AP36/AP$29,0) -> 0 | AR36: =SUM(AH36,AJ36,AL36,AN36,AP36) -> 1572588.8 | AS36: =IFERROR(AR36/AR$29,0) -> 0.52359189 | AV36: =AH36-T36 -> 14173.585 | AW36: =(AI36-U36)*100 -> 28.538835 | AX36: =AJ36-V36 -> 622372.37 | AY36: =(AK36-W36)*100 -> 17.110394 | AZ36: =AL36-X36 -> 10915.144 | BA36: =(AM36-Y36)*100 -> 35.012614 | BB36: =AN36-Z36 -> 0 | BC36: =(AO36-AA36)*100 -> 0 | BD36: =AP36-AB36 -> 0 | BE36: =(AQ36-AC36)*100 -> 0 | BF36: =AR36-AD36 -> 647461.1 | BG36: =(AS36-AE36)*100 -> 17.210294
E37: 기타원가 | AV37: =AH37-T37 -> 0 | AW37: =(AI37-U37)*100 -> 0 | AX37: =AJ37-V37 -> 0 | AY37: =(AK37-W37)*100 -> 0 | AZ37: =AL37-X37 -> 0 | BA37: =(AM37-Y37)*100 -> 0 | BB37: =AN37-Z37 -> 0 | BC37: =(AO37-AA37)*100 -> 0 | BD37: =AP37-AB37 -> 0 | BE37: =(AQ37-AC37)*100 -> 0 | BF37: =AR37-AD37 -> 0 | BG37: =(AS37-AE37)*100 -> 0
E38: 분기원가조정 | AV38: =AH38-T38 -> 0 | AW38: =(AI38-U38)*100 -> 0 | AX38: =AJ38-V38 -> 0 | AY38: =(AK38-W38)*100 -> 0 | AZ38: =AL38-X38 -> 0 | BA38: =(AM38-Y38)*100 -> 0 | BB38: =AN38-Z38 -> 0 | BC38: =(AO38-AA38)*100 -> 0 | BD38: =AP38-AB38 -> 0 | BE38: =(AQ38-AC38)*100 -> 0 | BF38: =AR38-AD38 -> 0 | BG38: =(AS38-AE38)*100 -> 0
E39: (생산원가율, M/U) | F39: =IFERROR(F36/F27,0) -> 0.19534541 | G39: =IFERROR(1/F39,0) -> 5.1191375 | H39: =IFERROR(H36/H27,0) -> 0.19424431 | I39: =IFERROR(1/H39,0) -> 5.148156 | J39: =IFERROR(J36/J27,0) -> 0.19195551 | K39: =IFERROR(1/J39,0) -> 5.2095404 | L39: =IFERROR(L36/L27,0) -> 0 | M39: =IFERROR(1/L39,0) -> 0 | N39: =IFERROR(N36/N27,0) -> 0 | O39: =IFERROR(1/N39,0) -> 0 | P39: =IFERROR(P36/P27,0) -> 0.20697675 | Q39: =IFERROR(1/P39,0) -> 4.8314605 | T39: =IFERROR(T36/T27,0) -> 0.17551607 | U39: =IFERROR(1/T39,0) -> 5.6974839 | V39: =IFERROR(V36/V27,0) -> 0.19996837 | W39: =IFERROR(1/V39,0) -> 5.0007908 | X39: =IFERROR(X36/X27,0) -> 0.19464486 | Y39: =IFERROR(1/X39,0) -> 5.1375617 | Z39: =IFERROR(Z36/Z27,0) -> 0 | AA39: =IFERROR(1/Z39,0) -> 0 | AB39: =IFERROR(AB36/AB27,0) -> 0 | AC39: =IFERROR(1/AB39,0) -> 0 | AD39: =IFERROR(AD36/AD27,0) -> 0.19640959 | AE39: =IFERROR(1/AD39,0) -> 5.091401 | AH39: =IFERROR(AH36/AH27,0) -> 0.22103908 | AI39: =IFERROR(1/AH39,0) -> 4.5240869 | AJ39: =IFERROR(AJ36/AJ27,0) -> 0.20724801 | AK39: =IFERROR(1/AJ39,0) -> 4.8251368 | AL39: =IFERROR(AL36/AL27,0) -> 0.26245036 | AM39: =IFERROR(1/AL39,0) -> 3.8102443 | AN39: =IFERROR(AN36/AN27,0) -> 0 | AO39: =IFERROR(1/AN39,0) -> 0 | AP39: =IFERROR(AP36/AP27,0) -> 0 | AQ39: =IFERROR(1/AP39,0) -> 0 | AR39: =IFERROR(AR36/AR27,0) -> 0.20643793 | AS39: =IFERROR(1/AR39,0) -> 4.8440711 | AV39: =(AH39-T39)*100 -> 4.5523006 | AW39: =(AI39-U39) -> -1.173397 | AX39: =(AJ39-V39)*100 -> 0.7279637 | AY39: =(AK39-W39) -> -0.175654 | AZ39: =(AL39-X39)*100 -> 6.7805495 | BA39: =(AM39-Y39) -> -1.3273173 | BB39: =AN39-Z39 -> 0 | BC39: =(AO39-AA39) -> 0 | BD39: =AP39-AB39 -> 0 | BE39: =(AQ39-AC39) -> 0 | BF39: =(AR39-AD39)*100 -> 1.0028333 | BG39: =(AS39-AE39) -> -0.24732987
E40: 매출총이익 | F40: =F29-F36 -> 18424.18 | G40: =IFERROR(F40/F29,0) -> 0.45453251 | H40: =H29-H36 -> 1084290.7 | I40: =IFERROR(H40/H29,0) -> 0.66370235 | J40: =J29-J36 -> 118654.49 | K40: =IFERROR(J40/J29,0) -> 0.75582622 | L40: =L29-L36 -> 61306.95 | M40: =IFERROR(L40/L29,0) -> 1 | N40: =N29-N36 -> -53018.25 | O40: =IFERROR(N40/N29,0) -> 0 | P40: =P29-P36 -> 1229658 | Q40: =IFERROR(P40/P$29,0) -> 0.64974365 | T40: =T29-T36 -> 13111.384 | U40: =IFERROR(T40/T29,0) -> 0.51913405 | V40: =V29-V36 -> 1573502.3 | W40: =IFERROR(V40/V29,0) -> 0.6398703 | X40: =X29-X36 -> 48665.019 | Y40: =IFERROR(X40/X29,0) -> 0.6398703 | Z40: =Z29-Z36 -> 71618.645 | AA40: =IFERROR(Z40/Z29,0) -> 1 | AB40: =AB29-AB36 -> 0 | AC40: =IFERROR(AB40/AB29,0) -> 0 | AD40: =AD29-AD36 -> 1706897.3 | AE40: =IFERROR(AD40/AD$29,0) -> 0.64851105 | AH40: =AH29-AH36 -> 8028.44 | AI40: =IFERROR(AH40/AH29,0) -> 0.23374569 | AJ40: =AJ29-AJ36 -> 1330645.4 | AK40: =IFERROR(AJ40/AJ29,0) -> 0.46876636 | AL40: =AL29-AL36 -> 15626.12 | AM40: =IFERROR(AL40/AL29,0) -> 0.28974416 | AN40: =AN29-AN36 -> 62076.42 | AO40: =IFERROR(AN40/AN29,0) -> 1 | AP40: =AP29-AP36 -> 14497.69 | AQ40: =IFERROR(AP40/AP29,0) -> 1 | AR40: =AR29-AR36 -> 1430874.1 | AS40: =IFERROR(AR40/AR$29,0) -> 0.47640811 | AV40: =AH40-T40 -> -5082.944 | AW40: =(AI40-U40)*100 -> -28.538835 | AX40: =AJ40-V40 -> -242856.86 | AY40: =(AK40-W40)*100 -> -17.110394 | AZ40: =AL40-X40 -> -33038.899 | BA40: =(AM40-Y40)*100 -> -35.012614 | BB40: =AN40-Z40 -> -9542.225 | BC40: =(AO40-AA40)*100 -> 0 | BD40: =AP40-AB40 -> 14497.69 | BE40: =(AQ40-AC40)*100 -> 100 | BF40: =AR40-AD40 -> -276023.24 | BG40: =(AS40-AE40)*100 -> -17.210294
E42: 직접비
E43: 운반비/보관료/ 물류용역비 | F43: =SUM(F44:F46) -> 4068.508 | G43: =IFERROR(F43/F$29,0) -> 0.10037186 | H43: =SUM(H44:H46) -> 129782.38 | I43: =IFERROR(H43/H$29,0) -> 0.079440759 | J43: =SUM(J44:J46) -> 16803.128 | K43: =IFERROR(J43/J$29,0) -> 0.10703552 | L43: =SUM(L44:L46) -> 0 | M43: =IFERROR(L43/L$29,0) -> 0 | N43: =SUM(N44:N46) -> 0 | O43: =IFERROR(N43/N$29,0) -> 0 | P43: =SUM(F43,H43,J43,L43,N43) -> 150654.02 | Q43: =IFERROR(P43/P$29,0) -> 0.079604646 | T43: =SUM(T44:T46) -> 17426.715 | U43: =IFERROR(T43/T$29,0) -> 0.68999589 | V43: =SUM(V44:V46) -> 193171.29 | W43: =IFERROR(V43/V$29,0) -> 0.078553791 | X43: =SUM(X44:X46) -> 22740.497 | Y43: =IFERROR(X43/X$29,0) -> 0.29900263 | Z43: =SUM(Z44:Z46) -> 0 | AA43: =IFERROR(Z43/Z$29,0) -> 0 | AB43: =SUM(AB44:AB46) -> 0 | AC43: =IFERROR(AB43/AB$29,0) -> 0 | AD43: =SUM(T43,V43,X43,Z43,AB43) -> 233338.5 | AE43: =IFERROR(AD43/AD$29,0) -> 0.088653601 | AH43: =SUM(AH44:AH46) -> 5454 | AI43: =IFERROR(AH43/AH$29,0) -> 0.15879162 | AJ43: =SUM(AJ44:AJ46) -> 207447.12 | AK43: =IFERROR(AJ43/AJ$29,0) -> 0.073080499 | AL43: =SUM(AL44:AL46) -> 8142.02 | AM43: =IFERROR(AL43/AL$29,0) -> 0.15097176 | AN43: =SUM(AN44:AN46) -> 0 | AO43: =IFERROR(AN43/AN$29,0) -> 0 | AP43: =SUM(AP44:AP46) -> 0 | AQ43: =IFERROR(AP43/AP$29,0) -> 0 | AR43: =SUM(AH43,AJ43,AL43,AN43,AP43) -> 221043.14 | AS43: =IFERROR(AR43/AR$29,0) -> 0.073596094 | AV43: =AH43-T43 -> -11972.715 | AW43: =(AI43-U43)*100 -> -53.120426 | AX43: =AJ43-V43 -> 14275.834 | AY43: =(AK43-W43)*100 -> -0.54732921 | AZ43: =AL43-X43 -> -14598.477 | BA43: =(AM43-Y43)*100 -> -14.803087 | BB43: =AN43-Z43 -> 0 | BC43: =(AO43-AA43)*100 -> 0 | BD43: =AP43-AB43 -> 0 | BE43: =(AQ43-AC43)*100 -> 0 | BF43: =AR43-AD43 -> -12295.357 | BG43: =(AS43-AE43)*100 -> -1.5057506
B44: 운반비 | C44: 운반비 (-) | E44: 운반비 | F44: 210.968 | G44: =IFERROR(F44/F$29,0) -> 0.0052046721 | H44: 60663.524 | I44: =IFERROR(H44/H$29,0) -> 0.037132593 | J44: 11042.588 | K44: =IFERROR(J44/J$29,0) -> 0.070341017 | L44: 0 | M44: =IFERROR(L44/L$29,0) -> 0 | N44: 0 | O44: =IFERROR(N44/N$29,0) -> 0 | P44: =SUM(F44,H44,J44,L44,N44) -> 71917.08 | Q44: =IFERROR(P44/P$29,0) -> 0.038000537 | T44: 1043.2797 | U44: =IFERROR(T44/T$29,0) -> 0.04130777 | V44: 93895.176 | W44: =IFERROR(V44/V$29,0) -> 0.038182808 | X44: 9389.5176 | Y44: =IFERROR(X44/X$29,0) -> 0.12345774 | Z44: 0 | AA44: =IFERROR(Z44/Z$29,0) -> 0 | AB44: 0 | AC44: =IFERROR(AB44/AB$29,0) -> 0 | AD44: =SUM(T44,V44,X44,Z44,AB44) -> 104327.97 | AE44: =IFERROR(AD44/AD$29,0) -> 0.03963791 | AH44: -614.74 | AI44: =IFERROR(AH44/AH$29,0) -> -0.017897976 | AJ44: 86981.35 | AK44: =IFERROR(AJ44/AJ$29,0) -> 0.030642221 | AL44: 1181.86 | AM44: =IFERROR(AL44/AL$29,0) -> 0.021914399 | AN44: 0 | AO44: =IFERROR(AN44/AN$29,0) -> 0 | AP44: 0 | AQ44: =IFERROR(AP44/AP$29,0) -> 0 | AR44: =SUM(AH44,AJ44,AL44,AN44,AP44) -> 87548.47 | AS44: =IFERROR(AR44/AR$29,0) -> 0.029149176 | AV44: =AH44-T44 -> -1658.0197 | AW44: =(AI44-U44)*100 -> -5.9205746 | AX44: =AJ44-V44 -> -6913.826 | AY44: =(AK44-W44)*100 -> -0.75405867 | AZ44: =AL44-X44 -> -8207.6576 | BA44: =(AM44-Y44)*100 -> -10.154335 | BB44: =AN44-Z44 -> 0 | BC44: =(AO44-AA44)*100 -> 0 | BD44: =AP44-AB44 -> 0 | BE44: =(AQ44-AC44)*100 -> 0 | BF44: =AR44-AD44 -> -16779.503 | BG44: =(AS44-AE44)*100 -> -1.0488734
B45: 보관료 | E45: 보관료 | F45: 739.54 | G45: =IFERROR(F45/F$29,0) -> 0.018244773 | H45: 20597.28 | I45: =IFERROR(H45/H$29,0) -> 0.012607748 | J45: 2038.87 | K45: =IFERROR(J45/J$29,0) -> 0.012987552 | L45: 0 | M45: =IFERROR(L45/L$29,0) -> 0 | N45: 0 | O45: =IFERROR(N45/N$29,0) -> 0 | P45: =SUM(F45,H45,J45,L45,N45) -> 23375.69 | Q45: =IFERROR(P45/P$29,0) -> 0.012351569 | T45: 9138.3325 | U45: =IFERROR(T45/T$29,0) -> 0.36182447 | V45: 35346.35 | W45: =IFERROR(V45/V$29,0) -> 0.014373719 | X45: 2252.2393 | Y45: =IFERROR(X45/X$29,0) -> 0.02961349 | Z45: 0 | AA45: =IFERROR(Z45/Z$29,0) -> 0 | AB45: 0 | AC45: =IFERROR(AB45/AB$29,0) -> 0 | AD45: =SUM(T45,V45,X45,Z45,AB45) -> 46736.922 | AE45: =IFERROR(AD45/AD$29,0) -> 0.01775702 | AH45: 3442.7 | AI45: =IFERROR(AH45/AH$29,0) -> 0.10023321 | AJ45: 39244.62 | AK45: =IFERROR(AJ45/AJ$29,0) -> 0.013825289 | AL45: 1558.93 | AM45: =IFERROR(AL45/AL$29,0) -> 0.028906144 | AN45: 0 | AO45: =IFERROR(AN45/AN$29,0) -> 0 | AP45: 0 | AQ45: =IFERROR(AP45/AP$29,0) -> 0 | AR45: =SUM(AH45,AJ45,AL45,AN45,AP45) -> 44246.25 | AS45: =IFERROR(AR45/AR$29,0) -> 0.014731745 | AV45: =AH45-T45 -> -5695.6325 | AW45: =(AI45-U45)*100 -> -26.159126 | AX45: =AJ45-V45 -> 3898.27 | AY45: =(AK45-W45)*100 -> -0.054842993 | AZ45: =AL45-X45 -> -693.30932 | BA45: =(AM45-Y45)*100 -> -0.070734671 | BB45: =AN45-Z45 -> 0 | BC45: =(AO45-AA45)*100 -> 0 | BD45: =AP45-AB45 -> 0 | BE45: =(AQ45-AC45)*100 -> 0 | BF45: =AR45-AD45 -> -2490.6718 | BG45: =(AS45-AE45)*100 -> -0.30252751
B46: 물류용역비 | E46: 물류용역비 | F46: 3118 | G46: =IFERROR(F46/F$29,0) -> 0.076922413 | H46: 48521.58 | I46: =IFERROR(H46/H$29,0) -> 0.029700419 | J46: 3721.67 | K46: =IFERROR(J46/J$29,0) -> 0.023706947 | L46: 0 | M46: =IFERROR(L46/L$29,0) -> 0 | N46: 0 | O46: =IFERROR(N46/N$29,0) -> 0 | P46: =SUM(F46,H46,J46,L46,N46) -> 55361.25 | Q46: =IFERROR(P46/P$29,0) -> 0.02925254 | T46: 7245.1027 | U46: =IFERROR(T46/T$29,0) -> 0.28686365 | V46: 63929.76 | W46: =IFERROR(V46/V$29,0) -> 0.025997265 | X46: 11098.74 | Y46: =IFERROR(X46/X$29,0) -> 0.14593139 | Z46: 0 | AA46: =IFERROR(Z46/Z$29,0) -> 0 | AB46: 0 | AC46: =IFERROR(AB46/AB$29,0) -> 0 | AD46: =SUM(T46,V46,X46,Z46,AB46) -> 82273.602 | AE46: =IFERROR(AD46/AD$29,0) -> 0.03125867 | AH46: 2626.04 | AI46: =IFERROR(AH46/AH$29,0) -> 0.076456391 | AJ46: 81221.15 | AK46: =IFERROR(AJ46/AJ$29,0) -> 0.028612989 | AL46: 5401.23 | AM46: =IFERROR(AL46/AL$29,0) -> 0.10015121 | AN46: 0 | AO46: =IFERROR(AN46/AN$29,0) -> 0 | AP46: 0 | AQ46: =IFERROR(AP46/AP$29,0) -> 0 | AR46: =SUM(AH46,AJ46,AL46,AN46,AP46) -> 89248.42 | AS46: =IFERROR(AR46/AR$29,0) -> 0.029715173 | AV46: =AH46-T46 -> -4619.0627 | AW46: =(AI46-U46)*100 -> -21.040726 | AX46: =AJ46-V46 -> 17291.39 | AY46: =(AK46-W46)*100 -> 0.26157246 | AZ46: =AL46-X46 -> -5697.5096 | BA46: =(AM46-Y46)*100 -> -4.5780179 | BB46: =AN46-Z46 -> 0 | BC46: =(AO46-AA46)*100 -> 0 | BD46: =AP46-AB46 -> 0 | BE46: =(AQ46-AC46)*100 -> 0 | BF46: =AR46-AD46 -> 6974.8178 | BG46: =(AS46-AE46)*100 -> -0.15434969
B47: Professional Service | C47: Direct Costs | E47: 지급수수료 | F47: 1360.11 | G47: =IFERROR(F47/F$29,0) -> 0.033554504 | H47: 78708.07 | I47: =IFERROR(H47/H$29,0) -> 0.048177793 | J47: 4042.13 | K47: =IFERROR(J47/J$29,0) -> 0.02574827 | L47: 0 | M47: =IFERROR(L47/L$29,0) -> 0 | N47: 0 | O47: =IFERROR(N47/N$29,0) -> 0 | P47: =SUM(F47,H47,J47,L47,N47) -> 84110.31 | Q47: =IFERROR(P47/P$29,0) -> 0.044443364 | T47: 5884.9519 | U47: =IFERROR(T47/T$29,0) -> 0.23300964 | V47: 79134.548 | W47: =IFERROR(V47/V$29,0) -> 0.032180346 | X47: 11405.401 | Y47: =IFERROR(X47/X$29,0) -> 0.14996352 | Z47: 0 | AA47: =IFERROR(Z47/Z$29,0) -> 0 | AB47: 0 | AC47: =IFERROR(AB47/AB$29,0) -> 0 | AD47: =SUM(T47,V47,X47,Z47,AB47) -> 96424.901 | AE47: =IFERROR(AD47/AD$29,0) -> 0.036635252 | AH47: 1412.19 | AI47: =IFERROR(AH47/AH$29,0) -> 0.041115501 | AJ47: 90826.47 | AK47: =IFERROR(AJ47/AJ$29,0) -> 0.031996799 | AL47: 5605.57 | AM47: =IFERROR(AL47/AL$29,0) -> 0.10394015 | AN47: 0 | AO47: =IFERROR(AN47/AN$29,0) -> 0 | AP47: 0 | AQ47: =IFERROR(AP47/AP$29,0) -> 0 | AR47: =SUM(AH47,AJ47,AL47,AN47,AP47) -> 97844.23 | AS47: =IFERROR(AR47/AR$29,0) -> 0.032577139 | AV47: =AH47-T47 -> -4472.7619 | AW47: =(AI47-U47)*100 -> -19.189414 | AX47: =AJ47-V47 -> 11691.922 | AY47: =(AK47-W47)*100 -> -0.018354679 | AZ47: =AL47-X47 -> -5799.8313 | BA47: =(AM47-Y47)*100 -> -4.6023376 | BB47: =AN47-Z47 -> 0 | BC47: =(AO47-AA47)*100 -> 0 | BD47: =AP47-AB47 -> 0 | BE47: =(AQ47-AC47)*100 -> 0 | BF47: =AR47-AD47 -> 1419.3291 | BG47: =(AS47-AE47)*100 -> -0.40581125
B48: 6451 - Service Processing Fee | C48: Direct Costs | E48: 결제수수료 | F48: 3530.35 | G48: =IFERROR(F48/F$29,0) -> 0.087095266 | H48: 46875.37 | I48: =IFERROR(H48/H$29,0) -> 0.028692761 | J48: 13985.15 | K48: =IFERROR(J48/J$29,0) -> 0.089085066 | L48: 0 | M48: =IFERROR(L48/L$29,0) -> 0 | N48: 0 | O48: =IFERROR(N48/N$29,0) -> 0 | P48: =SUM(F48,H48,J48,L48,N48) -> 64390.87 | Q48: =IFERROR(P48/P$29,0) -> 0.034023735 | T48: 434.75796 | U48: =IFERROR(T48/T$29,0) -> 0.01721387 | V48: 109282.71 | W48: =IFERROR(V48/V$29,0) -> 0.044440203 | X48: 4593.8567 | Y48: =IFERROR(X48/X$29,0) -> 0.060402165 | Z48: 0 | AA48: =IFERROR(Z48/Z$29,0) -> 0 | AB48: 0 | AC48: =IFERROR(AB48/AB$29,0) -> 0 | AD48: =SUM(T48,V48,X48,Z48,AB48) -> 114311.32 | AE48: =IFERROR(AD48/AD$29,0) -> 0.043430941 | AH48: 5028.11 | AI48: =IFERROR(AH48/AH$29,0) -> 0.14639196 | AJ48: 72412.21 | AK48: =IFERROR(AJ48/AJ$29,0) -> 0.025509732 | AL48: 3010.71 | AM48: =IFERROR(AL48/AL$29,0) -> 0.05582548 | AN48: 0 | AO48: =IFERROR(AN48/AN$29,0) -> 0 | AP48: 0 | AQ48: =IFERROR(AP48/AP$29,0) -> 0 | AR48: =SUM(AH48,AJ48,AL48,AN48,AP48) -> 80451.03 | AS48: =IFERROR(AR48/AR$29,0) -> 0.026786091 | AV48: =AH48-T48 -> 4593.352 | AW48: =(AI48-U48)*100 -> 12.917809 | AX48: =AJ48-V48 -> -36870.5 | AY48: =(AK48-W48)*100 -> -1.8930471 | AZ48: =AL48-X48 -> -1583.1467 | BA48: =(AM48-Y48)*100 -> -0.4576685 | BB48: =AN48-Z48 -> 0 | BC48: =(AO48-AA48)*100 -> 0 | BD48: =AP48-AB48 -> 0 | BE48: =(AQ48-AC48)*100 -> 0 | BF48: =AR48-AD48 -> -33860.294 | BG48: =(AS48-AE48)*100 -> -1.664485
B49: Marketing | C49: Direct Costs | E49: SEM 광고비 | F49: 0 | G49: =IFERROR(F49/F$29,0) -> 0 | H49: 233206 | I49: =IFERROR(H49/H$29,0) -> 0.14274712 | J49: 34899.27 | K49: =IFERROR(J49/J$29,0) -> 0.2223075 | L49: 0 | M49: =IFERROR(L49/L$29,0) -> 0 | N49: 0 | O49: =IFERROR(N49/N$29,0) -> 0 | P49: =SUM(F49,H49,J49,L49,N49) -> 268105.27 | Q49: =IFERROR(P49/P$29,0) -> 0.14166516 | T49: 0 | U49: =IFERROR(T49/T$29,0) -> 0 | V49: 349156.1 | W49: =IFERROR(V49/V$29,0) -> 0.14198557 | X49: 40991.906 | Y49: =IFERROR(X49/X$29,0) -> 0.53898064 | Z49: 0 | AA49: =IFERROR(Z49/Z$29,0) -> 0 | AB49: 0 | AC49: =IFERROR(AB49/AB$29,0) -> 0 | AD49: =SUM(T49,V49,X49,Z49,AB49) -> 390148.01 | AE49: =IFERROR(AD49/AD$29,0) -> 0.14823111 | AH49: 0 | AI49: =IFERROR(AH49/AH$29,0) -> 0 | AJ49: 457301.05 | AK49: =IFERROR(AJ49/AJ$29,0) -> 0.16110028 | AL49: 0 | AM49: =IFERROR(AL49/AL$29,0) -> 0 | AN49: 0 | AO49: =IFERROR(AN49/AN$29,0) -> 0 | AP49: 0 | AQ49: =IFERROR(AP49/AP$29,0) -> 0 | AR49: =SUM(AH49,AJ49,AL49,AN49,AP49) -> 457301.05 | AS49: =IFERROR(AR49/AR$29,0) -> 0.15225793 | AV49: =AH49-T49 -> 0 | AW49: =(AI49-U49)*100 -> 0 | AX49: =AJ49-V49 -> 108144.95 | AY49: =(AK49-W49)*100 -> 1.9114708 | AZ49: =AL49-X49 -> -40991.906 | BA49: =(AM49-Y49)*100 -> -53.898064 | BB49: =AN49-Z49 -> 0 | BC49: =(AO49-AA49)*100 -> 0 | BD49: =AP49-AB49 -> 0 | BE49: =(AQ49-AC49)*100 -> 0 | BF49: =AR49-AD49 -> 67153.045 | BG49: =(AS49-AE49)*100 -> 0.40268175
B50: Other | C50: Direct Costs | E50: 기타비용 | F50: 0 | G50: =IFERROR(F50/F$29,0) -> 0 | H50: 0 | I50: =IFERROR(H50/H$29,0) -> 0 | J50: 0 | K50: =IFERROR(J50/J$29,0) -> 0 | L50: 0 | M50: =IFERROR(L50/L$29,0) -> 0 | N50: 0 | O50: =IFERROR(N50/N$29,0) -> 0 | P50: =SUM(F50,H50,J50,L50,N50) -> 0 | Q50: =IFERROR(P50/P$29,0) -> 0 | T50: 0 | U50: =IFERROR(T50/T$29,0) -> 0 | V50: 0 | W50: =IFERROR(V50/V$29,0) -> 0 | X50: 0 | Y50: =IFERROR(X50/X$29,0) -> 0 | Z50: 0 | AA50: =IFERROR(Z50/Z$29,0) -> 0 | AB50: 0 | AC50: =IFERROR(AB50/AB$29,0) -> 0 | AD50: =SUM(T50,V50,X50,Z50,AB50) -> 0 | AE50: =IFERROR(AD50/AD$29,0) -> 0 | AH50: 0 | AI50: =IFERROR(AH50/AH$29,0) -> 0 | AJ50: 0 | AK50: =IFERROR(AJ50/AJ$29,0) -> 0 | AL50: 0 | AM50: =IFERROR(AL50/AL$29,0) -> 0 | AN50: 0 | AO50: =IFERROR(AN50/AN$29,0) -> 0 | AP50: 0 | AQ50: =IFERROR(AP50/AP$29,0) -> 0 | AR50: =SUM(AH50,AJ50,AL50,AN50,AP50) -> 0 | AS50: =IFERROR(AR50/AR$29,0) -> 0 | AV50: =AH50-T50 -> 0 | AW50: =(AI50-U50)*100 -> 0 | AX50: =AJ50-V50 -> 0 | AY50: =(AK50-W50)*100 -> 0 | AZ50: =AL50-X50 -> 0 | BA50: =(AM50-Y50)*100 -> 0 | BB50: =AN50-Z50 -> 0 | BC50: =(AO50-AA50)*100 -> 0 | BD50: =AP50-AB50 -> 0 | BE50: =(AQ50-AC50)*100 -> 0 | BF50: =AR50-AD50 -> 0 | BG50: =(AS50-AE50)*100 -> 0
E51: 직접비 소계 | F51: =F43+SUM(F47:F50) -> 8958.968 | G51: =IFERROR(F51/F$29,0) -> 0.22102163 | H51: =H43+SUM(H47:H50) -> 488571.82 | I51: =IFERROR(H51/H$29,0) -> 0.29905843 | J51: =J43+SUM(J47:J50) -> 69729.678 | K51: =IFERROR(J51/J$29,0) -> 0.44417635 | L51: =L43+SUM(L47:L50) -> 0 | M51: =IFERROR(L51/L$29,0) -> 0 | N51: =N43+SUM(N47:N50) -> 0 | O51: =IFERROR(N51/N$29,0) -> 0 | P51: =P43+SUM(P47:P50) -> 567260.47 | Q51: =IFERROR(P51/P$29,0) -> 0.2997369 | T51: =T43+SUM(T47:T50) -> 23746.425 | U51: =IFERROR(T51/T$29,0) -> 0.9402194 | V51: =V43+SUM(V47:V50) -> 730744.64 | W51: =IFERROR(V51/V$29,0) -> 0.29715991 | X51: =X43+SUM(X47:X50) -> 79731.66 | Y51: =IFERROR(X51/X$29,0) -> 1.048349 | Z51: =Z43+SUM(Z47:Z50) -> 0 | AA51: =IFERROR(Z51/Z$29,0) -> 0 | AB51: =AB43+SUM(AB47:AB50) -> 0 | AC51: =IFERROR(AB51/AB$29,0) -> 0 | AD51: =AD43+SUM(AD47:AD50) -> 834222.73 | AE51: =IFERROR(AD51/AD$29,0) -> 0.31695091 | AH51: =AH43+SUM(AH47:AH50) -> 11894.3 | AI51: =IFERROR(AH51/AH$29,0) -> 0.34629908 | AJ51: =AJ43+SUM(AJ47:AJ50) -> 827986.85 | AK51: =IFERROR(AJ51/AJ$29,0) -> 0.29168731 | AL51: =AL43+SUM(AL47:AL50) -> 16758.3 | AM51: =IFERROR(AL51/AL$29,0) -> 0.31073738 | AN51: =AN43+SUM(AN47:AN50) -> 0 | AO51: =IFERROR(AN51/AN$29,0) -> 0 | AP51: =AP43+SUM(AP47:AP50) -> 0 | AQ51: =IFERROR(AP51/AP$29,0) -> 0 | AR51: =AR43+SUM(AR47:AR50) -> 856639.45 | AS51: =IFERROR(AR51/AR$29,0) -> 0.28521726 | AV51: =AH51-T51 -> -11852.125 | AW51: =(AI51-U51)*100 -> -59.392032 | AX51: =AJ51-V51 -> 97242.207 | AY51: =(AK51-W51)*100 -> -0.54726015 | AZ51: =AL51-X51 -> -62973.36 | BA51: =(AM51-Y51)*100 -> -73.761157 | BB51: =AN51-Z51 -> 0 | BC51: =(AO51-AA51)*100 -> 0 | BD51: =AP51-AB51 -> 0 | BE51: =(AQ51-AC51)*100 -> 0 | BF51: =AR51-AD51 -> 22416.722 | BG51: =(AS51-AE51)*100 -> -3.1733651
E53: 직접이익 | F53: =F40-F51 -> 9465.212 | G53: =IFERROR(F53/F$29,0) -> 0.23351089 | H53: =H40-H51 -> 595718.84 | I53: =IFERROR(H53/H$29,0) -> 0.36464391 | J53: =J40-J51 -> 48924.812 | K53: =IFERROR(J53/J$29,0) -> 0.31164986 | L53: =L40-L51 -> 61306.95 | M53: =IFERROR(L53/L$29,0) -> 1 | N53: =N40-N51 -> -53018.25 | O53: =IFERROR(N53/N$29,0) -> 0 | P53: =P40-P51 -> 662397.56 | Q53: =IFERROR(P53/P$29,0) -> 0.35000675 | T53: =T40-T51 -> -10635.041 | U53: =IFERROR(T53/T$29,0) -> -0.42108535 | V53: =V40-V51 -> 842757.63 | W53: =IFERROR(V53/V$29,0) -> 0.34271039 | X53: =X40-X51 -> -31066.642 | Y53: =IFERROR(X53/X$29,0) -> -0.40847865 | Z53: =Z40-Z51 -> 71618.645 | AA53: =IFERROR(Z53/Z$29,0) -> 1 | AB53: =AB40-AB51 -> 0 | AC53: =IFERROR(AB53/AB$29,0) -> 0 | AD53: =AD40-AD51 -> 872674.59 | AE53: =IFERROR(AD53/AD$29,0) -> 0.33156014 | AH53: =AH40-AH51 -> -3865.86 | AI53: =IFERROR(AH53/AH$29,0) -> -0.11255339 | AJ53: =AJ40-AJ51 -> 502658.56 | AK53: =IFERROR(AJ53/AJ$29,0) -> 0.17707905 | AL53: =AL40-AL51 -> -1132.18 | AM53: =IFERROR(AL53/AL$29,0) -> -0.020993218 | AN53: =AN40-AN51 -> 62076.42 | AO53: =IFERROR(AN53/AN$29,0) -> 1 | AP53: =AP40-AP51 -> 14497.69 | AQ53: =IFERROR(AP53/AP$29,0) -> 1 | AR53: =AR40-AR51 -> 574234.63 | AS53: =IFERROR(AR53/AR$29,0) -> 0.19119085 | AV53: =AH53-T53 -> 6769.1807 | AW53: =(AI53-U53)*100 -> 30.853196 | AX53: =AJ53-V53 -> -340099.07 | AY53: =(AK53-W53)*100 -> -16.563134 | AZ53: =AL53-X53 -> 29934.462 | BA53: =(AM53-Y53)*100 -> 38.748544 | BB53: =AN53-Z53 -> -9542.225 | BC53: =(AO53-AA53)*100 -> 0 | BD53: =AP53-AB53 -> 14497.69 | BE53: =(AQ53-AC53)*100 -> 100 | BF53: =AR53-AD53 -> -298439.96 | BG53: =(AS53-AE53)*100 -> -14.036929
U54: 적자 | W54: =+W53-I53 -> -0.021933524 | Y54: =+Y53-K53 -> -0.72012852 | AI54: =+AI53-G53 -> -0.34606428 | AK54: =+AK53-I53 -> -0.18756487 | AM54: =+AM53-K53 -> -0.33264308
E55: 영업비
E56: 인건비 | P56: =SUM(P57:P60) -> 429082.91 | Q56: =IFERROR(P56/P$29,0) -> 0.22672474 | AD56: =SUM(AD57:AD60) -> 374176.34 | AE56: =IFERROR(AD56/AD$29,0) -> 0.14216291 | AR56: =SUM(AR57:AR60) -> 315403.06 | AS56: =IFERROR(AR56/AR$29,0) -> 0.10501314 | BF56: =AR56-AD56 -> -58773.28 | BG56: =(AS56-AE56)*100 -> -3.7149774
B57: HQ | C57: HQ Salaries | E57: 급여(정규) | P57: 274128.53 | Q57: =IFERROR(P57/P$29,0) -> 0.14484781 | AD57: 262175.17 | AE57: =IFERROR(AD57/AD$29,0) -> 0.09960968 | AR57: 209456.3 | AS57: =IFERROR(AR57/AR$29,0) -> 0.069738268 | BF57: =AR57-AD57 -> -52718.873 | BG57: =(AS57-AE57)*100 -> -2.9871413
B58: Contractors | C58: HQ Salaries | E58: 급여(계약) | P58: 59146.03 | Q58: =IFERROR(P58/P$29,0) -> 0.031252394 | AD58: 33348.615 | AE58: =IFERROR(AD58/AD$29,0) -> 0.012670326 | AR58: 54333.79 | AS58: =IFERROR(AR58/AR$29,0) -> 0.018090382 | BF58: =AR58-AD58 -> 20985.175 | BG58: =(AS58-AE58)*100 -> 0.54200559
B59: Benefits | C59: HQ Salaries | E59: 보험,복후비등 | P59: 51292.23 | Q59: =IFERROR(P59/P$29,0) -> 0.027102495 | AD59: 78652.552 | AE59: =IFERROR(AD59/AD$29,0) -> 0.029882904 | AR59: 51612.97 | AS59: =IFERROR(AR59/AR$29,0) -> 0.017184487 | BF59: =AR59-AD59 -> -27039.582 | BG59: =(AS59-AE59)*100 -> -1.2698417
B60: Bonus | C60: HQ Salaries | E60: 급여충당금 | P60: 44516.12 | Q60: =IFERROR(P60/P$29,0) -> 0.023522041 | AD60: 0 | AE60: =IFERROR(AD60/AD$29,0) -> 0 | AR60: 0 | AS60: =IFERROR(AR60/AR$29,0) -> 0 | BF60: =AR60-AD60 -> 0 | BG60: =(AS60-AE60)*100 -> 0
B61: Advertising | C61: SG&A | E61: 광고선전비 | P61: 90302.63 | Q61: =IFERROR(P61/P$29,0) -> 0.047715348 | AD61: 77726.014 | AE61: =IFERROR(AD61/AD$29,0) -> 0.029530879 | AR61: 112652.04 | AS61: =IFERROR(AR61/AR$29,0) -> 0.037507385 | BF61: =AR61-AD61 -> 34926.026 | BG61: =(AS61-AE61)*100 -> 0.79765058
E62: Photography | P62: 67767.51 | Q62: =IFERROR(P62/P$29,0) -> 0.03580793 | AE62: =IFERROR(AD62/AD$29,0) -> 0 | AS62: =IFERROR(AR62/AR$29,0) -> 0 | BF62: =AR62-AD62 -> 0 | BG62: =(AS62-AE62)*100 -> 0
E63: Selling | P63: 0 | Q63: =IFERROR(P63/P$29,0) -> 0 | AE63: =IFERROR(AD63/AD$29,0) -> 0 | AS63: =IFERROR(AR63/AR$29,0) -> 0 | BF63: =AR63-AD63 -> 0 | BG63: =(AS63-AE63)*100 -> 0
E64: Advertising | P64: 2291.66 | Q64: =IFERROR(P64/P$29,0) -> 0.0012108989 | AE64: =IFERROR(AD64/AD$29,0) -> 0 | AS64: =IFERROR(AR64/AR$29,0) -> 0 | BF64: =AR64-AD64 -> 0 | BG64: =(AS64-AE64)*100 -> 0
E65: SEM브랜드마케팅 | P65: 0 | Q65: =IFERROR(P65/P$29,0) -> 0 | AE65: =IFERROR(AD65/AD$29,0) -> 0 | AS65: =IFERROR(AR65/AR$29,0) -> 0 | BF65: =AR65-AD65 -> 0 | BG65: =(AS65-AE65)*100 -> 0
E66: Events | P66: 0 | Q66: =IFERROR(P66/P$29,0) -> 0 | AE66: =IFERROR(AD66/AD$29,0) -> 0 | AS66: =IFERROR(AR66/AR$29,0) -> 0 | BF66: =AR66-AD66 -> 0 | BG66: =(AS66-AE66)*100 -> 0
E67: Model | P67: 12630 | Q67: =IFERROR(P67/P$29,0) -> 0.0066736134 | AE67: =IFERROR(AD67/AD$29,0) -> 0 | AS67: =IFERROR(AR67/AR$29,0) -> 0 | BF67: =AR67-AD67 -> 0 | BG67: =(AS67-AE67)*100 -> 0
E68: Seeding | P68: 7613.46 | Q68: =IFERROR(P68/P$29,0) -> 0.0040229049 | AE68: =IFERROR(AD68/AD$29,0) -> 0 | AS68: =IFERROR(AR68/AR$29,0) -> 0 | BF68: =AR68-AD68 -> 0 | BG68: =(AS68-AE68)*100 -> 0
E69: 기타 광고비 | P69: 0 | Q69: =IFERROR(P69/P$29,0) -> 0 | AE69: =IFERROR(AD69/AD$29,0) -> 0 | AS69: =IFERROR(AR69/AR$29,0) -> 0 | BF69: =AR69-AD69 -> 0 | BG69: =(AS69-AE69)*100 -> 0
B70: Professional Service | C70: SG&A | E70: 지급수수료 | P70: 123364.37 | Q70: =IFERROR(P70/P$29,0) -> 0.065184965 | AD70: 53696.369 | AE70: =IFERROR(AD70/AD$29,0) -> 0.020401162 | AR70: 51717.66 | AS70: =IFERROR(AR70/AR$29,0) -> 0.017219344 | BF70: =AR70-AD70 -> -1978.7091 | BG70: =(AS70-AE70)*100 -> -0.31818182
B71: T&E | C71: SG&A | E71: 식대 / 출장비 | P71: 23450.02 | Q71: =IFERROR(P71/P$29,0) -> 0.012390845 | AD71: 12492.626 | AE71: =IFERROR(AD71/AD$29,0) -> 0.0047463933 | AR71: 3692.86 | AS71: =IFERROR(AR71/AR$29,0) -> 0.0012295341 | BF71: =AR71-AD71 -> -8799.7661 | BG71: =(AS71-AE71)*100 -> -0.35168592
B72: Rent | C72: SG&A | E72: 임차료 | P72: 24624.48 | Q72: =IFERROR(P72/P$29,0) -> 0.013011422 | AD72: 24658.39 | AE72: =IFERROR(AD72/AD$29,0) -> 0.0093686 | AR72: 24671.94 | AS72: =IFERROR(AR72/AR$29,0) -> 0.008214498 | BF72: =AR72-AD72 -> 13.55 | BG72: =(AS72-AE72)*100 -> -0.11541021
B73: Sample | C73: SG&A | E73: 샘플비/개발비 | P73: 5527.69 | Q73: =IFERROR(P73/P$29,0) -> 0.002920797 | AD73: 17149.874 | AE73: =IFERROR(AD73/AD$29,0) -> 0.0065158474 | AR73: 750 | AS73: =IFERROR(AR73/AR$29,0) -> 0.00024971176 | BF73: =AR73-AD73 -> -16399.874 | BG73: =(AS73-AE73)*100 -> -0.62661357
B74: Depreciation & Amortization | C74: SG&A | E74: 감가상각비 | P74: 4299.84 | Q74: =IFERROR(P74/P$29,0) -> 0.0022720087 | AD74: 4430.6163 | AE74: =IFERROR(AD74/AD$29,0) -> 0.0016833488 | AR74: 3925.54 | AS74: =IFERROR(AR74/AR$29,0) -> 0.0013070047 | BF74: =AR74-AD74 -> -505.07626 | BG74: =(AS74-AE74)*100 -> -0.037634417
B75: Other | C75: SG&A | E75: 기타비용 | P75: 15141.12 | Q75: =IFERROR(P75/P$29,0) -> 0.0080004736 | AD75: 32912.088 | AE75: =IFERROR(AD75/AD$29,0) -> 0.012504474 | AR75: 15248.44 | AS75: =IFERROR(AR75/AR$29,0) -> 0.005076953 | BF75: =AR75-AD75 -> -17663.648 | BG75: =(AS75-AE75)*100 -> -0.74275206 | BH75: =+AR56 -> 315403.06
E76: 영업비 소계 | P76: =SUM(P56,P61,P70:P75) -> 715793.06 | Q76: =IFERROR(P76/P$29,0) -> 0.3782206 | T76: =SUM(T57:T75) -> 0 | U76: =SUM(U57:U75) -> 0 | V76: =SUM(V57:V75) -> 0 | W76: =SUM(W57:W75) -> 0 | X76: =SUM(X57:X75) -> 0 | Y76: =SUM(Y57:Y75) -> 0 | Z76: =SUM(Z57:Z75) -> 0 | AA76: =SUM(AA57:AA75) -> 0 | AD76: =SUM(AD56,AD61,AD70:AD75) -> 597242.32 | AE76: =IFERROR(AD76/AD$29,0) -> 0.22691361 | AH76: =SUM(AH57:AH75) -> 0 | AI76: =SUM(AI57:AI75) -> 0 | AJ76: =SUM(AJ57:AJ75) -> 0 | AK76: =SUM(AK57:AK75) -> 0 | AL76: =SUM(AL57:AL75) -> 0 | AM76: =SUM(AM57:AM75) -> 0 | AN76: =SUM(AN57:AN75) -> 0 | AO76: =SUM(AO57:AO75) -> 0 | AR76: =SUM(AR56,AR61,AR70:AR75) -> 528061.54 | AS76: =IFERROR(AR76/AR$29,0) -> 0.17581757 | AV76: =SUM(AV57:AV75) -> 0 | AW76: =SUM(AW57:AW75) -> 0 | AX76: =SUM(AX57:AX75) -> 0 | AY76: =SUM(AY57:AY75) -> 0 | AZ76: =SUM(AZ57:AZ75) -> 0 | BA76: =SUM(BA57:BA75) -> 0 | BB76: =SUM(BB57:BB75) -> 0 | BC76: =SUM(BC57:BC75) -> 0 | BF76: =AR76-AD76 -> -69180.777 | BG76: =(AS76-AE76)*100 -> -5.1096048 | BH76: =+BH75/AR76 -> 0.59728466
E78: 영업이익 | P78: =P53-P76 -> -53395.5 | Q78: =IFERROR(P78/P$29,0) -> -0.02821385 | AD78: =AD53-AD76 -> 275432.27 | AE78: =IFERROR(AD78/AD$29,0) -> 0.10464652 | AR78: =AR53-AR76 -> 46173.09 | AS78: =IFERROR(AR78/AR$29,0) -> 0.015373285 | BF78: =AR78-AD78 -> -229259.18 | BG78: =(AS78-AE78)*100 -> -8.927324
E80: 영업외손익
E82: 이자비용
E83: 경상이익

Sheet YTD -12월까지
W3: 운반비 | X3: 1243576.5 | Z3: -9862.22
W4: 보관료 / 물류용역비 | X4: 1008752.2 | AC4: -327641.24
F5: =S53/F53 -> 0.50957982 | H5: =U53/H53 -> 0.70696349 | J5: =W53/J53 -> 0.22920995 | L5: =Y53/L53 -> 0.85198482 | U5: 273377.46 | W5: 지급수수료 | X5: 1986204.3
S6: =+'11월'!AH27 -> 119067 | W6: 촬영비 | X6: 0 | AC6: =+AC29-[1]미국연간!$AP$38 -> 2009592.8
E7: Date | F7: =EDATE($E$5,-12) -> #NUM! | H7: =F7 -> #NUM! | J7: =H7 -> #NUM! | L7: =J7 -> #NUM! | N7: =L7 -> #NUM! | P7: =L7 -> #NUM! | S7: =EDATE($E$5,0) -> 0 | U7: =S7 -> 0 | W7: 광고비 | X7: 3994149 | Y7: =W7 -> 광고비 | AA7: =Y7 -> 광고비 | AC7: =Y7 -> 광고비 | AG7: =EDATE($E$5,0) -> 0 | AI7: =AG7 -> 0 | AK7: =AI7 -> 0 | AO7: =AM7 -> 0 | AQ7: =AM7 -> 0
E8: Category | F8: Wholesale | H8: Ecommerce (US) | J8: Ecommerce (EU) | L8: License | N8: Other Income | S8: Wholesale | U8: Ecommerce (US) | W8: Ecommerce (EU) | Y8: License | AA8: Other Income | AG8: Wholesale | AI8: Ecommerce (US) | AK8: Ecommerce (EU) | AO8: Other Income
E9: M | F9: =MONTH(F7) -> #NUM! | S9: =MONTH(S7) -> 1 | AG9: =MONTH(AG7) -> 1
E10: Q | F10: ="Q"&ROUNDUP(MONTH(F7)/3,0)&"'"&TEXT(F7,"yy") -> #NUM! | S10: ="Q"&ROUNDUP(MONTH(S7)/3,0)&"'"&TEXT(S7,"yy") -> Q1'00 | AG10: ="Q"&ROUNDUP(MONTH(AG7)/3,0)&"'"&TEXT(AG7,"yy") -> Q1'00
E11: H | F11: ="H"&ROUNDUP(MONTH(F7)/6,0)&"'"&TEXT(F7,"yy") -> #NUM! | S11: ="H"&ROUNDUP(MONTH(S7)/6,0)&"'"&TEXT(S7,"yy") -> H1'00 | AG11: ="H"&ROUNDUP(MONTH(AG7)/6,0)&"'"&TEXT(AG7,"yy") -> H1'00
E12: Y | F12: =YEAR(F7) -> #NUM! | S12: =YEAR(S7) -> 1900 | AG12: =YEAR(AG7) -> 1900
E13: Actual / Forecast | F13: Actual | S13: Actual | AG13: Actual
S14: =+S15-S29 -> 0
S15: =+[1]미국연간!$AQ$32 -> 1514946.4 | U15: -521248.54 | AG15: vs 전년
F17: STO 24년 10월 누적 | S17: STO 25년 10월 누적 | AG17: STO 25년 10월 누적 전년대비
F18: 홀세일(미국) | H18: 온라인(미국) | J18: 온라인(유럽) | L18: 라이선스 | N18: 기타 | P18: STO 합계 | S18: 홀세일(미국) | U18: 온라인(미국) | W18: 온라인(유럽) | Y18: 라이선스 | AA18: 기타 | AC18: STO 합계 | AG18: 홀세일(미국) | AI18: 온라인(미국) | AK18: 온라인(유럽) | AM18: 라이선스 | AO18: 기타 | AQ18: STO 합계
E19: STO/STIP
E20: 라이선스
E21: 홀세일(미국)
E22: 온라인(미국)
E23: 할인율(%)
E24: 생산원가율(%)
E25: 온라인(유럽)
E26: 매출액(할인전) 계
E27: 총매출 (MSRP) | F27: =+'1월'!F27+'2월'!F27+'3월'!F27+'4월'!F27+'5월'!F27+'6월'!F27+'7월'!F27+'8월'!F27+'9월'!F27+'10월'!F27+'11월'!F27+'12월'!F27 -> 6580789 | H27: =+'1월'!H27+'2월'!H27+'3월'!H27+'4월'!H27+'5월'!H27+'6월'!H27+'7월'!H27+'8월'!H27+'9월'!H27+'10월'!H27+'11월'!H27+'12월'!H27 -> 24361330 | J27: =+'1월'!J27+'2월'!J27+'3월'!J27+'4월'!J27+'5월'!J27+'6월'!J27+'7월'!J27+'8월'!J27+'9월'!J27+'10월'!J27+'11월'!J27+'12월'!J27 -> 2278389 | L27: =+'1월'!L27+'2월'!L27+'3월'!L27+'4월'!L27+'5월'!L27+'6월'!L27+'7월'!L27+'8월'!L27+'9월'!L27+'10월'!L27+'11월'!L27+'12월'!L27 -> 976931.6 | N27: =+'1월'!N27+'2월'!N27+'3월'!N27+'4월'!N27+'5월'!N27+'6월'!N27+'7월'!N27+'8월'!N27+'9월'!N27+'10월'!N27+'11월'!N27+'12월'!N27 -> 216333.55 | P27: =SUM(F27,H27,J27,L27,N27) -> 34413773 | S27: =+'1월'!AH27+'2월'!AH27+'3월'!AH27+'4월'!AH27+'5월'!AH27+'6월'!AH27+'7월'!AH27+'8월'!AH27+'9월'!AH27+'10월'!AH27+'11월'!AH27+'12월'!AH27 -> 4134919 | U27: =+'1월'!AJ27+'2월'!AJ27+'3월'!AJ27+'4월'!AJ27+'5월'!AJ27+'6월'!AJ27+'7월'!AJ27+'8월'!AJ27+'9월'!AJ27+'10월'!AJ27+'11월'!AJ27+'12월'!AJ27 -> 38162577 | W27: =+'1월'!AL27+'2월'!AL27+'3월'!AL27+'4월'!AL27+'5월'!AL27+'6월'!AL27+'7월'!AL27+'8월'!AL27+'9월'!AL27+'10월'!AL27+'11월'!AL27+'12월'!AL27 -> 1491938 | Y27: =+'1월'!AN27+'2월'!AN27+'3월'!AN27+'4월'!AN27+'5월'!AN27+'6월'!AN27+'7월'!AN27+'8월'!AN27+'9월'!AN27+'10월'!AN27+'11월'!AN27+'12월'!AN27 -> 832330.89 | AA27: =+'1월'!AP27+'2월'!AP27+'3월'!AP27+'4월'!AP27+'5월'!AP27+'6월'!AP27+'7월'!AP27+'8월'!AP27+'9월'!AP27+'10월'!AP27+'11월'!AP27+'12월'!AP27 -> 149791.74 | AC27: =SUM(S27,U27,W27,Y27,AA27) -> 44771557 | AG27: =+S27-F27 -> -2445870 | AI27: =+U27-H27 -> 13801247 | AK27: =+W27-J27 -> -786451 | AM27: =+Y27-L27 -> -144600.71 | AO27: =+AA27-N27 -> -66541.81 | AQ27: =+AC27-P27 -> 10357783
E28: 할인액 | F28: =F27-F29 -> 4051936.1 | H28: =H27-H29 -> 9113308.4 | J28: =J27-J29 -> 439345.76 | L28: =L27-L29 -> 0 | N28: =N27-N29 -> 0 | P28: =SUM(F28,H28,J28,L28,N28) -> 13604590 | S28: =S27-S29 -> 2619972.6 | U28: =U27-U29 -> 18659741 | W28: =W27-W29 -> 673067.61 | Y28: =Y27-Y29 -> 0 | AA28: =AA27-AA29 -> 0 | AC28: =SUM(S28,U28,W28,Y28,AA28) -> 21952781 | AG28: =+S28-F28 -> -1431963.5 | AI28: =+U28-H28 -> 9546432.4 | AK28: =+W28-J28 -> 233721.85 | AM28: =+Y28-L28 -> 0 | AO28: =+AA28-N28 -> 0 | AQ28: =+AC28-P28 -> 8348190.7
C29: Revenue | E29: 실판매 | F29: =+'1월'!F29+'2월'!F29+'3월'!F29+'4월'!F29+'5월'!F29+'6월'!F29+'7월'!F29+'8월'!F29+'9월'!F29+'10월'!F29+'11월'!F29+'12월'!F29 -> 2528852.9 | G29: =IFERROR(1-F29/F27,0) -> 0.61572193 | H29: =+'1월'!H29+'2월'!H29+'3월'!H29+'4월'!H29+'5월'!H29+'6월'!H29+'7월'!H29+'8월'!H29+'9월'!H29+'10월'!H29+'11월'!H29+'12월'!H29 -> 15248022 | I29: =IFERROR(1-H29/H27,0) -> 0.37408912 | J29: =+'1월'!J29+'2월'!J29+'3월'!J29+'4월'!J29+'5월'!J29+'6월'!J29+'7월'!J29+'8월'!J29+'9월'!J29+'10월'!J29+'11월'!J29+'12월'!J29 -> 1839043.2 | K29: =IFERROR(1-J29/J27,0) -> 0.19283176 | L29: =+'1월'!L29+'2월'!L29+'3월'!L29+'4월'!L29+'5월'!L29+'6월'!L29+'7월'!L29+'8월'!L29+'9월'!L29+'10월'!L29+'11월'!L29+'12월'!L29 -> 976931.6 | M29: =IFERROR(1-L29/L27,0) -> 0 | N29: =+'1월'!N29+'2월'!N29+'3월'!N29+'4월'!N29+'5월'!N29+'6월'!N29+'7월'!N29+'8월'!N29+'9월'!N29+'10월'!N29+'11월'!N29+'12월'!N29 -> 216333.55 | O29: =IFERROR(1-N29/N27,0) -> 0 | P29: =SUM(F29,H29,J29,L29,N29) -> 20809183 | Q29: =IFERROR(1-P29/P27,0) -> 0.395324 | S29: =+'1월'!AH29+'2월'!AH29+'3월'!AH29+'4월'!AH29+'5월'!AH29+'6월'!AH29+'7월'!AH29+'8월'!AH29+'9월'!AH29+'10월'!AH29+'11월'!AH29+'12월'!AH29 -> 1514946.4 | T29: =IFERROR(1-S29/S27,0) -> 0.63362127 | U29: =+'1월'!AJ29+'2월'!AJ29+'3월'!AJ29+'4월'!AJ29+'5월'!AJ29+'6월'!AJ29+'7월'!AJ29+'8월'!AJ29+'9월'!AJ29+'10월'!AJ29+'11월'!AJ29+'12월'!AJ29 -> 19502836 | V29: =IFERROR(1-U29/U27,0) -> 0.4889539 | W29: =+'1월'!AL29+'2월'!AL29+'3월'!AL29+'4월'!AL29+'5월'!AL29+'6월'!AL29+'7월'!AL29+'8월'!AL29+'9월'!AL29+'10월'!AL29+'11월'!AL29+'12월'!AL29 -> 818870.39 | X29: =IFERROR(1-W29/W27,0) -> 0.45113645 | Y29: =+'1월'!AN29+'2월'!AN29+'3월'!AN29+'4월'!AN29+'5월'!AN29+'6월'!AN29+'7월'!AN29+'8월'!AN29+'9월'!AN29+'10월'!AN29+'11월'!AN29+'12월'!AN29 -> 832330.89 | Z29: =IFERROR(1-Y29/Y27,0) -> 0 | AA29: =+'1월'!AP29+'2월'!AP29+'3월'!AP29+'4월'!AP29+'5월'!AP29+'6월'!AP29+'7월'!AP29+'8월'!AP29+'9월'!AP29+'10월'!AP29+'11월'!AP29+'12월'!AP29 -> 149791.74 | AB29: =IFERROR(1-AA29/AA27,0) -> 0 | AC29: =SUM(S29,U29,W29,Y29,AA29) -> 22818776 | AD29: =IFERROR(1-AC29/AC27,0) -> 0.49032874 | AG29: =+S29-F29 -> -1013906.5 | AH29: =(T29-G29)*100 -> 1.7899335 | AI29: =+U29-H29 -> 4254814.6 | AJ29: =(V29-I29)*100 -> 11.486478 | AK29: =+W29-J29 -> -1020172.8 | AL29: =(X29-K29)*100 -> 25.830469 | AM29: =+Y29-L29 -> -144600.71 | AN29: =(Z29-M29)*100 -> 0 | AO29: =+AA29-N29 -> -66541.81 | AP29: =(AB29-O29)*100 -> 0 | AQ29: =+AC29-P29 -> 2009592.8 | AR29: =(AD29-Q29)*100 -> 9.5004746
E30: 제품매출 | AI30: =+U30-H30 -> 0 | AJ30: =(V30-I30)*100 -> 0 | AK30: =+W30-J30 -> 0 | AL30: =(X30-K30)*100 -> 0 | AM30: =+Y30-L30 -> 0 | AN30: =(Z30-M30)*100 -> 0 | AO30: =+AA30-N30 -> 0 | AP30: =(AB30-O30)*100 -> 0 | AQ30: =+AC30-P30 -> 0
E31: 기타매출 | AI31: =+U31-H31 -> 0 | AJ31: =(V31-I31)*100 -> 0 | AK31: =+W31-J31 -> 0 | AL31: =(X31-K31)*100 -> 0 | AM31: =+Y31-L31 -> 0 | AN31: =(Z31-M31)*100 -> 0 | AO31: =+AA31-N31 -> 0 | AP31: =(AB31-O31)*100 -> 0 | AQ31: =+AC31-P31 -> 0
AI32: =+U32-H32 -> 0 | AJ32: =(V32-I32)*100 -> 0 | AK32: =+W32-J32 -> 0 | AL32: =(X32-K32)*100 -> 0 | AM32: =+Y32-L32 -> 0 | AN32: =(Z32-M32)*100 -> 0 | AO32: =+AA32-N32 -> 0 | AP32: =(AB32-O32)*100 -> 0 | AQ32: =+AC32-P32 -> 0
E33: 계획대비 | F33: n/a | G33: n/a | H33: n/a | I33: n/a | J33: n/a | K33: n/a | L33: n/a | M33: n/a | N33: n/a | O33: n/a | P33: n/a | Q33: n/a | AD33: =IFERROR(AC29/#REF!-1,0) -> 0
E34: 전년대비 | F34: n/a | G34: n/a | H34: n/a | I34: n/a | J34: n/a | K34: n/a | L34: n/a | M34: n/a | N34: n/a | O34: n/a | P34: n/a | Q34: n/a | S34: =S29-F29 -> -1013906.5 | T34: =IFERROR(S29/F29-1,0) -> -0.40093534 | U34: =U29-H29 -> 4254814.6 | V34: =IFERROR(U29/H29-1,0) -> 0.27904044 | W34: =W29-J29 -> -1020172.8 | X34: =IFERROR(W29/J29-1,0) -> -0.55473021 | Y34: =Y29-L29 -> -144600.71 | Z34: =IFERROR(Y29/L29-1,0) -> -0.14801518 | AA34: =AA29-N29 -> -66541.81 | AB34: =IFERROR(AA29/N29-1,0) -> -0.30758895 | AC34: =AC29-P29 -> 2009592.8 | AD34: =IFERROR(AC29/P29-1,0) -> 0.096572401
AI35: =+U35-H35 -> 0 | AJ35: =(V35-I35)*100 -> 0 | AK35: =+W35-J35 -> 0 | AL35: =(X35-K35)*100 -> 0 | AM35: =+Y35-L35 -> 0 | AN35: =(Z35-M35)*100 -> 0 | AO35: =+AA35-N35 -> 0 | AP35: =(AB35-O35)*100 -> 0 | AQ35: =+AC35-P35 -> 0
C36: COGS | E36: 매출원가 | F36: =+'1월'!F36+'2월'!F36+'3월'!F36+'4월'!F36+'5월'!F36+'6월'!F36+'7월'!F36+'8월'!F36+'9월'!F36+'10월'!F36+'11월'!F36+'12월'!F36 -> 1244038.1 | G36: =IFERROR(F36/F$29,0) -> 0.4919377 | H36: =+'1월'!H36+'2월'!H36+'3월'!H36+'4월'!H36+'5월'!H36+'6월'!H36+'7월'!H36+'8월'!H36+'9월'!H36+'10월'!H36+'11월'!H36+'12월'!H36 -> 4574158.1 | I36: =IFERROR(H36/H$29,0) -> 0.29998371 | J36: =+'1월'!J36+'2월'!J36+'3월'!J36+'4월'!J36+'5월'!J36+'6월'!J36+'7월'!J36+'8월'!J36+'9월'!J36+'10월'!J36+'11월'!J36+'12월'!J36 -> 427578.23 | K36: =IFERROR(J36/J$29,0) -> 0.23250037 | L36: =+'1월'!L36+'2월'!L36+'3월'!L36+'4월'!L36+'5월'!L36+'6월'!L36+'7월'!L36+'8월'!L36+'9월'!L36+'10월'!L36+'11월'!L36+'12월'!L36 -> 0 | M36: =IFERROR(L36/L$29,0) -> 0 | N36: =+'1월'!N36+'2월'!N36+'3월'!N36+'4월'!N36+'5월'!N36+'6월'!N36+'7월'!N36+'8월'!N36+'9월'!N36+'10월'!N36+'11월'!N36+'12월'!N36 -> 391574.98 | O36: =IFERROR(N36/N$29,0) -> 1.810052 | P36: =SUM(F36,H36,J36,L36,N36) -> 6637349.4 | Q36: =IFERROR(P36/P$29,0) -> 0.31896252 | S36: =+'1월'!AH36+'2월'!AH36+'3월'!AH36+'4월'!AH36+'5월'!AH36+'6월'!AH36+'7월'!AH36+'8월'!AH36+'9월'!AH36+'10월'!AH36+'11월'!AH36+'12월'!AH36 -> 828369.69 | T36: =IFERROR(S36/S$29,0) -> 0.54679802 | U36: =+'1월'!AJ36+'2월'!AJ36+'3월'!AJ36+'4월'!AJ36+'5월'!AJ36+'6월'!AJ36+'7월'!AJ36+'8월'!AJ36+'9월'!AJ36+'10월'!AJ36+'11월'!AJ36+'12월'!AJ36 -> 8020662.5 | V36: =IFERROR(U36/U$29,0) -> 0.41125621 | W36: =+'1월'!AL36+'2월'!AL36+'3월'!AL36+'4월'!AL36+'5월'!AL36+'6월'!AL36+'7월'!AL36+'8월'!AL36+'9월'!AL36+'10월'!AL36+'11월'!AL36+'12월'!AL36 -> 328338.01 | X36: =IFERROR(W36/W$29,0) -> 0.40096457 | Y36: =+'1월'!AN36+'2월'!AN36+'3월'!AN36+'4월'!AN36+'5월'!AN36+'6월'!AN36+'7월'!AN36+'8월'!AN36+'9월'!AN36+'10월'!AN36+'11월'!AN36+'12월'!AN36 -> 0 | Z36: =IFERROR(Y36/Y$29,0) -> 0 | AA36: =+'1월'!AP36+'2월'!AP36+'3월'!AP36+'4월'!AP36+'5월'!AP36+'6월'!AP36+'7월'!AP36+'8월'!AP36+'9월'!AP36+'10월'!AP36+'11월'!AP36+'12월'!AP36 -> -106302.23 | AB36: =IFERROR(AA36/AA$29,0) -> -0.70966683 | AC36: =SUM(S36,U36,W36,Y36,AA36) -> 9071068 | AD36: =IFERROR(AC36/AC$29,0) -> 0.3975265 | AG36: =+S36-F36 -> -415668.39 | AH36: =(T36-G36)*100 -> 5.486032 | AI36: =+U36-H36 -> 3446504.4 | AJ36: =(V36-I36)*100 -> 11.12725 | AK36: =+W36-J36 -> -99240.22 | AL36: =(X36-K36)*100 -> 16.84642 | AM36: =+Y36-L36 -> 0 | AN36: =(Z36-M36)*100 -> 0 | AO36: =+AA36-N36 -> -497877.21 | AP36: =(AB36-O36)*100 -> -251.97189 | AQ36: =+AC36-P36 -> 2433718.6 | AR36: =(AD36-Q36)*100 -> 7.8563978
E37: 기타원가 | F37: =+'1월'!F37+'2월'!F37+'3월'!F37+'4월'!F37+'5월'!F37+'6월'!F37+'7월'!F37+'8월'!F37+'9월'!F37+'10월'!F37 -> 0 | H37: =+'1월'!H37+'2월'!H37+'3월'!H37+'4월'!H37+'5월'!H37+'6월'!H37+'7월'!H37+'8월'!H37+'9월'!H37+'10월'!H37 -> 0 | J37: =+'1월'!J37+'2월'!J37+'3월'!J37+'4월'!J37+'5월'!J37+'6월'!J37+'7월'!J37+'8월'!J37+'9월'!J37+'10월'!J37 -> 0 | L37: =+'1월'!L37+'2월'!L37+'3월'!L37+'4월'!L37+'5월'!L37+'6월'!L37+'7월'!L37+'8월'!L37+'9월'!L37+'10월'!L37 -> 0 | N37: =+'1월'!N37+'2월'!N37+'3월'!N37+'4월'!N37+'5월'!N37+'6월'!N37+'7월'!N37+'8월'!N37+'9월'!N37+'10월'!N37 -> 0 | S37: =+'1월'!AH37+'2월'!AH37+'3월'!AH37+'4월'!AH37+'5월'!AH37+'6월'!AH37+'7월'!AH37+'8월'!AH37+'9월'!AH37+'10월'!AH37 -> 0 | U37: =+'1월'!AJ37+'2월'!AJ37+'3월'!AJ37+'4월'!AJ37+'5월'!AJ37+'6월'!AJ37+'7월'!AJ37+'8월'!AJ37+'9월'!AJ37+'10월'!AJ37 -> 0 | W37: =+'1월'!AL37+'2월'!AL37+'3월'!AL37+'4월'!AL37+'5월'!AL37+'6월'!AL37+'7월'!AL37+'8월'!AL37+'9월'!AL37+'10월'!AL37 -> 0 | Y37: =+'1월'!AN37+'2월'!AN37+'3월'!AN37+'4월'!AN37+'5월'!AN37+'6월'!AN37+'7월'!AN37+'8월'!AN37+'9월'!AN37+'10월'!AN37 -> 0 | AG37: =+S37-F37 -> 0 | AH37: =(T37-G37)*100 -> 0 | AI37: =+U37-H37 -> 0 | AJ37: =(V37-I37)*100 -> 0 | AK37: =+W37-J37 -> 0 | AL37: =(X37-K37)*100 -> 0 | AM37: =+Y37-L37 -> 0 | AN37: =(Z37-M37)*100 -> 0 | AO37: =+AA37-N37 -> 0 | AP37: =(AB37-O37)*100 -> 0 | AQ37: =+AC37-P37 -> 0 | AR37: =(AD37-Q37)*100 -> 0
E38: 분기원가조정 | F38: =+'1월'!F38+'2월'!F38+'3월'!F38+'4월'!F38+'5월'!F38+'6월'!F38+'7월'!F38+'8월'!F38+'9월'!F38+'10월'!F38 -> 0 | H38: =+'1월'!H38+'2월'!H38+'3월'!H38+'4월'!H38+'5월'!H38+'6월'!H38+'7월'!H38+'8월'!H38+'9월'!H38+'10월'!H38 -> 0 | J38: =+'1월'!J38+'2월'!J38+'3월'!J38+'4월'!J38+'5월'!J38+'6월'!J38+'7월'!J38+'8월'!J38+'9월'!J38+'10월'!J38 -> 0 | L38: =+'1월'!L38+'2월'!L38+'3월'!L38+'4월'!L38+'5월'!L38+'6월'!L38+'7월'!L38+'8월'!L38+'9월'!L38+'10월'!L38 -> 0 | N38: =+'1월'!N38+'2월'!N38+'3월'!N38+'4월'!N38+'5월'!N38+'6월'!N38+'7월'!N38+'8월'!N38+'9월'!N38+'10월'!N38 -> 0 | S38: =+'1월'!AH38+'2월'!AH38+'3월'!AH38+'4월'!AH38+'5월'!AH38+'6월'!AH38+'7월'!AH38+'8월'!AH38+'9월'!AH38+'10월'!AH38 -> 0 | U38: =+'1월'!AJ38+'2월'!AJ38+'3월'!AJ38+'4월'!AJ38+'5월'!AJ38+'6월'!AJ38+'7월'!AJ38+'8월'!AJ38+'9월'!AJ38+'10월'!AJ38 -> 0 | W38: =+'1월'!AL38+'2월'!AL38+'3월'!AL38+'4월'!AL38+'5월'!AL38+'6월'!AL38+'7월'!AL38+'8월'!AL38+'9월'!AL38+'10월'!AL38 -> 0 | Y38: =+'1월'!AN38+'2월'!AN38+'3월'!AN38+'4월'!AN38+'5월'!AN38+'6월'!AN38+'7월'!AN38+'8월'!AN38+'9월'!AN38+'10월'!AN38 -> 0 | AA38: =+'1월'!AP38+'2월'!AP38+'3월'!AP38+'4월'!AP38+'5월'!AP38+'6월'!AP38+'7월'!AP38+'8월'!AP38+'9월'!AP38+'10월'!AP38 -> 0 | AG38: =+S38-F38 -> 0 | AH38: =(T38-G38)*100 -> 0 | AI38: =+U38-H38 -> 0 | AJ38: =(V38-I38)*100 -> 0 | AK38: =+W38-J38 -> 0 | AL38: =(X38-K38)*100 -> 0 | AM38: =+Y38-L38 -> 0 | AN38: =(Z38-M38)*100 -> 0 | AO38: =+AA38-N38 -> 0 | AP38: =(AB38-O38)*100 -> 0 | AQ38: =+AC38-P38 -> 0 | AR38: =(AD38-Q38)*100 -> 0
E39: (생산원가율, M/U) | F39: =IFERROR(F36/F27,0) -> 0.18904087 | G39: =IFERROR(1/F39,0) -> 5.2898614 | H39: =IFERROR(H36/H27,0) -> 0.18776307 | I39: =IFERROR(1/H39,0) -> 5.3258609 | J39: =IFERROR(J36/J27,0) -> 0.18766691 | K39: =IFERROR(1/J39,0) -> 5.3285898 | L39: =IFERROR(L36/L27,0) -> 0 | M39: =IFERROR(1/L39,0) -> 0 | N39: =IFERROR(N36/N27,0) -> 1.810052 | O39: =IFERROR(1/N39,0) -> 0.55247031 | P39: =IFERROR(P36/P27,0) -> 0.19286898 | Q39: =IFERROR(1/P39,0) -> 5.1848669 | S39: =IFERROR(S36/S27,0) -> 0.20033517 | T39: =IFERROR(1/S39,0) -> 4.9916348 | U39: =IFERROR(U36/U27,0) -> 0.21017088 | V39: =IFERROR(1/U39,0) -> 4.758033 | W39: =IFERROR(W36/W27,0) -> 0.22007484 | X39: =IFERROR(1/W39,0) -> 4.5439089 | Y39: =IFERROR(Y36/Y27,0) -> 0 | Z39: =IFERROR(1/Y39,0) -> 0 | AA39: =IFERROR(AA36/AA27,0) -> -0.70966683 | AB39: =IFERROR(1/AA39,0) -> -1.4091119 | AC39: =IFERROR(AC36/AC27,0) -> 0.20260783 | AD39: =IFERROR(1/AC39,0) -> 4.9356434 | AG39: =+S39-F39 -> 0.011294297 | AH39: =(T39-G39)*100 -> -29.822655 | AI39: =+U39-H39 -> 0.022407812 | AJ39: =(V39-I39)*100 -> -56.782791 | AK39: =+W39-J39 -> 0.032407923 | AL39: =(X39-K39)*100 -> -78.468093 | AM39: =+Y39-L39 -> 0 | AN39: =(Z39-M39)*100 -> 0 | AO39: =+AA39-N39 -> -2.5197189 | AP39: =(AB39-O39)*100 -> -196.15822 | AQ39: =+AC39-P39 -> 0.0097388482 | AR39: =(AD39-Q39)*100 -> -24.922349
E40: 매출총이익 | F40: =F29-F36 -> 1284814.8 | G40: =IFERROR(F40/F29,0) -> 0.5080623 | H40: =H29-H36 -> 10673863 | I40: =IFERROR(H40/H29,0) -> 0.70001629 | J40: =J29-J36 -> 1411465 | K40: =IFERROR(J40/J29,0) -> 0.76749963 | L40: =L29-L36 -> 976931.6 | M40: =IFERROR(L40/L29,0) -> 1 | N40: =N29-N36 -> -175241.43 | O40: =IFERROR(N40/N29,0) -> -0.81005202 | P40: =P29-P36 -> 14171833 | Q40: =IFERROR(P40/P$29,0) -> 0.68103748 | S40: =S29-S36 -> 686576.7 | T40: =IFERROR(S40/S29,0) -> 0.45320198 | U40: =U29-U36 -> 11482174 | V40: =IFERROR(U40/U29,0) -> 0.58874379 | W40: =W29-W36 -> 490532.38 | X40: =IFERROR(W40/W29,0) -> 0.59903543 | Y40: =Y29-Y36 -> 832330.89 | Z40: =IFERROR(Y40/Y29,0) -> 1 | AA40: =AA29-AA36 -> 256093.97 | AB40: =IFERROR(AA40/AA29,0) -> 1.7096668 | AC40: =AC29-AC36 -> 13747708 | AD40: =IFERROR(AC40/AC$29,0) -> 0.6024735 | AG40: =+S40-F40 -> -598238.11 | AH40: =(T40-G40)*100 -> -5.486032 | AI40: =+U40-H40 -> 808310.25 | AJ40: =(V40-I40)*100 -> -11.12725 | AK40: =+W40-J40 -> -920932.63 | AL40: =(X40-K40)*100 -> -16.84642 | AM40: =+Y40-L40 -> -144600.71 | AN40: =(Z40-M40)*100 -> 0 | AO40: =+AA40-N40 -> 431335.4 | AP40: =(AB40-O40)*100 -> 251.97189 | AQ40: =+AC40-P40 -> -424125.8 | AR40: =(AD40-Q40)*100 -> -7.8563978
AI41: =+U41-H41 -> 0 | AJ41: =(V41-I41)*100 -> 0 | AK41: =+W41-J41 -> 0 | AL41: =(X41-K41)*100 -> 0 | AM41: =+Y41-L41 -> 0 | AN41: =(Z41-M41)*100 -> 0 | AO41: =+AA41-N41 -> 0 | AP41: =(AB41-O41)*100 -> 0 | AQ41: =+AC41-P41 -> 0 | AR41: =(AD41-Q41)*100 -> 0
E42: 직접비 | F42: =+'1월'!F42+'2월'!F42+'3월'!F42+'4월'!F42+'5월'!F42+'6월'!F42+'7월'!F42+'8월'!F42+'9월'!F42+'10월'!F42 -> 0 | AI42: =+U42-H42 -> 0 | AJ42: =(V42-I42)*100 -> 0 | AK42: =+W42-J42 -> 0 | AL42: =(X42-K42)*100 -> 0 | AM42: =+Y42-L42 -> 0 | AN42: =(Z42-M42)*100 -> 0 | AO42: =+AA42-N42 -> 0 | AP42: =(AB42-O42)*100 -> 0 | AQ42: =+AC42-P42 -> 0 | AR42: =(AD42-Q42)*100 -> 0
E43: 운반비/보관료/ 물류용역비 | F43: =+'1월'!F43+'2월'!F43+'3월'!F43+'4월'!F43+'5월'!F43+'6월'!F43+'7월'!F43+'8월'!F43+'9월'!F43+'10월'!F43+'11월'!F43+'12월'!F43 -> 173892.84 | G43: =IFERROR(F43/F$29,0) -> 0.068763525 | H43: =+'1월'!H43+'2월'!H43+'3월'!H43+'4월'!H43+'5월'!H43+'6월'!H43+'7월'!H43+'8월'!H43+'9월'!H43+'10월'!H43+'11월'!H43+'12월'!H43 -> 1709442.8 | I43: =IFERROR(H43/H$29,0) -> 0.11210915 | J43: =+'1월'!J43+'2월'!J43+'3월'!J43+'4월'!J43+'5월'!J43+'6월'!J43+'7월'!J43+'8월'!J43+'9월'!J43+'10월'!J43+'11월'!J43+'12월'!J43 -> 306700.04 | K43: =IFERROR(J43/J$29,0) -> 0.16677152 | L43: =+'1월'!L43+'2월'!L43+'3월'!L43+'4월'!L43+'5월'!L43+'6월'!L43+'7월'!L43+'8월'!L43+'9월'!L43+'10월'!L43+'11월'!L43+'12월'!L43 -> 0 | M43: =IFERROR(L43/L$29,0) -> 0 | N43: =+'1월'!N43+'2월'!N43+'3월'!N43+'4월'!N43+'5월'!N43+'6월'!N43+'7월'!N43+'8월'!N43+'9월'!N43+'10월'!N43 -> 0 | O43: =IFERROR(N43/N$29,0) -> 0 | P43: =SUM(F43,H43,J43,L43,N43) -> 2190035.7 | Q43: =IFERROR(P43/P$29,0) -> 0.10524371 | S43: =+'1월'!AH43+'2월'!AH43+'3월'!AH43+'4월'!AH43+'5월'!AH43+'6월'!AH43+'7월'!AH43+'8월'!AH43+'9월'!AH43+'10월'!AH43+'11월'!AH43+'12월'!AH43 -> 105028.78 | T43: =IFERROR(S43/S$29,0) -> 0.069328381 | U43: =+'1월'!AJ43+'2월'!AJ43+'3월'!AJ43+'4월'!AJ43+'5월'!AJ43+'6월'!AJ43+'7월'!AJ43+'8월'!AJ43+'9월'!AJ43+'10월'!AJ43+'11월'!AJ43+'12월'!AJ43 -> 2342197.2 | V43: =IFERROR(U43/U$29,0) -> 0.12009521 | W43: =+'1월'!AL43+'2월'!AL43+'3월'!AL43+'4월'!AL43+'5월'!AL43+'6월'!AL43+'7월'!AL43+'8월'!AL43+'9월'!AL43+'10월'!AL43+'11월'!AL43+'12월'!AL43 -> 132744.02 | X43: =IFERROR(W43/W$29,0) -> 0.16210626 | Y43: =+'1월'!AN43+'2월'!AN43+'3월'!AN43+'4월'!AN43+'5월'!AN43+'6월'!AN43+'7월'!AN43+'8월'!AN43+'9월'!AN43+'10월'!AN43+'11월'!AN43 -> 0 | Z43: =IFERROR(Y43/Y$29,0) -> 0 | AA43: =+'1월'!AP43+'2월'!AP43+'3월'!AP43+'4월'!AP43+'5월'!AP43+'6월'!AP43+'7월'!AP43+'8월'!AP43+'9월'!AP43+'10월'!AP43+'11월'!AP43 -> 0 | AB43: =IFERROR(AA43/AA$29,0) -> 0 | AC43: =SUM(S43,U43,W43,Y43,AA43) -> 2579970 | AD43: =IFERROR(AC43/AC$29,0) -> 0.11306347 | AG43: =+S43-F43 -> -68864.06 | AH43: =(T43-G43)*100 -> 0.056485523 | AI43: =+U43-H43 -> 632754.39 | AJ43: =(V43-I43)*100 -> 0.79860548 | AK43: =+W43-J43 -> -173956.02 | AL43: =(X43-K43)*100 -> -0.46652575 | AM43: =+Y43-L43 -> 0 | AN43: =(Z43-M43)*100 -> 0 | AO43: =+AA43-N43 -> 0 | AP43: =(AB43-O43)*100 -> 0 | AQ43: =+AC43-P43 -> 389934.31 | AR43: =(AD43-Q43)*100 -> 0.78197581
B44: 운반비 | C44: 운반비 (-) | E44: 운반비 | F44: =+'1월'!F44+'2월'!F44+'3월'!F44+'4월'!F44+'5월'!F44+'6월'!F44+'7월'!F44+'8월'!F44+'9월'!F44+'10월'!F44+'11월'!F44+'12월'!F44 -> -22273.67 | G44: =IFERROR(F44/F$29,0) -> -0.0088078156 | H44: =+'1월'!H44+'2월'!H44+'3월'!H44+'4월'!H44+'5월'!H44+'6월'!H44+'7월'!H44+'8월'!H44+'9월'!H44+'10월'!H44+'11월'!H44+'12월'!H44 -> 923902.79 | I44: =IFERROR(H44/H$29,0) -> 0.06059165 | J44: =+'1월'!J44+'2월'!J44+'3월'!J44+'4월'!J44+'5월'!J44+'6월'!J44+'7월'!J44+'8월'!J44+'9월'!J44+'10월'!J44+'11월'!J44+'12월'!J44 -> 226929.6 | K44: =IFERROR(J44/J$29,0) -> 0.12339547 | L44: =+'1월'!L44+'2월'!L44+'3월'!L44+'4월'!L44+'5월'!L44+'6월'!L44+'7월'!L44+'8월'!L44+'9월'!L44+'10월'!L44+'11월'!L44+'12월'!L44 -> 0 | M44: =IFERROR(L44/L$29,0) -> 0 | N44: =+'1월'!N44+'2월'!N44+'3월'!N44+'4월'!N44+'5월'!N44+'6월'!N44+'7월'!N44+'8월'!N44+'9월'!N44+'10월'!N44 -> 0 | O44: =IFERROR(N44/N$29,0) -> 0 | P44: =SUM(F44,H44,J44,L44,N44) -> 1128558.7 | Q44: =IFERROR(P44/P$29,0) -> 0.054233688 | S44: =+'1월'!AH44+'2월'!AH44+'3월'!AH44+'4월'!AH44+'5월'!AH44+'6월'!AH44+'7월'!AH44+'8월'!AH44+'9월'!AH44+'10월'!AH44+'11월'!AH44+'12월'!AH44 -> -16615.53 | T44: =IFERROR(S44/S$29,0) -> -0.010967735 | U44: =+'1월'!AJ44+'2월'!AJ44+'3월'!AJ44+'4월'!AJ44+'5월'!AJ44+'6월'!AJ44+'7월'!AJ44+'8월'!AJ44+'9월'!AJ44+'10월'!AJ44+'11월'!AJ44+'12월'!AJ44 -> 1203805.9 | V44: =IFERROR(U44/U$29,0) -> 0.061724656 | W44: =+'1월'!AL44+'2월'!AL44+'3월'!AL44+'4월'!AL44+'5월'!AL44+'6월'!AL44+'7월'!AL44+'8월'!AL44+'9월'!AL44+'10월'!AL44+'11월'!AL44+'12월'!AL44 -> 46523.97 | X44: =IFERROR(W44/W$29,0) -> 0.056814815 | Y44: =+'1월'!AN44+'2월'!AN44+'3월'!AN44+'4월'!AN44+'5월'!AN44+'6월'!AN44+'7월'!AN44+'8월'!AN44+'9월'!AN44+'10월'!AN44+'11월'!AN44 -> 0 | Z44: =IFERROR(Y44/Y$29,0) -> 0 | AA44: =+'1월'!AP44+'2월'!AP44+'3월'!AP44+'4월'!AP44+'5월'!AP44+'6월'!AP44+'7월'!AP44+'8월'!AP44+'9월'!AP44+'10월'!AP44+'11월'!AP44 -> 0 | AB44: =IFERROR(AA44/AA$29,0) -> 0 | AC44: =SUM(S44,U44,W44,Y44,AA44) -> 1233714.3 | AD44: =IFERROR(AC44/AC$29,0) -> 0.054065753 | AG44: =+S44-F44 -> 5658.14 | AH44: =(T44-G44)*100 -> -0.2159919 | AI44: =+U44-H44 -> 279903.06 | AJ44: =(V44-I44)*100 -> 0.11330055 | AK44: =+W44-J44 -> -180405.63 | AL44: =(X44-K44)*100 -> -6.6580652 | AM44: =+Y44-L44 -> 0 | AN44: =(Z44-M44)*100 -> 0 | AO44: =+AA44-N44 -> 0 | AP44: =(AB44-O44)*100 -> 0 | AQ44: =+AC44-P44 -> 105155.57 | AR44: =(AD44-Q44)*100 -> -0.016793431
B45: 보관료 | E45: 보관료 | F45: =+'1월'!F45+'2월'!F45+'3월'!F45+'4월'!F45+'5월'!F45+'6월'!F45+'7월'!F45+'8월'!F45+'9월'!F45+'10월'!F45+'11월'!F45+'12월'!F45 -> 105768.18 | G45: =IFERROR(F45/F$29,0) -> 0.041824568 | H45: =+'1월'!H45+'2월'!H45+'3월'!H45+'4월'!H45+'5월'!H45+'6월'!H45+'7월'!H45+'8월'!H45+'9월'!H45+'10월'!H45+'11월'!H45+'12월'!H45 -> 217954.23 | I45: =IFERROR(H45/H$29,0) -> 0.014293935 | J45: =+'1월'!J45+'2월'!J45+'3월'!J45+'4월'!J45+'5월'!J45+'6월'!J45+'7월'!J45+'8월'!J45+'9월'!J45+'10월'!J45+'11월'!J45+'12월'!J45 -> 29481.32 | K45: =IFERROR(J45/J$29,0) -> 0.016030792 | L45: =+'1월'!L45+'2월'!L45+'3월'!L45+'4월'!L45+'5월'!L45+'6월'!L45+'7월'!L45+'8월'!L45+'9월'!L45+'10월'!L45+'11월'!L45+'12월'!L45 -> 0 | M45: =IFERROR(L45/L$29,0) -> 0 | N45: =+'1월'!N45+'2월'!N45+'3월'!N45+'4월'!N45+'5월'!N45+'6월'!N45+'7월'!N45+'8월'!N45+'9월'!N45+'10월'!N45 -> 0 | O45: =IFERROR(N45/N$29,0) -> 0 | P45: =SUM(F45,H45,J45,L45,N45) -> 353203.73 | Q45: =IFERROR(P45/P$29,0) -> 0.016973455 | S45: =+'1월'!AH45+'2월'!AH45+'3월'!AH45+'4월'!AH45+'5월'!AH45+'6월'!AH45+'7월'!AH45+'8월'!AH45+'9월'!AH45+'10월'!AH45+'11월'!AH45+'12월'!AH45 -> 57280.16 | T45: =IFERROR(S45/S$29,0) -> 0.037810024 | U45: =+'1월'!AJ45+'2월'!AJ45+'3월'!AJ45+'4월'!AJ45+'5월'!AJ45+'6월'!AJ45+'7월'!AJ45+'8월'!AJ45+'9월'!AJ45+'10월'!AJ45+'11월'!AJ45+'12월'!AJ45 -> 367320.8 | V45: =IFERROR(U45/U$29,0) -> 0.018834225 | W45: =+'1월'!AL45+'2월'!AL45+'3월'!AL45+'4월'!AL45+'5월'!AL45+'6월'!AL45+'7월'!AL45+'8월'!AL45+'9월'!AL45+'10월'!AL45+'11월'!AL45+'12월'!AL45 -> 19552.54 | X45: =IFERROR(W45/W$29,0) -> 0.023877454 | Y45: =+'1월'!AN45+'2월'!AN45+'3월'!AN45+'4월'!AN45+'5월'!AN45+'6월'!AN45+'7월'!AN45+'8월'!AN45+'9월'!AN45+'10월'!AN45+'11월'!AN45 -> 0 | Z45: =IFERROR(Y45/Y$29,0) -> 0 | AA45: =+'1월'!AP45+'2월'!AP45+'3월'!AP45+'4월'!AP45+'5월'!AP45+'6월'!AP45+'7월'!AP45+'8월'!AP45+'9월'!AP45+'10월'!AP45+'11월'!AP45 -> 0 | AB45: =IFERROR(AA45/AA$29,0) -> 0 | AC45: =SUM(S45,U45,W45,Y45,AA45) -> 444153.5 | AD45: =IFERROR(AC45/AC$29,0) -> 0.019464388 | AG45: =+S45-F45 -> -48488.02 | AH45: =(T45-G45)*100 -> -0.40145437 | AI45: =+U45-H45 -> 149366.57 | AJ45: =(V45-I45)*100 -> 0.45402897 | AK45: =+W45-J45 -> -9928.78 | AL45: =(X45-K45)*100 -> 0.78466617 | AM45: =+Y45-L45 -> 0 | AN45: =(Z45-M45)*100 -> 0 | AO45: =+AA45-N45 -> 0 | AP45: =(AB45-O45)*100 -> 0 | AQ45: =+AC45-P45 -> 90949.77 | AR45: =(AD45-Q45)*100 -> 0.24909329
B46: 물류용역비 | E46: 물류용역비 | F46: =+'1월'!F46+'2월'!F46+'3월'!F46+'4월'!F46+'5월'!F46+'6월'!F46+'7월'!F46+'8월'!F46+'9월'!F46+'10월'!F46+'11월'!F46+'12월'!F46 -> 90398.33 | G46: =IFERROR(F46/F$29,0) -> 0.035746773 | H46: =+'1월'!H46+'2월'!H46+'3월'!H46+'4월'!H46+'5월'!H46+'6월'!H46+'7월'!H46+'8월'!H46+'9월'!H46+'10월'!H46+'11월'!H46+'12월'!H46 -> 567585.79 | I46: =IFERROR(H46/H$29,0) -> 0.037223569 | J46: =+'1월'!J46+'2월'!J46+'3월'!J46+'4월'!J46+'5월'!J46+'6월'!J46+'7월'!J46+'8월'!J46+'9월'!J46+'10월'!J46+'11월'!J46+'12월'!J46 -> 50289.12 | K46: =IFERROR(J46/J$29,0) -> 0.027345262 | L46: =+'1월'!L46+'2월'!L46+'3월'!L46+'4월'!L46+'5월'!L46+'6월'!L46+'7월'!L46+'8월'!L46+'9월'!L46+'10월'!L46+'11월'!L46+'12월'!L46 -> 0 | M46: =IFERROR(L46/L$29,0) -> 0 | N46: =+'1월'!N46+'2월'!N46+'3월'!N46+'4월'!N46+'5월'!N46+'6월'!N46+'7월'!N46+'8월'!N46+'9월'!N46+'10월'!N46 -> 0 | O46: =IFERROR(N46/N$29,0) -> 0 | P46: =SUM(F46,H46,J46,L46,N46) -> 708273.24 | Q46: =IFERROR(P46/P$29,0) -> 0.034036572 | S46: =+'1월'!AH46+'2월'!AH46+'3월'!AH46+'4월'!AH46+'5월'!AH46+'6월'!AH46+'7월'!AH46+'8월'!AH46+'9월'!AH46+'10월'!AH46+'11월'!AH46+'12월'!AH46 -> 64364.15 | T46: =IFERROR(S46/S$29,0) -> 0.042486091 | U46: =+'1월'!AJ46+'2월'!AJ46+'3월'!AJ46+'4월'!AJ46+'5월'!AJ46+'6월'!AJ46+'7월'!AJ46+'8월'!AJ46+'9월'!AJ46+'10월'!AJ46+'11월'!AJ46+'12월'!AJ46 -> 771070.55 | V46: =IFERROR(U46/U$29,0) -> 0.039536329 | W46: =+'1월'!AL46+'2월'!AL46+'3월'!AL46+'4월'!AL46+'5월'!AL46+'6월'!AL46+'7월'!AL46+'8월'!AL46+'9월'!AL46+'10월'!AL46+'11월'!AL46+'12월'!AL46 -> 66667.51 | X46: =IFERROR(W46/W$29,0) -> 0.081413995 | Y46: =+'1월'!AN46+'2월'!AN46+'3월'!AN46+'4월'!AN46+'5월'!AN46+'6월'!AN46+'7월'!AN46+'8월'!AN46+'9월'!AN46+'10월'!AN46+'11월'!AN46 -> 0 | Z46: =IFERROR(Y46/Y$29,0) -> 0 | AA46: =+'1월'!AP46+'2월'!AP46+'3월'!AP46+'4월'!AP46+'5월'!AP46+'6월'!AP46+'7월'!AP46+'8월'!AP46+'9월'!AP46+'10월'!AP46+'11월'!AP46 -> 0 | AB46: =IFERROR(AA46/AA$29,0) -> 0 | AC46: =SUM(S46,U46,W46,Y46,AA46) -> 902102.21 | AD46: =IFERROR(AC46/AC$29,0) -> 0.039533331 | AG46: =+S46-F46 -> -26034.18 | AH46: =(T46-G46)*100 -> 0.6739318 | AI46: =+U46-H46 -> 203484.76 | AJ46: =(V46-I46)*100 -> 0.23127596 | AK46: =+W46-J46 -> 16378.39 | AL46: =(X46-K46)*100 -> 5.4068733 | AM46: =+Y46-L46 -> 0 | AN46: =(Z46-M46)*100 -> 0 | AO46: =+AA46-N46 -> 0 | AP46: =(AB46-O46)*100 -> 0 | AQ46: =+AC46-P46 -> 193828.97 | AR46: =(AD46-Q46)*100 -> 0.54967595
B47: Professional Service | C47: Direct Costs | E47: 지급수수료 | F47: =+'1월'!F47+'2월'!F47+'3월'!F47+'4월'!F47+'5월'!F47+'6월'!F47+'7월'!F47+'8월'!F47+'9월'!F47+'10월'!F47+'11월'!F47+'12월'!F47 -> 25476.75 | G47: =IFERROR(F47/F$29,0) -> 0.010074429 | H47: =+'1월'!H47+'2월'!H47+'3월'!H47+'4월'!H47+'5월'!H47+'6월'!H47+'7월'!H47+'8월'!H47+'9월'!H47+'10월'!H47+'11월'!H47+'12월'!H47 -> 860333.1 | I47: =IFERROR(H47/H$29,0) -> 0.056422605 | J47: =+'1월'!J47+'2월'!J47+'3월'!J47+'4월'!J47+'5월'!J47+'6월'!J47+'7월'!J47+'8월'!J47+'9월'!J47+'10월'!J47+'11월'!J47+'12월'!J47 -> 64343.27 | K47: =IFERROR(J47/J$29,0) -> 0.034987361 | L47: =+'1월'!L47+'2월'!L47+'3월'!L47+'4월'!L47+'5월'!L47+'6월'!L47+'7월'!L47+'8월'!L47+'9월'!L47+'10월'!L47+'11월'!L47+'12월'!L47 -> 0 | M47: =IFERROR(L47/L$29,0) -> 0 | N47: =+'1월'!N47+'2월'!N47+'3월'!N47+'4월'!N47+'5월'!N47+'6월'!N47+'7월'!N47+'8월'!N47+'9월'!N47+'10월'!N47 -> 0 | O47: =IFERROR(N47/N$29,0) -> 0 | P47: =SUM(F47,H47,J47,L47,N47) -> 950153.12 | Q47: =IFERROR(P47/P$29,0) -> 0.04566028 | S47: =+'1월'!AH47+'2월'!AH47+'3월'!AH47+'4월'!AH47+'5월'!AH47+'6월'!AH47+'7월'!AH47+'8월'!AH47+'9월'!AH47+'10월'!AH47+'11월'!AH47+'12월'!AH47 -> 18111.9 | T47: =IFERROR(S47/S$29,0) -> 0.011955473 | U47: =+'1월'!AJ47+'2월'!AJ47+'3월'!AJ47+'4월'!AJ47+'5월'!AJ47+'6월'!AJ47+'7월'!AJ47+'8월'!AJ47+'9월'!AJ47+'10월'!AJ47+'11월'!AJ47+'12월'!AJ47 -> 991182.99 | V47: =IFERROR(U47/U$29,0) -> 0.050822505 | W47: =+'1월'!AL47+'2월'!AL47+'3월'!AL47+'4월'!AL47+'5월'!AL47+'6월'!AL47+'7월'!AL47+'8월'!AL47+'9월'!AL47+'10월'!AL47+'11월'!AL47+'12월'!AL47 -> 66845.07 | X47: =IFERROR(W47/W$29,0) -> 0.08163083 | Y47: =+'1월'!AN47+'2월'!AN47+'3월'!AN47+'4월'!AN47+'5월'!AN47+'6월'!AN47+'7월'!AN47+'8월'!AN47+'9월'!AN47+'10월'!AN47+'11월'!AN47 -> 0 | Z47: =IFERROR(Y47/Y$29,0) -> 0 | AA47: =+'1월'!AP47+'2월'!AP47+'3월'!AP47+'4월'!AP47+'5월'!AP47+'6월'!AP47+'7월'!AP47+'8월'!AP47+'9월'!AP47+'10월'!AP47+'11월'!AP47 -> 0 | AB47: =IFERROR(AA47/AA$29,0) -> 0 | AC47: =SUM(S47,U47,W47,Y47,AA47) -> 1076140 | AD47: =IFERROR(AC47/AC$29,0) -> 0.047160285 | AG47: =+S47-F47 -> -7364.85 | AH47: =(T47-G47)*100 -> 0.18810431 | AI47: =+U47-H47 -> 130849.89 | AJ47: =(V47-I47)*100 -> -0.56001001 | AK47: =+W47-J47 -> 2501.8 | AL47: =(X47-K47)*100 -> 4.6643469 | AM47: =+Y47-L47 -> 0 | AN47: =(Z47-M47)*100 -> 0 | AO47: =+AA47-N47 -> 0 | AP47: =(AB47-O47)*100 -> 0 | AQ47: =+AC47-P47 -> 125986.84 | AR47: =(AD47-Q47)*100 -> 0.15000048
B48: 6451 - Service Processing Fee | C48: Direct Costs | E48: 결제수수료 | F48: =+'1월'!F48+'2월'!F48+'3월'!F48+'4월'!F48+'5월'!F48+'6월'!F48+'7월'!F48+'8월'!F48+'9월'!F48+'10월'!F48+'11월'!F48+'12월'!F48 -> 58847.08 | G48: =IFERROR(F48/F$29,0) -> 0.023270266 | H48: =+'1월'!H48+'2월'!H48+'3월'!H48+'4월'!H48+'5월'!H48+'6월'!H48+'7월'!H48+'8월'!H48+'9월'!H48+'10월'!H48+'11월'!H48+'12월'!H48 -> 518553.39 | I48: =IFERROR(H48/H$29,0) -> 0.034007913 | J48: =+'1월'!J48+'2월'!J48+'3월'!J48+'4월'!J48+'5월'!J48+'6월'!J48+'7월'!J48+'8월'!J48+'9월'!J48+'10월'!J48+'11월'!J48+'12월'!J48 -> 157736.82 | K48: =IFERROR(J48/J$29,0) -> 0.085771132 | L48: =+'1월'!L48+'2월'!L48+'3월'!L48+'4월'!L48+'5월'!L48+'6월'!L48+'7월'!L48+'8월'!L48+'9월'!L48+'10월'!L48+'11월'!L48+'12월'!L48 -> 0 | M48: =IFERROR(L48/L$29,0) -> 0 | N48: =+'1월'!N48+'2월'!N48+'3월'!N48+'4월'!N48+'5월'!N48+'6월'!N48+'7월'!N48+'8월'!N48+'9월'!N48+'10월'!N48 -> 0 | O48: =IFERROR(N48/N$29,0) -> 0 | P48: =SUM(F48,H48,J48,L48,N48) -> 735137.29 | Q48: =IFERROR(P48/P$29,0) -> 0.035327542 | S48: =+'1월'!AH48+'2월'!AH48+'3월'!AH48+'4월'!AH48+'5월'!AH48+'6월'!AH48+'7월'!AH48+'8월'!AH48+'9월'!AH48+'10월'!AH48+'11월'!AH48+'12월'!AH48 -> 40302.32 | T48: =IFERROR(S48/S$29,0) -> 0.026603133 | U48: =+'1월'!AJ48+'2월'!AJ48+'3월'!AJ48+'4월'!AJ48+'5월'!AJ48+'6월'!AJ48+'7월'!AJ48+'8월'!AJ48+'9월'!AJ48+'10월'!AJ48+'11월'!AJ48+'12월'!AJ48 -> 830038.54 | V48: =IFERROR(U48/U$29,0) -> 0.042559889 | W48: =+'1월'!AL48+'2월'!AL48+'3월'!AL48+'4월'!AL48+'5월'!AL48+'6월'!AL48+'7월'!AL48+'8월'!AL48+'9월'!AL48+'10월'!AL48+'11월'!AL48+'12월'!AL48 -> 49723.44 | X48: =IFERROR(W48/W$29,0) -> 0.06072199 | Y48: =+'1월'!AN48+'2월'!AN48+'3월'!AN48+'4월'!AN48+'5월'!AN48+'6월'!AN48+'7월'!AN48+'8월'!AN48+'9월'!AN48+'10월'!AN48+'11월'!AN48 -> 0 | Z48: =IFERROR(Y48/Y$29,0) -> 0 | AA48: =+'1월'!AP48+'2월'!AP48+'3월'!AP48+'4월'!AP48+'5월'!AP48+'6월'!AP48+'7월'!AP48+'8월'!AP48+'9월'!AP48+'10월'!AP48+'11월'!AP48 -> 0 | AB48: =IFERROR(AA48/AA$29,0) -> 0 | AC48: =SUM(S48,U48,W48,Y48,AA48) -> 920064.3 | AD48: =IFERROR(AC48/AC$29,0) -> 0.040320494 | AG48: =+S48-F48 -> -18544.76 | AH48: =(T48-G48)*100 -> 0.33328666 | AI48: =+U48-H48 -> 311485.15 | AJ48: =(V48-I48)*100 -> 0.85519759 | AK48: =+W48-J48 -> -108013.38 | AL48: =(X48-K48)*100 -> -2.5049141 | AM48: =+Y48-L48 -> 0 | AN48: =(Z48-M48)*100 -> 0 | AO48: =+AA48-N48 -> 0 | AP48: =(AB48-O48)*100 -> 0 | AQ48: =+AC48-P48 -> 184927.01 | AR48: =(AD48-Q48)*100 -> 0.49929514
B49: Marketing | C49: Direct Costs | E49: SEM 광고비 | F49: =+'1월'!F49+'2월'!F49+'3월'!F49+'4월'!F49+'5월'!F49+'6월'!F49+'7월'!F49+'8월'!F49+'9월'!F49+'10월'!F49+'11월'!F49+'12월'!F49 -> 0 | G49: =IFERROR(F49/F$29,0) -> 0 | H49: =+'1월'!H49+'2월'!H49+'3월'!H49+'4월'!H49+'5월'!H49+'6월'!H49+'7월'!H49+'8월'!H49+'9월'!H49+'10월'!H49+'11월'!H49+'12월'!H49 -> 2675636.5 | I49: =IFERROR(H49/H$29,0) -> 0.17547434 | J49: =+'1월'!J49+'2월'!J49+'3월'!J49+'4월'!J49+'5월'!J49+'6월'!J49+'7월'!J49+'8월'!J49+'9월'!J49+'10월'!J49+'11월'!J49+'12월'!J49 -> 469494.27 | K49: =IFERROR(J49/J$29,0) -> 0.25529268 | L49: =+'1월'!L49+'2월'!L49+'3월'!L49+'4월'!L49+'5월'!L49+'6월'!L49+'7월'!L49+'8월'!L49+'9월'!L49+'10월'!L49+'11월'!L49+'12월'!L49 -> 0 | M49: =IFERROR(L49/L$29,0) -> 0 | N49: =+'1월'!N49+'2월'!N49+'3월'!N49+'4월'!N49+'5월'!N49+'6월'!N49+'7월'!N49+'8월'!N49+'9월'!N49+'10월'!N49 -> 0 | O49: =IFERROR(N49/N$29,0) -> 0 | P49: =SUM(F49,H49,J49,L49,N49) -> 3145130.8 | Q49: =IFERROR(P49/P$29,0) -> 0.15114148 | S49: =+'1월'!AH49+'2월'!AH49+'3월'!AH49+'4월'!AH49+'5월'!AH49+'6월'!AH49+'7월'!AH49+'8월'!AH49+'9월'!AH49+'10월'!AH49+'11월'!AH49+'12월'!AH49 -> 0 | T49: =IFERROR(S49/S$29,0) -> 0 | U49: =+'1월'!AJ49+'2월'!AJ49+'3월'!AJ49+'4월'!AJ49+'5월'!AJ49+'6월'!AJ49+'7월'!AJ49+'8월'!AJ49+'9월'!AJ49+'10월'!AJ49+'11월'!AJ49+'12월'!AJ49 -> 3847636.6 | V49: =IFERROR(U49/U$29,0) -> 0.197286 | W49: =+'1월'!AL49+'2월'!AL49+'3월'!AL49+'4월'!AL49+'5월'!AL49+'6월'!AL49+'7월'!AL49+'8월'!AL49+'9월'!AL49+'10월'!AL49+'11월'!AL49+'12월'!AL49 -> 146512.45 | X49: =IFERROR(W49/W$29,0) -> 0.1789202 | Y49: =+'1월'!AN49+'2월'!AN49+'3월'!AN49+'4월'!AN49+'5월'!AN49+'6월'!AN49+'7월'!AN49+'8월'!AN49+'9월'!AN49+'10월'!AN49+'11월'!AN49 -> 0 | Z49: =IFERROR(Y49/Y$29,0) -> 0 | AA49: =+'1월'!AP49+'2월'!AP49+'3월'!AP49+'4월'!AP49+'5월'!AP49+'6월'!AP49+'7월'!AP49+'8월'!AP49+'9월'!AP49+'10월'!AP49+'11월'!AP49 -> 0 | AB49: =IFERROR(AA49/AA$29,0) -> 0 | AC49: =SUM(S49,U49,W49,Y49,AA49) -> 3994149 | AD49: =IFERROR(AC49/AC$29,0) -> 0.17503783 | AG49: =+S49-F49 -> 0 | AH49: =(T49-G49)*100 -> 0 | AI49: =+U49-H49 -> 1172000.1 | AJ49: =(V49-I49)*100 -> 2.1811664 | AK49: =+W49-J49 -> -322981.82 | AL49: =(X49-K49)*100 -> -7.6372483 | AM49: =+Y49-L49 -> 0 | AN49: =(Z49-M49)*100 -> 0 | AO49: =+AA49-N49 -> 0 | AP49: =(AB49-O49)*100 -> 0 | AQ49: =+AC49-P49 -> 849018.27 | AR49: =(AD49-Q49)*100 -> 2.389635
B50: Other | C50: Direct Costs | E50: 기타비용 | F50: =+'1월'!F50+'2월'!F50+'3월'!F50+'4월'!F50+'5월'!F50+'6월'!F50+'7월'!F50+'8월'!F50+'9월'!F50+'10월'!F50+'11월'!F50+'12월'!F50 -> 0 | G50: =IFERROR(F50/F$29,0) -> 0 | H50: =+'1월'!H50+'2월'!H50+'3월'!H50+'4월'!H50+'5월'!H50+'6월'!H50+'7월'!H50+'8월'!H50+'9월'!H50+'10월'!H50+'11월'!H50+'12월'!H50 -> 0 | I50: =IFERROR(H50/H$29,0) -> 0 | J50: =+'1월'!J50+'2월'!J50+'3월'!J50+'4월'!J50+'5월'!J50+'6월'!J50+'7월'!J50+'8월'!J50+'9월'!J50+'10월'!J50+'11월'!J50+'12월'!J50 -> 0 | K50: =IFERROR(J50/J$29,0) -> 0 | L50: =+'1월'!L50+'2월'!L50+'3월'!L50+'4월'!L50+'5월'!L50+'6월'!L50+'7월'!L50+'8월'!L50+'9월'!L50+'10월'!L50+'11월'!L50+'12월'!L50 -> 0 | M50: =IFERROR(L50/L$29,0) -> 0 | N50: =+'1월'!N50+'2월'!N50+'3월'!N50+'4월'!N50+'5월'!N50+'6월'!N50+'7월'!N50+'8월'!N50+'9월'!N50+'10월'!N50 -> 0 | O50: =IFERROR(N50/N$29,0) -> 0 | P50: =SUM(F50,H50,J50,L50,N50) -> 0 | Q50: =IFERROR(P50/P$29,0) -> 0 | S50: =+'1월'!AH50+'2월'!AH50+'3월'!AH50+'4월'!AH50+'5월'!AH50+'6월'!AH50+'7월'!AH50+'8월'!AH50+'9월'!AH50+'10월'!AH50+'11월'!AH50+'12월'!AH50 -> 0 | T50: =IFERROR(S50/S$29,0) -> 0 | U50: =+'1월'!AJ50+'2월'!AJ50+'3월'!AJ50+'4월'!AJ50+'5월'!AJ50+'6월'!AJ50+'7월'!AJ50+'8월'!AJ50+'9월'!AJ50+'10월'!AJ50+'11월'!AJ50+'12월'!AJ50 -> 0 | V50: =IFERROR(U50/U$29,0) -> 0 | W50: =+'1월'!AL50+'2월'!AL50+'3월'!AL50+'4월'!AL50+'5월'!AL50+'6월'!AL50+'7월'!AL50+'8월'!AL50+'9월'!AL50+'10월'!AL50+'11월'!AL50+'12월'!AL50 -> 0 | X50: =IFERROR(W50/W$29,0) -> 0 | Y50: =+'1월'!AN50+'2월'!AN50+'3월'!AN50+'4월'!AN50+'5월'!AN50+'6월'!AN50+'7월'!AN50+'8월'!AN50+'9월'!AN50+'10월'!AN50+'11월'!AN50 -> 0 | Z50: =IFERROR(Y50/Y$29,0) -> 0 | AA50: =+'1월'!AP50+'2월'!AP50+'3월'!AP50+'4월'!AP50+'5월'!AP50+'6월'!AP50+'7월'!AP50+'8월'!AP50+'9월'!AP50+'10월'!AP50+'11월'!AP50 -> 0 | AB50: =IFERROR(AA50/AA$29,0) -> 0 | AC50: =SUM(S50,U50,W50,Y50,AA50) -> 0 | AD50: =IFERROR(AC50/AC$29,0) -> 0 | AG50: =+S50-F50 -> 0 | AH50: =(T50-G50)*100 -> 0 | AI50: =+U50-H50 -> 0 | AJ50: =(V50-I50)*100 -> 0 | AK50: =+W50-J50 -> 0 | AL50: =(X50-K50)*100 -> 0 | AM50: =+Y50-L50 -> 0 | AN50: =(Z50-M50)*100 -> 0 | AO50: =+AA50-N50 -> 0 | AP50: =(AB50-O50)*100 -> 0 | AQ50: =+AC50-P50 -> 0 | AR50: =(AD50-Q50)*100 -> 0
E51: 직접비 소계 | F51: =F43+SUM(F47:F50) -> 258216.67 | G51: =IFERROR(F51/F$29,0) -> 0.10210822 | H51: =H43+SUM(H47:H50) -> 5763965.8 | I51: =IFERROR(H51/H$29,0) -> 0.37801401 | J51: =J43+SUM(J47:J50) -> 998274.4 | K51: =IFERROR(J51/J$29,0) -> 0.54282269 | L51: =L43+SUM(L47:L50) -> 0 | M51: =IFERROR(L51/L$29,0) -> 0 | N51: =N43+SUM(N47:N50) -> 0 | O51: =IFERROR(N51/N$29,0) -> 0 | P51: =P43+SUM(P47:P50) -> 7020456.9 | Q51: =IFERROR(P51/P$29,0) -> 0.33737302 | S51: =S43+SUM(S47:S50) -> 163443 | T51: =IFERROR(S51/S$29,0) -> 0.10788699 | U51: =U43+SUM(U47:U50) -> 8011055.3 | V51: =IFERROR(U51/U$29,0) -> 0.41076361 | W51: =W43+SUM(W47:W50) -> 395824.98 | X51: =IFERROR(W51/W$29,0) -> 0.48337928 | Y51: =Y43+SUM(Y47:Y50) -> 0 | Z51: =IFERROR(Y51/Y$29,0) -> 0 | AA51: =AA43+SUM(AA47:AA50) -> 0 | AB51: =IFERROR(AA51/AA$29,0) -> 0 | AC51: =AC43+SUM(AC47:AC50) -> 8570323.3 | AD51: =IFERROR(AC51/AC$29,0) -> 0.37558208 | AG51: =+S51-F51 -> -94773.67 | AH51: =(T51-G51)*100 -> 0.57787649 | AI51: =+U51-H51 -> 2247089.5 | AJ51: =(V51-I51)*100 -> 3.2749595 | AK51: =+W51-J51 -> -602449.42 | AL51: =(X51-K51)*100 -> -5.9443413 | AM51: =+Y51-L51 -> 0 | AN51: =(Z51-M51)*100 -> 0 | AO51: =+AA51-N51 -> 0 | AP51: =(AB51-O51)*100 -> 0 | AQ51: =+AC51-P51 -> 1549866.4 | AR51: =(AD51-Q51)*100 -> 3.8209064
AH52: =(T52-G52)*100 -> 0 | AI52: =+U52-H52 -> 0 | AJ52: =(V52-I52)*100 -> 0 | AK52: =+W52-J52 -> 0 | AL52: =(X52-K52)*100 -> 0 | AM52: =+Y52-L52 -> 0 | AN52: =(Z52-M52)*100 -> 0 | AO52: =+AA52-N52 -> 0 | AP52: =(AB52-O52)*100 -> 0 | AQ52: =+AC52-P52 -> 0 | AR52: =(AD52-Q52)*100 -> 0
E53: 직접이익 | F53: =F40-F51 -> 1026598.1 | G53: =IFERROR(F53/F$29,0) -> 0.40595408 | H53: =H40-H51 -> 4909897.7 | I53: =IFERROR(H53/H$29,0) -> 0.32200228 | J53: =J40-J51 -> 413190.61 | K53: =IFERROR(J53/J$29,0) -> 0.22467694 | L53: =L40-L51 -> 976931.6 | M53: =IFERROR(L53/L$29,0) -> 1 | N53: =N40-N51 -> -175241.43 | O53: =IFERROR(N53/N$29,0) -> -0.81005202 | P53: =P40-P51 -> 7151376.6 | Q53: =IFERROR(P53/P$29,0) -> 0.34366446 | S53: =S40-S51 -> 523133.7 | T53: =IFERROR(S53/S$29,0) -> 0.34531499 | U53: =U40-U51 -> 3471118.4 | V53: =IFERROR(U53/U$29,0) -> 0.17798018 | W53: =W40-W51 -> 94707.4 | X53: =IFERROR(W53/W$29,0) -> 0.11565615 | Y53: =Y40-Y51 -> 832330.89 | Z53: =IFERROR(Y53/Y$29,0) -> 1 | AA53: =AA40-AA51 -> 256093.97 | AB53: =IFERROR(AA53/AA$29,0) -> 1.7096668 | AC53: =AC40-AC51 -> 5177384.3 | AD53: =IFERROR(AC53/AC$29,0) -> 0.22689142 | AG53: =+S53-F53 -> -503464.44 | AH53: =(T53-G53)*100 -> -6.0639085 | AI53: =+U53-H53 -> -1438779.3 | AJ53: =(V53-I53)*100 -> -14.402209 | AK53: =+W53-J53 -> -318483.21 | AL53: =(X53-K53)*100 -> -10.902078 | AM53: =+Y53-L53 -> -144600.71 | AN53: =(Z53-M53)*100 -> 0 | AO53: =+AA53-N53 -> 431335.4 | AP53: =(AB53-O53)*100 -> 251.97189 | AQ53: =+AC53-P53 -> -1973992.2 | AR53: =(AD53-Q53)*100 -> -11.677304
S54: =+S53-F53 -> -503464.44 | T54: =+T53-G53 -> -0.060639085 | U54: =+U53-H53 -> -1438779.3 | V54: =+V53-I53 -> -0.14402209 | W54: =+W53-J53 -> -318483.21 | X54: =+X53-K53 -> -0.10902078 | Y54: =+Y53-L53 -> -144600.71 | AN54: =(Z54-M54)*100 -> 0 | AR54: =(AD54-Q54)*100 -> 0
E55: 영업비 | P55: =+'1월'!P55+'2월'!P55+'3월'!P55+'4월'!P55+'5월'!P55+'6월'!P55+'7월'!P55+'8월'!P55+'9월'!P55+'10월'!P55 -> 0 | S55: =+S53/F53 -> 0.50957982 | U55: =+U53/H53 -> 0.70696349 | W55: =+W53/J53 -> 0.22920995 | Y55: =+Y53/L53 -> 0.85198482 | AQ55: =+AC55-P55 -> 0 | AR55: =(AD55-Q55)*100 -> 0
E56: 인건비 | P56: =+'1월'!P56+'2월'!P56+'3월'!P56+'4월'!P56+'5월'!P56+'6월'!P56+'7월'!P56+'8월'!P56+'9월'!P56+'10월'!P56+'11월'!P56+'12월'!P56 -> 4119740.7 | Q56: =IFERROR(P56/P$29,0) -> 0.19797705 | AC56: =+'1월'!AR56+'2월'!AR56+'3월'!AR56+'4월'!AR56+'5월'!AR56+'6월'!AR56+'7월'!AR56+'8월'!AR56+'9월'!AR56+'10월'!AR56+'11월'!AR56+'12월'!AR56 -> 4137336.5 | AD56: =IFERROR(AC56/AC$29,0) -> 0.18131282 | AQ56: =+AC56-P56 -> 17595.77 | AR56: =(AD56-Q56)*100 -> -1.6664237
B57: HQ | C57: HQ Salaries | E57: 급여(정규) | P57: =+'1월'!P57+'2월'!P57+'3월'!P57+'4월'!P57+'5월'!P57+'6월'!P57+'7월'!P57+'8월'!P57+'9월'!P57+'10월'!P57+'11월'!P57+'12월'!P57 -> 2930287.8 | Q57: =IFERROR(P57/P$29,0) -> 0.14081705 | AC57: =+'1월'!AR57+'2월'!AR57+'3월'!AR57+'4월'!AR57+'5월'!AR57+'6월'!AR57+'7월'!AR57+'8월'!AR57+'9월'!AR57+'10월'!AR57+'11월'!AR57+'12월'!AR57 -> 2962315.2 | AD57: =IFERROR(AC57/AC$29,0) -> 0.1298192 | AQ57: =+AC57-P57 -> 32027.4 | AR57: =(AD57-Q57)*100 -> -1.0997853
B58: Contractors | C58: HQ Salaries | E58: 급여(계약) | P58: =+'1월'!P58+'2월'!P58+'3월'!P58+'4월'!P58+'5월'!P58+'6월'!P58+'7월'!P58+'8월'!P58+'9월'!P58+'10월'!P58+'11월'!P58+'12월'!P58 -> 425253.57 | Q58: =IFERROR(P58/P$29,0) -> 0.020435861 | AC58: =+'1월'!AR58+'2월'!AR58+'3월'!AR58+'4월'!AR58+'5월'!AR58+'6월'!AR58+'7월'!AR58+'8월'!AR58+'9월'!AR58+'10월'!AR58+'11월'!AR58+'12월'!AR58 -> 590830.35 | AD58: =IFERROR(AC58/AC$29,0) -> 0.02589229 | AQ58: =+AC58-P58 -> 165576.78 | AR58: =(AD58-Q58)*100 -> 0.54564287
B59: Benefits | C59: HQ Salaries | E59: 보험,복후비등 | P59: =+'1월'!P59+'2월'!P59+'3월'!P59+'4월'!P59+'5월'!P59+'6월'!P59+'7월'!P59+'8월'!P59+'9월'!P59+'10월'!P59+'11월'!P59+'12월'!P59 -> 639536.69 | Q59: =IFERROR(P59/P$29,0) -> 0.030733388 | AC59: =+'1월'!AR59+'2월'!AR59+'3월'!AR59+'4월'!AR59+'5월'!AR59+'6월'!AR59+'7월'!AR59+'8월'!AR59+'9월'!AR59+'10월'!AR59+'11월'!AR59+'12월'!AR59 -> 764507.39 | AD59: =IFERROR(AC59/AC$29,0) -> 0.033503436 | AQ59: =+AC59-P59 -> 124970.7 | AR59: =(AD59-Q59)*100 -> 0.27700481
B60: Bonus | C60: HQ Salaries | E60: 급여충당금 | P60: =+'1월'!P60+'2월'!P60+'3월'!P60+'4월'!P60+'5월'!P60+'6월'!P60+'7월'!P60+'8월'!P60+'9월'!P60+'10월'!P60+'11월'!P60+'12월'!P60 -> 124662.61 | Q60: =IFERROR(P60/P$29,0) -> 0.0059907499 | AC60: =+'1월'!AR60+'2월'!AR60+'3월'!AR60+'4월'!AR60+'5월'!AR60+'6월'!AR60+'7월'!AR60+'8월'!AR60+'9월'!AR60+'10월'!AR60+'11월'!AR60+'12월'!AR60 -> -180316.5 | AD60: =IFERROR(AC60/AC$29,0) -> -0.0079021111 | AQ60: =+AC60-P60 -> -304979.11 | AR60: =(AD60-Q60)*100 -> -1.3892861
B61: Advertising | C61: SG&A | E61: 광고선전비 | P61: =+'1월'!P61+'2월'!P61+'3월'!P61+'4월'!P61+'5월'!P61+'6월'!P61+'7월'!P61+'8월'!P61+'9월'!P61+'10월'!P61+'11월'!P61+'12월'!P61 -> 698476.71 | Q61: =IFERROR(P61/P$29,0) -> 0.033565792 | AC61: =+'1월'!AR61+'2월'!AR61+'3월'!AR61+'4월'!AR61+'5월'!AR61+'6월'!AR61+'7월'!AR61+'8월'!AR61+'9월'!AR61+'10월'!AR61+'11월'!AR61+'12월'!AR61 -> 1037190.8 | AD61: =IFERROR(AC61/AC$29,0) -> 0.045453392 | AQ61: =+AC61-P61 -> 338714.04 | AR61: =(AD61-Q61)*100 -> 1.18876
E62: Photography | P62: =+'1월'!P62+'2월'!P62+'3월'!P62+'4월'!P62+'5월'!P62+'6월'!P62+'7월'!P62+'8월'!P62+'9월'!P62+'10월'!P62+'11월'!P62+'12월'!P62 -> 496215.98 | Q62: =IFERROR(P62/P$29,0) -> 0.02384601 | AC62: =+'1월'!AR62+'2월'!AR62+'3월'!AR62+'4월'!AR62+'5월'!AR62+'6월'!AR62+'7월'!AR62+'8월'!AR62+'9월'!AR62+'10월'!AR62+'11월'!AR62+'12월'!AR62 -> 0 | AD62: =IFERROR(AC62/AC$29,0) -> 0 | AQ62: =+AC62-P62 -> -496215.98 | AR62: =(AD62-Q62)*100 -> -2.384601
E63: Selling | P63: =+'1월'!P63+'2월'!P63+'3월'!P63+'4월'!P63+'5월'!P63+'6월'!P63+'7월'!P63+'8월'!P63+'9월'!P63+'10월'!P63+'11월'!P63+'12월'!P63 -> 0 | Q63: =IFERROR(P63/P$29,0) -> 0 | AC63: =+'1월'!AR63+'2월'!AR63+'3월'!AR63+'4월'!AR63+'5월'!AR63+'6월'!AR63+'7월'!AR63+'8월'!AR63+'9월'!AR63+'10월'!AR63+'11월'!AR63+'12월'!AR63 -> 0 | AD63: =IFERROR(AC63/AC$29,0) -> 0 | AQ63: =+AC63-P63 -> 0 | AR63: =(AD63-Q63)*100 -> 0
E64: Advertising | P64: =+'1월'!P64+'2월'!P64+'3월'!P64+'4월'!P64+'5월'!P64+'6월'!P64+'7월'!P64+'8월'!P64+'9월'!P64+'10월'!P64+'11월'!P64+'12월'!P64 -> 21666.66 | Q64: =IFERROR(P64/P$29,0) -> 0.0010412067 | AC64: =+'1월'!AR64+'2월'!AR64+'3월'!AR64+'4월'!AR64+'5월'!AR64+'6월'!AR64+'7월'!AR64+'8월'!AR64+'9월'!AR64+'10월'!AR64+'11월'!AR64+'12월'!AR64 -> 0 | AD64: =IFERROR(AC64/AC$29,0) -> 0 | AQ64: =+AC64-P64 -> -21666.66 | AR64: =(AD64-Q64)*100 -> -0.10412067
E65: SEM브랜드마케팅 | P65: =+'1월'!P65+'2월'!P65+'3월'!P65+'4월'!P65+'5월'!P65+'6월'!P65+'7월'!P65+'8월'!P65+'9월'!P65+'10월'!P65+'11월'!P65+'12월'!P65 -> 0 | Q65: =IFERROR(P65/P$29,0) -> 0 | AC65: =+'1월'!AR65+'2월'!AR65+'3월'!AR65+'4월'!AR65+'5월'!AR65+'6월'!AR65+'7월'!AR65+'8월'!AR65+'9월'!AR65+'10월'!AR65+'11월'!AR65+'12월'!AR65 -> 0 | AD65: =IFERROR(AC65/AC$29,0) -> 0 | AQ65: =+AC65-P65 -> 0 | AR65: =(AD65-Q65)*100 -> 0
E66: Events | P66: =+'1월'!P66+'2월'!P66+'3월'!P66+'4월'!P66+'5월'!P66+'6월'!P66+'7월'!P66+'8월'!P66+'9월'!P66+'10월'!P66+'11월'!P66+'12월'!P66 -> 13473.22 | Q66: =IFERROR(P66/P$29,0) -> 0.00064746512 | AC66: =+'1월'!AR66+'2월'!AR66+'3월'!AR66+'4월'!AR66+'5월'!AR66+'6월'!AR66+'7월'!AR66+'8월'!AR66+'9월'!AR66+'10월'!AR66+'11월'!AR66+'12월'!AR66 -> 0 | AD66: =IFERROR(AC66/AC$29,0) -> 0 | AQ66: =+AC66-P66 -> -13473.22 | AR66: =(AD66-Q66)*100 -> -0.064746512
E67: Model | P67: =+'1월'!P67+'2월'!P67+'3월'!P67+'4월'!P67+'5월'!P67+'6월'!P67+'7월'!P67+'8월'!P67+'9월'!P67+'10월'!P67+'11월'!P67+'12월'!P67 -> 75425 | Q67: =IFERROR(P67/P$29,0) -> 0.0036246017 | AC67: =+'1월'!AR67+'2월'!AR67+'3월'!AR67+'4월'!AR67+'5월'!AR67+'6월'!AR67+'7월'!AR67+'8월'!AR67+'9월'!AR67+'10월'!AR67+'11월'!AR67+'12월'!AR67 -> 0 | AD67: =IFERROR(AC67/AC$29,0) -> 0 | AQ67: =+AC67-P67 -> -75425 | AR67: =(AD67-Q67)*100 -> -0.36246017
E68: Seeding | P68: =+'1월'!P68+'2월'!P68+'3월'!P68+'4월'!P68+'5월'!P68+'6월'!P68+'7월'!P68+'8월'!P68+'9월'!P68+'10월'!P68+'11월'!P68+'12월'!P68 -> 82402.65 | Q68: =IFERROR(P68/P$29,0) -> 0.0039599176 | AC68: =+'1월'!AR68+'2월'!AR68+'3월'!AR68+'4월'!AR68+'5월'!AR68+'6월'!AR68+'7월'!AR68+'8월'!AR68+'9월'!AR68+'10월'!AR68+'11월'!AR68+'12월'!AR68 -> 0 | AD68: =IFERROR(AC68/AC$29,0) -> 0 | AQ68: =+AC68-P68 -> -82402.65 | AR68: =(AD68-Q68)*100 -> -0.39599176
E69: 기타 광고비 | P69: =+'1월'!P69+'2월'!P69+'3월'!P69+'4월'!P69+'5월'!P69+'6월'!P69+'7월'!P69+'8월'!P69+'9월'!P69+'10월'!P69+'11월'!P69+'12월'!P69 -> 9293.2 | Q69: =IFERROR(P69/P$29,0) -> 0.0004465913 | AC69: =+'1월'!AR69+'2월'!AR69+'3월'!AR69+'4월'!AR69+'5월'!AR69+'6월'!AR69+'7월'!AR69+'8월'!AR69+'9월'!AR69+'10월'!AR69+'11월'!AR69+'12월'!AR69 -> 0 | AD69: =IFERROR(AC69/AC$29,0) -> 0 | AQ69: =+AC69-P69 -> -9293.2 | AR69: =(AD69-Q69)*100 -> -0.04465913
B70: Professional Service | C70: SG&A | E70: 지급수수료 | P70: =+'1월'!P70+'2월'!P70+'3월'!P70+'4월'!P70+'5월'!P70+'6월'!P70+'7월'!P70+'8월'!P70+'9월'!P70+'10월'!P70+'11월'!P70+'12월'!P70 -> 1094694.4 | Q70: =IFERROR(P70/P$29,0) -> 0.052606316 | AC70: =+'1월'!AR70+'2월'!AR70+'3월'!AR70+'4월'!AR70+'5월'!AR70+'6월'!AR70+'7월'!AR70+'8월'!AR70+'9월'!AR70+'10월'!AR70+'11월'!AR70+'12월'!AR70 -> 1258119.7 | AD70: =IFERROR(AC70/AC$29,0) -> 0.055135284 | AQ70: =+AC70-P70 -> 163425.24 | AR70: =(AD70-Q70)*100 -> 0.25289687
B71: T&E | C71: SG&A | E71: 식대 / 출장비 | P71: =+'1월'!P71+'2월'!P71+'3월'!P71+'4월'!P71+'5월'!P71+'6월'!P71+'7월'!P71+'8월'!P71+'9월'!P71+'10월'!P71+'11월'!P71+'12월'!P71 -> 136164.59 | Q71: =IFERROR(P71/P$29,0) -> 0.0065434857 | AC71: =+'1월'!AR71+'2월'!AR71+'3월'!AR71+'4월'!AR71+'5월'!AR71+'6월'!AR71+'7월'!AR71+'8월'!AR71+'9월'!AR71+'10월'!AR71+'11월'!AR71+'12월'!AR71 -> 67586.23 | AD71: =IFERROR(AC71/AC$29,0) -> 0.0029618693 | AQ71: =+AC71-P71 -> -68578.36 | AR71: =(AD71-Q71)*100 -> -0.35816164
B72: Rent | C72: SG&A | E72: 임차료 | P72: =+'1월'!P72+'2월'!P72+'3월'!P72+'4월'!P72+'5월'!P72+'6월'!P72+'7월'!P72+'8월'!P72+'9월'!P72+'10월'!P72+'11월'!P72+'12월'!P72 -> 295377.55 | Q72: =IFERROR(P72/P$29,0) -> 0.014194577 | AC72: =+'1월'!AR72+'2월'!AR72+'3월'!AR72+'4월'!AR72+'5월'!AR72+'6월'!AR72+'7월'!AR72+'8월'!AR72+'9월'!AR72+'10월'!AR72+'11월'!AR72+'12월'!AR72 -> 295941.66 | AD72: =IFERROR(AC72/AC$29,0) -> 0.012969217 | AQ72: =+AC72-P72 -> 564.11 | AR72: =(AD72-Q72)*100 -> -0.12253598
B73: Sample | C73: SG&A | E73: 샘플비/개발비 | P73: =+'1월'!P73+'2월'!P73+'3월'!P73+'4월'!P73+'5월'!P73+'6월'!P73+'7월'!P73+'8월'!P73+'9월'!P73+'10월'!P73+'11월'!P73+'12월'!P73 -> 158714.57 | Q73: =IFERROR(P73/P$29,0) -> 0.0076271409 | AC73: =+'1월'!AR73+'2월'!AR73+'3월'!AR73+'4월'!AR73+'5월'!AR73+'6월'!AR73+'7월'!AR73+'8월'!AR73+'9월'!AR73+'10월'!AR73+'11월'!AR73+'12월'!AR73 -> 152321.35 | AD73: =IFERROR(AC73/AC$29,0) -> 0.0066752639 | AQ73: =+AC73-P73 -> -6393.22 | AR73: =(AD73-Q73)*100 -> -0.095187698
B74: Depreciation & Amortization | C74: SG&A | E74: 감가상각비 | P74: =+'1월'!P74+'2월'!P74+'3월'!P74+'4월'!P74+'5월'!P74+'6월'!P74+'7월'!P74+'8월'!P74+'9월'!P74+'10월'!P74+'11월'!P74+'12월'!P74 -> 47549.62 | Q74: =IFERROR(P74/P$29,0) -> 0.0022850306 | AC74: =+'1월'!AR74+'2월'!AR74+'3월'!AR74+'4월'!AR74+'5월'!AR74+'6월'!AR74+'7월'!AR74+'8월'!AR74+'9월'!AR74+'10월'!AR74+'11월'!AR74+'12월'!AR74 -> 45456.06 | AD74: =IFERROR(AC74/AC$29,0) -> 0.0019920464 | AQ74: =+AC74-P74 -> -2093.56 | AR74: =(AD74-Q74)*100 -> -0.029298421
B75: Other | C75: SG&A | E75: 기타비용 | P75: =+'1월'!P75+'2월'!P75+'3월'!P75+'4월'!P75+'5월'!P75+'6월'!P75+'7월'!P75+'8월'!P75+'9월'!P75+'10월'!P75+'11월'!P75+'12월'!P75 -> 518200.58 | Q75: =IFERROR(P75/P$29,0) -> 0.024902495 | AC75: =+'1월'!AR75+'2월'!AR75+'3월'!AR75+'4월'!AR75+'5월'!AR75+'6월'!AR75+'7월'!AR75+'8월'!AR75+'9월'!AR75+'10월'!AR75+'11월'!AR75+'12월'!AR75 -> 110083.24 | AD75: =IFERROR(AC75/AC$29,0) -> 0.0048242396 | AQ75: =+AC75-P75 -> -408117.34 | AR75: =(AD75-Q75)*100 -> -2.0078256
E76: 영업비 소계 | P76: =SUM(P56,P61,P70:P75) -> 7068918.8 | Q76: =IFERROR(P76/P$29,0) -> 0.33970189 | S76: =SUM(S57:S75) -> 0 | T76: =SUM(T57:T75) -> 0 | U76: =SUM(U57:U75) -> 0 | V76: =SUM(V57:V75) -> 0 | W76: =SUM(W57:W75) -> 0 | X76: =SUM(X57:X75) -> 0 | Y76: =SUM(Y57:Y75) -> 0 | Z76: =SUM(Z57:Z75) -> 0 | AC76: =SUM(AC56,AC61,AC70:AC75) -> 7104035.4 | AD76: =IFERROR(AC76/AC$29,0) -> 0.31132413 | AG76: =SUM(AG57:AG75) -> 0 | AH76: =SUM(AH57:AH75) -> 0 | AI76: =SUM(AI57:AI75) -> 0 | AJ76: =SUM(AJ57:AJ75) -> 0 | AK76: =SUM(AK57:AK75) -> 0 | AL76: =SUM(AL57:AL75) -> 0 | AM76: =SUM(AM57:AM75) -> 0 | AN76: =SUM(AN57:AN75) -> 0 | AQ76: =+AC76-P76 -> 35116.68 | AR76: =(AD76-Q76)*100 -> -2.8377762
AQ77: =+AC77-P77 -> 0 | AR77: =(AD77-Q77)*100 -> 0
E78: 영업이익 | P78: =P53-P76 -> 82457.81 | Q78: =IFERROR(P78/P$29,0) -> 0.0039625684 | AC78: =AC53-AC76 -> -1926651.1 | AD78: =IFERROR(AC78/AC$29,0) -> -0.084432712 | AQ78: =+AC78-P78 -> -2009108.9 | AR78: =(AD78-Q78)*100 -> -8.839528
T122: EC | U122: SEM | V122: 비용율
S123: 25 | T123: 16924171 | U123: 3153353.7 | V123: =+U123/T123 -> 0.18632249
S124: 24 | T124: =+H29+J29 -> 17087065 | U124: =+H49+J49 -> 3145130.8 | V124: =+U124/T124 -> 0.18406501
S125: YOY | T125: =+T123/T124 -> 0.99046682 | U125: =+U123/U124 -> 1.0026145

Sheet Sheet1
D4: ACTUALS ONLY | P4: ACTUALS ONLY
C6: MSRP by Channel | D6: 45292 | E6: =EDATE(D6,1) -> 45323 | F6: =EDATE(E6,1) -> 45352 | G6: =EDATE(F6,1) -> 45383 | H6: =EDATE(G6,1) -> 45413 | I6: =EDATE(H6,1) -> 45444 | J6: =EDATE(I6,1) -> 45474 | K6: =EDATE(J6,1) -> 45505 | L6: =EDATE(K6,1) -> 45536 | ... AA6: =EDATE(Z6,1) -> 45992
C7: Ecom EU | D7: 180352 | E7: 157449 | F7: 167469 | G7: 224326 | H7: 215504 | I7: 171530 | J7: 157507 | K7: 161389 | L7: 214522 | M7: 203444 | N7: 199692 | O7: 225205 | P7: 129378 | Q7: 117896 | R7: 145387 | S7: 137621 | T7: 121769 | U7: 114510 | V7: 172090 | W7: 75984 | X7: 52689 | Y7: 82108 | Z7: 0 | AA7: 0
C8: Ecom US | D8: 1525290 | E8: 1765020 | F8: 1786154 | G8: 2018677 | H8: 2128892 | I8: 1902379 | J8: 1408747 | K8: 2038406 | L8: 1744721 | M8: 2050944 | N8: 2828446 | O8: 3163654 | P8: 1732286 | Q8: 1641273 | R8: 2161964 | S8: 1868116 | T8: 2182779 | U8: 2431420 | V8: 2705268 | W8: 2458769 | X8: 2735265 | Y8: 3265535 | Z8: 0 | AA8: 0
C9: Other | W9: 382948
C10: Wholesale | D10: 606280 | E10: 723694 | F10: 823502 | G10: 815968 | H10: 511352 | I10: 190928 | J10: 239669 | K10: 957253 | L10: 945416 | M10: 468854 | N10: 113185 | O10: 184688 | P10: 255066 | Q10: 450064 | R10: 656647 | S10: 509987 | T10: 236300 | U10: 165965 | V10: 220259 | W10: 475437 | X10: 417600 | Y10: 563572 | Z10: 0 | AA10: 0
C11: TOTAL | D11: =SUM(D7:D10) -> 2311922 | E11: =SUM(E7:E10) -> 2646163 | F11: =SUM(F7:F10) -> 2777125 | G11: =SUM(G7:G10) -> 3058971 | H11: =SUM(H7:H10) -> 2855748 | I11: =SUM(I7:I10) -> 2264837 | J11: =SUM(J7:J10) -> 1805923 | K11: =SUM(K7:K10) -> 3157048 | ... AA11: =SUM(AA7:AA10) -> 0

Sheet Sheet2
C4: 24년 | D4: 1월 | E4: 2월 | F4: 3월 | G4: 4월 | H4: 5월 | I4: 6월 | J4: 7월 | K4: 8월 | L4: 9월 | M4: 10월 | N4: 11월 | O4: 12월
C5: 홀세일 | D5: =+'1월'!G29 -> 0.5921622 | E5: =+'2월'!G29 -> 0.5929817 | F5: =+'3월'!G29 -> 0.60599169 | G5: =+'4월'!G29 -> 0.60550493 | H5: =+'5월'!G29 -> 0.66853866 | I5: =+'6월'!G29 -> 0.70084393 | J5: =+'7월'!G29 -> 0.63288932 | K5: =+'8월'!G29 -> 0.5863908 | L5: =+'9월'!G29 -> 0.58955634 | M5: =+'10월'!G29 -> 0.62584579
C6: US EC | D6: =+'1월'!I29 -> 0.24512349 | E6: =+'2월'!I29 -> 0.38656759 | F6: =+'3월'!I29 -> 0.28042424 | G6: =+'4월'!I29 -> 0.33569395 | H6: =+'5월'!I29 -> 0.3815419 | I6: =+'6월'!I29 -> 0.39296799 | J6: =+'7월'!I29 -> 0.384772 | K6: =+'8월'!I29 -> 0.45164419 | L6: =+'9월'!I29 -> 0.37960203 | M6: =+'10월'!I29 -> 0.38753482
C7: EU EC | D7: =+'1월'!K29 -> 0.16501974 | E7: =+'2월'!K29 -> 0.22843753 | F7: =+'3월'!K29 -> 0.0058081197 | G7: =+'4월'!K29 -> 0.088784358 | H7: =+'5월'!K29 -> 0.18101014 | I7: =+'6월'!K29 -> 0.23761086 | J7: =+'7월'!K29 -> 0.2090801 | K7: =+'8월'!K29 -> 0.27446381 | L7: =+'9월'!K29 -> 0.22956032 | M7: =+'10월'!K29 -> 0.26904229
C8: 전체할인율 | D8: =+'1월'!Q29 -> 0.32195703 | E8: =+'2월'!Q29 -> 0.41821618 | F8: =+'3월'!Q29 -> 0.35316745 | G8: =+'4월'!Q29 -> 0.37669824 | H8: =+'5월'!Q29 -> 0.3865302 | I8: =+'6월'!Q29 -> 0.39734596 | J8: =+'7월'!Q29 -> 0.37722958 | K8: =+'8월'!Q29 -> 0.46808193 | L8: =+'9월'!Q29 -> 0.42348106 | M8: =+'10월'!Q29 -> 0.4048491
C12: 25년 | D12: 1월 | E12: 2월 | F12: 3월 | G12: 4월 | H12: 5월 | I12: 6월 | J12: 7월 | K12: 8월 | L12: 9월 | M12: 10월 | N12: 11월 | O12: 12월
C13: 홀세일 | D13: =+'1월'!AI29 -> 0.64995158 | E13: =+'2월'!AI29 -> 0.60484676 | F13: =+'3월'!AI29 -> 0.58294548 | G13: =+'4월'!AI29 -> 0.58773273 | H13: =+'5월'!AI29 -> 0.69105836 | I13: =+'6월'!AI29 -> 0.77649095 | J13: =+'7월'!AI29 -> 0.71564431 | K13: =+'8월'!AI29 -> 0.6500509 | L13: =+'9월'!AI29 -> 0.58887763 | M13: =+'10월'!AI29 -> 0.641836
C14: US EC | D14: =+'1월'!AK29 -> 0.38318238 | E14: =+'2월'!AK29 -> 0.41672229 | F14: =+'3월'!AK29 -> 0.36497645 | G14: =+'4월'!AK29 -> 0.32159264 | H14: =+'5월'!AK29 -> 0.31778559 | I14: =+'6월'!AK29 -> 0.35863603 | J14: =+'7월'!AK29 -> 0.48784755 | K14: =+'8월'!AK29 -> 0.50132808 | L14: =+'9월'!AK29 -> 0.48978677 | M14: =+'10월'!AK29 -> 0.50533147
C15: EU EC | D15: =+'1월'!AM29 -> 0.30672927 | E15: =+'2월'!AM29 -> 0.45267906 | F15: =+'3월'!AM29 -> 0.40275142 | G15: =+'4월'!AM29 -> 0.31725151 | H15: =+'5월'!AM29 -> 0.31995442 | I15: =+'6월'!AM29 -> 0.39541682 | J15: =+'7월'!AM29 -> 0.49435156 | K15: =+'8월'!AM29 -> 0.4424546 | L15: =+'9월'!AM29 -> 0.42784908 | M15: =+'10월'!AM29 -> 0.41685219
C16: 전체할인율 | D16: =+'1월'!AS29 -> 0.39416272 | E16: =+'2월'!AS29 -> 0.44759729 | F16: =+'3월'!AS29 -> 0.40377875 | G16: =+'4월'!AS29 -> 0.36629098 | H16: =+'5월'!AS29 -> 0.34562337 | I16: =+'6월'!AS29 -> 0.38096615 | J16: =+'7월'!AS29 -> 0.48919926 | K16: =+'8월'!AS29 -> 0.49766904 | L16: =+'9월'!AS29 -> 0.48692394 | M16: =+'10월'!AS29 -> 0.51388881
C19: YOY | D19: 1월 | E19: 2월 | F19: 3월 | G19: 4월 | H19: 5월 | I19: 6월 | J19: 7월 | K19: 8월 | L19: 9월 | M19: 10월 | N19: 11월 | O19: 12월
C20: 홀세일
C21: US EC
C22: EU EC

Sheet 1월
E5: 45931
E7: Date | F7: =EDATE($E$5,-12) -> 45566 | H7: =F7 -> 45566 | J7: =H7 -> 45566 | L7: =J7 -> 45566 | N7: =L7 -> 45566 | P7: =L7 -> 45566 | T7: =EDATE($E$5,0) -> 45931 | V7: =T7 -> 45931 | X7: =V7 -> 45931 | Z7: =X7 -> 45931 | AB7: =Z7 -> 45931 | AD7: =Z7 -> 45931 | AH7: =EDATE($E$5,0) -> 45931 | AJ7: =AH7 -> 45931 | AL7: =AJ7 -> 45931 | AN7: =AL7 -> 45931 | AP7: =AN7 -> 45931 | AR7: =AN7 -> 45931 | AV7: =EDATE($E$5,0) -> 45931 | AX7: =AV7 -> 45931 | AZ7: =AX7 -> 45931 | BD7: =BB7 -> 0 | BF7: =BB7 -> 0
E8: Category | F8: Wholesale | H8: Ecommerce (US) | J8: Ecommerce (EU) | L8: License | N8: Other Income | T8: Wholesale | V8: Ecommerce (US) | X8: Ecommerce (EU) | Z8: License | AB8: Other Income | AH8: Wholesale | AJ8: Ecommerce (US) | AL8: Ecommerce (EU) | AN8: License | AP8: Other Income | AV8: Wholesale | AX8: Ecommerce (US) | AZ8: Ecommerce (EU) | BD8: Other Income
E9: M | F9: =MONTH(F7) -> 10 | T9: =MONTH(T7) -> 10 | AH9: =MONTH(AH7) -> 10 | AV9: =MONTH(AV7) -> 10
E10: Q | F10: ="Q"&ROUNDUP(MONTH(F7)/3,0)&"'"&TEXT(F7,"yy") -> Q4'24 | T10: ="Q"&ROUNDUP(MONTH(T7)/3,0)&"'"&TEXT(T7,"yy") -> Q4'25 | AH10: ="Q"&ROUNDUP(MONTH(AH7)/3,0)&"'"&TEXT(AH7,"yy") -> Q4'25 | AV10: ="Q"&ROUNDUP(MONTH(AV7)/3,0)&"'"&TEXT(AV7,"yy") -> Q4'25
E11: H | F11: ="H"&ROUNDUP(MONTH(F7)/6,0)&"'"&TEXT(F7,"yy") -> H2'24 | T11: ="H"&ROUNDUP(MONTH(T7)/6,0)&"'"&TEXT(T7,"yy") -> H2'25 | AH11: ="H"&ROUNDUP(MONTH(AH7)/6,0)&"'"&TEXT(AH7,"yy") -> H2'25 | AV11: ="H"&ROUNDUP(MONTH(AV7)/6,0)&"'"&TEXT(AV7,"yy") -> H2'25
E12: Y | F12: =YEAR(F7) -> 2024 | T12: =YEAR(T7) -> 2025 | AH12: =YEAR(AH7) -> 2025 | AV12: =YEAR(AV7) -> 2025
E13: Actual / Forecast | F13: Actual | T13: Forecast | AH13: Actual | AV13: Actual
F15: Last Year - Current Month | T15: Budget - Current Month | AH15: Actual - Current Month | AV15: vs Plan
F17: STO 24년 1월 전년 실적 | P17: STO 24년 1월 전년 실적 | T17: ="STO"&" "&RIGHT(YEAR($E$5),2)&"년"&" "&MONTH($E$5)&"월 당월 계획" -> STO 25년 10월 당월 계획 | AD17: ="STO"&" "&RIGHT(YEAR($E$5),2)&"년"&" "&MONTH($E$5)&"월 당월 계획" -> STO 25년 10월 당월 계획 | AH17: STO 25년 1월 당월 실적 | AR17: STO 25년 1월 당월 실적 | AV17: ="STO"&" "&RIGHT(YEAR($E$5),2)&"년"&" "&MONTH($E$5)&"월 계획대비" -> STO 25년 10월 계획대비 | BF17: ="STO"&" "&RIGHT(YEAR($E$5),2)&"년"&" "&MONTH($E$5)&"월 당월 실적" -> STO 25년 10월 당월 실적
F18: 홀세일(미국) | H18: 온라인(미국) | J18: 온라인(유럽) | L18: 라이선스 | N18: 기타 | P18: STO 합계 | T18: 홀세일(미국) | V18: 온라인(미국) | X18: 온라인(유럽) | Z18: 라이선스 | AB18: 기타 | AD18: STO 합계 | AH18: 홀세일(미국) | AJ18: 온라인(미국) | AL18: 온라인(유럽) | AN18: 라이선스 | AP18: 기타 | AR18: STO 합계 | AV18: 홀세일(미국) | AX18: 온라인(미국) | AZ18: 온라인(유럽) | BB18: 라이선스 | BD18: 기타 | BF18: STO 합계
E19: STO/STIP
E20: 라이선스
E21: 홀세일(미국)
E22: 온라인(미국)
E23: 할인율(%)
E24: 생산원가율(%)
E25: 온라인(유럽)
E26: 매출액(할인전) 계
E27: 총매출 (MSRP) | F27: 606280 | H27: 1525290 | J27: 180352 | L27: 56910.08 | N27: 0 | P27: 2368832.1 | T27: 255066 | V27: 1732286 | X27: 129378 | Z27: 88567.46 | AB27: 0 | AD27: 2205297.5 | AH27: 255066 | AJ27: 1732286 | AL27: 129378 | AN27: 88567.46 | AP27: 0 | AR27: 2205297.5 | AV27: =AH27-T27 -> 0 | AX27: =AJ27-V27 -> 0 | AZ27: =AL27-X27 -> 0 | BB27: =AN27-Z27 -> 0 | BD27: =AP27-AB27 -> 0 | BF27: =AR27-AD27 -> 0
E28: 할인액 | F28: 359016.1 | H28: 373884.41 | J28: 29761.64 | L28: 0 | N28: 0 | P28: 762662.15 | T28: 165780.55 | V28: 663781.48 | X28: 39684.02 | Z28: 0 | AB28: 0 | AD28: 869246.05 | AH28: 165780.55 | AJ28: 663781.48 | AL28: 39684.02 | AN28: 0 | AP28: 0 | AR28: 869246.05 | AV28: =AH28-T28 -> 0 | AX28: =AJ28-V28 -> 0 | AZ28: =AL28-X28 -> 0 | BB28: =AN28-Z28 -> 0 | BD28: =AP28-AB28 -> 0 | BF28: =AR28-AD28 -> 0
C29: Revenue | E29: 실판매 | F29: 247263.9 | G29: 0.5921622 | H29: 1151405.6 | I29: 0.24512349 | J29: 150590.36 | K29: 0.16501974 | L29: 56910.08 | M29: 0 | N29: 0 | O29: 0 | P29: 1606169.9 | Q29: 0.32195703 | T29: 89285.45 | U29: 0.64995158 | V29: 1068504.5 | W29: 0.38318238 | X29: 89693.98 | Y29: 0.30672927 | Z29: 88567.46 | AA29: 0 | AB29: 0 | AC29: 0 | AD29: 1336051.4 | AE29: 0.39416272 | AH29: 89285.45 | AI29: 0.64995158 | AJ29: 1068504.5 | AK29: 0.38318238 | AL29: 89693.98 | AM29: 0.30672927 | AN29: 88567.46 | AO29: 0 | AP29: 0 | AQ29: 0 | AR29: 1336051.4 | AS29: 0.39416272 | AV29: =AH29-T29 -> 0 | AW29: =(AI29-U29)*100 -> 0 | AX29: =AJ29-V29 -> 0 | AY29: =(AK29-W29)*100 -> 0 | AZ29: =AL29-X29 -> 0 | BA29: =(AM29-Y29)*100 -> 0 | BB29: =AN29-Z29 -> 0 | BC29: =(AO29-AA29)*100 -> 0 | BD29: =AP29-AB29 -> 0 | BE29: =(AQ29-AC29)*100 -> 0 | BF29: =AR29-AD29 -> 0 | BG29: =(AS29-AE29)*100 -> 0
E30: 제품매출
E31: 기타매출
E33: 계획대비 | F33: n/a | G33: n/a | H33: n/a | I33: n/a | J33: n/a | K33: n/a | L33: n/a | M33: n/a | N33: n/a | O33: n/a | P33: n/a | Q33: n/a | AH33: 0 | AI33: 0 | AJ33: 0 | AK33: 0 | AL33: 0 | AM33: 0 | AN33: 0 | AO33: 0 | AP33: 0 | AQ33: 0 | AR33: 0 | AS33: 0
E34: 전년대비 | F34: n/a | G34: n/a | H34: n/a | I34: n/a | J34: n/a | K34: n/a | L34: n/a | M34: n/a | N34: n/a | O34: n/a | P34: n/a | Q34: n/a | T34: -157978.45 | U34: -0.63890625 | V34: -82901.07 | W34: -0.071999885 | X34: -60896.38 | Y34: -0.40438432 | Z34: 31657.38 | AA34: 0.55627017 | AB34: 0 | AC34: 0 | AD34: -270118.52 | AE34: -0.16817556 | AH34: -157978.45 | AI34: -0.63890625 | AJ34: -82901.07 | AK34: -0.071999885 | AL34: -60896.38 | AM34: -0.40438432 | AN34: 31657.38 | AO34: 0.55627017 | AP34: 0 | AQ34: 0 | AR34: -270118.52 | AS34: -0.16817556
C36: COGS | E36: 매출원가 | F36: 107402.76 | G36: 0.4343649 | H36: 345142.08 | I36: 0.29975717 | J36: 37225.1 | K36: 0.24719444 | L36: 0 | M36: 0 | N36: 0 | O36: 0 | P36: 489769.94 | Q36: 0.30493034 | T36: 39955.21 | U36: 0.44749968 | V36: 365096.35 | W36: 0.3416891 | X36: 26831.89 | Y36: 0.29914929 | Z36: 0 | AA36: 0 | AB36: -49448.72 | AC36: 0 | AD36: 382434.73 | AE36: 0.28624253 | AH36: 39955.21 | AI36: 0.44749968 | AJ36: 365096.35 | AK36: 0.3416891 | AL36: 26831.89 | AM36: 0.29914929 | AN36: 0 | AO36: 0 | AP36: -49448.72 | AQ36: 0 | AR36: 382434.73 | AS36: 0.28624253 | AV36: =AH36-T36 -> 0 | AW36: =(AI36-U36)*100 -> 1.110223e-14 | AX36: =AJ36-V36 -> 0 | AY36: =(AK36-W36)*100 -> 0 | AZ36: =AL36-X36 -> 0 | BA36: =(AM36-Y36)*100 -> 0 | BB36: =AN36-Z36 -> 0 | BC36: =(AO36-AA36)*100 -> 0 | BD36: =AP36-AB36 -> 0 | BE36: =(AQ36-AC36)*100 -> 0 | BF36: =AR36-AD36 -> 0 | BG36: =(AS36-AE36)*100 -> 0
E37: 기타원가 | AV37: =AH37-T37 -> 0 | AW37: =(AI37-U37)*100 -> 0 | AX37: =AJ37-V37 -> 0 | AY37: =(AK37-W37)*100 -> 0 | AZ37: =AL37-X37 -> 0 | BA37: =(AM37-Y37)*100 -> 0 | BB37: =AN37-Z37 -> 0 | BC37: =(AO37-AA37)*100 -> 0 | BD37: =AP37-AB37 -> 0 | BE37: =(AQ37-AC37)*100 -> 0 | BF37: =AR37-AD37 -> 0 | BG37: =(AS37-AE37)*100 -> 0
E38: 분기원가조정 | AV38: =AH38-T38 -> 0 | AW38: =(AI38-U38)*100 -> 0 | AX38: =AJ38-V38 -> 0 | AY38: =(AK38-W38)*100 -> 0 | AZ38: =AL38-X38 -> 0 | BA38: =(AM38-Y38)*100 -> 0 | BB38: =AN38-Z38 -> 0 | BC38: =(AO38-AA38)*100 -> 0 | BD38: =AP38-AB38 -> 0 | BE38: =(AQ38-AC38)*100 -> 0 | BF38: =AR38-AD38 -> 0 | BG38: =(AS38-AE38)*100 -> 0
E39: (생산원가율, M/U) | F39: 0.17715043 | G39: 5.6449201 | H39: 0.22627965 | I39: 4.4193104 | J39: 0.20640248 | K39: 4.844903 | L39: 0 | M39: 0 | N39: 0 | O39: 0 | P39: 0.20675587 | Q39: 4.836622 | T39: 0.15664655 | U39: 6.3837983 | V39: 0.21075986 | W39: 4.7447366 | X39: 0.20739144 | Y39: 4.8217997 | Z39: 0 | AA39: 0 | AB39: 0 | AC39: 0 | AD39: 0.17341639 | AE39: 5.7664675 | AH39: 0.15664655 | AI39: 6.3837983 | AJ39: 0.21075986 | AK39: 4.7447366 | AL39: 0.20739144 | AM39: 4.8217997 | AN39: 0 | AO39: 0 | AP39: 0 | AQ39: 0 | AR39: 0.17341639 | AS39: 5.7664675 | AV39: =(AH39-T39)*100 -> 2.7755576e-15 | AW39: =(AI39-U39) -> -1.7763568e-15 | AX39: =(AJ39-V39)*100 -> 0 | AY39: =(AK39-W39) -> 0 | AZ39: =(AL39-X39)*100 -> 0 | BA39: =(AM39-Y39) -> 0 | BB39: =AN39-Z39 -> 0 | BC39: =(AO39-AA39) -> 0 | BD39: =AP39-AB39 -> 0 | BE39: =(AQ39-AC39) -> 0 | BF39: =(AR39-AD39)*100 -> 0 | BG39: =(AS39-AE39) -> 0
E40: 매출총이익 | F40: 139861.14 | G40: 0.5656351 | H40: 806263.51 | I40: 0.70024283 | J40: 113365.26 | K40: 0.75280556 | L40: 56910.08 | M40: 1 | N40: 0 | O40: 0 | P40: 1116400 | Q40: 0.69506966 | T40: 49330.24 | U40: 0.55250032 | V40: 703408.17 | W40: 0.6583109 | X40: 62862.09 | Y40: 0.70085071 | Z40: 88567.46 | AA40: 1 | AB40: 49448.72 | AC40: 0 | AD40: 953616.68 | AE40: 0.71375747 | AH40: 49330.24 | AI40: 0.55250032 | AJ40: 703408.17 | AK40: 0.6583109 | AL40: 62862.09 | AM40: 0.70085071 | AN40: 88567.46 | AO40: 1 | AP40: 49448.72 | AQ40: 0 | AR40: 953616.68 | AS40: 0.71375747 | AV40: =AH40-T40 -> 0 | AW40: =(AI40-U40)*100 -> 0 | AX40: =AJ40-V40 -> 0 | AY40: =(AK40-W40)*100 -> 0 | AZ40: =AL40-X40 -> 0 | BA40: =(AM40-Y40)*100 -> 0 | BB40: =AN40-Z40 -> 0 | BC40: =(AO40-AA40)*100 -> 0 | BD40: =AP40-AB40 -> 0 | BE40: =(AQ40-AC40)*100 -> 0 | BF40: =AR40-AD40 -> 0 | BG40: =(AS40-AE40)*100 -> 0
E42: 직접비
E43: 운반비/보관료/ 물류용역비 | F43: 35880.81 | G43: 0.1451114 | H43: 150457.2 | I43: 0.13067263 | J43: 27043.85 | K43: 0.17958553 | L43: 0 | M43: 0 | N43: 0 | O43: 0 | P43: 213381.86 | Q43: 0.13285136 | T43: 3895.55 | U43: 0.043630289 | V43: 121533.97 | W43: 0.11374212 | X43: 15441.72 | Y43: 0.17216005 | Z43: 0 | AA43: 0 | AB43: 0 | AC43: 0 | AD43: 140871.24 | AE43: 0.10543849 | AH43: 6642.03 | AI43: 0.074390956 | AJ43: 122851.97 | AK43: 0.11497562 | AL43: 15503.02 | AM43: 0.17284348 | AN43: 0 | AO43: 0 | AP43: 0 | AQ43: 0 | AR43: 144997.02 | AS43: 0.10852653 | AV43: =AH43-T43 -> 2746.48 | AW43: =(AI43-U43)*100 -> 3.0760667 | AX43: =AJ43-V43 -> 1318 | AY43: =(AK43-W43)*100 -> 0.12334997 | AZ43: =AL43-X43 -> 61.3 | BA43: =(AM43-Y43)*100 -> 0.068343494 | BB43: =AN43-Z43 -> 0 | BC43: =(AO43-AA43)*100 -> 0 | BD43: =AP43-AB43 -> 0 | BE43: =(AQ43-AC43)*100 -> 0 | BF43: =AR43-AD43 -> 4125.78 | BG43: =(AS43-AE43)*100 -> 0.30880399
B44: 운반비 | C44: 운반비 (-) | E44: 운반비 | F44: 2051.12 | G44: 0.0082952667 | H44: 10539.6 | I44: 0.0091536815 | J44: 17616.47 | K44: 0.11698272 | L44: 0 | M44: 0 | N44: 0 | O44: 0 | P44: 30207.19 | Q44: 0.01880697 | T44: -786.65 | U44: -0.0088105061 | V44: 66495.8 | W44: 0.062232587 | X44: 6623.48 | Y44: 0.073845313 | Z44: 0 | AA44: 0 | AB44: 0 | AC44: 0 | AD44: 72332.63 | AE44: 0.054139107 | AH44: 1959.83 | AI44: 0.021950161 | AJ44: 67813.8 | AK44: 0.063466086 | AL44: 6684.78 | AM44: 0.074528748 | AN44: 0 | AO44: 0 | AP44: 0 | AQ44: 0 | AR44: 76458.41 | AS44: 0.057227147 | AV44: =AH44-T44 -> 2746.48 | AW44: =(AI44-U44)*100 -> 3.0760667 | AX44: =AJ44-V44 -> 1318 | AY44: =(AK44-W44)*100 -> 0.12334997 | AZ44: =AL44-X44 -> 61.3 | BA44: =(AM44-Y44)*100 -> 0.068343494 | BB44: =AN44-Z44 -> 0 | BC44: =(AO44-AA44)*100 -> 0 | BD44: =AP44-AB44 -> 0 | BE44: =(AQ44-AC44)*100 -> 0 | BF44: =AR44-AD44 -> 4125.78 | BG44: =(AS44-AE44)*100 -> 0.30880399
B45: 보관료 | E45: 보관료 | F45: 20453.52 | G45: 0.082719394 | H45: 21703.97 | I45: 0.018849978 | J45: 3215.9 | K45: 0.021355285 | L45: 0 | M45: 0 | N45: 0 | O45: 0 | P45: 45373.39 | Q45: 0.028249433 | T45: 1977.76 | U45: 0.022150978 | V45: 19001.76 | W45: 0.017783509 | X45: 1594.64 | Y45: 0.017778674 | Z45: 0 | AA45: 0 | AB45: 0 | AC45: 0 | AD45: 22574.16 | AE45: 0.016896176 | AH45: 1977.76 | AI45: 0.022150978 | AJ45: 19001.76 | AK45: 0.017783509 | AL45: 1594.64 | AM45: 0.017778674 | AN45: 0 | AO45: 0 | AP45: 0 | AQ45: 0 | AR45: 22574.16 | AS45: 0.016896176 | AV45: =AH45-T45 -> 0 | AW45: =(AI45-U45)*100 -> 0 | AX45: =AJ45-V45 -> 0 | AY45: =(AK45-W45)*100 -> 0 | AZ45: =AL45-X45 -> 0 | BA45: =(AM45-Y45)*100 -> 0 | BB45: =AN45-Z45 -> 0 | BC45: =(AO45-AA45)*100 -> 0 | BD45: =AP45-AB45 -> 0 | BE45: =(AQ45-AC45)*100 -> 0 | BF45: =AR45-AD45 -> 0 | BG45: =(AS45-AE45)*100 -> 0
B46: 물류용역비 | E46: 물류용역비 | F46: 13376.17 | G46: 0.054096736 | H46: 118213.63 | I46: 0.10266897 | J46: 6211.48 | K46: 0.041247527 | L46: 0 | M46: 0 | N46: 0 | O46: 0 | P46: 137801.28 | Q46: 0.085794957 | T46: 2704.44 | U46: 0.030289818 | V46: 36036.41 | W46: 0.033726025 | X46: 7223.6 | Y46: 0.080536063 | Z46: 0 | AA46: 0 | AB46: 0 | AC46: 0 | AD46: 45964.45 | AE46: 0.034403205 | AH46: 2704.44 | AI46: 0.030289818 | AJ46: 36036.41 | AK46: 0.033726025 | AL46: 7223.6 | AM46: 0.080536063 | AN46: 0 | AO46: 0 | AP46: 0 | AQ46: 0 | AR46: 45964.45 | AS46: 0.034403205 | AV46: =AH46-T46 -> 0 | AW46: =(AI46-U46)*100 -> -6.9388939e-16 | AX46: =AJ46-V46 -> 0 | AY46: =(AK46-W46)*100 -> 6.9388939e-16 | AZ46: =AL46-X46 -> 0 | BA46: =(AM46-Y46)*100 -> 0 | BB46: =AN46-Z46 -> 0 | BC46: =(AO46-AA46)*100 -> 0 | BD46: =AP46-AB46 -> 0 | BE46: =(AQ46-AC46)*100 -> 0 | BF46: =AR46-AD46 -> 0 | BG46: =(AS46-AE46)*100 -> 6.9388939e-16
B47: Professional Service | C47: Direct Costs | E47: 지급수수료 | F47: 1570.45 | G47: 0.0063513113 | H47: 61033.8 | I47: 0.05300808 | J47: 4823.26 | K47: 0.032029009 | L47: 0 | M47: 0 | N47: 0 | O47: 0 | P47: 67427.51 | Q47: 0.041980309 | T47: 2397.86 | U47: 0.026856111 | V47: 66883.67 | W47: 0.062595589 | X47: 5071.06 | Y47: 0.056537351 | Z47: 0 | AA47: 0 | AB47: 0 | AC47: 0 | AD47: 74352.59 | AE47: 0.055650995 | AH47: 2397.86 | AI47: 0.026856111 | AJ47: 66883.82 | AK47: 0.06259573 | AL47: 5071.06 | AM47: 0.056537351 | AN47: 0 | AO47: 0 | AP47: 0 | AQ47: 0 | AR47: 74352.74 | AS47: 0.055651107 | AV47: =AH47-T47 -> 0 | AW47: =(AI47-U47)*100 -> 0 | AX47: =AJ47-V47 -> 0.15 | AY47: =(AK47-W47)*100 -> 1.4038312e-05 | AZ47: =AL47-X47 -> 0 | BA47: =(AM47-Y47)*100 -> 0 | BB47: =AN47-Z47 -> 0 | BC47: =(AO47-AA47)*100 -> 0 | BD47: =AP47-AB47 -> 0 | BE47: =(AQ47-AC47)*100 -> 0 | BF47: =AR47-AD47 -> 0.15 | BG47: =(AS47-AE47)*100 -> 1.1227113e-05
B48: 6451 - Service Processing Fee | C48: Direct Costs | E48: 결제수수료 | F48: 1230.77 | G48: 0.0049775564 | H48: 35943.69 | I48: 0.031217227 | J48: 10356.83 | K48: 0.068774854 | L48: 0 | M48: 0 | N48: 0 | O48: 0 | P48: 47531.29 | Q48: 0.02959294 | T48: 2170.32 | U48: 0.024307656 | V48: 63248.96 | W48: 0.05919391 | X48: 5196.25 | Y48: 0.057933097 | Z48: 0 | AA48: 0 | AB48: 0 | AC48: 0 | AD48: 70615.53 | AE48: 0.052853902 | AH48: 2170.32 | AI48: 0.024307656 | AJ48: 63248.81 | AK48: 0.059193769 | AL48: 5196.25 | AM48: 0.057933097 | AN48: 0 | AO48: 0 | AP48: 0 | AQ48: 0 | AR48: 70615.38 | AS48: 0.05285379 | AV48: =AH48-T48 -> 0 | AW48: =(AI48-U48)*100 -> 0 | AX48: =AJ48-V48 -> -0.15 | AY48: =(AK48-W48)*100 -> -1.4038312e-05 | AZ48: =AL48-X48 -> 0 | BA48: =(AM48-Y48)*100 -> 0 | BB48: =AN48-Z48 -> 0 | BC48: =(AO48-AA48)*100 -> 0 | BD48: =AP48-AB48 -> 0 | BE48: =(AQ48-AC48)*100 -> 0 | BF48: =AR48-AD48 -> -0.15 | BG48: =(AS48-AE48)*100 -> -1.1227113e-05
B49: Marketing | C49: Direct Costs | E49: SEM 광고비 | F49: 0 | G49: 0 | H49: 179265.18 | I49: 0.15569247 | J49: 23445.784 | K49: 0.15569247 | L49: 0 | M49: 0 | N49: 0 | O49: 0 | P49: 202710.96 | Q49: 0.12620767 | T49: 0 | U49: 0 | V49: 177488.77 | W49: 0.16610952 | X49: 16064.23 | Y49: 0.17910043 | Z49: 0 | AA49: 0 | AB49: 0 | AC49: 0 | AD49: 193553 | AE49: 0.14486943 | AH49: 0 | AI49: 0 | AJ49: 177488.77 | AK49: 0.16610952 | AL49: 16064.23 | AM49: 0.17910043 | AN49: 0 | AO49: 0 | AP49: 0 | AQ49: 0 | AR49: 193553 | AS49: 0.14486943 | AV49: =AH49-T49 -> 0 | AW49: =(AI49-U49)*100 -> 0 | AX49: =AJ49-V49 -> 0 | AY49: =(AK49-W49)*100 -> 0 | AZ49: =AL49-X49 -> 0 | BA49: =(AM49-Y49)*100 -> 0 | BB49: =AN49-Z49 -> 0 | BC49: =(AO49-AA49)*100 -> 0 | BD49: =AP49-AB49 -> 0 | BE49: =(AQ49-AC49)*100 -> 0 | BF49: =AR49-AD49 -> 0 | BG49: =(AS49-AE49)*100 -> 0
B50: Other | C50: Direct Costs | E50: 기타비용 | F50: 0 | G50: 0 | H50: 0 | I50: 0 | J50: 0 | K50: 0 | L50: 0 | M50: 0 | N50: 0 | O50: 0 | P50: 0 | Q50: 0 | T50: 0 | U50: 0 | V50: 0 | W50: 0 | X50: 0 | Y50: 0 | Z50: 0 | AA50: 0 | AB50: 0 | AC50: 0 | AD50: 0 | AE50: 0 | AH50: 0 | AI50: 0 | AJ50: 0 | AK50: 0 | AL50: 0 | AM50: 0 | AN50: 0 | AO50: 0 | AP50: 0 | AQ50: 0 | AR50: 0 | AS50: 0 | AV50: =AH50-T50 -> 0 | AW50: =(AI50-U50)*100 -> 0 | AX50: =AJ50-V50 -> 0 | AY50: =(AK50-W50)*100 -> 0 | AZ50: =AL50-X50 -> 0 | BA50: =(AM50-Y50)*100 -> 0 | BB50: =AN50-Z50 -> 0 | BC50: =(AO50-AA50)*100 -> 0 | BD50: =AP50-AB50 -> 0 | BE50: =(AQ50-AC50)*100 -> 0 | BF50: =AR50-AD50 -> 0 | BG50: =(AS50-AE50)*100 -> 0
E51: 직접비 소계 | F51: 38682.03 | G51: 0.15644026 | H51: 426699.87 | I51: 0.37059041 | J51: 65669.724 | K51: 0.43608186 | L51: 0 | M51: 0 | N51: 0 | O51: 0 | P51: 531051.62 | Q51: 0.33063228 | T51: 8463.73 | U51: 0.094794057 | V51: 429155.37 | W51: 0.40164114 | X51: 41773.26 | Y51: 0.46573092 | Z51: 0 | AA51: 0 | AB51: 0 | AC51: 0 | AD51: 479392.36 | AE51: 0.35881281 | AH51: 11210.21 | AI51: 0.12555472 | AJ51: 430473.37 | AK51: 0.40287464 | AL51: 41834.56 | AM51: 0.46641436 | AN51: 0 | AO51: 0 | AP51: 0 | AQ51: 0 | AR51: 483518.14 | AS51: 0.36190085 | AV51: =AH51-T51 -> 2746.48 | AW51: =(AI51-U51)*100 -> 3.0760667 | AX51: =AJ51-V51 -> 1318 | AY51: =(AK51-W51)*100 -> 0.12334997 | AZ51: =AL51-X51 -> 61.3 | BA51: =(AM51-Y51)*100 -> 0.068343494 | BB51: =AN51-Z51 -> 0 | BC51: =(AO51-AA51)*100 -> 0 | BD51: =AP51-AB51 -> 0 | BE51: =(AQ51-AC51)*100 -> 0 | BF51: =AR51-AD51 -> 4125.78 | BG51: =(AS51-AE51)*100 -> 0.30880399
E53: 직접이익 | F53: 101179.11 | G53: 0.40919483 | H53: 379563.64 | I53: 0.32965242 | J53: 47695.536 | K53: 0.3167237 | L53: 56910.08 | M53: 1 | N53: 0 | O53: 0 | P53: 585348.37 | Q53: 0.36443739 | T53: 40866.51 | U53: 0.45770627 | V53: 274252.8 | W53: 0.25666976 | X53: 21088.83 | Y53: 0.23511979 | Z53: 88567.46 | AA53: 1 | AB53: 49448.72 | AC53: 0 | AD53: 474224.32 | AE53: 0.35494466 | AH53: 38120.03 | AI53: 0.4269456 | AJ53: 272934.8 | AK53: 0.25543626 | AL53: 21027.53 | AM53: 0.23443636 | AN53: 88567.46 | AO53: 1 | AP53: 49448.72 | AQ53: 0 | AR53: 470098.54 | AS53: 0.35185663 | AV53: =AH53-T53 -> -2746.48 | AW53: =(AI53-U53)*100 -> -3.0760667 | AX53: =AJ53-V53 -> -1318 | AY53: =(AK53-W53)*100 -> -0.12334997 | AZ53: =AL53-X53 -> -61.3 | BA53: =(AM53-Y53)*100 -> -0.068343494 | BB53: =AN53-Z53 -> 0 | BC53: =(AO53-AA53)*100 -> 0 | BD53: =AP53-AB53 -> 0 | BE53: =(AQ53-AC53)*100 -> 0 | BF53: =AR53-AD53 -> -4125.78 | BG53: =(AS53-AE53)*100 -> -0.30880399
AI54: =+AI53-G53 -> 0.017750768 | AK54: =+AK53-I53 -> -0.074216163 | AM54: =+AM53-K53 -> -0.082287339 | AO54: =+AO53-M53 -> 0
E55: 영업비
E56: 인건비 | P56: 381657.95 | Q56: 0.23761991 | AD56: 380784.07 | AE56: 0.28500705 | AR56: 380784.07 | AS56: 0.28500705 | BF56: =AR56-AD56 -> 0 | BG56: =(AS56-AE56)*100 -> 0
B57: HQ | C57: HQ Salaries | E57: 급여(정규) | P57: 243986.01 | Q57: 0.15190548 | AD57: 275739.47 | AE57: 0.20638388 | AR57: 275739.47 | AS57: 0.20638388 | BF57: =AR57-AD57 -> 0 | BG57: =(AS57-AE57)*100 -> 0
B58: Contractors | C58: HQ Salaries | E58: 급여(계약) | P58: 29472.8 | Q58: 0.01834974 | AD58: 43705.33 | AE58: 0.032712312 | AR58: 43705.33 | AS58: 0.032712312 | BF58: =AR58-AD58 -> 0 | BG58: =(AS58-AE58)*100 -> 0
B59: Benefits | C59: HQ Salaries | E59: 보험,복후비등 | P59: 59636.94 | Q59: 0.037129907 | AD59: 61339.27 | AE59: 0.045910861 | AR59: 61339.27 | AS59: 0.045910861 | BF59: =AR59-AD59 -> 0 | BG59: =(AS59-AE59)*100 -> 0
B60: Bonus | C60: HQ Salaries | E60: 급여충당금 | P60: 48562.2 | Q60: 0.030234783 | AD60: 0 | AE60: 0 | AR60: 0 | AS60: 0 | BF60: =AR60-AD60 -> 0 | BG60: =(AS60-AE60)*100 -> 0
B61: Advertising | C61: SG&A | E61: 광고선전비 | P61: -15427.71 | Q61: -0.0096052788 | AD61: 118210.21 | AE61: 0.088477291 | AR61: 118210.21 | AS61: 0.088477291 | BF61: =AR61-AD61 -> 0 | BG61: =(AS61-AE61)*100 -> -1.3877788e-15
E62: Photography | P62: 71.94 | Q62: 4.4789781e-05 | AE62: 0 | AS62: 0 | BF62: =AR62-AD62 -> 0 | BG62: =(AS62-AE62)*100 -> 0
E63: Selling | P63: 0 | Q63: 0 | AE63: 0 | AS63: 0 | BF63: =AR63-AD63 -> 0 | BG63: =(AS63-AE63)*100 -> 0
E64: Advertising | P64: 2916.67 | Q64: 0.0018159162 | AE64: 0 | AS64: 0 | BF64: =AR64-AD64 -> 0 | BG64: =(AS64-AE64)*100 -> 0
E65: SEM브랜드마케팅 | P65: 0 | Q65: 0 | AE65: 0 | AS65: 0 | BF65: =AR65-AD65 -> 0 | BG65: =(AS65-AE65)*100 -> 0
E66: Events | P66: 0 | Q66: 0 | AE66: 0 | AS66: 0 | BF66: =AR66-AD66 -> 0 | BG66: =(AS66-AE66)*100 -> 0
E67: Model | P67: 4425 | Q67: 0.0027550011 | AE67: 0 | AS67: 0 | BF67: =AR67-AD67 -> 0 | BG67: =(AS67-AE67)*100 -> 0
E68: Seeding | P68: 4958.68 | Q68: 0.0030872699 | AE68: 0 | AS68: 0 | BF68: =AR68-AD68 -> 0 | BG68: =(AS68-AE68)*100 -> 0
E69: 기타 광고비 | P69: -27800 | Q69: -0.017308256 | AE69: 0 | AS69: 0 | BF69: =AR69-AD69 -> 0 | BG69: =(AS69-AE69)*100 -> 0
B70: Professional Service | C70: SG&A | E70: 지급수수료 | P70: 74248.11 | Q70: 0.046226809 | AD70: 52659.67 | AE70: 0.039414404 | AR70: 52659.67 | AS70: 0.039414404 | BF70: =AR70-AD70 -> 0 | BG70: =(AS70-AE70)*100 -> 0
B71: T&E | C71: SG&A | E71: 식대 / 출장비 | P71: 8476.25 | Q71: 0.0052773059 | AD71: 4954.15 | AE71: 0.0037080534 | AR71: 4954.15 | AS71: 0.0037080534 | BF71: =AR71-AD71 -> 0 | BG71: =(AS71-AE71)*100 -> -4.3368087e-17
B72: Rent | C72: SG&A | E72: 임차료 | P72: 33913.35 | Q72: 0.021114422 | AD72: 24649.53 | AE72: 0.018449537 | AR72: 24649.53 | AS72: 0.018449537 | BF72: =AR72-AD72 -> 0 | BG72: =(AS72-AE72)*100 -> 0
B73: Sample | C73: SG&A | E73: 샘플비/개발비 | P73: 6774.8 | Q73: 0.0042179846 | AD73: 38117.17 | AE73: 0.028529718 | AR73: 38117.17 | AS73: 0.028529718 | BF73: =AR73-AD73 -> 0 | BG73: =(AS73-AE73)*100 -> -3.469447e-16
B74: Depreciation & Amortization | C74: SG&A | E74: 감가상각비 | P74: 3647.09 | Q74: 0.0022706751 | AD74: 4311.46 | AE74: 0.0032270165 | AR74: 4311.46 | AS74: 0.0032270165 | BF74: =AR74-AD74 -> 0 | BG74: =(AS74-AE74)*100 -> 0
B75: Other | C75: SG&A | E75: 기타비용 | P75: -3735.24 | Q75: -0.0023255572 | AD75: 8123.05 | AE75: 0.0060798933 | AR75: 8123.05 | AS75: 0.0060798933 | BF75: =AR75-AD75 -> 0 | BG75: =(AS75-AE75)*100 -> 8.6736174e-17
E76: 영업비 소계 | P76: 489554.6 | Q76: 0.30479627 | T76: 0 | U76: 0 | V76: 0 | W76: 0 | X76: 0 | Y76: 0 | Z76: 0 | AA76: 0 | AD76: 631809.31 | AE76: 0.47289296 | AH76: 0 | AI76: 0 | AJ76: 0 | AK76: 0 | AL76: 0 | AM76: 0 | AN76: 0 | AO76: 0 | AR76: 631809.31 | AS76: 0.47289296 | AV76: =SUM(AV57:AV75) -> 0 | AW76: =SUM(AW57:AW75) -> 0 | AX76: =SUM(AX57:AX75) -> 0 | AY76: =SUM(AY57:AY75) -> 0 | AZ76: =SUM(AZ57:AZ75) -> 0 | BA76: =SUM(BA57:BA75) -> 0 | BB76: =SUM(BB57:BB75) -> 0 | BC76: =SUM(BC57:BC75) -> 0 | BF76: =AR76-AD76 -> 0 | BG76: =(AS76-AE76)*100 -> 0
E78: 영업이익 | P78: 95793.77 | Q78: 0.059641118 | AD78: -157584.99 | AE78: -0.1179483 | AR78: -161710.77 | AS78: -0.12103634 | BF78: =AR78-AD78 -> -4125.78 | BG78: =(AS78-AE78)*100 -> -0.30880399
E80: 영업외손익
E82: 이자비용
E83: 경상이익

Sheet 2월
E5: 45931
E7: Date | F7: =EDATE($E$5,-12) -> 45566 | H7: =F7 -> 45566 | J7: =H7 -> 45566 | L7: =J7 -> 45566 | N7: =L7 -> 45566 | P7: =L7 -> 45566 | T7: =EDATE($E$5,0) -> 45931 | V7: =T7 -> 45931 | X7: =V7 -> 45931 | Z7: =X7 -> 45931 | AB7: =Z7 -> 45931 | AD7: =Z7 -> 45931 | AH7: =EDATE($E$5,0) -> 45931 | AJ7: =AH7 -> 45931 | AL7: =AJ7 -> 45931 | AN7: =AL7 -> 45931 | AP7: =AN7 -> 45931 | AR7: =AN7 -> 45931 | AV7: =EDATE($E$5,0) -> 45931 | AX7: =AV7 -> 45931 | AZ7: =AX7 -> 45931 | BD7: =BB7 -> 0 | BF7: =BB7 -> 0
E8: Category | F8: Wholesale | H8: Ecommerce (US) | J8: Ecommerce (EU) | L8: License | N8: Other Income | T8: Wholesale | V8: Ecommerce (US) | X8: Ecommerce (EU) | Z8: License | AB8: Other Income | AH8: Wholesale | AJ8: Ecommerce (US) | AL8: Ecommerce (EU) | AN8: License | AP8: Other Income | AV8: Wholesale | AX8: Ecommerce (US) | AZ8: Ecommerce (EU) | BD8: Other Income
E9: M | F9: =MONTH(F7) -> 10 | T9: =MONTH(T7) -> 10 | AH9: =MONTH(AH7) -> 10 | AV9: =MONTH(AV7) -> 10
E10: Q | F10: ="Q"&ROUNDUP(MONTH(F7)/3,0)&"'"&TEXT(F7,"yy") -> Q4'24 | T10: ="Q"&ROUNDUP(MONTH(T7)/3,0)&"'"&TEXT(T7,"yy") -> Q4'25 | AH10: ="Q"&ROUNDUP(MONTH(AH7)/3,0)&"'"&TEXT(AH7,"yy") -> Q4'25 | AV10: ="Q"&ROUNDUP(MONTH(AV7)/3,0)&"'"&TEXT(AV7,"yy") -> Q4'25
E11: H | F11: ="H"&ROUNDUP(MONTH(F7)/6,0)&"'"&TEXT(F7,"yy") -> H2'24 | T11: ="H"&ROUNDUP(MONTH(T7)/6,0)&"'"&TEXT(T7,"yy") -> H2'25 | AH11: ="H"&ROUNDUP(MONTH(AH7)/6,0)&"'"&TEXT(AH7,"yy") -> H2'25 | AV11: ="H"&ROUNDUP(MONTH(AV7)/6,0)&"'"&TEXT(AV7,"yy") -> H2'25
E12: Y | F12: =YEAR(F7) -> 2024 | T12: =YEAR(T7) -> 2025 | AH12: =YEAR(AH7) -> 2025 | AV12: =YEAR(AV7) -> 2025
E13: Actual / Forecast | F13: Actual | T13: Forecast | AH13: Actual | AV13: Actual
F15: Last Year - Current Month | T15: Budget - Current Month | AH15: Actual - Current Month | AV15: vs Plan
F17: STO 24년 2월 전년 실적 | P17: STO 24년 2월 전년 실적 | T17: STO 25년 2월 당월 계획 | AD17: STO 25년 2월 당월 계획 | AH17: STO 25년 2월 당월 실적 | AR17: STO 25년 2월 당월 실적 | AV17: ="STO"&" "&RIGHT(YEAR($E$5),2)&"년"&" "&MONTH($E$5)&"월 계획대비" -> STO 25년 10월 계획대비 | BF17: ="STO"&" "&RIGHT(YEAR($E$5),2)&"년"&" "&MONTH($E$5)&"월 당월 실적" -> STO 25년 10월 당월 실적
F18: 홀세일(미국) | H18: 온라인(미국) | J18: 온라인(유럽) | L18: 라이선스 | N18: 기타 | P18: STO 합계 | T18: 홀세일(미국) | V18: 온라인(미국) | X18: 온라인(유럽) | Z18: 라이선스 | AB18: 기타 | AD18: STO 합계 | AH18: 홀세일(미국) | AJ18: 온라인(미국) | AL18: 온라인(유럽) | AN18: 라이선스 | AP18: 기타 | AR18: STO 합계 | AV18: 홀세일(미국) | AX18: 온라인(미국) | AZ18: 온라인(유럽) | BB18: 라이선스 | BD18: 기타 | BF18: STO 합계
E19: STO/STIP
E20: 라이선스
E21: 홀세일(미국)
E22: 온라인(미국)
E23: 할인율(%)
E24: 생산원가율(%)
E25: 온라인(유럽)
E26: 매출액(할인전) 계
E27: 총매출 (MSRP) | F27: 723694 | H27: 1765020 | J27: 157449 | L27: 56910.08 | N27: 40493.9 | P27: 2743567 | T27: 450064 | V27: 1641273 | X27: 117896 | Z27: 46240.52 | AB27: 0 | AD27: 2255473.5 | AH27: 450064 | AJ27: 1641273 | AL27: 117896 | AN27: 46240.52 | AP27: 0 | AR27: 2255473.5 | AV27: =AH27-T27 -> 0 | AX27: =AJ27-V27 -> 0 | AZ27: =AL27-X27 -> 0 | BB27: =AN27-Z27 -> 0 | BD27: =AP27-AB27 -> 0 | BF27: =AR27-AD27 -> 0
E28: 할인액 | F28: 429137.3 | H28: 682299.53 | J28: 35967.26 | L28: 0 | N28: 0 | P28: 1147404.1 | T28: 272219.75 | V28: 683955.04 | X28: 53369.05 | Z28: 0 | AB28: 0 | AD28: 1009543.8 | AH28: 272219.75 | AJ28: 683955.04 | AL28: 53369.05 | AN28: 0 | AP28: 0 | AR28: 1009543.8 | AV28: =AH28-T28 -> 0 | AX28: =AJ28-V28 -> 0 | AZ28: =AL28-X28 -> 0 | BB28: =AN28-Z28 -> 0 | BD28: =AP28-AB28 -> 0 | BF28: =AR28-AD28 -> 0
C29: Revenue | E29: 실판매 | F29: 294556.7 | G29: 0.5929817 | H29: 1082720.5 | I29: 0.38656759 | J29: 121481.74 | K29: 0.22843753 | L29: 56910.08 | M29: 0 | N29: 40493.9 | O29: 0 | P29: 1596162.9 | Q29: 0.41821618 | T29: 177844.25 | U29: 0.60484676 | V29: 957317.96 | W29: 0.41672229 | X29: 64526.95 | Y29: 0.45267906 | Z29: 46240.52 | AA29: 0 | AB29: 0 | AC29: 0 | AD29: 1245929.7 | AE29: 0.44759729 | AH29: 177844.25 | AI29: 0.60484676 | AJ29: 957317.96 | AK29: 0.41672229 | AL29: 64526.95 | AM29: 0.45267906 | AN29: 46240.52 | AO29: 0 | AP29: 0 | AQ29: 0 | AR29: 1245929.7 | AS29: 0.44759729 | AV29: =AH29-T29 -> 0 | AW29: =(AI29-U29)*100 -> 0 | AX29: =AJ29-V29 -> 0 | AY29: =(AK29-W29)*100 -> 0 | AZ29: =AL29-X29 -> 0 | BA29: =(AM29-Y29)*100 -> 0 | BB29: =AN29-Z29 -> 0 | BC29: =(AO29-AA29)*100 -> 0 | BD29: =AP29-AB29 -> 0 | BE29: =(AQ29-AC29)*100 -> 0 | BF29: =AR29-AD29 -> 0 | BG29: =(AS29-AE29)*100 -> 0
E30: 제품매출
E31: 기타매출
E33: 계획대비 | F33: n/a | G33: n/a | H33: n/a | I33: n/a | J33: n/a | K33: n/a | L33: n/a | M33: n/a | N33: n/a | O33: n/a | P33: n/a | Q33: n/a | AH33: 0 | AI33: 0 | AJ33: 0 | AK33: 0 | AL33: 0 | AM33: 0 | AN33: 0 | AO33: 0 | AP33: 0 | AQ33: 0 | AR33: 0 | AS33: 0
E34: 전년대비 | F34: n/a | G34: n/a | H34: n/a | I34: n/a | J34: n/a | K34: n/a | L34: n/a | M34: n/a | N34: n/a | O34: n/a | P34: n/a | Q34: n/a | T34: -116712.45 | U34: -0.39623084 | V34: -125402.51 | W34: -0.11582169 | X34: -56954.79 | Y34: -0.46883416 | Z34: -10669.56 | AA34: -0.18748102 | AB34: -40493.9 | AC34: -1 | AD34: -350233.21 | AE34: -0.21942197 | AH34: -116712.45 | AI34: -0.39623084 | AJ34: -125402.51 | AK34: -0.11582169 | AL34: -56954.79 | AM34: -0.46883416 | AN34: -10669.56 | AO34: -0.18748102 | AP34: -40493.9 | AQ34: -1 | AR34: -350233.21 | AS34: -0.21942197
C36: COGS | E36: 매출원가 | F36: 126926.85 | G36: 0.43090804 | H36: 359519.62 | I36: 0.33205211 | J36: 32349.33 | K36: 0.26628965 | L36: 0 | M36: 0 | N36: 81130.22 | O36: 2.0035171 | P36: 599926.02 | Q36: 0.37585514 | T36: 83936.44 | U36: 0.471966 | V36: 326402.15 | W36: 0.3409548 | X36: 25299.74 | Y36: 0.39208021 | Z36: 0 | AA36: 0 | AB36: -45644.97 | AC36: 0 | AD36: 389993.36 | AE36: 0.31301394 | AH36: 83936.44 | AI36: 0.471966 | AJ36: 326402.15 | AK36: 0.3409548 | AL36: 25299.74 | AM36: 0.39208021 | AN36: 0 | AO36: 0 | AP36: -45644.97 | AQ36: 0 | AR36: 389993.36 | AS36: 0.31301394 | AV36: =AH36-T36 -> 0 | AW36: =(AI36-U36)*100 -> 0 | AX36: =AJ36-V36 -> 0 | AY36: =(AK36-W36)*100 -> 0 | AZ36: =AL36-X36 -> 0 | BA36: =(AM36-Y36)*100 -> 0 | BB36: =AN36-Z36 -> 0 | BC36: =(AO36-AA36)*100 -> 0 | BD36: =AP36-AB36 -> 0 | BE36: =(AQ36-AC36)*100 -> 0 | BF36: =AR36-AD36 -> 0 | BG36: =(AS36-AE36)*100 -> 0
E37: 기타원가 | AV37: =AH37-T37 -> 0 | AW37: =(AI37-U37)*100 -> 0 | AX37: =AJ37-V37 -> 0 | AY37: =(AK37-W37)*100 -> 0 | AZ37: =AL37-X37 -> 0 | BA37: =(AM37-Y37)*100 -> 0 | BB37: =AN37-Z37 -> 0 | BC37: =(AO37-AA37)*100 -> 0 | BD37: =AP37-AB37 -> 0 | BE37: =(AQ37-AC37)*100 -> 0 | BF37: =AR37-AD37 -> 0 | BG37: =(AS37-AE37)*100 -> 0
E38: 분기원가조정 | AV38: =AH38-T38 -> 0 | AW38: =(AI38-U38)*100 -> 0 | AX38: =AJ38-V38 -> 0 | AY38: =(AK38-W38)*100 -> 0 | AZ38: =AL38-X38 -> 0 | BA38: =(AM38-Y38)*100 -> 0 | BB38: =AN38-Z38 -> 0 | BC38: =(AO38-AA38)*100 -> 0 | BD38: =AP38-AB38 -> 0 | BE38: =(AQ38-AC38)*100 -> 0 | BF38: =AR38-AD38 -> 0 | BG38: =(AS38-AE38)*100 -> 0
E39: (생산원가율, M/U) | F39: 0.17538746 | G39: 5.701662 | H39: 0.20369153 | I39: 4.9093844 | J39: 0.2054591 | K39: 4.8671487 | L39: 0 | M39: 0 | N39: 2.0035171 | O39: 0.49912228 | P39: 0.21866644 | Q39: 4.5731755 | T39: 0.1864989 | U39: 5.361962 | V39: 0.19887133 | W39: 5.0283768 | X39: 0.21459371 | Y39: 4.6599688 | Z39: 0 | AA39: 0 | AB39: 0 | AC39: 0 | AD39: 0.17290975 | AE39: 5.7833639 | AH39: 0.1864989 | AI39: 5.361962 | AJ39: 0.19887133 | AK39: 5.0283768 | AL39: 0.21459371 | AM39: 4.6599688 | AN39: 0 | AO39: 0 | AP39: 0 | AQ39: 0 | AR39: 0.17290975 | AS39: 5.7833639 | AV39: =(AH39-T39)*100 -> 0 | AW39: =(AI39-U39) -> 0 | AX39: =(AJ39-V39)*100 -> 0 | AY39: =(AK39-W39) -> 0 | AZ39: =(AL39-X39)*100 -> 0 | BA39: =(AM39-Y39) -> 0 | BB39: =AN39-Z39 -> 0 | BC39: =(AO39-AA39) -> 0 | BD39: =AP39-AB39 -> 0 | BE39: =(AQ39-AC39) -> 0 | BF39: =(AR39-AD39)*100 -> 0 | BG39: =(AS39-AE39) -> 0
E40: 매출총이익 | F40: 167629.85 | G40: 0.56909196 | H40: 723200.85 | I40: 0.66794789 | J40: 89132.41 | K40: 0.73371035 | L40: 56910.08 | M40: 1 | N40: -40636.32 | O40: -1.0035171 | P40: 996236.87 | Q40: 0.62414486 | T40: 93907.81 | U40: 0.528034 | V40: 630915.81 | W40: 0.6590452 | X40: 39227.21 | Y40: 0.60791979 | Z40: 46240.52 | AA40: 1 | AB40: 45644.97 | AC40: 0 | AD40: 855936.32 | AE40: 0.68698606 | AH40: 93907.81 | AI40: 0.528034 | AJ40: 630915.81 | AK40: 0.6590452 | AL40: 39227.21 | AM40: 0.60791979 | AN40: 46240.52 | AO40: 1 | AP40: 45644.97 | AQ40: 0 | AR40: 855936.32 | AS40: 0.68698606 | AV40: =AH40-T40 -> 0 | AW40: =(AI40-U40)*100 -> 0 | AX40: =AJ40-V40 -> 0 | AY40: =(AK40-W40)*100 -> 0 | AZ40: =AL40-X40 -> 0 | BA40: =(AM40-Y40)*100 -> 0 | BB40: =AN40-Z40 -> 0 | BC40: =(AO40-AA40)*100 -> 0 | BD40: =AP40-AB40 -> 0 | BE40: =(AQ40-AC40)*100 -> 0 | BF40: =AR40-AD40 -> 0 | BG40: =(AS40-AE40)*100 -> 0
E42: 직접비
E43: 운반비/보관료/ 물류용역비 | F43: 24266.662 | G43: 0.08238367 | H43: 121492.05 | I43: 0.11220998 | J43: 25528.362 | K43: 0.21014156 | L43: 0 | M43: 0 | N43: 0 | O43: 0 | P43: 171287.07 | Q43: 0.10731177 | T43: 8676.5 | U43: 0.048787071 | V43: 105677.88 | W43: 0.11038953 | X43: 11236.62 | Y43: 0.1741384 | Z43: 0 | AA43: 0 | AB43: 0 | AC43: 0 | AD43: 125591 | AE43: 0.10080103 | AH43: 8676.5 | AI43: 0.048787071 | AJ43: 105677.88 | AK43: 0.11038953 | AL43: 11236.62 | AM43: 0.1741384 | AN43: 0 | AO43: 0 | AP43: 0 | AQ43: 0 | AR43: 125591 | AS43: 0.10080103 | AV43: =AH43-T43 -> 0 | AW43: =(AI43-U43)*100 -> 0 | AX43: =AJ43-V43 -> 0 | AY43: =(AK43-W43)*100 -> 0 | AZ43: =AL43-X43 -> 0 | BA43: =(AM43-Y43)*100 -> 0 | BB43: =AN43-Z43 -> 0 | BC43: =(AO43-AA43)*100 -> 0 | BD43: =AP43-AB43 -> 0 | BE43: =(AQ43-AC43)*100 -> 0 | BF43: =AR43-AD43 -> 0 | BG43: =(AS43-AE43)*100 -> 0
B44: 운반비 | C44: 운반비 (-) | E44: 운반비 | F44: -4668.108 | G44: -0.01584791 | H44: 64825.196 | I44: 0.059872514 | J44: 18437.442 | K44: 0.1517713 | L44: 0 | M44: 0 | N44: 0 | O44: 0 | P44: 78594.53 | Q44: 0.049239668 | T44: -2194.97 | U44: -0.012342091 | V44: 54051.32 | W44: 0.056461199 | X44: 4038.73 | Y44: 0.062589817 | Z44: 0 | AA44: 0 | AB44: 0 | AC44: 0 | AD44: 55895.08 | AE44: 0.044862147 | AH44: -2194.97 | AI44: -0.012342091 | AJ44: 54051.32 | AK44: 0.056461199 | AL44: 4038.73 | AM44: 0.062589817 | AN44: 0 | AO44: 0 | AP44: 0 | AQ44: 0 | AR44: 55895.08 | AS44: 0.044862147 | AV44: =AH44-T44 -> 0 | AW44: =(AI44-U44)*100 -> 0 | AX44: =AJ44-V44 -> 0 | AY44: =(AK44-W44)*100 -> 0 | AZ44: =AL44-X44 -> 0 | BA44: =(AM44-Y44)*100 -> 0 | BB44: =AN44-Z44 -> 0 | BC44: =(AO44-AA44)*100 -> 0 | BD44: =AP44-AB44 -> 0 | BE44: =(AQ44-AC44)*100 -> 0 | BF44: =AR44-AD44 -> 0 | BG44: =(AS44-AE44)*100 -> 0
B45: 보관료 | E45: 보관료 | F45: 17472.48 | G45: 0.059317883 | H45: 21246.6 | I45: 0.019623347 | J45: 2910.16 | K45: 0.023955534 | L45: 0 | M45: 0 | N45: 0 | O45: 0 | P45: 41629.24 | Q45: 0.026080822 | T45: 5712.24 | U45: 0.03211934 | V45: 19202.69 | W45: 0.020058842 | X45: 1294.34 | Y45: 0.020058906 | Z45: 0 | AA45: 0 | AB45: 0 | AC45: 0 | AD45: 26209.27 | AE45: 0.021035914 | AH45: 5712.24 | AI45: 0.03211934 | AJ45: 19202.69 | AK45: 0.020058842 | AL45: 1294.34 | AM45: 0.020058906 | AN45: 0 | AO45: 0 | AP45: 0 | AQ45: 0 | AR45: 26209.27 | AS45: 0.021035914 | AV45: =AH45-T45 -> 0 | AW45: =(AI45-U45)*100 -> 0 | AX45: =AJ45-V45 -> 0 | AY45: =(AK45-W45)*100 -> 0 | AZ45: =AL45-X45 -> 0 | BA45: =(AM45-Y45)*100 -> 0 | BB45: =AN45-Z45 -> 0 | BC45: =(AO45-AA45)*100 -> 0 | BD45: =AP45-AB45 -> 0 | BE45: =(AQ45-AC45)*100 -> 0 | BF45: =AR45-AD45 -> 0 | BG45: =(AS45-AE45)*100 -> 0
B46: 물류용역비 | E46: 물류용역비 | F46: 11462.29 | G46: 0.038913696 | H46: 35420.25 | I46: 0.032714122 | J46: 4180.76 | K46: 0.034414719 | L46: 0 | M46: 0 | N46: 0 | O46: 0 | P46: 51063.3 | Q46: 0.031991284 | T46: 5159.23 | U46: 0.029009822 | V46: 32423.87 | W46: 0.033869489 | X46: 5903.55 | Y46: 0.09148968 | Z46: 0 | AA46: 0 | AB46: 0 | AC46: 0 | AD46: 43486.65 | AE46: 0.034902973 | AH46: 5159.23 | AI46: 0.029009822 | AJ46: 32423.87 | AK46: 0.033869489 | AL46: 5903.55 | AM46: 0.09148968 | AN46: 0 | AO46: 0 | AP46: 0 | AQ46: 0 | AR46: 43486.65 | AS46: 0.034902973 | AV46: =AH46-T46 -> 0 | AW46: =(AI46-U46)*100 -> 0 | AX46: =AJ46-V46 -> 0 | AY46: =(AK46-W46)*100 -> 0 | AZ46: =AL46-X46 -> 0 | BA46: =(AM46-Y46)*100 -> -1.3877788e-15 | BB46: =AN46-Z46 -> 0 | BC46: =(AO46-AA46)*100 -> 0 | BD46: =AP46-AB46 -> 0 | BE46: =(AQ46-AC46)*100 -> 0 | BF46: =AR46-AD46 -> 0 | BG46: =(AS46-AE46)*100 -> 0
B47: Professional Service | C47: Direct Costs | E47: 지급수수료 | F47: 1531.75 | G47: 0.0052001873 | H47: 57378.05 | I47: 0.052994334 | J47: 5202.24 | K47: 0.042823226 | L47: 0 | M47: 0 | N47: 0 | O47: 0 | P47: 64112.04 | Q47: 0.040166352 | T47: 1397.76 | U47: 0.0078594613 | V47: 71283.24 | W47: 0.074461405 | X47: 9808.05 | Y47: 0.15199928 | Z47: 0 | AA47: 0 | AB47: 0 | AC47: 0 | AD47: 82489.05 | AE47: 0.066206826 | AH47: 1397.76 | AI47: 0.0078594613 | AJ47: 71283.67 | AK47: 0.074461854 | AL47: 9808.05 | AM47: 0.15199928 | AN47: 0 | AO47: 0 | AP47: 0 | AQ47: 0 | AR47: 82489.48 | AS47: 0.066207171 | AV47: =AH47-T47 -> 0 | AW47: =(AI47-U47)*100 -> 0 | AX47: =AJ47-V47 -> 0.43 | AY47: =(AK47-W47)*100 -> 4.4917156e-05 | AZ47: =AL47-X47 -> 0 | BA47: =(AM47-Y47)*100 -> 0 | BB47: =AN47-Z47 -> 0 | BC47: =(AO47-AA47)*100 -> 0 | BD47: =AP47-AB47 -> 0 | BE47: =(AQ47-AC47)*100 -> 0 | BF47: =AR47-AD47 -> 0.43 | BG47: =(AS47-AE47)*100 -> 3.4512381e-05
B48: 6451 - Service Processing Fee | C48: Direct Costs | E48: 결제수수료 | F48: 5450.26 | G48: 0.018503263 | H48: 36276.72 | I48: 0.033505158 | J48: 14206.45 | K48: 0.11694309 | L48: 0 | M48: 0 | N48: 0 | O48: 0 | P48: 55933.43 | Q48: 0.035042432 | T48: 1784.61 | U48: 0.010034679 | V48: 41099.1 | W48: 0.042931504 | X48: 3834.04 | Y48: 0.059417654 | Z48: 0 | AA48: 0 | AB48: 0 | AC48: 0 | AD48: 46717.75 | AE48: 0.037496298 | AH48: 1784.61 | AI48: 0.010034679 | AJ48: 41098.67 | AK48: 0.042931055 | AL48: 3834.04 | AM48: 0.059417654 | AN48: 0 | AO48: 0 | AP48: 0 | AQ48: 0 | AR48: 46717.32 | AS48: 0.037495952 | AV48: =AH48-T48 -> 0 | AW48: =(AI48-U48)*100 -> 0 | AX48: =AJ48-V48 -> -0.43 | AY48: =(AK48-W48)*100 -> -4.4917156e-05 | AZ48: =AL48-X48 -> 0 | BA48: =(AM48-Y48)*100 -> 0 | BB48: =AN48-Z48 -> 0 | BC48: =(AO48-AA48)*100 -> 0 | BD48: =AP48-AB48 -> 0 | BE48: =(AQ48-AC48)*100 -> 0 | BF48: =AR48-AD48 -> -0.43 | BG48: =(AS48-AE48)*100 -> -3.4512381e-05
B49: Marketing | C49: Direct Costs | E49: SEM 광고비 | F49: 0 | G49: 0 | H49: 139866.39 | I49: 0.12918051 | J49: 15693.074 | K49: 0.12918051 | L49: 0 | M49: 0 | N49: 0 | O49: 0 | P49: 155559.46 | Q49: 0.097458387 | T49: 0 | U49: 0 | V49: 160911.85 | W49: 0.16808611 | X49: 25333.38 | Y49: 0.39260154 | Z49: 0 | AA49: 0 | AB49: 0 | AC49: 0 | AD49: 186245.23 | AE49: 0.14948294 | AH49: 0 | AI49: 0 | AJ49: 160911.85 | AK49: 0.16808611 | AL49: 25333.38 | AM49: 0.39260154 | AN49: 0 | AO49: 0 | AP49: 0 | AQ49: 0 | AR49: 186245.23 | AS49: 0.14948294 | AV49: =AH49-T49 -> 0 | AW49: =(AI49-U49)*100 -> 0 | AX49: =AJ49-V49 -> 0 | AY49: =(AK49-W49)*100 -> 0 | AZ49: =AL49-X49 -> 0 | BA49: =(AM49-Y49)*100 -> 0 | BB49: =AN49-Z49 -> 0 | BC49: =(AO49-AA49)*100 -> 0 | BD49: =AP49-AB49 -> 0 | BE49: =(AQ49-AC49)*100 -> 0 | BF49: =AR49-AD49 -> 0 | BG49: =(AS49-AE49)*100 -> 0
B50: Other | C50: Direct Costs | E50: 기타비용 | F50: 0 | G50: 0 | H50: 0 | I50: 0 | J50: 0 | K50: 0 | L50: 0 | M50: 0 | N50: 0 | O50: 0 | P50: 0 | Q50: 0 | T50: 0 | U50: 0 | V50: 0 | W50: 0 | X50: 0 | Y50: 0 | Z50: 0 | AA50: 0 | AB50: 0 | AC50: 0 | AD50: 0 | AE50: 0 | AH50: 0 | AI50: 0 | AJ50: 0 | AK50: 0 | AL50: 0 | AM50: 0 | AN50: 0 | AO50: 0 | AP50: 0 | AQ50: 0 | AR50: 0 | AS50: 0 | AV50: =AH50-T50 -> 0 | AW50: =(AI50-U50)*100 -> 0 | AX50: =AJ50-V50 -> 0 | AY50: =(AK50-W50)*100 -> 0 | AZ50: =AL50-X50 -> 0 | BA50: =(AM50-Y50)*100 -> 0 | BB50: =AN50-Z50 -> 0 | BC50: =(AO50-AA50)*100 -> 0 | BD50: =AP50-AB50 -> 0 | BE50: =(AQ50-AC50)*100 -> 0 | BF50: =AR50-AD50 -> 0 | BG50: =(AS50-AE50)*100 -> 0
E51: 직접비 소계 | F51: 31248.672 | G51: 0.10608712 | H51: 355013.2 | I51: 0.32788999 | J51: 60630.126 | K51: 0.49908839 | L51: 0 | M51: 0 | N51: 0 | O51: 0 | P51: 446892 | Q51: 0.27997894 | T51: 11858.87 | U51: 0.066681211 | V51: 378972.07 | W51: 0.39586855 | X51: 50212.09 | Y51: 0.77815688 | Z51: 0 | AA51: 0 | AB51: 0 | AC51: 0 | AD51: 441043.03 | AE51: 0.3539871 | AH51: 11858.87 | AI51: 0.066681211 | AJ51: 378972.07 | AK51: 0.39586855 | AL51: 50212.09 | AM51: 0.77815688 | AN51: 0 | AO51: 0 | AP51: 0 | AQ51: 0 | AR51: 441043.03 | AS51: 0.3539871 | AV51: =AH51-T51 -> 0 | AW51: =(AI51-U51)*100 -> 0 | AX51: =AJ51-V51 -> 0 | AY51: =(AK51-W51)*100 -> 0 | AZ51: =AL51-X51 -> 0 | BA51: =(AM51-Y51)*100 -> 0 | BB51: =AN51-Z51 -> 0 | BC51: =(AO51-AA51)*100 -> 0 | BD51: =AP51-AB51 -> 0 | BE51: =(AQ51-AC51)*100 -> 0 | BF51: =AR51-AD51 -> 0 | BG51: =(AS51-AE51)*100 -> 0
E53: 직접이익 | F53: 136381.18 | G53: 0.46300484 | H53: 368187.65 | I53: 0.3400579 | J53: 28502.284 | K53: 0.23462196 | L53: 56910.08 | M53: 1 | N53: -40636.32 | O53: -1.0035171 | P53: 549344.87 | Q53: 0.34416592 | T53: 82048.94 | U53: 0.46135278 | V53: 251943.74 | W53: 0.26317666 | X53: -10984.88 | Y53: -0.17023709 | Z53: 46240.52 | AA53: 1 | AB53: 45644.97 | AC53: 0 | AD53: 414893.29 | AE53: 0.33299896 | AH53: 82048.94 | AI53: 0.46135278 | AJ53: 251943.74 | AK53: 0.26317666 | AL53: -10984.88 | AM53: -0.17023709 | AN53: 46240.52 | AO53: 1 | AP53: 45644.97 | AQ53: 0 | AR53: 414893.29 | AS53: 0.33299896 | AV53: =AH53-T53 -> 0 | AW53: =(AI53-U53)*100 -> 0 | AX53: =AJ53-V53 -> 0 | AY53: =(AK53-W53)*100 -> 0 | AZ53: =AL53-X53 -> 0 | BA53: =(AM53-Y53)*100 -> 0 | BB53: =AN53-Z53 -> 0 | BC53: =(AO53-AA53)*100 -> 0 | BD53: =AP53-AB53 -> 0 | BE53: =(AQ53-AC53)*100 -> 0 | BF53: =AR53-AD53 -> 0 | BG53: =(AS53-AE53)*100 -> 0
AI54: =+AI53-G53 -> -0.001652056 | AK54: =+AK53-I53 -> -0.076881242 | AM54: =+AM53-K53 -> -0.40485905 | AO54: =+AO53-M53 -> 0
E55: 영업비
E56: 인건비 | P56: 311388.78 | Q56: 0.19508584 | AD56: 320839.77 | AE56: 0.25751034 | AR56: 320839.77 | AS56: 0.25751034 | BF56: =AR56-AD56 -> 0 | BG56: =(AS56-AE56)*100 -> 0
B57: HQ | C57: HQ Salaries | E57: 급여(정규) | P57: 204890.76 | Q57: 0.12836457 | AD57: 228343.66 | AE57: 0.18327171 | AR57: 228343.66 | AS57: 0.18327171 | BF57: =AR57-AD57 -> 0 | BG57: =(AS57-AE57)*100 -> 0
B58: Contractors | C58: HQ Salaries | E58: 급여(계약) | P58: 12087.5 | Q58: 0.0075728487 | AD58: 41458.63 | AE58: 0.033275257 | AR58: 41458.63 | AS58: 0.033275257 | BF58: =AR58-AD58 -> 0 | BG58: =(AS58-AE58)*100 -> 0
B59: Benefits | C59: HQ Salaries | E59: 보험,복후비등 | P59: 45848.32 | Q59: 0.028724086 | AD59: 51037.48 | AE59: 0.040963371 | AR59: 51037.48 | AS59: 0.040963371 | BF59: =AR59-AD59 -> 0 | BG59: =(AS59-AE59)*100 -> 0
B60: Bonus | C60: HQ Salaries | E60: 급여충당금 | P60: 48562.2 | Q60: 0.030424338 | AD60: 0 | AE60: 0 | AR60: 0 | AS60: 0 | BF60: =AR60-AD60 -> 0 | BG60: =(AS60-AE60)*100 -> 0
B61: Advertising | C61: SG&A | E61: 광고선전비 | P61: 6973.77 | Q61: 0.0043690842 | AD61: 70499.5 | AE61: 0.056583852 | AR61: 70499.5 | AS61: 0.056583852 | BF61: =AR61-AD61 -> 0 | BG61: =(AS61-AE61)*100 -> 0
E62: Photography | P62: 5298 | Q62: 0.0033192101 | AE62: 0 | AS62: 0 | BF62: =AR62-AD62 -> 0 | BG62: =(AS62-AE62)*100 -> 0
E63: Selling | P63: 0 | Q63: 0 | AE63: 0 | AS63: 0 | BF63: =AR63-AD63 -> 0 | BG63: =(AS63-AE63)*100 -> 0
E64: Advertising | P64: -2916.67 | Q64: -0.001827301 | AE64: 0 | AS64: 0 | BF64: =AR64-AD64 -> 0 | BG64: =(AS64-AE64)*100 -> 0
E65: SEM브랜드마케팅 | P65: 0 | Q65: 0 | AE65: 0 | AS65: 0 | BF65: =AR65-AD65 -> 0 | BG65: =(AS65-AE65)*100 -> 0
E66: Events | P66: 272.81 | Q66: 0.00017091614 | AE66: 0 | AS66: 0 | BF66: =AR66-AD66 -> 0 | BG66: =(AS66-AE66)*100 -> 0
E67: Model | P67: 1740 | Q67: 0.0010901143 | AE67: 0 | AS67: 0 | BF67: =AR67-AD67 -> 0 | BG67: =(AS67-AE67)*100 -> 0
E68: Seeding | P68: 2579.63 | Q68: 0.0016161446 | AE68: 0 | AS68: 0 | BF68: =AR68-AD68 -> 0 | BG68: =(AS68-AE68)*100 -> 0
E69: 기타 광고비 | P69: 0 | Q69: 0 | AE69: 0 | AS69: 0 | BF69: =AR69-AD69 -> 0 | BG69: =(AS69-AE69)*100 -> 0
B70: Professional Service | C70: SG&A | E70: 지급수수료 | P70: 55464.18 | Q70: 0.034748446 | AD70: 81730.59 | AE70: 0.065598076 | AR70: 81730.59 | AS70: 0.065598076 | BF70: =AR70-AD70 -> 0 | BG70: =(AS70-AE70)*100 -> -1.3877788e-15
B71: T&E | C71: SG&A | E71: 식대 / 출장비 | P71: 8270.88 | Q71: 0.0051817268 | AD71: 4505.18 | AE71: 0.0036159184 | AR71: 4505.18 | AS71: 0.0036159184 | BF71: =AR71-AD71 -> 0 | BG71: =(AS71-AE71)*100 -> 0
B72: Rent | C72: SG&A | E72: 임차료 | P72: 33915.44 | Q72: 0.021248107 | AD72: 24651.74 | AE72: 0.01978582 | AR72: 24651.74 | AS72: 0.01978582 | BF72: =AR72-AD72 -> 0 | BG72: =(AS72-AE72)*100 -> -3.469447e-16
B73: Sample | C73: SG&A | E73: 샘플비/개발비 | P73: 44201.07 | Q73: 0.02769208 | AD73: 5126.67 | AE73: 0.0041147346 | AR73: 5126.67 | AS73: 0.0041147346 | BF73: =AR73-AD73 -> 0 | BG73: =(AS73-AE73)*100 -> 0
B74: Depreciation & Amortization | C74: SG&A | E74: 감가상각비 | P74: 3663.72 | Q74: 0.0022953296 | AD74: 4317.45 | AE74: 0.0034652437 | AR74: 4317.45 | AS74: 0.0034652437 | BF74: =AR74-AD74 -> 0 | BG74: =(AS74-AE74)*100 -> 0
B75: Other | C75: SG&A | E75: 기타비용 | P75: 10831.16 | Q75: 0.0067857485 | AD75: 12141.34 | AE75: 0.0097448036 | AR75: 12141.34 | AS75: 0.0097448036 | BF75: =AR75-AD75 -> 0 | BG75: =(AS75-AE75)*100 -> -1.7347235e-16
E76: 영업비 소계 | P76: 474709 | Q76: 0.29740636 | T76: 0 | U76: 0 | V76: 0 | W76: 0 | X76: 0 | Y76: 0 | Z76: 0 | AA76: 0 | AD76: 523812.24 | AE76: 0.42041878 | AH76: 0 | AI76: 0 | AJ76: 0 | AK76: 0 | AL76: 0 | AM76: 0 | AN76: 0 | AO76: 0 | AR76: 523812.24 | AS76: 0.42041878 | AV76: =SUM(AV57:AV75) -> 0 | AW76: =SUM(AW57:AW75) -> 0 | AX76: =SUM(AX57:AX75) -> 0 | AY76: =SUM(AY57:AY75) -> 0 | AZ76: =SUM(AZ57:AZ75) -> 0 | BA76: =SUM(BA57:BA75) -> 0 | BB76: =SUM(BB57:BB75) -> 0 | BC76: =SUM(BC57:BC75) -> 0 | BF76: =AR76-AD76 -> 0 | BG76: =(AS76-AE76)*100 -> 0
E78: 영업이익 | P78: 74635.87 | Q78: 0.046759557 | AD78: -108918.95 | AE78: -0.087419821 | AR78: -108918.95 | AS78: -0.087419821 | BF78: =AR78-AD78 -> 0 | BG78: =(AS78-AE78)*100 -> 0
E80: 영업외손익
E82: 이자비용
E83: 경상이익

Sheet 3월
E5: 45931
E7: Date | F7: =EDATE($E$5,-12) -> 45566 | H7: =F7 -> 45566 | J7: =H7 -> 45566 | L7: =J7 -> 45566 | N7: =L7 -> 45566 | P7: =L7 -> 45566 | T7: =EDATE($E$5,0) -> 45931 | V7: =T7 -> 45931 | X7: =V7 -> 45931 | Z7: =X7 -> 45931 | AB7: =Z7 -> 45931 | AD7: =Z7 -> 45931 | AH7: =EDATE($E$5,0) -> 45931 | AJ7: =AH7 -> 45931 | AL7: =AJ7 -> 45931 | AN7: =AL7 -> 45931 | AP7: =AN7 -> 45931 | AR7: =AN7 -> 45931 | AV7: =EDATE($E$5,0) -> 45931 | AX7: =AV7 -> 45931 | AZ7: =AX7 -> 45931 | BD7: =BB7 -> 0 | BF7: =BB7 -> 0
E8: Category | F8: Wholesale | H8: Ecommerce (US) | J8: Ecommerce (EU) | L8: License | N8: Other Income | T8: Wholesale | V8: Ecommerce (US) | X8: Ecommerce (EU) | Z8: License | AB8: Other Income | AH8: Wholesale | AJ8: Ecommerce (US) | AL8: Ecommerce (EU) | AN8: License | AP8: Other Income | AV8: Wholesale | AX8: Ecommerce (US) | AZ8: Ecommerce (EU) | BD8: Other Income
E9: M | F9: =MONTH(F7) -> 10 | T9: =MONTH(T7) -> 10 | AH9: =MONTH(AH7) -> 10 | AV9: =MONTH(AV7) -> 10
E10: Q | F10: ="Q"&ROUNDUP(MONTH(F7)/3,0)&"'"&TEXT(F7,"yy") -> Q4'24 | T10: ="Q"&ROUNDUP(MONTH(T7)/3,0)&"'"&TEXT(T7,"yy") -> Q4'25 | AH10: ="Q"&ROUNDUP(MONTH(AH7)/3,0)&"'"&TEXT(AH7,"yy") -> Q4'25 | AV10: ="Q"&ROUNDUP(MONTH(AV7)/3,0)&"'"&TEXT(AV7,"yy") -> Q4'25
E11: H | F11: ="H"&ROUNDUP(MONTH(F7)/6,0)&"'"&TEXT(F7,"yy") -> H2'24 | T11: ="H"&ROUNDUP(MONTH(T7)/6,0)&"'"&TEXT(T7,"yy") -> H2'25 | AH11: ="H"&ROUNDUP(MONTH(AH7)/6,0)&"'"&TEXT(AH7,"yy") -> H2'25 | AV11: ="H"&ROUNDUP(MONTH(AV7)/6,0)&"'"&TEXT(AV7,"yy") -> H2'25
E12: Y | F12: =YEAR(F7) -> 2024 | T12: =YEAR(T7) -> 2025 | AH12: =YEAR(AH7) -> 2025 | AV12: =YEAR(AV7) -> 2025
E13: Actual / Forecast | F13: Actual | T13: Forecast | AH13: Actual | AV13: Actual
F15: Last Year - Current Month | T15: Budget - Current Month | AH15: Actual - Current Month | AV15: vs Plan
F17: STO 24년 3월 전년 실적 | P17: STO 24년 3월 전년 실적 | T17: STO 25년 3월 당월 계획 | AD17: STO 25년 3월 당월 계획 | AH17: STO 25년 3월 당월 실적 | AR17: STO 25년 3월 당월 실적 | AV17: ="STO"&" "&RIGHT(YEAR($E$5),2)&"년"&" "&MONTH($E$5)&"월 계획대비" -> STO 25년 10월 계획대비 | BF17: ="STO"&" "&RIGHT(YEAR($E$5),2)&"년"&" "&MONTH($E$5)&"월 당월 실적" -> STO 25년 10월 당월 실적
F18: 홀세일(미국) | H18: 온라인(미국) | J18: 온라인(유럽) | L18: 라이선스 | N18: 기타 | P18: STO 합계 | T18: 홀세일(미국) | V18: 온라인(미국) | X18: 온라인(유럽) | Z18: 라이선스 | AB18: 기타 | AD18: STO 합계 | AH18: 홀세일(미국) | AJ18: 온라인(미국) | AL18: 온라인(유럽) | AN18: 라이선스 | AP18: 기타 | AR18: STO 합계 | AV18: 홀세일(미국) | AX18: 온라인(미국) | AZ18: 온라인(유럽) | BB18: 라이선스 | BD18: 기타 | BF18: STO 합계
E19: STO/STIP
E20: 라이선스
E21: 홀세일(미국)
E22: 온라인(미국)
E23: 할인율(%)
E24: 생산원가율(%)
E25: 온라인(유럽)
E26: 매출액(할인전) 계
E27: 총매출 (MSRP) | F27: 823502 | H27: 1786154 | J27: 167469 | L27: 56910.08 | N27: 0 | P27: 2834035.1 | T27: 656647 | V27: 2161964 | X27: 145387 | Z27: 83240.52 | AB27: 0 | AD27: 3047238.5 | AH27: 656647 | AJ27: 2161964 | AL27: 145387 | AN27: 83240.52 | AP27: 0 | AR27: 3047238.5 | AV27: =AH27-T27 -> 0 | AX27: =AJ27-V27 -> 0 | AZ27: =AL27-X27 -> 0 | BB27: =AN27-Z27 -> 0 | BD27: =AP27-AB27 -> 0 | BF27: =AR27-AD27 -> 0
E28: 할인액 | F28: 499035.37 | H28: 500880.88 | J28: 972.68 | L28: 0 | N28: 0 | P28: 1000888.9 | T28: 382789.4 | V28: 789065.95 | X28: 58554.82 | Z28: 0 | AB28: 0 | AD28: 1230410.2 | AH28: 382789.4 | AJ28: 789065.95 | AL28: 58554.82 | AN28: 0 | AP28: 0 | AR28: 1230410.2 | AV28: =AH28-T28 -> 0 | AX28: =AJ28-V28 -> 0 | AZ28: =AL28-X28 -> 0 | BB28: =AN28-Z28 -> 0 | BD28: =AP28-AB28 -> 0 | BF28: =AR28-AD28 -> 0
C29: Revenue | E29: 실판매 | F29: 324466.63 | G29: 0.60599169 | H29: 1285273.1 | I29: 0.28042424 | J29: 166496.32 | K29: 0.0058081197 | L29: 56910.08 | M29: 0 | N29: 0 | O29: 0 | P29: 1833146.2 | Q29: 0.35316745 | T29: 273857.6 | U29: 0.58294548 | V29: 1372898 | W29: 0.36497645 | X29: 86832.18 | Y29: 0.40275142 | Z29: 83240.52 | AA29: 0 | AB29: 0 | AC29: 0 | AD29: 1816828.3 | AE29: 0.40377875 | AH29: 273857.6 | AI29: 0.58294548 | AJ29: 1372898 | AK29: 0.36497645 | AL29: 86832.18 | AM29: 0.40275142 | AN29: 83240.52 | AO29: 0 | AP29: 0 | AQ29: 0 | AR29: 1816828.3 | AS29: 0.40377875 | AV29: =AH29-T29 -> 0 | AW29: =(AI29-U29)*100 -> 0 | AX29: =AJ29-V29 -> 0 | AY29: =(AK29-W29)*100 -> 0 | AZ29: =AL29-X29 -> 0 | BA29: =(AM29-Y29)*100 -> 0 | BB29: =AN29-Z29 -> 0 | BC29: =(AO29-AA29)*100 -> 0 | BD29: =AP29-AB29 -> 0 | BE29: =(AQ29-AC29)*100 -> 0 | BF29: =AR29-AD29 -> 0 | BG29: =(AS29-AE29)*100 -> 0
E30: 제품매출
E31: 기타매출
E33: 계획대비 | F33: n/a | G33: n/a | H33: n/a | I33: n/a | J33: n/a | K33: n/a | L33: n/a | M33: n/a | N33: n/a | O33: n/a | P33: n/a | Q33: n/a | AH33: 0 | AI33: 0 | AJ33: 0 | AK33: 0 | AL33: 0 | AM33: 0 | AN33: 0 | AO33: 0 | AP33: 0 | AQ33: 0 | AR33: 0 | AS33: 0
E34: 전년대비 | F34: n/a | G34: n/a | H34: n/a | I34: n/a | J34: n/a | K34: n/a | L34: n/a | M34: n/a | N34: n/a | O34: n/a | P34: n/a | Q34: n/a | T34: -50609.03 | U34: -0.15597607 | V34: 87624.93 | W34: 0.068176117 | X34: -79664.14 | Y34: -0.47847388 | Z34: 26330.44 | AA34: 0.46266742 | AB34: 0 | AC34: 0 | AD34: -16317.8 | AE34: -0.008901527 | AH34: -50609.03 | AI34: -0.15597607 | AJ34: 87624.93 | AK34: 0.068176117 | AL34: -79664.14 | AM34: -0.47847388 | AN34: 26330.44 | AO34: 0.46266742 | AP34: 0 | AQ34: 0 | AR34: -16317.8 | AS34: -0.008901527
C36: COGS | E36: 매출원가 | F36: 150677.72 | G36: 0.46438588 | H36: 360073.82 | I36: 0.28015354 | J36: 32688.63 | K36: 0.19633245 | L36: 0 | M36: 0 | N36: 0 | O36: 0 | P36: 543440.17 | Q36: 0.29645218 | T36: 129572.95 | U36: 0.47313987 | V36: 473867.93 | W36: 0.34515886 | X36: 34996.57 | Y36: 0.40303687 | Z36: 0 | AA36: 0 | AB36: -95093.68 | AC36: 0 | AD36: 543343.77 | AE36: 0.2990617 | AH36: 129572.95 | AI36: 0.47313987 | AJ36: 473867.93 | AK36: 0.34515886 | AL36: 34996.57 | AM36: 0.40303687 | AN36: 0 | AO36: 0 | AP36: -95093.68 | AQ36: 0 | AR36: 543343.77 | AS36: 0.2990617 | AV36: =AH36-T36 -> 0 | AW36: =(AI36-U36)*100 -> 0 | AX36: =AJ36-V36 -> 0 | AY36: =(AK36-W36)*100 -> 0 | AZ36: =AL36-X36 -> 0 | BA36: =(AM36-Y36)*100 -> 0 | BB36: =AN36-Z36 -> 0 | BC36: =(AO36-AA36)*100 -> 0 | BD36: =AP36-AB36 -> 0 | BE36: =(AQ36-AC36)*100 -> 0 | BF36: =AR36-AD36 -> 0 | BG36: =(AS36-AE36)*100 -> 0
E37: 기타원가 | AV37: =AH37-T37 -> 0 | AW37: =(AI37-U37)*100 -> 0 | AX37: =AJ37-V37 -> 0 | AY37: =(AK37-W37)*100 -> 0 | AZ37: =AL37-X37 -> 0 | BA37: =(AM37-Y37)*100 -> 0 | BB37: =AN37-Z37 -> 0 | BC37: =(AO37-AA37)*100 -> 0 | BD37: =AP37-AB37 -> 0 | BE37: =(AQ37-AC37)*100 -> 0 | BF37: =AR37-AD37 -> 0 | BG37: =(AS37-AE37)*100 -> 0
E38: 분기원가조정 | AV38: =AH38-T38 -> 0 | AW38: =(AI38-U38)*100 -> 0 | AX38: =AJ38-V38 -> 0 | AY38: =(AK38-W38)*100 -> 0 | AZ38: =AL38-X38 -> 0 | BA38: =(AM38-Y38)*100 -> 0 | BB38: =AN38-Z38 -> 0 | BC38: =(AO38-AA38)*100 -> 0 | BD38: =AP38-AB38 -> 0 | BE38: =(AQ38-AC38)*100 -> 0 | BF38: =AR38-AD38 -> 0 | BG38: =(AS38-AE38)*100 -> 0
E39: (생산원가율, M/U) | F39: 0.18297189 | G39: 5.4653203 | H39: 0.2015917 | I39: 4.9605217 | J39: 0.19519213 | K39: 5.1231575 | L39: 0 | M39: 0 | N39: 0 | O39: 0 | P39: 0.19175492 | Q39: 5.2149901 | T39: 0.19732512 | U39: 5.0677784 | V39: 0.21918401 | W39: 4.5623767 | X39: 0.2407132 | Y39: 4.1543214 | Z39: 0 | AA39: 0 | AB39: 0 | AC39: 0 | AD39: 0.17830694 | AE39: 5.6083067 | AH39: 0.19732512 | AI39: 5.0677784 | AJ39: 0.21918401 | AK39: 4.5623767 | AL39: 0.2407132 | AM39: 4.1543214 | AN39: 0 | AO39: 0 | AP39: 0 | AQ39: 0 | AR39: 0.17830694 | AS39: 5.6083067 | AV39: =(AH39-T39)*100 -> 0 | AW39: =(AI39-U39) -> 0 | AX39: =(AJ39-V39)*100 -> 0 | AY39: =(AK39-W39) -> 0 | AZ39: =(AL39-X39)*100 -> 0 | BA39: =(AM39-Y39) -> 0 | BB39: =AN39-Z39 -> 0 | BC39: =(AO39-AA39) -> 0 | BD39: =AP39-AB39 -> 0 | BE39: =(AQ39-AC39) -> 0 | BF39: =(AR39-AD39)*100 -> 0 | BG39: =(AS39-AE39) -> 0
E40: 매출총이익 | F40: 173788.91 | G40: 0.53561412 | H40: 925199.3 | I40: 0.71984646 | J40: 133807.69 | K40: 0.80366755 | L40: 56910.08 | M40: 1 | N40: 0 | O40: 0 | P40: 1289706 | Q40: 0.70354782 | T40: 144284.65 | U40: 0.52686013 | V40: 899030.12 | W40: 0.65484114 | X40: 51835.61 | Y40: 0.59696313 | Z40: 83240.52 | AA40: 1 | AB40: 95093.68 | AC40: 0 | AD40: 1273484.6 | AE40: 0.7009383 | AH40: 144284.65 | AI40: 0.52686013 | AJ40: 899030.12 | AK40: 0.65484114 | AL40: 51835.61 | AM40: 0.59696313 | AN40: 83240.52 | AO40: 1 | AP40: 95093.68 | AQ40: 0 | AR40: 1273484.6 | AS40: 0.7009383 | AV40: =AH40-T40 -> 0 | AW40: =(AI40-U40)*100 -> 0 | AX40: =AJ40-V40 -> 0 | AY40: =(AK40-W40)*100 -> 0 | AZ40: =AL40-X40 -> 0 | BA40: =(AM40-Y40)*100 -> 0 | BB40: =AN40-Z40 -> 0 | BC40: =(AO40-AA40)*100 -> 0 | BD40: =AP40-AB40 -> 0 | BE40: =(AQ40-AC40)*100 -> 0 | BF40: =AR40-AD40 -> 0 | BG40: =(AS40-AE40)*100 -> 0
E42: 직접비
E43: 운반비/보관료/ 물류용역비 | F43: 21350.895 | G43: 0.065803053 | H43: 163276.06 | I43: 0.12703608 | J43: 55401.185 | K43: 0.3327472 | L43: 0 | M43: 0 | N43: 0 | O43: 0 | P43: 240028.14 | Q43: 0.13093781 | T43: 12458.8 | U43: 0.045493716 | V43: 137967.05 | W43: 0.1004933 | X43: 15409.25 | Y43: 0.17746013 | Z43: 0 | AA43: 0 | AB43: 0 | AC43: 0 | AD43: 165835.1 | AE43: 0.091277252 | AH43: 12458.8 | AI43: 0.045493716 | AJ43: 137967.05 | AK43: 0.1004933 | AL43: 15409.25 | AM43: 0.17746013 | AN43: 0 | AO43: 0 | AP43: 0 | AQ43: 0 | AR43: 165835.1 | AS43: 0.091277252 | AV43: =AH43-T43 -> 0 | AW43: =(AI43-U43)*100 -> 0 | AX43: =AJ43-V43 -> 0 | AY43: =(AK43-W43)*100 -> 0 | AZ43: =AL43-X43 -> 0 | BA43: =(AM43-Y43)*100 -> 0 | BB43: =AN43-Z43 -> 0 | BC43: =(AO43-AA43)*100 -> 0 | BD43: =AP43-AB43 -> 0 | BE43: =(AQ43-AC43)*100 -> 0 | BF43: =AR43-AD43 -> 0 | BG43: =(AS43-AE43)*100 -> 0
B44: 운반비 | C44: 운반비 (-) | E44: 운반비 | F44: -7003.965 | G44: -0.021586087 | H44: 107487.57 | I44: 0.083630139 | J44: 49017.785 | K44: 0.29440762 | L44: 0 | M44: 0 | N44: 0 | O44: 0 | P44: 149501.39 | Q44: 0.081554539 | T44: -3626.69 | U44: -0.013242977 | V44: 64174.68 | W44: 0.046743952 | X44: 6363.96 | Y44: 0.07329034 | Z44: 0 | AA44: 0 | AB44: 0 | AC44: 0 | AD44: 66911.95 | AE44: 0.036828988 | AH44: -3626.69 | AI44: -0.013242977 | AJ44: 64174.68 | AK44: 0.046743952 | AL44: 6363.96 | AM44: 0.07329034 | AN44: 0 | AO44: 0 | AP44: 0 | AQ44: 0 | AR44: 66911.95 | AS44: 0.036828988 | AV44: =AH44-T44 -> 0 | AW44: =(AI44-U44)*100 -> 0 | AX44: =AJ44-V44 -> 0 | AY44: =(AK44-W44)*100 -> 0 | AZ44: =AL44-X44 -> 0 | BA44: =(AM44-Y44)*100 -> 0 | BB44: =AN44-Z44 -> 0 | BC44: =(AO44-AA44)*100 -> 0 | BD44: =AP44-AB44 -> 0 | BE44: =(AQ44-AC44)*100 -> 0 | BF44: =AR44-AD44 -> 0 | BG44: =(AS44-AE44)*100 -> 0
B45: 보관료 | E45: 보관료 | F45: 16326.79 | G45: 0.050318857 | H45: 20495.57 | I45: 0.015946471 | J45: 2898.62 | K45: 0.017409514 | L45: 0 | M45: 0 | N45: 0 | O45: 0 | P45: 39720.98 | Q45: 0.021668201 | T45: 6079.74 | U45: 0.02220037 | V45: 24017.53 | W45: 0.017494038 | X45: 1519.05 | Y45: 0.01749409 | Z45: 0 | AA45: 0 | AB45: 0 | AC45: 0 | AD45: 31616.32 | AE45: 0.01740193 | AH45: 6079.74 | AI45: 0.02220037 | AJ45: 24017.53 | AK45: 0.017494038 | AL45: 1519.05 | AM45: 0.01749409 | AN45: 0 | AO45: 0 | AP45: 0 | AQ45: 0 | AR45: 31616.32 | AS45: 0.01740193 | AV45: =AH45-T45 -> 0 | AW45: =(AI45-U45)*100 -> 0 | AX45: =AJ45-V45 -> 0 | AY45: =(AK45-W45)*100 -> 0 | AZ45: =AL45-X45 -> 0 | BA45: =(AM45-Y45)*100 -> 0 | BB45: =AN45-Z45 -> 0 | BC45: =(AO45-AA45)*100 -> 0 | BD45: =AP45-AB45 -> 0 | BE45: =(AQ45-AC45)*100 -> 0 | BF45: =AR45-AD45 -> 0 | BG45: =(AS45-AE45)*100 -> 0
B46: 물류용역비 | E46: 물류용역비 | F46: 12028.07 | G46: 0.037070284 | H46: 35292.92 | I46: 0.027459471 | J46: 3484.78 | K46: 0.020930072 | L46: 0 | M46: 0 | N46: 0 | O46: 0 | P46: 50805.77 | Q46: 0.027715068 | T46: 10005.75 | U46: 0.036536324 | V46: 49774.84 | W46: 0.036255307 | X46: 7526.24 | Y46: 0.0866757 | Z46: 0 | AA46: 0 | AB46: 0 | AC46: 0 | AD46: 67306.83 | AE46: 0.037046334 | AH46: 10005.75 | AI46: 0.036536324 | AJ46: 49774.84 | AK46: 0.036255307 | AL46: 7526.24 | AM46: 0.0866757 | AN46: 0 | AO46: 0 | AP46: 0 | AQ46: 0 | AR46: 67306.83 | AS46: 0.037046334 | AV46: =AH46-T46 -> 0 | AW46: =(AI46-U46)*100 -> 0 | AX46: =AJ46-V46 -> 0 | AY46: =(AK46-W46)*100 -> 0 | AZ46: =AL46-X46 -> 0 | BA46: =(AM46-Y46)*100 -> 0 | BB46: =AN46-Z46 -> 0 | BC46: =(AO46-AA46)*100 -> 0 | BD46: =AP46-AB46 -> 0 | BE46: =(AQ46-AC46)*100 -> 0 | BF46: =AR46-AD46 -> 0 | BG46: =(AS46-AE46)*100 -> 0
B47: Professional Service | C47: Direct Costs | E47: 지급수수료 | F47: 1572.35 | G47: 0.0048459529 | H47: 48742.68 | I47: 0.037923986 | J47: 10882.02 | K47: 0.065358922 | L47: 0 | M47: 0 | N47: 0 | O47: 0 | P47: 61197.05 | Q47: 0.033383618 | T47: 1398.46 | U47: 0.0051065225 | V47: 94388.15 | W47: 0.068751026 | X47: 5237.82 | Y47: 0.060321185 | Z47: 0 | AA47: 0 | AB47: 0 | AC47: 0 | AD47: 101024.43 | AE47: 0.055604829 | AH47: 1398.46 | AI47: 0.0051065225 | AJ47: 94388.51 | AK47: 0.068751289 | AL47: 5237.82 | AM47: 0.060321185 | AN47: 0 | AO47: 0 | AP47: 0 | AQ47: 0 | AR47: 101024.79 | AS47: 0.055605027 | AV47: =AH47-T47 -> 0 | AW47: =(AI47-U47)*100 -> 0 | AX47: =AJ47-V47 -> 0.36 | AY47: =(AK47-W47)*100 -> 2.6221903e-05 | AZ47: =AL47-X47 -> 0 | BA47: =(AM47-Y47)*100 -> 0 | BB47: =AN47-Z47 -> 0 | BC47: =(AO47-AA47)*100 -> 0 | BD47: =AP47-AB47 -> 0 | BE47: =(AQ47-AC47)*100 -> 0 | BF47: =AR47-AD47 -> 0.36 | BG47: =(AS47-AE47)*100 -> 1.981475e-05
B48: 6451 - Service Processing Fee | C48: Direct Costs | E48: 결제수수료 | F48: 4275.97 | G48: 0.013178458 | H48: 43239.59 | I48: 0.033642336 | J48: 13874.29 | K48: 0.083330911 | L48: 0 | M48: 0 | N48: 0 | O48: 0 | P48: 61389.85 | Q48: 0.033488792 | T48: 2381.49 | U48: 0.0086960888 | V48: 52563.3 | W48: 0.038286383 | X48: 5038.89 | Y48: 0.058030214 | Z48: 0 | AA48: 0 | AB48: 0 | AC48: 0 | AD48: 59983.68 | AE48: 0.033015601 | AH48: 2381.49 | AI48: 0.0086960888 | AJ48: 52562.94 | AK48: 0.03828612 | AL48: 5038.89 | AM48: 0.058030214 | AN48: 0 | AO48: 0 | AP48: 0 | AQ48: 0 | AR48: 59983.32 | AS48: 0.033015403 | AV48: =AH48-T48 -> 0 | AW48: =(AI48-U48)*100 -> 0 | AX48: =AJ48-V48 -> -0.36 | AY48: =(AK48-W48)*100 -> -2.6221903e-05 | AZ48: =AL48-X48 -> 0 | BA48: =(AM48-Y48)*100 -> 0 | BB48: =AN48-Z48 -> 0 | BC48: =(AO48-AA48)*100 -> 0 | BD48: =AP48-AB48 -> 0 | BE48: =(AQ48-AC48)*100 -> 0 | BF48: =AR48-AD48 -> -0.36 | BG48: =(AS48-AE48)*100 -> -1.981475e-05
B49: Marketing | C49: Direct Costs | E49: SEM 광고비 | F49: 0 | G49: 0 | H49: 227981.66 | I49: 0.17737994 | J49: 29533.107 | K49: 0.17737994 | L49: 0 | M49: 0 | N49: 0 | O49: 0 | P49: 257514.77 | Q49: 0.14047694 | T49: 0 | U49: 0 | V49: 233332.27 | W49: 0.16995601 | X49: 25243.74 | Y49: 0.29071872 | Z49: 0 | AA49: 0 | AB49: 0 | AC49: 0 | AD49: 258576.01 | AE49: 0.14232275 | AH49: 0 | AI49: 0 | AJ49: 233332.27 | AK49: 0.16995601 | AL49: 25243.74 | AM49: 0.29071872 | AN49: 0 | AO49: 0 | AP49: 0 | AQ49: 0 | AR49: 258576.01 | AS49: 0.14232275 | AV49: =AH49-T49 -> 0 | AW49: =(AI49-U49)*100 -> 0 | AX49: =AJ49-V49 -> 0 | AY49: =(AK49-W49)*100 -> 0 | AZ49: =AL49-X49 -> 0 | BA49: =(AM49-Y49)*100 -> 0 | BB49: =AN49-Z49 -> 0 | BC49: =(AO49-AA49)*100 -> 0 | BD49: =AP49-AB49 -> 0 | BE49: =(AQ49-AC49)*100 -> 0 | BF49: =AR49-AD49 -> 0 | BG49: =(AS49-AE49)*100 -> 0
B50: Other | C50: Direct Costs | E50: 기타비용 | F50: 0 | G50: 0 | H50: 0 | I50: 0 | J50: 0 | K50: 0 | L50: 0 | M50: 0 | N50: 0 | O50: 0 | P50: 0 | Q50: 0 | T50: 0 | U50: 0 | V50: 0 | W50: 0 | X50: 0 | Y50: 0 | Z50: 0 | AA50: 0 | AB50: 0 | AC50: 0 | AD50: 0 | AE50: 0 | AH50: 0 | AI50: 0 | AJ50: 0 | AK50: 0 | AL50: 0 | AM50: 0 | AN50: 0 | AO50: 0 | AP50: 0 | AQ50: 0 | AR50: 0 | AS50: 0 | AV50: =AH50-T50 -> 0 | AW50: =(AI50-U50)*100 -> 0 | AX50: =AJ50-V50 -> 0 | AY50: =(AK50-W50)*100 -> 0 | AZ50: =AL50-X50 -> 0 | BA50: =(AM50-Y50)*100 -> 0 | BB50: =AN50-Z50 -> 0 | BC50: =(AO50-AA50)*100 -> 0 | BD50: =AP50-AB50 -> 0 | BE50: =(AQ50-AC50)*100 -> 0 | BF50: =AR50-AD50 -> 0 | BG50: =(AS50-AE50)*100 -> 0
E51: 직접비 소계 | F51: 27199.215 | G51: 0.083827465 | H51: 483239.99 | I51: 0.37598234 | J51: 109690.6 | K51: 0.65881697 | L51: 0 | M51: 0 | N51: 0 | O51: 0 | P51: 620129.81 | Q51: 0.33828716 | T51: 16238.75 | U51: 0.059296328 | V51: 518250.77 | W51: 0.37748671 | X51: 50929.7 | Y51: 0.58653025 | Z51: 0 | AA51: 0 | AB51: 0 | AC51: 0 | AD51: 585419.22 | AE51: 0.32222043 | AH51: 16238.75 | AI51: 0.059296328 | AJ51: 518250.77 | AK51: 0.37748671 | AL51: 50929.7 | AM51: 0.58653025 | AN51: 0 | AO51: 0 | AP51: 0 | AQ51: 0 | AR51: 585419.22 | AS51: 0.32222043 | AV51: =AH51-T51 -> 0 | AW51: =(AI51-U51)*100 -> 0 | AX51: =AJ51-V51 -> 0 | AY51: =(AK51-W51)*100 -> 0 | AZ51: =AL51-X51 -> 0 | BA51: =(AM51-Y51)*100 -> 0 | BB51: =AN51-Z51 -> 0 | BC51: =(AO51-AA51)*100 -> 0 | BD51: =AP51-AB51 -> 0 | BE51: =(AQ51-AC51)*100 -> 0 | BF51: =AR51-AD51 -> 0 | BG51: =(AS51-AE51)*100 -> 0
E53: 직접이익 | F53: 146589.7 | G53: 0.45178666 | H53: 441959.31 | I53: 0.34386412 | J53: 24117.088 | K53: 0.14485058 | L53: 56910.08 | M53: 1 | N53: 0 | O53: 0 | P53: 669576.17 | Q53: 0.36526066 | T53: 128045.9 | U53: 0.4675638 | V53: 380779.35 | W53: 0.27735443 | X53: 905.91 | Y53: 0.010432883 | Z53: 83240.52 | AA53: 1 | AB53: 95093.68 | AC53: 0 | AD53: 688065.36 | AE53: 0.37871787 | AH53: 128045.9 | AI53: 0.4675638 | AJ53: 380779.35 | AK53: 0.27735443 | AL53: 905.91 | AM53: 0.010432883 | AN53: 83240.52 | AO53: 1 | AP53: 95093.68 | AQ53: 0 | AR53: 688065.36 | AS53: 0.37871787 | AV53: =AH53-T53 -> 0 | AW53: =(AI53-U53)*100 -> 0 | AX53: =AJ53-V53 -> 0 | AY53: =(AK53-W53)*100 -> 0 | AZ53: =AL53-X53 -> 0 | BA53: =(AM53-Y53)*100 -> 0 | BB53: =AN53-Z53 -> 0 | BC53: =(AO53-AA53)*100 -> 0 | BD53: =AP53-AB53 -> 0 | BE53: =(AQ53-AC53)*100 -> 0 | BF53: =AR53-AD53 -> 0 | BG53: =(AS53-AE53)*100 -> 0
AI54: =+AI53-G53 -> 0.01577714 | AK54: =+AK53-I53 -> -0.066509691 | AM54: =+AM53-K53 -> -0.1344177
E55: 영업비
E56: 인건비 | P56: 92703.28 | Q56: 0.050570589 | AD56: 365453.29 | AE56: 0.20114905 | AR56: 365453.29 | AS56: 0.20114905 | BF56: =AR56-AD56 -> 0 | BG56: =(AS56-AE56)*100 -> 0
B57: HQ | C57: HQ Salaries | E57: 급여(정규) | P57: 223743.14 | Q57: 0.12205417 | AD57: 245269.28 | AE57: 0.1349986 | AR57: 245269.28 | AS57: 0.1349986 | BF57: =AR57-AD57 -> 0 | BG57: =(AS57-AE57)*100 -> 0
B58: Contractors | C58: HQ Salaries | E58: 급여(계약) | P58: 37193 | Q58: 0.020289162 | AD58: 41578.93 | AE58: 0.022885448 | AR58: 41578.93 | AS58: 0.022885448 | BF58: =AR58-AD58 -> 0 | BG58: =(AS58-AE58)*100 -> 0
B59: Benefits | C59: HQ Salaries | E59: 보험,복후비등 | P59: 71978.8 | Q59: 0.039265173 | AD59: 78605.08 | AE59: 0.043265001 | AR59: 78605.08 | AS59: 0.043265001 | BF59: =AR59-AD59 -> 0 | BG59: =(AS59-AE59)*100 -> 0
B60: Bonus | C60: HQ Salaries | E60: 급여충당금 | P60: -240211.66 | Q60: -0.13103792 | AD60: 0 | AE60: 0 | AR60: 0 | AS60: 0 | BF60: =AR60-AD60 -> 0 | BG60: =(AS60-AE60)*100 -> 0
B61: Advertising | C61: SG&A | E61: 광고선전비 | P61: 49370.03 | Q61: 0.026931857 | AD61: 122283.39 | AE61: 0.067305968 | AR61: 122283.39 | AS61: 0.067305968 | BF61: =AR61-AD61 -> 0 | BG61: =(AS61-AE61)*100 -> 0
E62: Photography | P62: 36250 | Q62: 0.019774746 | AE62: 0 | AS62: 0 | BF62: =AR62-AD62 -> 0 | BG62: =(AS62-AE62)*100 -> 0
E63: Selling | P63: 0 | Q63: 0 | AE63: 0 | AS63: 0 | BF63: =AR63-AD63 -> 0 | BG63: =(AS63-AE63)*100 -> 0
E64: Advertising | P64: 0 | Q64: 0 | AE64: 0 | AS64: 0 | BF64: =AR64-AD64 -> 0 | BG64: =(AS64-AE64)*100 -> 0
E65: SEM브랜드마케팅 | P65: 0 | Q65: 0 | AE65: 0 | AS65: 0 | BF65: =AR65-AD65 -> 0 | BG65: =(AS65-AE65)*100 -> 0
E66: Events | P66: 5006.9 | Q66: 0.0027313152 | AE66: 0 | AS66: 0 | BF66: =AR66-AD66 -> 0 | BG66: =(AS66-AE66)*100 -> 0
E67: Model | P67: 2100 | Q67: 0.0011455715 | AE67: 0 | AS67: 0 | BF67: =AR67-AD67 -> 0 | BG67: =(AS67-AE67)*100 -> 0
E68: Seeding | P68: 6013.13 | Q68: 0.003280224 | AE68: 0 | AS68: 0 | BF68: =AR68-AD68 -> 0 | BG68: =(AS68-AE68)*100 -> 0
E69: 기타 광고비 | P69: 0 | Q69: 0 | AE69: 0 | AS69: 0 | BF69: =AR69-AD69 -> 0 | BG69: =(AS69-AE69)*100 -> 0
B70: Professional Service | C70: SG&A | E70: 지급수수료 | P70: 163784.21 | Q70: 0.089345964 | AD70: 56640.99 | AE70: 0.031175752 | AR70: 56640.99 | AS70: 0.031175752 | BF70: =AR70-AD70 -> 0 | BG70: =(AS70-AE70)*100 -> 0
B71: T&E | C71: SG&A | E71: 식대 / 출장비 | P71: 19581.61 | Q71: 0.010681969 | AD71: 23731.36 | AE71: 0.013061971 | AR71: 23731.36 | AS71: 0.013061971 | BF71: =AR71-AD71 -> 0 | BG71: =(AS71-AE71)*100 -> 1.7347235e-16
B72: Rent | C72: SG&A | E72: 임차료 | P72: 33917.55 | Q72: 0.018502371 | AD72: 24653.99 | AE72: 0.013569796 | AR72: 24653.99 | AS72: 0.013569796 | BF72: =AR72-AD72 -> 0 | BG72: =(AS72-AE72)*100 -> 0
B73: Sample | C73: SG&A | E73: 샘플비/개발비 | P73: 315.84 | Q73: 0.00017229395 | AD73: 3228.46 | AE73: 0.0017769758 | AR73: 3228.46 | AS73: 0.0017769758 | BF73: =AR73-AD73 -> 0 | BG73: =(AS73-AE73)*100 -> 0
B74: Depreciation & Amortization | C74: SG&A | E74: 감가상각비 | P74: 3692.04 | Q74: 0.0020140456 | AD74: -269.21 | AE74: -0.0001481758 | AR74: -269.21 | AS74: -0.0001481758 | BF74: =AR74-AD74 -> 0 | BG74: =(AS74-AE74)*100 -> 2.1684043e-17
B75: Other | C75: SG&A | E75: 기타비용 | P75: -93316.11 | Q75: -0.050904894 | AD75: 97426.2 | AE75: 0.053624328 | AR75: 97426.2 | AS75: 0.053624328 | BF75: =AR75-AD75 -> 0 | BG75: =(AS75-AE75)*100 -> 0
E76: 영업비 소계 | P76: 270048.45 | Q76: 0.1473142 | T76: 0 | U76: 0 | V76: 0 | W76: 0 | X76: 0 | Y76: 0 | Z76: 0 | AA76: 0 | AD76: 693148.47 | AE76: 0.38151566 | AH76: 0 | AI76: 0 | AJ76: 0 | AK76: 0 | AL76: 0 | AM76: 0 | AN76: 0 | AO76: 0 | AR76: 693148.47 | AS76: 0.38151566 | AV76: =SUM(AV57:AV75) -> 0 | AW76: =SUM(AW57:AW75) -> 0 | AX76: =SUM(AX57:AX75) -> 0 | AY76: =SUM(AY57:AY75) -> 0 | AZ76: =SUM(AZ57:AZ75) -> 0 | BA76: =SUM(BA57:BA75) -> 0 | BB76: =SUM(BB57:BB75) -> 0 | BC76: =SUM(BC57:BC75) -> 0 | BF76: =AR76-AD76 -> 0 | BG76: =(AS76-AE76)*100 -> 0
E78: 영업이익 | P78: 399527.72 | Q78: 0.21794646 | AD78: -5083.11 | AE78: -0.0027977932 | AR78: -5083.11 | AS78: -0.0027977932 | BF78: =AR78-AD78 -> 0 | BG78: =(AS78-AE78)*100 -> 0
E80: 영업외손익
E82: 이자비용
E83: 경상이익

Sheet 4월
E5: 45931
E7: Date | F7: =EDATE($E$5,-12) -> 45566 | H7: =F7 -> 45566 | J7: =H7 -> 45566 | L7: =J7 -> 45566 | N7: =L7 -> 45566 | P7: =L7 -> 45566 | T7: =EDATE($E$5,0) -> 45931 | V7: =T7 -> 45931 | X7: =V7 -> 45931 | Z7: =X7 -> 45931 | AB7: =Z7 -> 45931 | AD7: =Z7 -> 45931 | AH7: =EDATE($E$5,0) -> 45931 | AJ7: =AH7 -> 45931 | AL7: =AJ7 -> 45931 | AN7: =AL7 -> 45931 | AP7: =AN7 -> 45931 | AR7: =AN7 -> 45931 | AV7: =EDATE($E$5,0) -> 45931 | AX7: =AV7 -> 45931 | AZ7: =AX7 -> 45931 | BD7: =BB7 -> 0 | BF7: =BB7 -> 0
E8: Category | F8: Wholesale | H8: Ecommerce (US) | J8: Ecommerce (EU) | L8: License | N8: Other Income | T8: Wholesale | V8: Ecommerce (US) | X8: Ecommerce (EU) | Z8: License | AB8: Other Income | AH8: Wholesale | AJ8: Ecommerce (US) | AL8: Ecommerce (EU) | AN8: License | AP8: Other Income | AV8: Wholesale | AX8: Ecommerce (US) | AZ8: Ecommerce (EU) | BD8: Other Income
E9: M | F9: =MONTH(F7) -> 10 | T9: =MONTH(T7) -> 10 | AH9: =MONTH(AH7) -> 10 | AV9: =MONTH(AV7) -> 10
E10: Q | F10: ="Q"&ROUNDUP(MONTH(F7)/3,0)&"'"&TEXT(F7,"yy") -> Q4'24 | T10: ="Q"&ROUNDUP(MONTH(T7)/3,0)&"'"&TEXT(T7,"yy") -> Q4'25 | AH10: ="Q"&ROUNDUP(MONTH(AH7)/3,0)&"'"&TEXT(AH7,"yy") -> Q4'25 | AV10: ="Q"&ROUNDUP(MONTH(AV7)/3,0)&"'"&TEXT(AV7,"yy") -> Q4'25
E11: H | F11: ="H"&ROUNDUP(MONTH(F7)/6,0)&"'"&TEXT(F7,"yy") -> H2'24 | T11: ="H"&ROUNDUP(MONTH(T7)/6,0)&"'"&TEXT(T7,"yy") -> H2'25 | AH11: ="H"&ROUNDUP(MONTH(AH7)/6,0)&"'"&TEXT(AH7,"yy") -> H2'25 | AV11: ="H"&ROUNDUP(MONTH(AV7)/6,0)&"'"&TEXT(AV7,"yy") -> H2'25
E12: Y | F12: =YEAR(F7) -> 2024 | T12: =YEAR(T7) -> 2025 | AH12: =YEAR(AH7) -> 2025 | AV12: =YEAR(AV7) -> 2025
E13: Actual / Forecast | F13: Actual | T13: Forecast | AH13: Actual | AV13: Actual
F15: Last Year - Current Month | T15: Budget - Current Month | AH15: Actual - Current Month | AV15: vs Plan
F17: STO 24년 4월 전년 실적 | P17: STO 24년 4월 전년 실적 | T17: STO 25년 4월 당월 계획 | AD17: STO 25년 4월 당월 계획 | AH17: STO 25년 4월 당월 실적 | AR17: STO 25년 4월 당월 실적 | AV17: ="STO"&" "&RIGHT(YEAR($E$5),2)&"년"&" "&MONTH($E$5)&"월 계획대비" -> STO 25년 10월 계획대비 | BF17: ="STO"&" "&RIGHT(YEAR($E$5),2)&"년"&" "&MONTH($E$5)&"월 당월 실적" -> STO 25년 10월 당월 실적
F18: 홀세일(미국) | H18: 온라인(미국) | J18: 온라인(유럽) | L18: 라이선스 | N18: 기타 | P18: STO 합계 | T18: 홀세일(미국) | V18: 온라인(미국) | X18: 온라인(유럽) | Z18: 라이선스 | AB18: 기타 | AD18: STO 합계 | AH18: 홀세일(미국) | AJ18: 온라인(미국) | AL18: 온라인(유럽) | AN18: 라이선스 | AP18: 기타 | AR18: STO 합계 | AV18: 홀세일(미국) | AX18: 온라인(미국) | AZ18: 온라인(유럽) | BB18: 라이선스 | BD18: 기타 | BF18: STO 합계
E19: STO/STIP
E20: 라이선스
E21: 홀세일(미국)
E22: 온라인(미국)
E23: 할인율(%)
E24: 생산원가율(%)
E25: 온라인(유럽)
E26: 매출액(할인전) 계
E27: 총매출 (MSRP) | F27: 815968 | H27: 2018677 | J27: 224326 | L27: 104428.32 | N27: 0 | P27: 3163399.3 | T27: 509987 | V27: 1868116 | X27: 137621 | Z27: 61923.1 | AB27: 0 | AD27: 2577647.1 | AH27: 509987 | AJ27: 1868116 | AL27: 137621 | AN27: 61923.1 | AP27: 0 | AR27: 2577647.1 | AV27: =AH27-T27 -> 0 | AX27: =AJ27-V27 -> 0 | AZ27: =AL27-X27 -> 0 | BB27: =AN27-Z27 -> 0 | BD27: =AP27-AB27 -> 0 | BF27: =AR27-AD27 -> 0
E28: 할인액 | F28: 494072.65 | H28: 677657.66 | J28: 19916.64 | L28: 0 | N28: 0 | P28: 1191647 | T28: 299736.05 | V28: 600772.36 | X28: 43660.47 | Z28: 0 | AB28: 0 | AD28: 944168.88 | AH28: 299736.05 | AJ28: 600772.36 | AL28: 43660.47 | AN28: 0 | AP28: 0 | AR28: 944168.88 | AV28: =AH28-T28 -> 0 | AX28: =AJ28-V28 -> 0 | AZ28: =AL28-X28 -> 0 | BB28: =AN28-Z28 -> 0 | BD28: =AP28-AB28 -> 0 | BF28: =AR28-AD28 -> 0
C29: Revenue | E29: 실판매 | F29: 321895.35 | G29: 0.60550493 | H29: 1341019.3 | I29: 0.33569395 | J29: 204409.36 | K29: 0.088784358 | L29: 104428.32 | M29: 0 | N29: 0 | O29: 0 | P29: 1971752.4 | Q29: 0.37669824 | T29: 210250.95 | U29: 0.58773273 | V29: 1267343.6 | W29: 0.32159264 | X29: 93960.53 | Y29: 0.31725151 | Z29: 61923.1 | AA29: 0 | AB29: 0 | AC29: 0 | AD29: 1633478.2 | AE29: 0.36629098 | AH29: 210250.95 | AI29: 0.58773273 | AJ29: 1267343.6 | AK29: 0.32159264 | AL29: 93960.53 | AM29: 0.31725151 | AN29: 61923.1 | AO29: 0 | AP29: 0 | AQ29: 0 | AR29: 1633478.2 | AS29: 0.36629098 | AV29: =AH29-T29 -> 0 | AW29: =(AI29-U29)*100 -> 0 | AX29: =AJ29-V29 -> 0 | AY29: =(AK29-W29)*100 -> 0 | AZ29: =AL29-X29 -> 0 | BA29: =(AM29-Y29)*100 -> 0 | BB29: =AN29-Z29 -> 0 | BC29: =(AO29-AA29)*100 -> 0 | BD29: =AP29-AB29 -> 0 | BE29: =(AQ29-AC29)*100 -> 0 | BF29: =AR29-AD29 -> 0 | BG29: =(AS29-AE29)*100 -> 0
E30: 제품매출
E31: 기타매출
E33: 계획대비 | F33: n/a | G33: n/a | H33: n/a | I33: n/a | J33: n/a | K33: n/a | L33: n/a | M33: n/a | N33: n/a | O33: n/a | P33: n/a | Q33: n/a | AH33: 0 | AI33: 0 | AJ33: 0 | AK33: 0 | AL33: 0 | AM33: 0 | AN33: 0 | AO33: 0 | AP33: 0 | AQ33: 0 | AR33: 0 | AS33: 0
E34: 전년대비 | F34: n/a | G34: n/a | H34: n/a | I34: n/a | J34: n/a | K34: n/a | L34: n/a | M34: n/a | N34: n/a | O34: n/a | P34: n/a | Q34: n/a | T34: -111644.4 | U34: -0.34683446 | V34: -73675.7 | W34: -0.054940073 | X34: -110448.83 | Y34: -0.54033157 | Z34: -42505.22 | AA34: -0.40702771 | AB34: 0 | AC34: 0 | AD34: -338274.15 | AE34: -0.17156016 | AH34: -111644.4 | AI34: -0.34683446 | AJ34: -73675.7 | AK34: -0.054940073 | AL34: -110448.83 | AM34: -0.54033157 | AN34: -42505.22 | AO34: -0.40702771 | AP34: 0 | AQ34: 0 | AR34: -338274.15 | AS34: -0.17156016
C36: COGS | E36: 매출원가 | F36: 146090.19 | G36: 0.45384374 | H36: 399331.28 | I36: 0.29778189 | J36: 42895.89 | K36: 0.20985287 | L36: 0 | M36: 0 | N36: 0 | O36: 0 | P36: 588317.36 | Q36: 0.29837284 | T36: 101063.06 | U36: 0.48067826 | V36: 410320.84 | W36: 0.32376447 | X36: 26297.46 | Y36: 0.27987773 | Z36: 0 | AA36: 0 | AB36: 0 | AC36: 0 | AD36: 537681.36 | AE36: 0.32916347 | AH36: 101063.06 | AI36: 0.48067826 | AJ36: 410320.84 | AK36: 0.32376447 | AL36: 26297.46 | AM36: 0.27987773 | AN36: 0 | AO36: 0 | AP36: 0 | AQ36: 0 | AR36: 537681.36 | AS36: 0.32916347 | AV36: =AH36-T36 -> 0 | AW36: =(AI36-U36)*100 -> 0 | AX36: =AJ36-V36 -> 0 | AY36: =(AK36-W36)*100 -> 0 | AZ36: =AL36-X36 -> 0 | BA36: =(AM36-Y36)*100 -> 0 | BB36: =AN36-Z36 -> 0 | BC36: =(AO36-AA36)*100 -> 0 | BD36: =AP36-AB36 -> 0 | BE36: =(AQ36-AC36)*100 -> 0 | BF36: =AR36-AD36 -> 0 | BG36: =(AS36-AE36)*100 -> 0
E37: 기타원가 | AV37: =AH37-T37 -> 0 | AW37: =(AI37-U37)*100 -> 0 | AX37: =AJ37-V37 -> 0 | AY37: =(AK37-W37)*100 -> 0 | AZ37: =AL37-X37 -> 0 | BA37: =(AM37-Y37)*100 -> 0 | BB37: =AN37-Z37 -> 0 | BC37: =(AO37-AA37)*100 -> 0 | BD37: =AP37-AB37 -> 0 | BE37: =(AQ37-AC37)*100 -> 0 | BF37: =AR37-AD37 -> 0 | BG37: =(AS37-AE37)*100 -> 0
E38: 분기원가조정 | AV38: =AH38-T38 -> 0 | AW38: =(AI38-U38)*100 -> 0 | AX38: =AJ38-V38 -> 0 | AY38: =(AK38-W38)*100 -> 0 | AZ38: =AL38-X38 -> 0 | BA38: =(AM38-Y38)*100 -> 0 | BB38: =AN38-Z38 -> 0 | BC38: =(AO38-AA38)*100 -> 0 | BD38: =AP38-AB38 -> 0 | BE38: =(AQ38-AC38)*100 -> 0 | BF38: =AR38-AD38 -> 0 | BG38: =(AS38-AE38)*100 -> 0
E39: (생산원가율, M/U) | F39: 0.17903912 | G39: 5.5853716 | H39: 0.19781831 | I39: 5.0551437 | J39: 0.19122121 | K39: 5.2295453 | L39: 0 | M39: 0 | N39: 0 | O39: 0 | P39: 0.18597632 | Q39: 5.3770287 | T39: 0.19816791 | U39: 5.0462256 | V39: 0.2196442 | W39: 4.5528177 | X39: 0.1910861 | Y39: 5.2332431 | Z39: 0 | AA39: 0 | AB39: 0 | AC39: 0 | AD39: 0.20859386 | AE39: 4.7940049 | AH39: 0.19816791 | AI39: 5.0462256 | AJ39: 0.2196442 | AK39: 4.5528177 | AL39: 0.1910861 | AM39: 5.2332431 | AN39: 0 | AO39: 0 | AP39: 0 | AQ39: 0 | AR39: 0.20859386 | AS39: 4.7940049 | AV39: =(AH39-T39)*100 -> 0 | AW39: =(AI39-U39) -> 0 | AX39: =(AJ39-V39)*100 -> 0 | AY39: =(AK39-W39) -> 0 | AZ39: =(AL39-X39)*100 -> 0 | BA39: =(AM39-Y39) -> 0 | BB39: =AN39-Z39 -> 0 | BC39: =(AO39-AA39) -> 0 | BD39: =AP39-AB39 -> 0 | BE39: =(AQ39-AC39) -> 0 | BF39: =(AR39-AD39)*100 -> 0 | BG39: =(AS39-AE39) -> 0
E40: 매출총이익 | F40: 175805.16 | G40: 0.54615626 | H40: 941688.06 | I40: 0.70221811 | J40: 161513.47 | K40: 0.79014713 | L40: 104428.32 | M40: 1 | N40: 0 | O40: 0 | P40: 1383435 | Q40: 0.70162716 | T40: 109187.89 | U40: 0.51932174 | V40: 857022.8 | W40: 0.67623553 | X40: 67663.07 | Y40: 0.72012227 | Z40: 61923.1 | AA40: 1 | AB40: 0 | AC40: 0 | AD40: 1095796.9 | AE40: 0.67083653 | AH40: 109187.89 | AI40: 0.51932174 | AJ40: 857022.8 | AK40: 0.67623553 | AL40: 67663.07 | AM40: 0.72012227 | AN40: 61923.1 | AO40: 1 | AP40: 0 | AQ40: 0 | AR40: 1095796.9 | AS40: 0.67083653 | AV40: =AH40-T40 -> 0 | AW40: =(AI40-U40)*100 -> 0 | AX40: =AJ40-V40 -> 0 | AY40: =(AK40-W40)*100 -> 0 | AZ40: =AL40-X40 -> 0 | BA40: =(AM40-Y40)*100 -> 0 | BB40: =AN40-Z40 -> 0 | BC40: =(AO40-AA40)*100 -> 0 | BD40: =AP40-AB40 -> 0 | BE40: =(AQ40-AC40)*100 -> 0 | BF40: =AR40-AD40 -> 0 | BG40: =(AS40-AE40)*100 -> 0
E42: 직접비
E43: 운반비/보관료/ 물류용역비 | F43: 15992.442 | G43: 0.049682116 | H43: 142034.62 | I43: 0.10591541 | J43: 22005.912 | K43: 0.10765609 | L43: 0 | M43: 0 | N43: 0 | O43: 0 | P43: 180032.97 | Q43: 0.091306075 | T43: 9588.94 | U43: 0.045607119 | V43: 147543.54 | W43: 0.11641952 | X43: 19306.55 | Y43: 0.20547511 | Z43: 0 | AA43: 0 | AB43: 0 | AC43: 0 | AD43: 176439.03 | AE43: 0.10801431 | AH43: 9588.94 | AI43: 0.045607119 | AJ43: 147543.54 | AK43: 0.11641952 | AL43: 19306.55 | AM43: 0.20547511 | AN43: 0 | AO43: 0 | AP43: 0 | AQ43: 0 | AR43: 176439.03 | AS43: 0.10801431 | AV43: =AH43-T43 -> 0 | AW43: =(AI43-U43)*100 -> 0 | AX43: =AJ43-V43 -> 0 | AY43: =(AK43-W43)*100 -> -2.7755576e-15 | AZ43: =AL43-X43 -> 0 | BA43: =(AM43-Y43)*100 -> 0 | BB43: =AN43-Z43 -> 0 | BC43: =(AO43-AA43)*100 -> 0 | BD43: =AP43-AB43 -> 0 | BE43: =(AQ43-AC43)*100 -> 0 | BF43: =AR43-AD43 -> 0 | BG43: =(AS43-AE43)*100 -> -1.3877788e-15
B44: 운반비 | C44: 운반비 (-) | E44: 운반비 | F44: -7727.728 | G44: -0.024006958 | H44: 79953.566 | I44: 0.059621486 | J44: 13533.822 | K44: 0.066209405 | L44: 0 | M44: 0 | N44: 0 | O44: 0 | P44: 85759.66 | Q44: 0.043494133 | T44: -3504.38 | U44: -0.016667606 | V44: 71907.7 | W44: 0.056738913 | X44: 8592.08 | Y44: 0.091443503 | Z44: 0 | AA44: 0 | AB44: 0 | AC44: 0 | AD44: 76995.4 | AE44: 0.04713586 | AH44: -3504.38 | AI44: -0.016667606 | AJ44: 71907.7 | AK44: 0.056738913 | AL44: 8592.08 | AM44: 0.091443503 | AN44: 0 | AO44: 0 | AP44: 0 | AQ44: 0 | AR44: 76995.4 | AS44: 0.04713586 | AV44: =AH44-T44 -> 0 | AW44: =(AI44-U44)*100 -> 0 | AX44: =AJ44-V44 -> 0 | AY44: =(AK44-W44)*100 -> 0 | AZ44: =AL44-X44 -> 0 | BA44: =(AM44-Y44)*100 -> 0 | BB44: =AN44-Z44 -> 0 | BC44: =(AO44-AA44)*100 -> 0 | BD44: =AP44-AB44 -> 0 | BE44: =(AQ44-AC44)*100 -> 0 | BF44: =AR44-AD44 -> 0 | BG44: =(AS44-AE44)*100 -> 0
B45: 보관료 | E45: 보관료 | F45: 13856.38 | G45: 0.043046226 | H45: 19290.16 | I45: 0.014384699 | J45: 3295.85 | K45: 0.016123772 | L45: 0 | M45: 0 | N45: 0 | O45: 0 | P45: 36442.39 | Q45: 0.018482235 | T45: 5613.25 | U45: 0.026697858 | V45: 27502.9 | W45: 0.021701218 | X45: 2039.06 | Y45: 0.02170124 | Z45: 0 | AA45: 0 | AB45: 0 | AC45: 0 | AD45: 35155.21 | AE45: 0.021521689 | AH45: 5613.25 | AI45: 0.026697858 | AJ45: 27502.9 | AK45: 0.021701218 | AL45: 2039.06 | AM45: 0.02170124 | AN45: 0 | AO45: 0 | AP45: 0 | AQ45: 0 | AR45: 35155.21 | AS45: 0.021521689 | AV45: =AH45-T45 -> 0 | AW45: =(AI45-U45)*100 -> 0 | AX45: =AJ45-V45 -> 0 | AY45: =(AK45-W45)*100 -> 0 | AZ45: =AL45-X45 -> 0 | BA45: =(AM45-Y45)*100 -> 0 | BB45: =AN45-Z45 -> 0 | BC45: =(AO45-AA45)*100 -> 0 | BD45: =AP45-AB45 -> 0 | BE45: =(AQ45-AC45)*100 -> 0 | BF45: =AR45-AD45 -> 0 | BG45: =(AS45-AE45)*100 -> 0
B46: 물류용역비 | E46: 물류용역비 | F46: 9863.79 | G46: 0.030642847 | H46: 42790.89 | I46: 0.031909227 | J46: 5176.24 | K46: 0.025322911 | L46: 0 | M46: 0 | N46: 0 | O46: 0 | P46: 57830.92 | Q46: 0.029329707 | T46: 7480.07 | U46: 0.035576867 | V46: 48132.94 | W46: 0.037979391 | X46: 8675.41 | Y46: 0.092330365 | Z46: 0 | AA46: 0 | AB46: 0 | AC46: 0 | AD46: 64288.42 | AE46: 0.039356766 | AH46: 7480.07 | AI46: 0.035576867 | AJ46: 48132.94 | AK46: 0.037979391 | AL46: 8675.41 | AM46: 0.092330365 | AN46: 0 | AO46: 0 | AP46: 0 | AQ46: 0 | AR46: 64288.42 | AS46: 0.039356766 | AV46: =AH46-T46 -> 0 | AW46: =(AI46-U46)*100 -> -6.9388939e-16 | AX46: =AJ46-V46 -> 0 | AY46: =(AK46-W46)*100 -> 0 | AZ46: =AL46-X46 -> 0 | BA46: =(AM46-Y46)*100 -> 0 | BB46: =AN46-Z46 -> 0 | BC46: =(AO46-AA46)*100 -> 0 | BD46: =AP46-AB46 -> 0 | BE46: =(AQ46-AC46)*100 -> 0 | BF46: =AR46-AD46 -> 0 | BG46: =(AS46-AE46)*100 -> -6.9388939e-16
B47: Professional Service | C47: Direct Costs | E47: 지급수수료 | F47: 4957.44 | G47: 0.015400782 | H47: 99385.18 | I47: 0.074111668 | J47: 4083.74 | K47: 0.019978244 | L47: 0 | M47: 0 | N47: 0 | O47: 0 | P47: 108426.36 | Q47: 0.054989846 | T47: 1410.69 | U47: 0.0067095535 | V47: 87739.5 | W47: 0.069231026 | X47: 4457.7 | Y47: 0.047442261 | Z47: 0 | AA47: 0 | AB47: 0 | AC47: 0 | AD47: 93607.89 | AE47: 0.05730587 | AH47: 1410.69 | AI47: 0.0067095535 | AJ47: 87739.86 | AK47: 0.06923131 | AL47: 4457.7 | AM47: 0.047442261 | AN47: 0 | AO47: 0 | AP47: 0 | AQ47: 0 | AR47: 93608.25 | AS47: 0.05730609 | AV47: =AH47-T47 -> 0 | AW47: =(AI47-U47)*100 -> 0 | AX47: =AJ47-V47 -> 0.36 | AY47: =(AK47-W47)*100 -> 2.8405871e-05 | AZ47: =AL47-X47 -> 0 | BA47: =(AM47-Y47)*100 -> 0 | BB47: =AN47-Z47 -> 0 | BC47: =(AO47-AA47)*100 -> 0 | BD47: =AP47-AB47 -> 0 | BE47: =(AQ47-AC47)*100 -> 0 | BF47: =AR47-AD47 -> 0.36 | BG47: =(AS47-AE47)*100 -> 2.2038861e-05
B48: 6451 - Service Processing Fee | C48: Direct Costs | E48: 결제수수료 | F48: 7432.85 | G48: 0.02309089 | H48: 44894.7 | I48: 0.033478041 | J48: 18118.53 | K48: 0.088638456 | L48: 0 | M48: 0 | N48: 0 | O48: 0 | P48: 70446.08 | Q48: 0.035727651 | T48: 3747.66 | U48: 0.017824699 | V48: 57026.86 | W48: 0.044997156 | X48: 5881.46 | Y48: 0.062595007 | Z48: 0 | AA48: 0 | AB48: 0 | AC48: 0 | AD48: 66655.98 | AE48: 0.040806164 | AH48: 3747.66 | AI48: 0.017824699 | AJ48: 57026.5 | AK48: 0.044996872 | AL48: 5881.46 | AM48: 0.062595007 | AN48: 0 | AO48: 0 | AP48: 0 | AQ48: 0 | AR48: 66655.62 | AS48: 0.040805944 | AV48: =AH48-T48 -> 0 | AW48: =(AI48-U48)*100 -> 0 | AX48: =AJ48-V48 -> -0.36 | AY48: =(AK48-W48)*100 -> -2.8405871e-05 | AZ48: =AL48-X48 -> 0 | BA48: =(AM48-Y48)*100 -> 0 | BB48: =AN48-Z48 -> 0 | BC48: =(AO48-AA48)*100 -> 0 | BD48: =AP48-AB48 -> 0 | BE48: =(AQ48-AC48)*100 -> 0 | BF48: =AR48-AD48 -> -0.36 | BG48: =(AS48-AE48)*100 -> -2.2038861e-05
B49: Marketing | C49: Direct Costs | E49: SEM 광고비 | F49: 0 | G49: 0 | H49: 224729.68 | I49: 0.16758123 | J49: 34255.173 | K49: 0.16758123 | L49: 0 | M49: 0 | N49: 0 | O49: 0 | P49: 258984.85 | Q49: 0.13134755 | T49: 0 | U49: 0 | V49: 229082.82 | W49: 0.18075825 | X49: 23908.01 | Y49: 0.25444737 | Z49: 0 | AA49: 0 | AB49: 0 | AC49: 0 | AD49: 252990.83 | AE49: 0.15487861 | AH49: 0 | AI49: 0 | AJ49: 229082.82 | AK49: 0.18075825 | AL49: 23908.01 | AM49: 0.25444737 | AN49: 0 | AO49: 0 | AP49: 0 | AQ49: 0 | AR49: 252990.83 | AS49: 0.15487861 | AV49: =AH49-T49 -> 0 | AW49: =(AI49-U49)*100 -> 0 | AX49: =AJ49-V49 -> 0 | AY49: =(AK49-W49)*100 -> 0 | AZ49: =AL49-X49 -> 0 | BA49: =(AM49-Y49)*100 -> 0 | BB49: =AN49-Z49 -> 0 | BC49: =(AO49-AA49)*100 -> 0 | BD49: =AP49-AB49 -> 0 | BE49: =(AQ49-AC49)*100 -> 0 | BF49: =AR49-AD49 -> 0 | BG49: =(AS49-AE49)*100 -> 0
B50: Other | C50: Direct Costs | E50: 기타비용 | F50: 0 | G50: 0 | H50: 0 | I50: 0 | J50: 0 | K50: 0 | L50: 0 | M50: 0 | N50: 0 | O50: 0 | P50: 0 | Q50: 0 | T50: 0 | U50: 0 | V50: 0 | W50: 0 | X50: 0 | Y50: 0 | Z50: 0 | AA50: 0 | AB50: 0 | AC50: 0 | AD50: 0 | AE50: 0 | AH50: 0 | AI50: 0 | AJ50: 0 | AK50: 0 | AL50: 0 | AM50: 0 | AN50: 0 | AO50: 0 | AP50: 0 | AQ50: 0 | AR50: 0 | AS50: 0 | AV50: =AH50-T50 -> 0 | AW50: =(AI50-U50)*100 -> 0 | AX50: =AJ50-V50 -> 0 | AY50: =(AK50-W50)*100 -> 0 | AZ50: =AL50-X50 -> 0 | BA50: =(AM50-Y50)*100 -> 0 | BB50: =AN50-Z50 -> 0 | BC50: =(AO50-AA50)*100 -> 0 | BD50: =AP50-AB50 -> 0 | BE50: =(AQ50-AC50)*100 -> 0 | BF50: =AR50-AD50 -> 0 | BG50: =(AS50-AE50)*100 -> 0
E51: 직접비 소계 | F51: 28382.732 | G51: 0.088173787 | H51: 511044.17 | I51: 0.38108636 | J51: 78463.355 | K51: 0.38385402 | L51: 0 | M51: 0 | N51: 0 | O51: 0 | P51: 617890.26 | Q51: 0.31337113 | T51: 14747.29 | U51: 0.070141372 | V51: 521392.72 | W51: 0.41140595 | X51: 53553.72 | Y51: 0.56995975 | Z51: 0 | AA51: 0 | AB51: 0 | AC51: 0 | AD51: 589693.73 | AE51: 0.36100495 | AH51: 14747.29 | AI51: 0.070141372 | AJ51: 521392.72 | AK51: 0.41140595 | AL51: 53553.72 | AM51: 0.56995975 | AN51: 0 | AO51: 0 | AP51: 0 | AQ51: 0 | AR51: 589693.73 | AS51: 0.36100495 | AV51: =AH51-T51 -> 0 | AW51: =(AI51-U51)*100 -> 0 | AX51: =AJ51-V51 -> 0 | AY51: =(AK51-W51)*100 -> -5.5511151e-15 | AZ51: =AL51-X51 -> 0 | BA51: =(AM51-Y51)*100 -> 0 | BB51: =AN51-Z51 -> 0 | BC51: =(AO51-AA51)*100 -> 0 | BD51: =AP51-AB51 -> 0 | BE51: =(AQ51-AC51)*100 -> 0 | BF51: =AR51-AD51 -> 0 | BG51: =(AS51-AE51)*100 -> -1.110223e-14
E53: 직접이익 | F53: 147422.43 | G53: 0.45798247 | H53: 430643.89 | I53: 0.32113175 | J53: 83050.115 | K53: 0.40629311 | L53: 104428.32 | M53: 1 | N53: 0 | O53: 0 | P53: 765544.75 | Q53: 0.38825603 | T53: 94440.6 | U53: 0.44918037 | V53: 335630.08 | W53: 0.26482958 | X53: 14109.35 | Y53: 0.15016252 | Z53: 61923.1 | AA53: 1 | AB53: 0 | AC53: 0 | AD53: 506103.13 | AE53: 0.30983158 | AH53: 94440.6 | AI53: 0.44918037 | AJ53: 335630.08 | AK53: 0.26482958 | AL53: 14109.35 | AM53: 0.15016252 | AN53: 61923.1 | AO53: 1 | AP53: 0 | AQ53: 0 | AR53: 506103.13 | AS53: 0.30983158 | AV53: =AH53-T53 -> 0 | AW53: =(AI53-U53)*100 -> 0 | AX53: =AJ53-V53 -> 0 | AY53: =(AK53-W53)*100 -> 0 | AZ53: =AL53-X53 -> 0 | BA53: =(AM53-Y53)*100 -> 0 | BB53: =AN53-Z53 -> 0 | BC53: =(AO53-AA53)*100 -> 0 | BD53: =AP53-AB53 -> 0 | BE53: =(AQ53-AC53)*100 -> 0 | BF53: =AR53-AD53 -> 0 | BG53: =(AS53-AE53)*100 -> 5.5511151e-15
AI54: =+AI53-G53 -> -0.0088020993 | AK54: =+AK53-I53 -> -0.056302173 | AM54: =+AM53-K53 -> -0.25613059
E55: 영업비
E56: 인건비 | P56: 343689.12 | Q56: 0.17430643 | AD56: 361577.7 | AE56: 0.22135447 | AR56: 361577.7 | AS56: 0.22135447 | BF56: =AR56-AD56 -> 0 | BG56: =(AS56-AE56)*100 -> 0
B57: HQ | C57: HQ Salaries | E57: 급여(정규) | P57: 233827.79 | Q57: 0.11858882 | AD57: 249552.93 | AE57: 0.15277396 | AR57: 249552.93 | AS57: 0.15277396 | BF57: =AR57-AD57 -> 0 | BG57: =(AS57-AE57)*100 -> 0
B58: Contractors | C58: HQ Salaries | E58: 급여(계약) | P58: 24630 | Q58: 0.012491427 | AD58: 40615.93 | AE58: 0.02486469 | AR58: 40615.93 | AS58: 0.02486469 | BF58: =AR58-AD58 -> 0 | BG58: =(AS58-AE58)*100 -> 0
B59: Benefits | C59: HQ Salaries | E59: 보험,복후비등 | P59: 46293.83 | Q59: 0.023478521 | AD59: 71408.84 | AE59: 0.04371582 | AR59: 71408.84 | AS59: 0.04371582 | BF59: =AR59-AD59 -> 0 | BG59: =(AS59-AE59)*100 -> 0
B60: Bonus | C60: HQ Salaries | E60: 급여충당금 | P60: 38937.5 | Q60: 0.019747662 | AD60: 0 | AE60: 0 | AR60: 0 | AS60: 0 | BF60: =AR60-AD60 -> 0 | BG60: =(AS60-AE60)*100 -> 0
B61: Advertising | C61: SG&A | E61: 광고선전비 | P61: 38324.42 | Q61: 0.019436731 | AD61: 53581.1 | AE61: 0.032801845 | AR61: 53581.1 | AS61: 0.032801845 | BF61: =AR61-AD61 -> 0 | BG61: =(AS61-AE61)*100 -> 0
E62: Photography | P62: 36250 | Q62: 0.018384662 | AE62: 0 | AS62: 0 | BF62: =AR62-AD62 -> 0 | BG62: =(AS62-AE62)*100 -> 0
E63: Selling | P63: 0 | Q63: 0 | AE63: 0 | AS63: 0 | BF63: =AR63-AD63 -> 0 | BG63: =(AS63-AE63)*100 -> 0
E64: Advertising | P64: 0 | Q64: 0 | AE64: 0 | AS64: 0 | BF64: =AR64-AD64 -> 0 | BG64: =(AS64-AE64)*100 -> 0
E65: SEM브랜드마케팅 | P65: 0 | Q65: 0 | AE65: 0 | AS65: 0 | BF65: =AR65-AD65 -> 0 | BG65: =(AS65-AE65)*100 -> 0
E66: Events | P66: 0 | Q66: 0 | AE66: 0 | AS66: 0 | BF66: =AR66-AD66 -> 0 | BG66: =(AS66-AE66)*100 -> 0
E67: Model | P67: 540 | Q67: 0.00027386806 | AE67: 0 | AS67: 0 | BF67: =AR67-AD67 -> 0 | BG67: =(AS67-AE67)*100 -> 0
E68: Seeding | P68: 1534.42 | Q68: 0.00077820117 | AE68: 0 | AS68: 0 | BF68: =AR68-AD68 -> 0 | BG68: =(AS68-AE68)*100 -> 0
E69: 기타 광고비 | P69: 0 | Q69: 0 | AE69: 0 | AS69: 0 | BF69: =AR69-AD69 -> 0 | BG69: =(AS69-AE69)*100 -> 0
B70: Professional Service | C70: SG&A | E70: 지급수수료 | P70: 75320.02 | Q70: 0.038199533 | AD70: 89562.29 | AE70: 0.054829191 | AR70: 89562.29 | AS70: 0.054829191 | BF70: =AR70-AD70 -> 0 | BG70: =(AS70-AE70)*100 -> 0
B71: T&E | C71: SG&A | E71: 식대 / 출장비 | P71: 8317.46 | Q71: 0.0042183086 | AD71: 4693.87 | AE71: 0.0028735431 | AR71: 4693.87 | AS71: 0.0028735431 | BF71: =AR71-AD71 -> 0 | BG71: =(AS71-AE71)*100 -> 1.7347235e-16
B72: Rent | C72: SG&A | E72: 임차료 | P72: 33919.67 | Q72: 0.017202804 | AD72: 24656.17 | AE72: 0.015094275 | AR72: 24656.17 | AS72: 0.015094275 | BF72: =AR72-AD72 -> 0 | BG72: =(AS72-AE72)*100 -> 1.7347235e-16
B73: Sample | C73: SG&A | E73: 샘플비/개발비 | P73: 1154.31 | Q73: 0.00058542341 | AD73: 19361.09 | AE73: 0.011852677 | AR73: 19361.09 | AS73: 0.011852677 | BF73: =AR73-AD73 -> 0 | BG73: =(AS73-AE73)*100 -> 0
B74: Depreciation & Amortization | C74: SG&A | E74: 감가상각비 | P74: 3699.17 | Q74: 0.0018760824 | AD74: 5350.16 | AE74: 0.0032753176 | AR74: 5350.16 | AS74: 0.0032753176 | BF74: =AR74-AD74 -> 0 | BG74: =(AS74-AE74)*100 -> -4.3368087e-17
B75: Other | C75: SG&A | E75: 기타비용 | P75: 27682.06 | Q75: 0.014039319 | AD75: 6880.89 | AE75: 0.0042124161 | AR75: 6880.89 | AS75: 0.0042124161 | BF75: =AR75-AD75 -> 0 | BG75: =(AS75-AE75)*100 -> 0
E76: 영업비 소계 | P76: 532106.23 | Q76: 0.26986463 | T76: 0 | U76: 0 | V76: 0 | W76: 0 | X76: 0 | Y76: 0 | Z76: 0 | AA76: 0 | AD76: 565663.27 | AE76: 0.34629373 | AH76: 0 | AI76: 0 | AJ76: 0 | AK76: 0 | AL76: 0 | AM76: 0 | AN76: 0 | AO76: 0 | AR76: 565663.27 | AS76: 0.34629373 | AV76: =SUM(AV57:AV75) -> 0 | AW76: =SUM(AW57:AW75) -> 0 | AX76: =SUM(AX57:AX75) -> 0 | AY76: =SUM(AY57:AY75) -> 0 | AZ76: =SUM(AZ57:AZ75) -> 0 | BA76: =SUM(BA57:BA75) -> 0 | BB76: =SUM(BB57:BB75) -> 0 | BC76: =SUM(BC57:BC75) -> 0 | BF76: =AR76-AD76 -> 0 | BG76: =(AS76-AE76)*100 -> 0
E78: 영업이익 | P78: 233438.52 | Q78: 0.1183914 | AD78: -59560.14 | AE78: -0.036462157 | AR78: -59560.14 | AS78: -0.036462157 | BF78: =AR78-AD78 -> 1.1641532e-10 | BG78: =(AS78-AE78)*100 -> 6.9388939e-15
E80: 영업외손익
E82: 이자비용
E83: 경상이익

Sheet 5월
E5: 45931
E7: Date | F7: =EDATE($E$5,-12) -> 45566 | H7: =F7 -> 45566 | J7: =H7 -> 45566 | L7: =J7 -> 45566 | N7: =L7 -> 45566 | P7: =L7 -> 45566 | T7: =EDATE($E$5,0) -> 45931 | V7: =T7 -> 45931 | X7: =V7 -> 45931 | Z7: =X7 -> 45931 | AB7: =Z7 -> 45931 | AD7: =Z7 -> 45931 | AH7: =EDATE($E$5,0) -> 45931 | AJ7: =AH7 -> 45931 | AL7: =AJ7 -> 45931 | AN7: =AL7 -> 45931 | AP7: =AN7 -> 45931 | AR7: =AN7 -> 45931 | AV7: =EDATE($E$5,0) -> 45931 | AX7: =AV7 -> 45931 | AZ7: =AX7 -> 45931 | BD7: =BB7 -> 0 | BF7: =BB7 -> 0
E8: Category | F8: Wholesale | H8: Ecommerce (US) | J8: Ecommerce (EU) | L8: License | N8: Other Income | T8: Wholesale | V8: Ecommerce (US) | X8: Ecommerce (EU) | Z8: License | AB8: Other Income | AH8: Wholesale | AJ8: Ecommerce (US) | AL8: Ecommerce (EU) | AN8: License | AP8: Other Income | AV8: Wholesale | AX8: Ecommerce (US) | AZ8: Ecommerce (EU) | BD8: Other Income
E9: M | F9: =MONTH(F7) -> 10 | T9: =MONTH(T7) -> 10 | AH9: =MONTH(AH7) -> 10 | AV9: =MONTH(AV7) -> 10
E10: Q | F10: ="Q"&ROUNDUP(MONTH(F7)/3,0)&"'"&TEXT(F7,"yy") -> Q4'24 | T10: ="Q"&ROUNDUP(MONTH(T7)/3,0)&"'"&TEXT(T7,"yy") -> Q4'25 | AH10: ="Q"&ROUNDUP(MONTH(AH7)/3,0)&"'"&TEXT(AH7,"yy") -> Q4'25 | AV10: ="Q"&ROUNDUP(MONTH(AV7)/3,0)&"'"&TEXT(AV7,"yy") -> Q4'25
E11: H | F11: ="H"&ROUNDUP(MONTH(F7)/6,0)&"'"&TEXT(F7,"yy") -> H2'24 | T11: ="H"&ROUNDUP(MONTH(T7)/6,0)&"'"&TEXT(T7,"yy") -> H2'25 | AH11: ="H"&ROUNDUP(MONTH(AH7)/6,0)&"'"&TEXT(AH7,"yy") -> H2'25 | AV11: ="H"&ROUNDUP(MONTH(AV7)/6,0)&"'"&TEXT(AV7,"yy") -> H2'25
E12: Y | F12: =YEAR(F7) -> 2024 | T12: =YEAR(T7) -> 2025 | AH12: =YEAR(AH7) -> 2025 | AV12: =YEAR(AV7) -> 2025
E13: Actual / Forecast | F13: Actual | T13: Forecast | AH13: Actual | AV13: Actual
F15: Last Year - Current Month | T15: Budget - Current Month | AH15: Actual - Current Month | AV15: vs Plan
F17: STO 24년 5월 전년 실적 | P17: STO 24년 5월 전년 실적 | T17: ="STO"&" "&RIGHT(YEAR($E$5),2)&"년"&" "&MONTH($E$5)&"월 당월 계획" -> STO 25년 10월 당월 계획 | AD17: ="STO"&" "&RIGHT(YEAR($E$5),2)&"년"&" "&MONTH($E$5)&"월 당월 계획" -> STO 25년 10월 당월 계획 | AH17: STO 25년 5월 당월 실적 | AR17: STO 25년 5월 당월 실적 | AV17: ="STO"&" "&RIGHT(YEAR($E$5),2)&"년"&" "&MONTH($E$5)&"월 계획대비" -> STO 25년 10월 계획대비 | BF17: ="STO"&" "&RIGHT(YEAR($E$5),2)&"년"&" "&MONTH($E$5)&"월 당월 실적" -> STO 25년 10월 당월 실적
F18: 홀세일(미국) | H18: 온라인(미국) | J18: 온라인(유럽) | L18: 라이선스 | N18: 기타 | P18: STO 합계 | T18: 홀세일(미국) | V18: 온라인(미국) | X18: 온라인(유럽) | Z18: 라이선스 | AB18: 기타 | AD18: STO 합계 | AH18: 홀세일(미국) | AJ18: 온라인(미국) | AL18: 온라인(유럽) | AN18: 라이선스 | AP18: 기타 | AR18: STO 합계 | AV18: 홀세일(미국) | AX18: 온라인(미국) | AZ18: 온라인(유럽) | BB18: 라이선스 | BD18: 기타 | BF18: STO 합계
E19: STO/STIP
E20: 라이선스
E21: 홀세일(미국)
E22: 온라인(미국)
E23: 할인율(%)
E24: 생산원가율(%)
E25: 온라인(유럽)
E26: 매출액(할인전) 계
E27: 총매출 (MSRP) | F27: 511352 | H27: 2128892 | J27: 215504 | L27: 55547.9 | N27: 175470.68 | P27: 3086766.6 | T27: 236300 | V27: 2182779 | X27: 121769 | Z27: 51318.55 | AB27: 0 | AD27: 2592166.5 | AH27: 236300 | AJ27: 2182779 | AL27: 121769 | AN27: 51318.55 | AP27: 0 | AR27: 2592166.5 | AV27: =AH27-T27 -> 0 | AX27: =AJ27-V27 -> 0 | AZ27: =AL27-X27 -> 0 | BB27: =AN27-Z27 -> 0 | BD27: =AP27-AB27 -> 0 | BF27: =AR27-AD27 -> 0
E28: 할인액 | F28: 341858.58 | H28: 812261.5 | J28: 39008.41 | L28: 0 | N28: 0 | P28: 1193128.5 | T28: 163297.09 | V28: 693655.72 | X28: 38960.53 | Z28: 0 | AB28: 0 | AD28: 895913.34 | AH28: 163297.09 | AJ28: 693655.72 | AL28: 38960.53 | AN28: 0 | AP28: 0 | AR28: 895913.34 | AV28: =AH28-T28 -> 0 | AX28: =AJ28-V28 -> 0 | AZ28: =AL28-X28 -> 0 | BB28: =AN28-Z28 -> 0 | BD28: =AP28-AB28 -> 0 | BF28: =AR28-AD28 -> 0
C29: Revenue | E29: 실판매 | F29: 169493.42 | G29: 0.66853866 | H29: 1316630.5 | I29: 0.3815419 | J29: 176495.59 | K29: 0.18101014 | L29: 55547.9 | M29: 0 | N29: 175470.68 | O29: 0 | P29: 1893638.1 | Q29: 0.3865302 | T29: 73002.91 | U29: 0.69105836 | V29: 1489123.3 | W29: 0.31778559 | X29: 82808.47 | Y29: 0.31995442 | Z29: 51318.55 | AA29: 0 | AB29: 0 | AC29: 0 | AD29: 1696253.2 | AE29: 0.34562337 | AH29: 73002.91 | AI29: 0.69105836 | AJ29: 1489123.3 | AK29: 0.31778559 | AL29: 82808.47 | AM29: 0.31995442 | AN29: 51318.55 | AO29: 0 | AP29: 0 | AQ29: 0 | AR29: 1696253.2 | AS29: 0.34562337 | AV29: =AH29-T29 -> 0 | AW29: =(AI29-U29)*100 -> 0 | AX29: =AJ29-V29 -> 0 | AY29: =(AK29-W29)*100 -> 0 | AZ29: =AL29-X29 -> 0 | BA29: =(AM29-Y29)*100 -> 0 | BB29: =AN29-Z29 -> 0 | BC29: =(AO29-AA29)*100 -> 0 | BD29: =AP29-AB29 -> 0 | BE29: =(AQ29-AC29)*100 -> 0 | BF29: =AR29-AD29 -> 0 | BG29: =(AS29-AE29)*100 -> 0
E30: 제품매출
E31: 기타매출
E33: 계획대비 | F33: n/a | G33: n/a | H33: n/a | I33: n/a | J33: n/a | K33: n/a | L33: n/a | M33: n/a | N33: n/a | O33: n/a | P33: n/a | Q33: n/a | AH33: 0 | AI33: 0 | AJ33: 0 | AK33: 0 | AL33: 0 | AM33: 0 | AN33: 0 | AO33: 0 | AP33: 0 | AQ33: 0 | AR33: 0 | AS33: 0
E34: 전년대비 | F34: n/a | G34: n/a | H34: n/a | I34: n/a | J34: n/a | K34: n/a | L34: n/a | M34: n/a | N34: n/a | O34: n/a | P34: n/a | Q34: n/a | T34: -96490.51 | U34: -0.56928765 | V34: 172492.78 | W34: 0.13101077 | X34: -93687.12 | Y34: -0.53081848 | Z34: -4229.35 | AA34: -0.076138792 | AB34: -175470.68 | AC34: -1 | AD34: -197384.88 | AE34: -0.1042358 | AH34: -96490.51 | AI34: -0.56928765 | AJ34: 172492.78 | AK34: 0.13101077 | AL34: -93687.12 | AM34: -0.53081848 | AN34: -4229.35 | AO34: -0.076138792 | AP34: -175470.68 | AQ34: -1 | AR34: -197384.88 | AS34: -0.1042358
C36: COGS | E36: 매출원가 | F36: 97577.02 | G36: 0.57569798 | H36: 427348.89 | I36: 0.32457769 | J36: 41236.04 | K36: 0.23363779 | L36: 0 | M36: 0 | N36: 83037.67 | O36: 0.47322818 | P36: 649199.62 | Q36: 0.34283194 | T36: 47356.93 | U36: 0.64869921 | V36: 468645.29 | W36: 0.31471222 | X36: 28184.86 | Y36: 0.34036204 | Z36: 0 | AA36: 0 | AB36: 0 | AC36: 0 | AD36: 544187.08 | AE36: 0.32081713 | AH36: 47356.93 | AI36: 0.64869921 | AJ36: 468645.29 | AK36: 0.31471222 | AL36: 28184.86 | AM36: 0.34036204 | AN36: 0 | AO36: 0 | AP36: 0 | AQ36: 0 | AR36: 544187.08 | AS36: 0.32081713 | AV36: =AH36-T36 -> 0 | AW36: =(AI36-U36)*100 -> 0 | AX36: =AJ36-V36 -> 0 | AY36: =(AK36-W36)*100 -> 0 | AZ36: =AL36-X36 -> 0 | BA36: =(AM36-Y36)*100 -> 0 | BB36: =AN36-Z36 -> 0 | BC36: =(AO36-AA36)*100 -> 0 | BD36: =AP36-AB36 -> 0 | BE36: =(AQ36-AC36)*100 -> 0 | BF36: =AR36-AD36 -> 0 | BG36: =(AS36-AE36)*100 -> 0
E37: 기타원가 | AV37: =AH37-T37 -> 0 | AW37: =(AI37-U37)*100 -> 0 | AX37: =AJ37-V37 -> 0 | AY37: =(AK37-W37)*100 -> 0 | AZ37: =AL37-X37 -> 0 | BA37: =(AM37-Y37)*100 -> 0 | BB37: =AN37-Z37 -> 0 | BC37: =(AO37-AA37)*100 -> 0 | BD37: =AP37-AB37 -> 0 | BE37: =(AQ37-AC37)*100 -> 0 | BF37: =AR37-AD37 -> 0 | BG37: =(AS37-AE37)*100 -> 0
E38: 분기원가조정 | AV38: =AH38-T38 -> 0 | AW38: =(AI38-U38)*100 -> 0 | AX38: =AJ38-V38 -> 0 | AY38: =(AK38-W38)*100 -> 0 | AZ38: =AL38-X38 -> 0 | BA38: =(AM38-Y38)*100 -> 0 | BB38: =AN38-Z38 -> 0 | BC38: =(AO38-AA38)*100 -> 0 | BD38: =AP38-AB38 -> 0 | BE38: =(AQ38-AC38)*100 -> 0 | BF38: =AR38-AD38 -> 0 | BG38: =(AS38-AE38)*100 -> 0
E39: (생산원가율, M/U) | F39: 0.19082163 | G39: 5.2404962 | H39: 0.2007377 | I39: 4.9816252 | J39: 0.19134698 | K39: 5.226108 | L39: 0 | M39: 0 | N39: 0.47322818 | O39: 2.1131455 | P39: 0.21031704 | Q39: 4.7547264 | T39: 0.2004102 | U39: 4.989766 | V39: 0.21470121 | W39: 4.6576356 | X39: 0.2314617 | Y39: 4.3203692 | Z39: 0 | AA39: 0 | AB39: 0 | AC39: 0 | AD39: 0.20993523 | AE39: 4.7633739 | AH39: 0.2004102 | AI39: 4.989766 | AJ39: 0.21470121 | AK39: 4.6576356 | AL39: 0.2314617 | AM39: 4.3203692 | AN39: 0 | AO39: 0 | AP39: 0 | AQ39: 0 | AR39: 0.20993523 | AS39: 4.7633739 | AV39: =(AH39-T39)*100 -> 0 | AW39: =(AI39-U39) -> 0 | AX39: =(AJ39-V39)*100 -> 0 | AY39: =(AK39-W39) -> 0 | AZ39: =(AL39-X39)*100 -> 0 | BA39: =(AM39-Y39) -> 0 | BB39: =AN39-Z39 -> 0 | BC39: =(AO39-AA39) -> 0 | BD39: =AP39-AB39 -> 0 | BE39: =(AQ39-AC39) -> 0 | BF39: =(AR39-AD39)*100 -> 0 | BG39: =(AS39-AE39) -> 0
E40: 매출총이익 | F40: 71916.4 | G40: 0.42430202 | H40: 889281.61 | I40: 0.67542231 | J40: 135259.55 | K40: 0.76636221 | L40: 55547.9 | M40: 1 | N40: 92433.01 | O40: 0.52677182 | P40: 1244438.5 | Q40: 0.65716806 | T40: 25645.98 | U40: 0.35130079 | V40: 1020478 | W40: 0.68528778 | X40: 54623.61 | Y40: 0.65963796 | Z40: 51318.55 | AA40: 1 | AB40: 0 | AC40: 0 | AD40: 1152066.1 | AE40: 0.67918287 | AH40: 25645.98 | AI40: 0.35130079 | AJ40: 1020478 | AK40: 0.68528778 | AL40: 54623.61 | AM40: 0.65963796 | AN40: 51318.55 | AO40: 1 | AP40: 0 | AQ40: 0 | AR40: 1152066.1 | AS40: 0.67918287 | AV40: =AH40-T40 -> 0 | AW40: =(AI40-U40)*100 -> 0 | AX40: =AJ40-V40 -> 0 | AY40: =(AK40-W40)*100 -> 0 | AZ40: =AL40-X40 -> 0 | BA40: =(AM40-Y40)*100 -> 0 | BB40: =AN40-Z40 -> 0 | BC40: =(AO40-AA40)*100 -> 0 | BD40: =AP40-AB40 -> 0 | BE40: =(AQ40-AC40)*100 -> 0 | BF40: =AR40-AD40 -> 0 | BG40: =(AS40-AE40)*100 -> 0
E42: 직접비
E43: 운반비/보관료/ 물류용역비 | F43: 23044.783 | G43: 0.1359627 | H43: 132120.86 | I43: 0.10034772 | J43: 22888.813 | K43: 0.1296849 | L43: 0 | M43: 0 | N43: 0 | O43: 0 | P43: 178054.46 | Q43: 0.094027714 | T43: 9716.56 | U43: 0.13309826 | V43: 146892.34 | W43: 0.098643505 | X43: 17918.6 | Y43: 0.21638608 | Z43: 0 | AA43: 0 | AB43: 0 | AC43: 0 | AD43: 174527.5 | AE43: 0.10289 | AH43: 9716.56 | AI43: 0.13309826 | AJ43: 146892.34 | AK43: 0.098643505 | AL43: 17918.6 | AM43: 0.21638608 | AN43: 0 | AO43: 0 | AP43: 0 | AQ43: 0 | AR43: 174527.5 | AS43: 0.10289 | AV43: =AH43-T43 -> 0 | AW43: =(AI43-U43)*100 -> 0 | AX43: =AJ43-V43 -> 0 | AY43: =(AK43-W43)*100 -> 0 | AZ43: =AL43-X43 -> 0 | BA43: =(AM43-Y43)*100 -> 0 | BB43: =AN43-Z43 -> 0 | BC43: =(AO43-AA43)*100 -> 0 | BD43: =AP43-AB43 -> 0 | BE43: =(AQ43-AC43)*100 -> 0 | BF43: =AR43-AD43 -> 0 | BG43: =(AS43-AE43)*100 -> 0
B44: 운반비 | C44: 운반비 (-) | E44: 운반비 | F44: 2266.333 | G44: 0.013371215 | H44: 71807.144 | I44: 0.054538569 | J44: 16124.933 | K44: 0.091361677 | L44: 0 | M44: 0 | N44: 0 | O44: 0 | P44: 90198.41 | Q44: 0.047632338 | T44: -691.24 | U44: -0.0094686636 | V44: 68860.45 | W44: 0.046242276 | X44: 8760.28 | Y44: 0.10578966 | Z44: 0 | AA44: 0 | AB44: 0 | AC44: 0 | AD44: 76929.49 | AE44: 0.045352598 | AH44: -691.24 | AI44: -0.0094686636 | AJ44: 68860.45 | AK44: 0.046242276 | AL44: 8760.28 | AM44: 0.10578966 | AN44: 0 | AO44: 0 | AP44: 0 | AQ44: 0 | AR44: 76929.49 | AS44: 0.045352598 | AV44: =AH44-T44 -> 0 | AW44: =(AI44-U44)*100 -> 0 | AX44: =AJ44-V44 -> 0 | AY44: =(AK44-W44)*100 -> 0 | AZ44: =AL44-X44 -> 0 | BA44: =(AM44-Y44)*100 -> 0 | BB44: =AN44-Z44 -> 0 | BC44: =(AO44-AA44)*100 -> 0 | BD44: =AP44-AB44 -> 0 | BE44: =(AQ44-AC44)*100 -> 0 | BF44: =AR44-AD44 -> 0 | BG44: =(AS44-AE44)*100 -> 0
B45: 보관료 | E45: 보관료 | F45: 13731.42 | G45: 0.081014472 | H45: 19325.95 | I45: 0.01467834 | J45: 2706.04 | K45: 0.015332054 | L45: 0 | M45: 0 | N45: 0 | O45: 0 | P45: 35763.41 | Q45: 0.018886085 | T45: 5805.25 | U45: 0.079520803 | V45: 27782.54 | W45: 0.018656978 | X45: 1544.96 | Y45: 0.018657029 | Z45: 0 | AA45: 0 | AB45: 0 | AC45: 0 | AD45: 35132.75 | AE45: 0.020711973 | AH45: 5805.25 | AI45: 0.079520803 | AJ45: 27782.54 | AK45: 0.018656978 | AL45: 1544.96 | AM45: 0.018657029 | AN45: 0 | AO45: 0 | AP45: 0 | AQ45: 0 | AR45: 35132.75 | AS45: 0.020711973 | AV45: =AH45-T45 -> 0 | AW45: =(AI45-U45)*100 -> 0 | AX45: =AJ45-V45 -> 0 | AY45: =(AK45-W45)*100 -> 0 | AZ45: =AL45-X45 -> 0 | BA45: =(AM45-Y45)*100 -> 0 | BB45: =AN45-Z45 -> 0 | BC45: =(AO45-AA45)*100 -> 0 | BD45: =AP45-AB45 -> 0 | BE45: =(AQ45-AC45)*100 -> 0 | BF45: =AR45-AD45 -> 0 | BG45: =(AS45-AE45)*100 -> 0
B46: 물류용역비 | E46: 물류용역비 | F46: 7047.03 | G46: 0.041577012 | H46: 40987.77 | I46: 0.031130807 | J46: 4057.84 | K46: 0.022991169 | L46: 0 | M46: 0 | N46: 0 | O46: 0 | P46: 52092.64 | Q46: 0.02750929 | T46: 4602.55 | U46: 0.063046117 | V46: 50249.35 | W46: 0.033744251 | X46: 7613.36 | Y46: 0.091939387 | Z46: 0 | AA46: 0 | AB46: 0 | AC46: 0 | AD46: 62465.26 | AE46: 0.036825434 | AH46: 4602.55 | AI46: 0.063046117 | AJ46: 50249.35 | AK46: 0.033744251 | AL46: 7613.36 | AM46: 0.091939387 | AN46: 0 | AO46: 0 | AP46: 0 | AQ46: 0 | AR46: 62465.26 | AS46: 0.036825434 | AV46: =AH46-T46 -> 0 | AW46: =(AI46-U46)*100 -> 0 | AX46: =AJ46-V46 -> 0 | AY46: =(AK46-W46)*100 -> 0 | AZ46: =AL46-X46 -> 0 | BA46: =(AM46-Y46)*100 -> 1.3877788e-15 | BB46: =AN46-Z46 -> 0 | BC46: =(AO46-AA46)*100 -> 0 | BD46: =AP46-AB46 -> 0 | BE46: =(AQ46-AC46)*100 -> 0 | BF46: =AR46-AD46 -> 0 | BG46: =(AS46-AE46)*100 -> 0
B47: Professional Service | C47: Direct Costs | E47: 지급수수료 | F47: 2074.95 | G47: 0.012242068 | H47: 103162.74 | I47: 0.0783536 | J47: 4146.56 | K47: 0.023493845 | L47: 0 | M47: 0 | N47: 0 | O47: 0 | P47: 109384.25 | Q47: 0.057764074 | T47: 1411.09 | U47: 0.019329229 | V47: 68169.89 | W47: 0.04577854 | X47: 6401.25 | Y47: 0.077301875 | Z47: 0 | AA47: 0 | AB47: 0 | AC47: 0 | AD47: 75982.23 | AE47: 0.044794155 | AH47: 1411.09 | AI47: 0.019329229 | AJ47: 68356.13 | AK47: 0.045903607 | AL47: 6401.25 | AM47: 0.077301875 | AN47: 0 | AO47: 0 | AP47: 0 | AQ47: 0 | AR47: 76168.47 | AS47: 0.04490395 | AV47: =AH47-T47 -> 0 | AW47: =(AI47-U47)*100 -> 0 | AX47: =AJ47-V47 -> 186.24 | AY47: =(AK47-W47)*100 -> 0.012506688 | AZ47: =AL47-X47 -> 0 | BA47: =(AM47-Y47)*100 -> 0 | BB47: =AN47-Z47 -> 0 | BC47: =(AO47-AA47)*100 -> 0 | BD47: =AP47-AB47 -> 0 | BE47: =(AQ47-AC47)*100 -> 0 | BF47: =AR47-AD47 -> 186.24 | BG47: =(AS47-AE47)*100 -> 0.010979493
B48: 6451 - Service Processing Fee | C48: Direct Costs | E48: 결제수수료 | F48: 4382.35 | G48: 0.025855576 | H48: 45385.75 | I48: 0.034471137 | J48: 17003.42 | K48: 0.096339064 | L48: 0 | M48: 0 | N48: 0 | O48: 0 | P48: 66771.52 | Q48: 0.035260972 | T48: 4104.3 | U48: 0.056221047 | V48: 59599.56 | W48: 0.040023254 | X48: 5286.72 | Y48: 0.063842745 | Z48: 0 | AA48: 0 | AB48: 0 | AC48: 0 | AD48: 68990.58 | AE48: 0.040672336 | AH48: 4104.3 | AI48: 0.056221047 | AJ48: 59413.32 | AK48: 0.039898188 | AL48: 5286.72 | AM48: 0.063842745 | AN48: 0 | AO48: 0 | AP48: 0 | AQ48: 0 | AR48: 68804.34 | AS48: 0.040562541 | AV48: =AH48-T48 -> 0 | AW48: =(AI48-U48)*100 -> 0 | AX48: =AJ48-V48 -> -186.24 | AY48: =(AK48-W48)*100 -> -0.012506688 | AZ48: =AL48-X48 -> 0 | BA48: =(AM48-Y48)*100 -> 0 | BB48: =AN48-Z48 -> 0 | BC48: =(AO48-AA48)*100 -> 0 | BD48: =AP48-AB48 -> 0 | BE48: =(AQ48-AC48)*100 -> 0 | BF48: =AR48-AD48 -> -186.24 | BG48: =(AS48-AE48)*100 -> -0.010979493
B49: Marketing | C49: Direct Costs | E49: SEM 광고비 | F49: 0 | G49: 0 | H49: 287876.72 | I49: 0.21864655 | J49: 38590.152 | K49: 0.21864655 | L49: 0 | M49: 0 | N49: 0 | O49: 0 | P49: 326466.87 | Q49: 0.17240193 | T49: 0 | U49: 0 | V49: 241021.83 | W49: 0.16185485 | X49: 31765.29 | Y49: 0.38359953 | Z49: 0 | AA49: 0 | AB49: 0 | AC49: 0 | AD49: 272787.12 | AE49: 0.16081745 | AH49: 0 | AI49: 0 | AJ49: 241021.83 | AK49: 0.16185485 | AL49: 31765.29 | AM49: 0.38359953 | AN49: 0 | AO49: 0 | AP49: 0 | AQ49: 0 | AR49: 272787.12 | AS49: 0.16081745 | AV49: =AH49-T49 -> 0 | AW49: =(AI49-U49)*100 -> 0 | AX49: =AJ49-V49 -> 0 | AY49: =(AK49-W49)*100 -> 0 | AZ49: =AL49-X49 -> 0 | BA49: =(AM49-Y49)*100 -> 0 | BB49: =AN49-Z49 -> 0 | BC49: =(AO49-AA49)*100 -> 0 | BD49: =AP49-AB49 -> 0 | BE49: =(AQ49-AC49)*100 -> 0 | BF49: =AR49-AD49 -> 0 | BG49: =(AS49-AE49)*100 -> 0
B50: Other | C50: Direct Costs | E50: 기타비용 | F50: 0 | G50: 0 | H50: 0 | I50: 0 | J50: 0 | K50: 0 | L50: 0 | M50: 0 | N50: 0 | O50: 0 | P50: 0 | Q50: 0 | T50: 0 | U50: 0 | V50: 0 | W50: 0 | X50: 0 | Y50: 0 | Z50: 0 | AA50: 0 | AB50: 0 | AC50: 0 | AD50: 0 | AE50: 0 | AH50: 0 | AI50: 0 | AJ50: 0 | AK50: 0 | AL50: 0 | AM50: 0 | AN50: 0 | AO50: 0 | AP50: 0 | AQ50: 0 | AR50: 0 | AS50: 0 | AV50: =AH50-T50 -> 0 | AW50: =(AI50-U50)*100 -> 0 | AX50: =AJ50-V50 -> 0 | AY50: =(AK50-W50)*100 -> 0 | AZ50: =AL50-X50 -> 0 | BA50: =(AM50-Y50)*100 -> 0 | BB50: =AN50-Z50 -> 0 | BC50: =(AO50-AA50)*100 -> 0 | BD50: =AP50-AB50 -> 0 | BE50: =(AQ50-AC50)*100 -> 0 | BF50: =AR50-AD50 -> 0 | BG50: =(AS50-AE50)*100 -> 0
E51: 직접비 소계 | F51: 29502.083 | G51: 0.17406034 | H51: 568546.07 | I51: 0.431819 | J51: 82628.945 | K51: 0.46816436 | L51: 0 | M51: 0 | N51: 0 | O51: 0 | P51: 680677.1 | Q51: 0.35945469 | T51: 15231.95 | U51: 0.20864853 | V51: 515683.62 | W51: 0.34630015 | X51: 61371.86 | Y51: 0.74113022 | Z51: 0 | AA51: 0 | AB51: 0 | AC51: 0 | AD51: 592287.43 | AE51: 0.34917395 | AH51: 15231.95 | AI51: 0.20864853 | AJ51: 515683.62 | AK51: 0.34630015 | AL51: 61371.86 | AM51: 0.74113022 | AN51: 0 | AO51: 0 | AP51: 0 | AQ51: 0 | AR51: 592287.43 | AS51: 0.34917395 | AV51: =AH51-T51 -> 0 | AW51: =(AI51-U51)*100 -> 0 | AX51: =AJ51-V51 -> 0 | AY51: =(AK51-W51)*100 -> 0 | AZ51: =AL51-X51 -> 0 | BA51: =(AM51-Y51)*100 -> 0 | BB51: =AN51-Z51 -> 0 | BC51: =(AO51-AA51)*100 -> 0 | BD51: =AP51-AB51 -> 0 | BE51: =(AQ51-AC51)*100 -> 0 | BF51: =AR51-AD51 -> 0 | BG51: =(AS51-AE51)*100 -> 0
E53: 직접이익 | F53: 42414.317 | G53: 0.25024167 | H53: 320735.54 | I53: 0.2436033 | J53: 52630.605 | K53: 0.29819785 | L53: 55547.9 | M53: 1 | N53: 92433.01 | O53: 0.52677182 | P53: 563761.37 | Q53: 0.29771337 | T53: 10414.03 | U53: 0.14265226 | V53: 504794.37 | W53: 0.33898763 | X53: -6748.25 | Y53: -0.081492268 | Z53: 51318.55 | AA53: 1 | AB53: 0 | AC53: 0 | AD53: 559778.7 | AE53: 0.33000893 | AH53: 10414.03 | AI53: 0.14265226 | AJ53: 504794.37 | AK53: 0.33898763 | AL53: -6748.25 | AM53: -0.081492268 | AN53: 51318.55 | AO53: 1 | AP53: 0 | AQ53: 0 | AR53: 559778.7 | AS53: 0.33000893 | AV53: =AH53-T53 -> 0 | AW53: =(AI53-U53)*100 -> 0 | AX53: =AJ53-V53 -> 0 | AY53: =(AK53-W53)*100 -> 0 | AZ53: =AL53-X53 -> 0 | BA53: =(AM53-Y53)*100 -> 0 | BB53: =AN53-Z53 -> 0 | BC53: =(AO53-AA53)*100 -> 0 | BD53: =AP53-AB53 -> 0 | BE53: =(AQ53-AC53)*100 -> 0 | BF53: =AR53-AD53 -> 0 | BG53: =(AS53-AE53)*100 -> 0
AI54: =+AI53-G53 -> -0.10758941 | AK54: =+AK53-I53 -> 0.095384326 | AM54: =+AM53-K53 -> -0.37969011
E55: 영업비
E56: 인건비 | P56: 342492.76 | Q56: 0.18086495 | AD56: 214189.44 | AE56: 0.12627209 | AR56: 214189.44 | AS56: 0.12627209 | BF56: =AR56-AD56 -> 0 | BG56: =(AS56-AE56)*100 -> 0
B57: HQ | C57: HQ Salaries | E57: 급여(정규) | P57: 236261.06 | Q57: 0.12476569 | AD57: 265326.61 | AE57: 0.15641922 | AR57: 265326.61 | AS57: 0.15641922 | BF57: =AR57-AD57 -> 0 | BG57: =(AS57-AE57)*100 -> 0
B58: Contractors | C58: HQ Salaries | E58: 급여(계약) | P58: 34947.3 | Q58: 0.01845511 | AD58: 39879.53 | AE58: 0.023510364 | AR58: 39879.53 | AS58: 0.023510364 | BF58: =AR58-AD58 -> 0 | BG58: =(AS58-AE58)*100 -> 0
B59: Benefits | C59: HQ Salaries | E59: 보험,복후비등 | P59: 48346.9 | Q59: 0.025531225 | AD59: 89299.8 | AE59: 0.052645324 | AR59: 89299.8 | AS59: 0.052645324 | BF59: =AR59-AD59 -> 0 | BG59: =(AS59-AE59)*100 -> 0
B60: Bonus | C60: HQ Salaries | E60: 급여충당금 | P60: 22937.5 | Q60: 0.012112927 | AD60: -180316.5 | AE60: -0.10630282 | AR60: -180316.5 | AS60: -0.10630282 | BF60: =AR60-AD60 -> 0 | BG60: =(AS60-AE60)*100 -> 0
B61: Advertising | C61: SG&A | E61: 광고선전비 | P61: 69395.24 | Q61: 0.036646517 | AD61: 60412.22 | AE61: 0.035615095 | AR61: 60412.22 | AS61: 0.035615095 | BF61: =AR61-AD61 -> 0 | BG61: =(AS61-AE61)*100 -> 0
E62: Photography | P62: 49260 | Q62: 0.026013418 | AE62: 0 | AS62: 0 | BF62: =AR62-AD62 -> 0 | BG62: =(AS62-AE62)*100 -> 0
E63: Selling | P63: 0 | Q63: 0 | AE63: 0 | AS63: 0 | BF63: =AR63-AD63 -> 0 | BG63: =(AS63-AE63)*100 -> 0
E64: Advertising | P64: 0 | Q64: 0 | AE64: 0 | AS64: 0 | BF64: =AR64-AD64 -> 0 | BG64: =(AS64-AE64)*100 -> 0
E65: SEM브랜드마케팅 | P65: 0 | Q65: 0 | AE65: 0 | AS65: 0 | BF65: =AR65-AD65 -> 0 | BG65: =(AS65-AE65)*100 -> 0
E66: Events | P66: 0 | Q66: 0 | AE66: 0 | AS66: 0 | BF66: =AR66-AD66 -> 0 | BG66: =(AS66-AE66)*100 -> 0
E67: Model | P67: 2400 | Q67: 0.0012674016 | AE67: 0 | AS67: 0 | BF67: =AR67-AD67 -> 0 | BG67: =(AS67-AE67)*100 -> 0
E68: Seeding | P68: 1468.04 | Q68: 0.00077524845 | AE68: 0 | AS68: 0 | BF68: =AR68-AD68 -> 0 | BG68: =(AS68-AE68)*100 -> 0
E69: 기타 광고비 | P69: 16267.2 | Q69: 0.0085904482 | AE69: 0 | AS69: 0 | BF69: =AR69-AD69 -> 0 | BG69: =(AS69-AE69)*100 -> 0
B70: Professional Service | C70: SG&A | E70: 지급수수료 | P70: 53595.3 | Q70: 0.028302821 | AD70: 218381.12 | AE70: 0.12874323 | AR70: 218381.12 | AS70: 0.12874323 | BF70: =AR70-AD70 -> 0 | BG70: =(AS70-AE70)*100 -> 0
B71: T&E | C71: SG&A | E71: 식대 / 출장비 | P71: 8876.4 | Q71: 0.0046874849 | AD71: 11759.87 | AE71: 0.0069328506 | AR71: 11759.87 | AS71: 0.0069328506 | BF71: =AR71-AD71 -> 0 | BG71: =(AS71-AE71)*100 -> -1.7347235e-16
B72: Rent | C72: SG&A | E72: 임차료 | P72: 33921.8 | Q72: 0.01791356 | AD72: 24658.39 | AE72: 0.014536975 | AR72: 24658.39 | AS72: 0.014536975 | BF72: =AR72-AD72 -> 0 | BG72: =(AS72-AE72)*100 -> 1.7347235e-16
B73: Sample | C73: SG&A | E73: 샘플비/개발비 | P73: 21269.01 | Q73: 0.011231824 | AD73: 2318.47 | AE73: 0.0013668183 | AR73: 2318.47 | AS73: 0.0013668183 | BF73: =AR73-AD73 -> 0 | BG73: =(AS73-AE73)*100 -> 2.1684043e-17
B74: Depreciation & Amortization | C74: SG&A | E74: 감가상각비 | P74: 3899.15 | Q74: 0.0020590788 | AD74: 3896.96 | AE74: 0.0022973929 | AR74: 3896.96 | AS74: 0.0022973929 | BF74: =AR74-AD74 -> 0 | BG74: =(AS74-AE74)*100 -> 0
B75: Other | C75: SG&A | E75: 기타비용 | P75: 38823.76 | Q75: 0.020502207 | AD75: 11079.79 | AE75: 0.0065319198 | AR75: 11079.79 | AS75: 0.0065319198 | BF75: =AR75-AD75 -> 0 | BG75: =(AS75-AE75)*100 -> 0
E76: 영업비 소계 | P76: 572273.42 | Q76: 0.30220844 | T76: 0 | U76: 0 | V76: 0 | W76: 0 | X76: 0 | Y76: 0 | Z76: 0 | AA76: 0 | AD76: 546696.26 | AE76: 0.32229637 | AH76: 0 | AI76: 0 | AJ76: 0 | AK76: 0 | AL76: 0 | AM76: 0 | AN76: 0 | AO76: 0 | AR76: 546696.26 | AS76: 0.32229637 | AV76: =SUM(AV57:AV75) -> 0 | AW76: =SUM(AW57:AW75) -> 0 | AX76: =SUM(AX57:AX75) -> 0 | AY76: =SUM(AY57:AY75) -> 0 | AZ76: =SUM(AZ57:AZ75) -> 0 | BA76: =SUM(BA57:BA75) -> 0 | BB76: =SUM(BB57:BB75) -> 0 | BC76: =SUM(BC57:BC75) -> 0 | BF76: =AR76-AD76 -> 0 | BG76: =(AS76-AE76)*100 -> 0
E78: 영업이익 | P78: -8512.05 | Q78: -0.0044950775 | AD78: 13082.44 | AE78: 0.0077125514 | AR78: 13082.44 | AS78: 0.0077125514 | BF78: =AR78-AD78 -> 0 | BG78: =(AS78-AE78)*100 -> 0
E80: 영업외손익
E82: 이자비용
E83: 경상이익

Sheet 6월
E5: 45931
E7: Date | F7: =EDATE($E$5,-12) -> 45566 | H7: =F7 -> 45566 | J7: =H7 -> 45566 | L7: =J7 -> 45566 | N7: =L7 -> 45566 | P7: =L7 -> 45566 | T7: =EDATE($E$5,0) -> 45931 | V7: =T7 -> 45931 | X7: =V7 -> 45931 | Z7: =X7 -> 45931 | AB7: =Z7 -> 45931 | AD7: =Z7 -> 45931 | AH7: =EDATE($E$5,0) -> 45931 | AJ7: =AH7 -> 45931 | AL7: =AJ7 -> 45931 | AN7: =AL7 -> 45931 | AP7: =AN7 -> 45931 | AR7: =AN7 -> 45931 | AV7: =EDATE($E$5,0) -> 45931 | AX7: =AV7 -> 45931 | AZ7: =AX7 -> 45931 | BD7: =BB7 -> 0 | BF7: =BB7 -> 0
E8: Category | F8: Wholesale | H8: Ecommerce (US) | J8: Ecommerce (EU) | L8: License | N8: Other Income | T8: Wholesale | V8: Ecommerce (US) | X8: Ecommerce (EU) | Z8: License | AB8: Other Income | AH8: Wholesale | AJ8: Ecommerce (US) | AL8: Ecommerce (EU) | AN8: License | AP8: Other Income | AV8: Wholesale | AX8: Ecommerce (US) | AZ8: Ecommerce (EU) | BD8: Other Income
E9: M | F9: =MONTH(F7) -> 10 | T9: =MONTH(T7) -> 10 | AH9: =MONTH(AH7) -> 10 | AV9: =MONTH(AV7) -> 10
E10: Q | F10: ="Q"&ROUNDUP(MONTH(F7)/3,0)&"'"&TEXT(F7,"yy") -> Q4'24 | T10: ="Q"&ROUNDUP(MONTH(T7)/3,0)&"'"&TEXT(T7,"yy") -> Q4'25 | AH10: ="Q"&ROUNDUP(MONTH(AH7)/3,0)&"'"&TEXT(AH7,"yy") -> Q4'25 | AV10: ="Q"&ROUNDUP(MONTH(AV7)/3,0)&"'"&TEXT(AV7,"yy") -> Q4'25
E11: H | F11: ="H"&ROUNDUP(MONTH(F7)/6,0)&"'"&TEXT(F7,"yy") -> H2'24 | T11: ="H"&ROUNDUP(MONTH(T7)/6,0)&"'"&TEXT(T7,"yy") -> H2'25 | AH11: ="H"&ROUNDUP(MONTH(AH7)/6,0)&"'"&TEXT(AH7,"yy") -> H2'25 | AV11: ="H"&ROUNDUP(MONTH(AV7)/6,0)&"'"&TEXT(AV7,"yy") -> H2'25
