Workbook
Name _?: #REF!
Name _?춑_TOTAL: #REF!
Name _?춮t2: #REF!
Name _?춮ta: #REF!
Name _?춮tb: #REF!
Name __: #REF!
Name __?: #REF!
Name __?춑_TOTAL: #REF!
Name __?춮t2: #REF!
Name __?춮ta: #REF!
Name __?춮tb: #REF!
Name ___: #REF!
Name ___?: #REF!
Name ___?춑_TOTAL: #REF!
Name ____: #REF!
Name ____?: #REF!
Name ____?춑_TOTAL: #REF!
Name ____?춮t2: #REF!
Name ____?춮ta: #REF!
Name ____?춮tb: #REF!
Name _____: #REF!
Name _____?: #REF!
Name _____?춑_TOTAL: #REF!
Name ______: #REF!
Name ______?: #REF!
Name ______?춑_TOTAL: #REF!
Name _______: #REF!
Name _______?: #REF!
Name _______?춑_TOTAL: #REF!
Name ________: #REF!
Name ________?: #REF!
Name ________?춑_TOTAL: #REF!
Name _________: #REF!
Name _________?: #REF!
Name _________?춑_TOTAL: #REF!
Name __________: #REF!
Name __________?: #REF!
Name __________?춑_TOTAL: #REF!
Name ___________: #REF!
Name ___________?: #REF!
Name ___________?춑_TOTAL: #REF!
Name ____________?: #REF!
Name ____________?춑_TOTAL: #REF!
Name _____________?: #REF!
Name ____________________C332897: #REF!
Name ____________________E65954: #REF!
Name ___________________C332897: #REF!
Name ___________________E65954: #REF!
Name __________________C332897: #REF!
Name __________________E65954: #REF!
Name _________________C332897: #REF!
Name _________________E65954: #REF!
Name ________________C332897: #REF!
Name ________________E65954: #REF!
Name _______________C332897: #REF!
Name _______________E65954: #REF!
Name ______________C332897: #REF!
Name ______________E65954: #REF!
Name _____________Ａ４: #REF!
Name _____________C1244ㅁ1430: #REF!

Sheet G&A Vendor x GL Analysis
E7: =[1]TOC!$B$6 -> 45962
F8: <- Department
E10: YTD | G10: =IF(MONTH(G$20)<=MONTH($E$7),1,0) -> 1 | H10: =IF(MONTH(H$20)<=MONTH($E$7),1,0) -> 1 | I10: =IF(MONTH(I$20)<=MONTH($E$7),1,0) -> 1 | J10: =IF(MONTH(J$20)<=MONTH($E$7),1,0) -> 1 | K10: =IF(MONTH(K$20)<=MONTH($E$7),1,0) -> 1 | L10: =IF(MONTH(L$20)<=MONTH($E$7),1,0) -> 1 | M10: =IF(MONTH(M$20)<=MONTH($E$7),1,0) -> 1 | N10: =IF(MONTH(N$20)<=MONTH($E$7),1,0) -> 1 | ... AD10: =IF(MONTH(AD$20)<=MONTH($E$7),1,0) -> 0
E11: M | G11: =MONTH(G20) -> 1 | H11: =MONTH(H20) -> 2 | I11: =MONTH(I20) -> 3 | J11: =MONTH(J20) -> 4 | K11: =MONTH(K20) -> 5 | L11: =MONTH(L20) -> 6 | M11: =MONTH(M20) -> 7 | N11: =MONTH(N20) -> 8 | ... AD11: =MONTH(AD20) -> 12
E12: Q | G12: ="Q"&ROUNDUP(MONTH(G20)/3,0)&"'"&TEXT(G20,"yy") -> Q1'24 | H12: ="Q"&ROUNDUP(MONTH(H20)/3,0)&"'"&TEXT(H20,"yy") -> Q1'24 | I12: ="Q"&ROUNDUP(MONTH(I20)/3,0)&"'"&TEXT(I20,"yy") -> Q1'24 | J12: ="Q"&ROUNDUP(MONTH(J20)/3,0)&"'"&TEXT(J20,"yy") -> Q2'24 | K12: ="Q"&ROUNDUP(MONTH(K20)/3,0)&"'"&TEXT(K20,"yy") -> Q2'24 | L12: ="Q"&ROUNDUP(MONTH(L20)/3,0)&"'"&TEXT(L20,"yy") -> Q2'24 | M12: ="Q"&ROUNDUP(MONTH(M20)/3,0)&"'"&TEXT(M20,"yy") -> Q3'24 | N12: ="Q"&ROUNDUP(MONTH(N20)/3,0)&"'"&TEXT(N20,"yy") -> Q3'24 | ... AD12: ="Q"&ROUNDUP(MONTH(AD20)/3,0)&"'"&TEXT(AD20,"yy") -> Q4'25
E13: H | G13: ="H"&ROUNDUP(MONTH(G20)/6,0)&"'"&TEXT(G20,"yy") -> H1'24 | H13: ="H"&ROUNDUP(MONTH(H20)/6,0)&"'"&TEXT(H20,"yy") -> H1'24 | I13: ="H"&ROUNDUP(MONTH(I20)/6,0)&"'"&TEXT(I20,"yy") -> H1'24 | J13: ="H"&ROUNDUP(MONTH(J20)/6,0)&"'"&TEXT(J20,"yy") -> H1'24 | K13: ="H"&ROUNDUP(MONTH(K20)/6,0)&"'"&TEXT(K20,"yy") -> H1'24 | L13: ="H"&ROUNDUP(MONTH(L20)/6,0)&"'"&TEXT(L20,"yy") -> H1'24 | M13: ="H"&ROUNDUP(MONTH(M20)/6,0)&"'"&TEXT(M20,"yy") -> H2'24 | N13: ="H"&ROUNDUP(MONTH(N20)/6,0)&"'"&TEXT(N20,"yy") -> H2'24 | ... AD13: ="H"&ROUNDUP(MONTH(AD20)/6,0)&"'"&TEXT(AD20,"yy") -> H2'25
E14: Y | G14: =YEAR(G20) -> 2024 | H14: =YEAR(H20) -> 2024 | I14: =YEAR(I20) -> 2024 | J14: =YEAR(J20) -> 2024 | K14: =YEAR(K20) -> 2024 | L14: =YEAR(L20) -> 2024 | M14: =YEAR(M20) -> 2024 | N14: =YEAR(N20) -> 2024 | ... AD14: =YEAR(AD20) -> 2025
E15: Actual / Forecast | G15: =IF(G$20<=$E$7,"Actual","Forecast") -> Actual | H15: =IF(H$20<=$E$7,"Actual","Forecast") -> Actual | I15: =IF(I$20<=$E$7,"Actual","Forecast") -> Actual | J15: =IF(J$20<=$E$7,"Actual","Forecast") -> Actual | K15: =IF(K$20<=$E$7,"Actual","Forecast") -> Actual | L15: =IF(L$20<=$E$7,"Actual","Forecast") -> Actual | M15: =IF(M$20<=$E$7,"Actual","Forecast") -> Actual | N15: =IF(N$20<=$E$7,"Actual","Forecast") -> Actual | ... AD15: =IF(AD$20<=$E$7,"Actual","Forecast") -> Forecast
E20: G&A | G20: 45292 | H20: =EDATE(G20,1) -> 45323 | I20: =EDATE(H20,1) -> 45352 | J20: =EDATE(I20,1) -> 45383 | K20: =EDATE(J20,1) -> 45413 | L20: =EDATE(K20,1) -> 45444 | M20: =EDATE(L20,1) -> 45474 | N20: =EDATE(M20,1) -> 45505 | O20: =EDATE(N20,1) -> 45536 | ... AD20: =EDATE(AC20,1) -> 45992 | AF20: FILTER
B21: x | E21: Advertising | G21: =SUMIFS(G:G,$D:$D,$E21) -> -96638.55 | H21: =SUMIFS(H:H,$D:$D,$E21) -> 9776.85 | I21: =SUMIFS(I:I,$D:$D,$E21) -> 238450.15 | J21: =SUMIFS(J:J,$D:$D,$E21) -> 189462.1 | K21: =SUMIFS(K:K,$D:$D,$E21) -> 220267.4 | L21: =SUMIFS(L:L,$D:$D,$E21) -> 232231.25 | M21: =SUMIFS(M:M,$D:$D,$E21) -> 281819.3 | N21: =SUMIFS(N:N,$D:$D,$E21) -> 282008.1 | O21: =SUMIFS(O:O,$D:$D,$E21) -> 90004.01 | P21: =SUMIFS(P:P,$D:$D,$E21) -> 159433.86 | Q21: =SUMIFS(Q:Q,$D:$D,$E21) -> 129923.11 | R21: =SUMIFS(R:R,$D:$D,$E21) -> 265932.56 | S21: =SUMIFS(S:S,$D:$D,$E21) -> 118210.21 | T21: =SUMIFS(T:T,$D:$D,$E21) -> 70499.5 | U21: =SUMIFS(U:U,$D:$D,$E21) -> 122283.39 | V21: =SUMIFS(V:V,$D:$D,$E21) -> 53581.1 | W21: =SUMIFS(W:W,$D:$D,$E21) -> 60412.22 | X21: =SUMIFS(X:X,$D:$D,$E21) -> 87353.46 | Y21: =SUMIFS(Y:Y,$D:$D,$E21) -> 78331.04 | Z21: =SUMIFS(Z:Z,$D:$D,$E21) -> 87554.58 | AA21: =SUMIFS(AA:AA,$D:$D,$E21) -> 77015 | AB21: =SUMIFS(AB:AB,$D:$D,$E21) -> 36940.36 | AC21: =SUMIFS(AC:AC,$D:$D,$E21) -> 97683.71 | AD21: =SUMIFS(AD:AD,$D:$D,$E21) -> 0 | AF21: =ABS(S21)+ABS(T21)+ABS(U21)+ABS(V21)+ABS(W21)+ABS(X21)+ABS(Y21)+ABS(Z21)+ABS(AA21)+ABS(AB21)+ABS(AC21)+ABS(AD21) -> 889864.57
A22: =D22&E22 -> Advertising6240 - Product Photography | C22: SG&A | D22: =E21 -> Advertising | E22: 6240 - Product Photography | F22: Theerapol Thammasitboon | G22: =IF(AND(G$15="Actual",ISBLANK($E$8)),SUMIFS('[1]NS Vendor Details'!$D:$D,'[1]NS Vendor Details'!$H:$H,'G&A Vendor x GL Analysis'!G$20,'[1]NS Vendor Details'!$L:$L,'G&A Vendor x GL Analysis'!$D22,'[1]NS Vendor Details'!$O:$O,'G&A Vendor x GL Analysis'!$F22,'[1]NS Vendor Details'!$N:$N,'G&A Vendor x GL Analysis'!$C22),IF(G$15="Actual",SUMIFS('[1]NS Vendor Details'!$D:$D,'[1]NS Vendor Details'!$H:$H,'G&A Vendor x GL Analysis'!G$20,'[1]NS Vendor Details'!$L:$L,'G&A Vendor x GL Analysis'!$D22,'[1]NS Vendor Details'!$O:$O,'G&A Vendor x GL Analysis'!$F22,'[1]NS Vendor Details'!$N:$N,'G&A Vendor x GL Analysis'!$C22,'[1]NS Vendor Details'!$K:$K,'G&A Vendor x GL Analysis'!$E$8),0)) -> 0 | H22: =IF(AND(H$15="Actual",ISBLANK($E$8)),SUMIFS('[1]NS Vendor Details'!$D:$D,'[1]NS Vendor Details'!$H:$H,'G&A Vendor x GL Analysis'!H$20,'[1]NS Vendor Details'!$L:$L,'G&A Vendor x GL Analysis'!$D22,'[1]NS Vendor Details'!$O:$O,'G&A Vendor x GL Analysis'!$F22,'[1]NS Vendor Details'!$N:$N,'G&A Vendor x GL Analysis'!$C22),IF(H$15="Actual",SUMIFS('[1]NS Vendor Details'!$D:$D,'[1]NS Vendor Details'!$H:$H,'G&A Vendor x GL Analysis'!H$20,'[1]NS Vendor Details'!$L:$L,'G&A Vendor x GL Analysis'!$D22,'[1]NS Vendor Details'!$O:$O,'G&A Vendor x GL Analysis'!$F22,'[1]NS Vendor Details'!$N:$N,'G&A Vendor x GL Analysis'!$C22,'[1]NS Vendor Details'!$K:$K,'G&A Vendor x GL Analysis'!$E$8),0)) -> 5298 | I22: =IF(AND(I$15="Actual",ISBLANK($E$8)),SUMIFS('[1]NS Vendor Details'!$D:$D,'[1]NS Vendor Details'!$H:$H,'G&A Vendor x GL Analysis'!I$20,'[1]NS Vendor Details'!$L:$L,'G&A Vendor x GL Analysis'!$D22,'[1]NS Vendor Details'!$O:$O,'G&A Vendor x GL Analysis'!$F22,'[1]NS Vendor Details'!$N:$N,'G&A Vendor x GL Analysis'!$C22),IF(I$15="Actual",SUMIFS('[1]NS Vendor Details'!$D:$D,'[1]NS Vendor Details'!$H:$H,'G&A Vendor x GL Analysis'!I$20,'[1]NS Vendor Details'!$L:$L,'G&A Vendor x GL Analysis'!$D22,'[1]NS Vendor Details'!$O:$O,'G&A Vendor x GL Analysis'!$F22,'[1]NS Vendor Details'!$N:$N,'G&A Vendor x GL Analysis'!$C22,'[1]NS Vendor Details'!$K:$K,'G&A Vendor x GL Analysis'!$E$8),0)) -> 0 | J22: =IF(AND(J$15="Actual",ISBLANK($E$8)),SUMIFS('[1]NS Vendor Details'!$D:$D,'[1]NS Vendor Details'!$H:$H,'G&A Vendor x GL Analysis'!J$20,'[1]NS Vendor Details'!$L:$L,'G&A Vendor x GL Analysis'!$D22,'[1]NS Vendor Details'!$O:$O,'G&A Vendor x GL Analysis'!$F22,'[1]NS Vendor Details'!$N:$N,'G&A Vendor x GL Analysis'!$C22),IF(J$15="Actual",SUMIFS('[1]NS Vendor Details'!$D:$D,'[1]NS Vendor Details'!$H:$H,'G&A Vendor x GL Analysis'!J$20,'[1]NS Vendor Details'!$L:$L,'G&A Vendor x GL Analysis'!$D22,'[1]NS Vendor Details'!$O:$O,'G&A Vendor x GL Analysis'!$F22,'[1]NS Vendor Details'!$N:$N,'G&A Vendor x GL Analysis'!$C22,'[1]NS Vendor Details'!$K:$K,'G&A Vendor x GL Analysis'!$E$8),0)) -> 0 | K22: =IF(AND(K$15="Actual",ISBLANK($E$8)),SUMIFS('[1]NS Vendor Details'!$D:$D,'[1]NS Vendor Details'!$H:$H,'G&A Vendor x GL Analysis'!K$20,'[1]NS Vendor Details'!$L:$L,'G&A Vendor x GL Analysis'!$D22,'[1]NS Vendor Details'!$O:$O,'G&A Vendor x GL Analysis'!$F22,'[1]NS Vendor Details'!$N:$N,'G&A Vendor x GL Analysis'!$C22),IF(K$15="Actual",SUMIFS('[1]NS Vendor Details'!$D:$D,'[1]NS Vendor Details'!$H:$H,'G&A Vendor x GL Analysis'!K$20,'[1]NS Vendor Details'!$L:$L,'G&A Vendor x GL Analysis'!$D22,'[1]NS Vendor Details'!$O:$O,'G&A Vendor x GL Analysis'!$F22,'[1]NS Vendor Details'!$N:$N,'G&A Vendor x GL Analysis'!$C22,'[1]NS Vendor Details'!$K:$K,'G&A Vendor x GL Analysis'!$E$8),0)) -> 0 | L22: =IF(AND(L$15="Actual",ISBLANK($E$8)),SUMIFS('[1]NS Vendor Details'!$D:$D,'[1]NS Vendor Details'!$H:$H,'G&A Vendor x GL Analysis'!L$20,'[1]NS Vendor Details'!$L:$L,'G&A Vendor x GL Analysis'!$D22,'[1]NS Vendor Details'!$O:$O,'G&A Vendor x GL Analysis'!$F22,'[1]NS Vendor Details'!$N:$N,'G&A Vendor x GL Analysis'!$C22),IF(L$15="Actual",SUMIFS('[1]NS Vendor Details'!$D:$D,'[1]NS Vendor Details'!$H:$H,'G&A Vendor x GL Analysis'!L$20,'[1]NS Vendor Details'!$L:$L,'G&A Vendor x GL Analysis'!$D22,'[1]NS Vendor Details'!$O:$O,'G&A Vendor x GL Analysis'!$F22,'[1]NS Vendor Details'!$N:$N,'G&A Vendor x GL Analysis'!$C22,'[1]NS Vendor Details'!$K:$K,'G&A Vendor x GL Analysis'!$E$8),0)) -> 9450 | M22: =IF(AND(M$15="Actual",ISBLANK($E$8)),SUMIFS('[1]NS Vendor Details'!$D:$D,'[1]NS Vendor Details'!$H:$H,'G&A Vendor x GL Analysis'!M$20,'[1]NS Vendor Details'!$L:$L,'G&A Vendor x GL Analysis'!$D22,'[1]NS Vendor Details'!$O:$O,'G&A Vendor x GL Analysis'!$F22,'[1]NS Vendor Details'!$N:$N,'G&A Vendor x GL Analysis'!$C22),IF(M$15="Actual",SUMIFS('[1]NS Vendor Details'!$D:$D,'[1]NS Vendor Details'!$H:$H,'G&A Vendor x GL Analysis'!M$20,'[1]NS Vendor Details'!$L:$L,'G&A Vendor x GL Analysis'!$D22,'[1]NS Vendor Details'!$O:$O,'G&A Vendor x GL Analysis'!$F22,'[1]NS Vendor Details'!$N:$N,'G&A Vendor x GL Analysis'!$C22,'[1]NS Vendor Details'!$K:$K,'G&A Vendor x GL Analysis'!$E$8),0)) -> 13645.5 | N22: =IF(AND(N$15="Actual",ISBLANK($E$8)),SUMIFS('[1]NS Vendor Details'!$D:$D,'[1]NS Vendor Details'!$H:$H,'G&A Vendor x GL Analysis'!N$20,'[1]NS Vendor Details'!$L:$L,'G&A Vendor x GL Analysis'!$D22,'[1]NS Vendor Details'!$O:$O,'G&A Vendor x GL Analysis'!$F22,'[1]NS Vendor Details'!$N:$N,'G&A Vendor x GL Analysis'!$C22),IF(N$15="Actual",SUMIFS('[1]NS Vendor Details'!$D:$D,'[1]NS Vendor Details'!$H:$H,'G&A Vendor x GL Analysis'!N$20,'[1]NS Vendor Details'!$L:$L,'G&A Vendor x GL Analysis'!$D22,'[1]NS Vendor Details'!$O:$O,'G&A Vendor x GL Analysis'!$F22,'[1]NS Vendor Details'!$N:$N,'G&A Vendor x GL Analysis'!$C22,'[1]NS Vendor Details'!$K:$K,'G&A Vendor x GL Analysis'!$E$8),0)) -> 4875.5 | ... R22: =IF(AND(R$15="Actual",ISBLANK($E$8)),SUMIFS('[1]NS Vendor Details'!$D:$D,'[1]NS Vendor Details'!$H:$H,'G&A Vendor x GL Analysis'!R$20,'[1]NS Vendor Details'!$L:$L,'G&A Vendor x GL Analysis'!$D22,'[1]NS Vendor Details'!$O:$O,'G&A Vendor x GL Analysis'!$F22,'[1]NS Vendor Details'!$N:$N,'G&A Vendor x GL Analysis'!$C22),IF(R$15="Actual",SUMIFS('[1]NS Vendor Details'!$D:$D,'[1]NS Vendor Details'!$H:$H,'G&A Vendor x GL Analysis'!R$20,'[1]NS Vendor Details'!$L:$L,'G&A Vendor x GL Analysis'!$D22,'[1]NS Vendor Details'!$O:$O,'G&A Vendor x GL Analysis'!$F22,'[1]NS Vendor Details'!$N:$N,'G&A Vendor x GL Analysis'!$C22,'[1]NS Vendor Details'!$K:$K,'G&A Vendor x GL Analysis'!$E$8),0)) -> 18262 | S22: =IF(AND(S$15="Actual",ISBLANK($E$8)),SUMIFS('[1]NS Vendor Details'!$D:$D,'[1]NS Vendor Details'!$H:$H,'G&A Vendor x GL Analysis'!S$20,'[1]NS Vendor Details'!$L:$L,'G&A Vendor x GL Analysis'!$D22,'[1]NS Vendor Details'!$O:$O,'G&A Vendor x GL Analysis'!$F22,'[1]NS Vendor Details'!$N:$N,'G&A Vendor x GL Analysis'!$C22,'[1]NS Vendor Details'!$I:$I,'G&A Vendor x GL Analysis'!$E22),IF(S$15="Actual",SUMIFS('[1]NS Vendor Details'!$D:$D,'[1]NS Vendor Details'!$H:$H,'G&A Vendor x GL Analysis'!S$20,'[1]NS Vendor Details'!$L:$L,'G&A Vendor x GL Analysis'!$D22,'[1]NS Vendor Details'!$O:$O,'G&A Vendor x GL Analysis'!$F22,'[1]NS Vendor Details'!$N:$N,'G&A Vendor x GL Analysis'!$C22,'[1]NS Vendor Details'!$K:$K,'G&A Vendor x GL Analysis'!$E$8,'[1]NS Vendor Details'!$I:$I,'G&A Vendor x GL Analysis'!$E22),0)) -> 4718 | T22: =IF(AND(T$15="Actual",ISBLANK($E$8)),SUMIFS('[1]NS Vendor Details'!$D:$D,'[1]NS Vendor Details'!$H:$H,'G&A Vendor x GL Analysis'!T$20,'[1]NS Vendor Details'!$L:$L,'G&A Vendor x GL Analysis'!$D22,'[1]NS Vendor Details'!$O:$O,'G&A Vendor x GL Analysis'!$F22,'[1]NS Vendor Details'!$N:$N,'G&A Vendor x GL Analysis'!$C22,'[1]NS Vendor Details'!$I:$I,'G&A Vendor x GL Analysis'!$E22),IF(T$15="Actual",SUMIFS('[1]NS Vendor Details'!$D:$D,'[1]NS Vendor Details'!$H:$H,'G&A Vendor x GL Analysis'!T$20,'[1]NS Vendor Details'!$L:$L,'G&A Vendor x GL Analysis'!$D22,'[1]NS Vendor Details'!$O:$O,'G&A Vendor x GL Analysis'!$F22,'[1]NS Vendor Details'!$N:$N,'G&A Vendor x GL Analysis'!$C22,'[1]NS Vendor Details'!$K:$K,'G&A Vendor x GL Analysis'!$E$8,'[1]NS Vendor Details'!$I:$I,'G&A Vendor x GL Analysis'!$E22),0)) -> 0 | U22: =IF(AND(U$15="Actual",ISBLANK($E$8)),SUMIFS('[1]NS Vendor Details'!$D:$D,'[1]NS Vendor Details'!$H:$H,'G&A Vendor x GL Analysis'!U$20,'[1]NS Vendor Details'!$L:$L,'G&A Vendor x GL Analysis'!$D22,'[1]NS Vendor Details'!$O:$O,'G&A Vendor x GL Analysis'!$F22,'[1]NS Vendor Details'!$N:$N,'G&A Vendor x GL Analysis'!$C22,'[1]NS Vendor Details'!$I:$I,'G&A Vendor x GL Analysis'!$E22),IF(U$15="Actual",SUMIFS('[1]NS Vendor Details'!$D:$D,'[1]NS Vendor Details'!$H:$H,'G&A Vendor x GL Analysis'!U$20,'[1]NS Vendor Details'!$L:$L,'G&A Vendor x GL Analysis'!$D22,'[1]NS Vendor Details'!$O:$O,'G&A Vendor x GL Analysis'!$F22,'[1]NS Vendor Details'!$N:$N,'G&A Vendor x GL Analysis'!$C22,'[1]NS Vendor Details'!$K:$K,'G&A Vendor x GL Analysis'!$E$8,'[1]NS Vendor Details'!$I:$I,'G&A Vendor x GL Analysis'!$E22),0)) -> 0 | V22: =IF(AND(V$15="Actual",ISBLANK($E$8)),SUMIFS('[1]NS Vendor Details'!$D:$D,'[1]NS Vendor Details'!$H:$H,'G&A Vendor x GL Analysis'!V$20,'[1]NS Vendor Details'!$L:$L,'G&A Vendor x GL Analysis'!$D22,'[1]NS Vendor Details'!$O:$O,'G&A Vendor x GL Analysis'!$F22,'[1]NS Vendor Details'!$N:$N,'G&A Vendor x GL Analysis'!$C22,'[1]NS Vendor Details'!$I:$I,'G&A Vendor x GL Analysis'!$E22),IF(V$15="Actual",SUMIFS('[1]NS Vendor Details'!$D:$D,'[1]NS Vendor Details'!$H:$H,'G&A Vendor x GL Analysis'!V$20,'[1]NS Vendor Details'!$L:$L,'G&A Vendor x GL Analysis'!$D22,'[1]NS Vendor Details'!$O:$O,'G&A Vendor x GL Analysis'!$F22,'[1]NS Vendor Details'!$N:$N,'G&A Vendor x GL Analysis'!$C22,'[1]NS Vendor Details'!$K:$K,'G&A Vendor x GL Analysis'!$E$8,'[1]NS Vendor Details'!$I:$I,'G&A Vendor x GL Analysis'!$E22),0)) -> 0 | W22: =IF(AND(W$15="Actual",ISBLANK($E$8)),SUMIFS('[1]NS Vendor Details'!$D:$D,'[1]NS Vendor Details'!$H:$H,'G&A Vendor x GL Analysis'!W$20,'[1]NS Vendor Details'!$L:$L,'G&A Vendor x GL Analysis'!$D22,'[1]NS Vendor Details'!$O:$O,'G&A Vendor x GL Analysis'!$F22,'[1]NS Vendor Details'!$N:$N,'G&A Vendor x GL Analysis'!$C22,'[1]NS Vendor Details'!$I:$I,'G&A Vendor x GL Analysis'!$E22),IF(W$15="Actual",SUMIFS('[1]NS Vendor Details'!$D:$D,'[1]NS Vendor Details'!$H:$H,'G&A Vendor x GL Analysis'!W$20,'[1]NS Vendor Details'!$L:$L,'G&A Vendor x GL Analysis'!$D22,'[1]NS Vendor Details'!$O:$O,'G&A Vendor x GL Analysis'!$F22,'[1]NS Vendor Details'!$N:$N,'G&A Vendor x GL Analysis'!$C22,'[1]NS Vendor Details'!$K:$K,'G&A Vendor x GL Analysis'!$E$8,'[1]NS Vendor Details'!$I:$I,'G&A Vendor x GL Analysis'!$E22),0)) -> 0 | X22: =IF(AND(X$15="Actual",ISBLANK($E$8)),SUMIFS('[1]NS Vendor Details'!$D:$D,'[1]NS Vendor Details'!$H:$H,'G&A Vendor x GL Analysis'!X$20,'[1]NS Vendor Details'!$L:$L,'G&A Vendor x GL Analysis'!$D22,'[1]NS Vendor Details'!$O:$O,'G&A Vendor x GL Analysis'!$F22,'[1]NS Vendor Details'!$N:$N,'G&A Vendor x GL Analysis'!$C22,'[1]NS Vendor Details'!$I:$I,'G&A Vendor x GL Analysis'!$E22),IF(X$15="Actual",SUMIFS('[1]NS Vendor Details'!$D:$D,'[1]NS Vendor Details'!$H:$H,'G&A Vendor x GL Analysis'!X$20,'[1]NS Vendor Details'!$L:$L,'G&A Vendor x GL Analysis'!$D22,'[1]NS Vendor Details'!$O:$O,'G&A Vendor x GL Analysis'!$F22,'[1]NS Vendor Details'!$N:$N,'G&A Vendor x GL Analysis'!$C22,'[1]NS Vendor Details'!$K:$K,'G&A Vendor x GL Analysis'!$E$8,'[1]NS Vendor Details'!$I:$I,'G&A Vendor x GL Analysis'!$E22),0)) -> 20705 | Y22: =IF(AND(Y$15="Actual",ISBLANK($E$8)),SUMIFS('[1]NS Vendor Details'!$D:$D,'[1]NS Vendor Details'!$H:$H,'G&A Vendor x GL Analysis'!Y$20,'[1]NS Vendor Details'!$L:$L,'G&A Vendor x GL Analysis'!$D22,'[1]NS Vendor Details'!$O:$O,'G&A Vendor x GL Analysis'!$F22,'[1]NS Vendor Details'!$N:$N,'G&A Vendor x GL Analysis'!$C22,'[1]NS Vendor Details'!$I:$I,'G&A Vendor x GL Analysis'!$E22),IF(Y$15="Actual",SUMIFS('[1]NS Vendor Details'!$D:$D,'[1]NS Vendor Details'!$H:$H,'G&A Vendor x GL Analysis'!Y$20,'[1]NS Vendor Details'!$L:$L,'G&A Vendor x GL Analysis'!$D22,'[1]NS Vendor Details'!$O:$O,'G&A Vendor x GL Analysis'!$F22,'[1]NS Vendor Details'!$N:$N,'G&A Vendor x GL Analysis'!$C22,'[1]NS Vendor Details'!$K:$K,'G&A Vendor x GL Analysis'!$E$8,'[1]NS Vendor Details'!$I:$I,'G&A Vendor x GL Analysis'!$E22),0)) -> 9840 | Z22: =IF(AND(Z$15="Actual",ISBLANK($E$8)),SUMIFS('[1]NS Vendor Details'!$D:$D,'[1]NS Vendor Details'!$H:$H,'G&A Vendor x GL Analysis'!Z$20,'[1]NS Vendor Details'!$L:$L,'G&A Vendor x GL Analysis'!$D22,'[1]NS Vendor Details'!$O:$O,'G&A Vendor x GL Analysis'!$F22,'[1]NS Vendor Details'!$N:$N,'G&A Vendor x GL Analysis'!$C22,'[1]NS Vendor Details'!$I:$I,'G&A Vendor x GL Analysis'!$E22),IF(Z$15="Actual",SUMIFS('[1]NS Vendor Details'!$D:$D,'[1]NS Vendor Details'!$H:$H,'G&A Vendor x GL Analysis'!Z$20,'[1]NS Vendor Details'!$L:$L,'G&A Vendor x GL Analysis'!$D22,'[1]NS Vendor Details'!$O:$O,'G&A Vendor x GL Analysis'!$F22,'[1]NS Vendor Details'!$N:$N,'G&A Vendor x GL Analysis'!$C22,'[1]NS Vendor Details'!$K:$K,'G&A Vendor x GL Analysis'!$E$8,'[1]NS Vendor Details'!$I:$I,'G&A Vendor x GL Analysis'!$E22),0)) -> 0 | ... AD22: =IF(AND(AD$15="Actual",ISBLANK($E$8)),SUMIFS('[1]NS Vendor Details'!$D:$D,'[1]NS Vendor Details'!$H:$H,'G&A Vendor x GL Analysis'!AD$20,'[1]NS Vendor Details'!$L:$L,'G&A Vendor x GL Analysis'!$D22,'[1]NS Vendor Details'!$O:$O,'G&A Vendor x GL Analysis'!$F22,'[1]NS Vendor Details'!$N:$N,'G&A Vendor x GL Analysis'!$C22,'[1]NS Vendor Details'!$I:$I,'G&A Vendor x GL Analysis'!$E22),IF(AD$15="Actual",SUMIFS('[1]NS Vendor Details'!$D:$D,'[1]NS Vendor Details'!$H:$H,'G&A Vendor x GL Analysis'!AD$20,'[1]NS Vendor Details'!$L:$L,'G&A Vendor x GL Analysis'!$D22,'[1]NS Vendor Details'!$O:$O,'G&A Vendor x GL Analysis'!$F22,'[1]NS Vendor Details'!$N:$N,'G&A Vendor x GL Analysis'!$C22,'[1]NS Vendor Details'!$K:$K,'G&A Vendor x GL Analysis'!$E$8,'[1]NS Vendor Details'!$I:$I,'G&A Vendor x GL Analysis'!$E22),0)) -> 0 | AF22: =ABS(S22)+ABS(T22)+ABS(U22)+ABS(V22)+ABS(W22)+ABS(X22)+ABS(Y22)+ABS(Z22)+ABS(AA22)+ABS(AB22)+ABS(AC22)+ABS(AD22) -> 35263
A23: =D23&E23 -> Advertising6240 - Product Photography | C23: SG&A | D23: =D22 -> Advertising | E23: 6240 - Product Photography | F23: GOSFilms LLC | G23: =IF(AND(G$15="Actual",ISBLANK($E$8)),SUMIFS('[1]NS Vendor Details'!$D:$D,'[1]NS Vendor Details'!$H:$H,'G&A Vendor x GL Analysis'!G$20,'[1]NS Vendor Details'!$L:$L,'G&A Vendor x GL Analysis'!$D23,'[1]NS Vendor Details'!$O:$O,'G&A Vendor x GL Analysis'!$F23,'[1]NS Vendor Details'!$N:$N,'G&A Vendor x GL Analysis'!$C23),IF(G$15="Actual",SUMIFS('[1]NS Vendor Details'!$D:$D,'[1]NS Vendor Details'!$H:$H,'G&A Vendor x GL Analysis'!G$20,'[1]NS Vendor Details'!$L:$L,'G&A Vendor x GL Analysis'!$D23,'[1]NS Vendor Details'!$O:$O,'G&A Vendor x GL Analysis'!$F23,'[1]NS Vendor Details'!$N:$N,'G&A Vendor x GL Analysis'!$C23,'[1]NS Vendor Details'!$K:$K,'G&A Vendor x GL Analysis'!$E$8),0)) -> 0 | H23: =IF(AND(H$15="Actual",ISBLANK($E$8)),SUMIFS('[1]NS Vendor Details'!$D:$D,'[1]NS Vendor Details'!$H:$H,'G&A Vendor x GL Analysis'!H$20,'[1]NS Vendor Details'!$L:$L,'G&A Vendor x GL Analysis'!$D23,'[1]NS Vendor Details'!$O:$O,'G&A Vendor x GL Analysis'!$F23,'[1]NS Vendor Details'!$N:$N,'G&A Vendor x GL Analysis'!$C23),IF(H$15="Actual",SUMIFS('[1]NS Vendor Details'!$D:$D,'[1]NS Vendor Details'!$H:$H,'G&A Vendor x GL Analysis'!H$20,'[1]NS Vendor Details'!$L:$L,'G&A Vendor x GL Analysis'!$D23,'[1]NS Vendor Details'!$O:$O,'G&A Vendor x GL Analysis'!$F23,'[1]NS Vendor Details'!$N:$N,'G&A Vendor x GL Analysis'!$C23,'[1]NS Vendor Details'!$K:$K,'G&A Vendor x GL Analysis'!$E$8),0)) -> 0 | I23: =IF(AND(I$15="Actual",ISBLANK($E$8)),SUMIFS('[1]NS Vendor Details'!$D:$D,'[1]NS Vendor Details'!$H:$H,'G&A Vendor x GL Analysis'!I$20,'[1]NS Vendor Details'!$L:$L,'G&A Vendor x GL Analysis'!$D23,'[1]NS Vendor Details'!$O:$O,'G&A Vendor x GL Analysis'!$F23,'[1]NS Vendor Details'!$N:$N,'G&A Vendor x GL Analysis'!$C23),IF(I$15="Actual",SUMIFS('[1]NS Vendor Details'!$D:$D,'[1]NS Vendor Details'!$H:$H,'G&A Vendor x GL Analysis'!I$20,'[1]NS Vendor Details'!$L:$L,'G&A Vendor x GL Analysis'!$D23,'[1]NS Vendor Details'!$O:$O,'G&A Vendor x GL Analysis'!$F23,'[1]NS Vendor Details'!$N:$N,'G&A Vendor x GL Analysis'!$C23,'[1]NS Vendor Details'!$K:$K,'G&A Vendor x GL Analysis'!$E$8),0)) -> 0 | J23: =IF(AND(J$15="Actual",ISBLANK($E$8)),SUMIFS('[1]NS Vendor Details'!$D:$D,'[1]NS Vendor Details'!$H:$H,'G&A Vendor x GL Analysis'!J$20,'[1]NS Vendor Details'!$L:$L,'G&A Vendor x GL Analysis'!$D23,'[1]NS Vendor Details'!$O:$O,'G&A Vendor x GL Analysis'!$F23,'[1]NS Vendor Details'!$N:$N,'G&A Vendor x GL Analysis'!$C23),IF(J$15="Actual",SUMIFS('[1]NS Vendor Details'!$D:$D,'[1]NS Vendor Details'!$H:$H,'G&A Vendor x GL Analysis'!J$20,'[1]NS Vendor Details'!$L:$L,'G&A Vendor x GL Analysis'!$D23,'[1]NS Vendor Details'!$O:$O,'G&A Vendor x GL Analysis'!$F23,'[1]NS Vendor Details'!$N:$N,'G&A Vendor x GL Analysis'!$C23,'[1]NS Vendor Details'!$K:$K,'G&A Vendor x GL Analysis'!$E$8),0)) -> 0 | K23: =IF(AND(K$15="Actual",ISBLANK($E$8)),SUMIFS('[1]NS Vendor Details'!$D:$D,'[1]NS Vendor Details'!$H:$H,'G&A Vendor x GL Analysis'!K$20,'[1]NS Vendor Details'!$L:$L,'G&A Vendor x GL Analysis'!$D23,'[1]NS Vendor Details'!$O:$O,'G&A Vendor x GL Analysis'!$F23,'[1]NS Vendor Details'!$N:$N,'G&A Vendor x GL Analysis'!$C23),IF(K$15="Actual",SUMIFS('[1]NS Vendor Details'!$D:$D,'[1]NS Vendor Details'!$H:$H,'G&A Vendor x GL Analysis'!K$20,'[1]NS Vendor Details'!$L:$L,'G&A Vendor x GL Analysis'!$D23,'[1]NS Vendor Details'!$O:$O,'G&A Vendor x GL Analysis'!$F23,'[1]NS Vendor Details'!$N:$N,'G&A Vendor x GL Analysis'!$C23,'[1]NS Vendor Details'!$K:$K,'G&A Vendor x GL Analysis'!$E$8),0)) -> 0 | L23: =IF(AND(L$15="Actual",ISBLANK($E$8)),SUMIFS('[1]NS Vendor Details'!$D:$D,'[1]NS Vendor Details'!$H:$H,'G&A Vendor x GL Analysis'!L$20,'[1]NS Vendor Details'!$L:$L,'G&A Vendor x GL Analysis'!$D23,'[1]NS Vendor Details'!$O:$O,'G&A Vendor x GL Analysis'!$F23,'[1]NS Vendor Details'!$N:$N,'G&A Vendor x GL Analysis'!$C23),IF(L$15="Actual",SUMIFS('[1]NS Vendor Details'!$D:$D,'[1]NS Vendor Details'!$H:$H,'G&A Vendor x GL Analysis'!L$20,'[1]NS Vendor Details'!$L:$L,'G&A Vendor x GL Analysis'!$D23,'[1]NS Vendor Details'!$O:$O,'G&A Vendor x GL Analysis'!$F23,'[1]NS Vendor Details'!$N:$N,'G&A Vendor x GL Analysis'!$C23,'[1]NS Vendor Details'!$K:$K,'G&A Vendor x GL Analysis'!$E$8),0)) -> 0 | M23: =IF(AND(M$15="Actual",ISBLANK($E$8)),SUMIFS('[1]NS Vendor Details'!$D:$D,'[1]NS Vendor Details'!$H:$H,'G&A Vendor x GL Analysis'!M$20,'[1]NS Vendor Details'!$L:$L,'G&A Vendor x GL Analysis'!$D23,'[1]NS Vendor Details'!$O:$O,'G&A Vendor x GL Analysis'!$F23,'[1]NS Vendor Details'!$N:$N,'G&A Vendor x GL Analysis'!$C23),IF(M$15="Actual",SUMIFS('[1]NS Vendor Details'!$D:$D,'[1]NS Vendor Details'!$H:$H,'G&A Vendor x GL Analysis'!M$20,'[1]NS Vendor Details'!$L:$L,'G&A Vendor x GL Analysis'!$D23,'[1]NS Vendor Details'!$O:$O,'G&A Vendor x GL Analysis'!$F23,'[1]NS Vendor Details'!$N:$N,'G&A Vendor x GL Analysis'!$C23,'[1]NS Vendor Details'!$K:$K,'G&A Vendor x GL Analysis'!$E$8),0)) -> 0 | N23: =IF(AND(N$15="Actual",ISBLANK($E$8)),SUMIFS('[1]NS Vendor Details'!$D:$D,'[1]NS Vendor Details'!$H:$H,'G&A Vendor x GL Analysis'!N$20,'[1]NS Vendor Details'!$L:$L,'G&A Vendor x GL Analysis'!$D23,'[1]NS Vendor Details'!$O:$O,'G&A Vendor x GL Analysis'!$F23,'[1]NS Vendor Details'!$N:$N,'G&A Vendor x GL Analysis'!$C23),IF(N$15="Actual",SUMIFS('[1]NS Vendor Details'!$D:$D,'[1]NS Vendor Details'!$H:$H,'G&A Vendor x GL Analysis'!N$20,'[1]NS Vendor Details'!$L:$L,'G&A Vendor x GL Analysis'!$D23,'[1]NS Vendor Details'!$O:$O,'G&A Vendor x GL Analysis'!$F23,'[1]NS Vendor Details'!$N:$N,'G&A Vendor x GL Analysis'!$C23,'[1]NS Vendor Details'!$K:$K,'G&A Vendor x GL Analysis'!$E$8),0)) -> 0 | ... R23: =IF(AND(R$15="Actual",ISBLANK($E$8)),SUMIFS('[1]NS Vendor Details'!$D:$D,'[1]NS Vendor Details'!$H:$H,'G&A Vendor x GL Analysis'!R$20,'[1]NS Vendor Details'!$L:$L,'G&A Vendor x GL Analysis'!$D23,'[1]NS Vendor Details'!$O:$O,'G&A Vendor x GL Analysis'!$F23,'[1]NS Vendor Details'!$N:$N,'G&A Vendor x GL Analysis'!$C23),IF(R$15="Actual",SUMIFS('[1]NS Vendor Details'!$D:$D,'[1]NS Vendor Details'!$H:$H,'G&A Vendor x GL Analysis'!R$20,'[1]NS Vendor Details'!$L:$L,'G&A Vendor x GL Analysis'!$D23,'[1]NS Vendor Details'!$O:$O,'G&A Vendor x GL Analysis'!$F23,'[1]NS Vendor Details'!$N:$N,'G&A Vendor x GL Analysis'!$C23,'[1]NS Vendor Details'!$K:$K,'G&A Vendor x GL Analysis'!$E$8),0)) -> 38242.51 | S23: =IF(AND(S$15="Actual",ISBLANK($E$8)),SUMIFS('[1]NS Vendor Details'!$D:$D,'[1]NS Vendor Details'!$H:$H,'G&A Vendor x GL Analysis'!S$20,'[1]NS Vendor Details'!$L:$L,'G&A Vendor x GL Analysis'!$D23,'[1]NS Vendor Details'!$O:$O,'G&A Vendor x GL Analysis'!$F23,'[1]NS Vendor Details'!$N:$N,'G&A Vendor x GL Analysis'!$C23,'[1]NS Vendor Details'!$I:$I,'G&A Vendor x GL Analysis'!$E23),IF(S$15="Actual",SUMIFS('[1]NS Vendor Details'!$D:$D,'[1]NS Vendor Details'!$H:$H,'G&A Vendor x GL Analysis'!S$20,'[1]NS Vendor Details'!$L:$L,'G&A Vendor x GL Analysis'!$D23,'[1]NS Vendor Details'!$O:$O,'G&A Vendor x GL Analysis'!$F23,'[1]NS Vendor Details'!$N:$N,'G&A Vendor x GL Analysis'!$C23,'[1]NS Vendor Details'!$K:$K,'G&A Vendor x GL Analysis'!$E$8,'[1]NS Vendor Details'!$I:$I,'G&A Vendor x GL Analysis'!$E23),0)) -> 48540.43 | T23: =IF(AND(T$15="Actual",ISBLANK($E$8)),SUMIFS('[1]NS Vendor Details'!$D:$D,'[1]NS Vendor Details'!$H:$H,'G&A Vendor x GL Analysis'!T$20,'[1]NS Vendor Details'!$L:$L,'G&A Vendor x GL Analysis'!$D23,'[1]NS Vendor Details'!$O:$O,'G&A Vendor x GL Analysis'!$F23,'[1]NS Vendor Details'!$N:$N,'G&A Vendor x GL Analysis'!$C23,'[1]NS Vendor Details'!$I:$I,'G&A Vendor x GL Analysis'!$E23),IF(T$15="Actual",SUMIFS('[1]NS Vendor Details'!$D:$D,'[1]NS Vendor Details'!$H:$H,'G&A Vendor x GL Analysis'!T$20,'[1]NS Vendor Details'!$L:$L,'G&A Vendor x GL Analysis'!$D23,'[1]NS Vendor Details'!$O:$O,'G&A Vendor x GL Analysis'!$F23,'[1]NS Vendor Details'!$N:$N,'G&A Vendor x GL Analysis'!$C23,'[1]NS Vendor Details'!$K:$K,'G&A Vendor x GL Analysis'!$E$8,'[1]NS Vendor Details'!$I:$I,'G&A Vendor x GL Analysis'!$E23),0)) -> 38242.45 | U23: =IF(AND(U$15="Actual",ISBLANK($E$8)),SUMIFS('[1]NS Vendor Details'!$D:$D,'[1]NS Vendor Details'!$H:$H,'G&A Vendor x GL Analysis'!U$20,'[1]NS Vendor Details'!$L:$L,'G&A Vendor x GL Analysis'!$D23,'[1]NS Vendor Details'!$O:$O,'G&A Vendor x GL Analysis'!$F23,'[1]NS Vendor Details'!$N:$N,'G&A Vendor x GL Analysis'!$C23,'[1]NS Vendor Details'!$I:$I,'G&A Vendor x GL Analysis'!$E23),IF(U$15="Actual",SUMIFS('[1]NS Vendor Details'!$D:$D,'[1]NS Vendor Details'!$H:$H,'G&A Vendor x GL Analysis'!U$20,'[1]NS Vendor Details'!$L:$L,'G&A Vendor x GL Analysis'!$D23,'[1]NS Vendor Details'!$O:$O,'G&A Vendor x GL Analysis'!$F23,'[1]NS Vendor Details'!$N:$N,'G&A Vendor x GL Analysis'!$C23,'[1]NS Vendor Details'!$K:$K,'G&A Vendor x GL Analysis'!$E$8,'[1]NS Vendor Details'!$I:$I,'G&A Vendor x GL Analysis'!$E23),0)) -> 29993.75 | V23: =IF(AND(V$15="Actual",ISBLANK($E$8)),SUMIFS('[1]NS Vendor Details'!$D:$D,'[1]NS Vendor Details'!$H:$H,'G&A Vendor x GL Analysis'!V$20,'[1]NS Vendor Details'!$L:$L,'G&A Vendor x GL Analysis'!$D23,'[1]NS Vendor Details'!$O:$O,'G&A Vendor x GL Analysis'!$F23,'[1]NS Vendor Details'!$N:$N,'G&A Vendor x GL Analysis'!$C23,'[1]NS Vendor Details'!$I:$I,'G&A Vendor x GL Analysis'!$E23),IF(V$15="Actual",SUMIFS('[1]NS Vendor Details'!$D:$D,'[1]NS Vendor Details'!$H:$H,'G&A Vendor x GL Analysis'!V$20,'[1]NS Vendor Details'!$L:$L,'G&A Vendor x GL Analysis'!$D23,'[1]NS Vendor Details'!$O:$O,'G&A Vendor x GL Analysis'!$F23,'[1]NS Vendor Details'!$N:$N,'G&A Vendor x GL Analysis'!$C23,'[1]NS Vendor Details'!$K:$K,'G&A Vendor x GL Analysis'!$E$8,'[1]NS Vendor Details'!$I:$I,'G&A Vendor x GL Analysis'!$E23),0)) -> 40291.67 | W23: =IF(AND(W$15="Actual",ISBLANK($E$8)),SUMIFS('[1]NS Vendor Details'!$D:$D,'[1]NS Vendor Details'!$H:$H,'G&A Vendor x GL Analysis'!W$20,'[1]NS Vendor Details'!$L:$L,'G&A Vendor x GL Analysis'!$D23,'[1]NS Vendor Details'!$O:$O,'G&A Vendor x GL Analysis'!$F23,'[1]NS Vendor Details'!$N:$N,'G&A Vendor x GL Analysis'!$C23,'[1]NS Vendor Details'!$I:$I,'G&A Vendor x GL Analysis'!$E23),IF(W$15="Actual",SUMIFS('[1]NS Vendor Details'!$D:$D,'[1]NS Vendor Details'!$H:$H,'G&A Vendor x GL Analysis'!W$20,'[1]NS Vendor Details'!$L:$L,'G&A Vendor x GL Analysis'!$D23,'[1]NS Vendor Details'!$O:$O,'G&A Vendor x GL Analysis'!$F23,'[1]NS Vendor Details'!$N:$N,'G&A Vendor x GL Analysis'!$C23,'[1]NS Vendor Details'!$K:$K,'G&A Vendor x GL Analysis'!$E$8,'[1]NS Vendor Details'!$I:$I,'G&A Vendor x GL Analysis'!$E23),0)) -> 40291.67 | X23: =IF(AND(X$15="Actual",ISBLANK($E$8)),SUMIFS('[1]NS Vendor Details'!$D:$D,'[1]NS Vendor Details'!$H:$H,'G&A Vendor x GL Analysis'!X$20,'[1]NS Vendor Details'!$L:$L,'G&A Vendor x GL Analysis'!$D23,'[1]NS Vendor Details'!$O:$O,'G&A Vendor x GL Analysis'!$F23,'[1]NS Vendor Details'!$N:$N,'G&A Vendor x GL Analysis'!$C23,'[1]NS Vendor Details'!$I:$I,'G&A Vendor x GL Analysis'!$E23),IF(X$15="Actual",SUMIFS('[1]NS Vendor Details'!$D:$D,'[1]NS Vendor Details'!$H:$H,'G&A Vendor x GL Analysis'!X$20,'[1]NS Vendor Details'!$L:$L,'G&A Vendor x GL Analysis'!$D23,'[1]NS Vendor Details'!$O:$O,'G&A Vendor x GL Analysis'!$F23,'[1]NS Vendor Details'!$N:$N,'G&A Vendor x GL Analysis'!$C23,'[1]NS Vendor Details'!$K:$K,'G&A Vendor x GL Analysis'!$E$8,'[1]NS Vendor Details'!$I:$I,'G&A Vendor x GL Analysis'!$E23),0)) -> 40291.67 | Y23: =IF(AND(Y$15="Actual",ISBLANK($E$8)),SUMIFS('[1]NS Vendor Details'!$D:$D,'[1]NS Vendor Details'!$H:$H,'G&A Vendor x GL Analysis'!Y$20,'[1]NS Vendor Details'!$L:$L,'G&A Vendor x GL Analysis'!$D23,'[1]NS Vendor Details'!$O:$O,'G&A Vendor x GL Analysis'!$F23,'[1]NS Vendor Details'!$N:$N,'G&A Vendor x GL Analysis'!$C23,'[1]NS Vendor Details'!$I:$I,'G&A Vendor x GL Analysis'!$E23),IF(Y$15="Actual",SUMIFS('[1]NS Vendor Details'!$D:$D,'[1]NS Vendor Details'!$H:$H,'G&A Vendor x GL Analysis'!Y$20,'[1]NS Vendor Details'!$L:$L,'G&A Vendor x GL Analysis'!$D23,'[1]NS Vendor Details'!$O:$O,'G&A Vendor x GL Analysis'!$F23,'[1]NS Vendor Details'!$N:$N,'G&A Vendor x GL Analysis'!$C23,'[1]NS Vendor Details'!$K:$K,'G&A Vendor x GL Analysis'!$E$8,'[1]NS Vendor Details'!$I:$I,'G&A Vendor x GL Analysis'!$E23),0)) -> 40291.67 | Z23: =IF(AND(Z$15="Actual",ISBLANK($E$8)),SUMIFS('[1]NS Vendor Details'!$D:$D,'[1]NS Vendor Details'!$H:$H,'G&A Vendor x GL Analysis'!Z$20,'[1]NS Vendor Details'!$L:$L,'G&A Vendor x GL Analysis'!$D23,'[1]NS Vendor Details'!$O:$O,'G&A Vendor x GL Analysis'!$F23,'[1]NS Vendor Details'!$N:$N,'G&A Vendor x GL Analysis'!$C23,'[1]NS Vendor Details'!$I:$I,'G&A Vendor x GL Analysis'!$E23),IF(Z$15="Actual",SUMIFS('[1]NS Vendor Details'!$D:$D,'[1]NS Vendor Details'!$H:$H,'G&A Vendor x GL Analysis'!Z$20,'[1]NS Vendor Details'!$L:$L,'G&A Vendor x GL Analysis'!$D23,'[1]NS Vendor Details'!$O:$O,'G&A Vendor x GL Analysis'!$F23,'[1]NS Vendor Details'!$N:$N,'G&A Vendor x GL Analysis'!$C23,'[1]NS Vendor Details'!$K:$K,'G&A Vendor x GL Analysis'!$E$8,'[1]NS Vendor Details'!$I:$I,'G&A Vendor x GL Analysis'!$E23),0)) -> 40291.65 | ... AD23: =IF(AND(AD$15="Actual",ISBLANK($E$8)),SUMIFS('[1]NS Vendor Details'!$D:$D,'[1]NS Vendor Details'!$H:$H,'G&A Vendor x GL Analysis'!AD$20,'[1]NS Vendor Details'!$L:$L,'G&A Vendor x GL Analysis'!$D23,'[1]NS Vendor Details'!$O:$O,'G&A Vendor x GL Analysis'!$F23,'[1]NS Vendor Details'!$N:$N,'G&A Vendor x GL Analysis'!$C23,'[1]NS Vendor Details'!$I:$I,'G&A Vendor x GL Analysis'!$E23),IF(AD$15="Actual",SUMIFS('[1]NS Vendor Details'!$D:$D,'[1]NS Vendor Details'!$H:$H,'G&A Vendor x GL Analysis'!AD$20,'[1]NS Vendor Details'!$L:$L,'G&A Vendor x GL Analysis'!$D23,'[1]NS Vendor Details'!$O:$O,'G&A Vendor x GL Analysis'!$F23,'[1]NS Vendor Details'!$N:$N,'G&A Vendor x GL Analysis'!$C23,'[1]NS Vendor Details'!$K:$K,'G&A Vendor x GL Analysis'!$E$8,'[1]NS Vendor Details'!$I:$I,'G&A Vendor x GL Analysis'!$E23),0)) -> 0 | AF23: =ABS(S23)+ABS(T23)+ABS(U23)+ABS(V23)+ABS(W23)+ABS(X23)+ABS(Y23)+ABS(Z23)+ABS(AA23)+ABS(AB23)+ABS(AC23)+ABS(AD23) -> 404734.95
A24: =D24&E24 -> Advertising6240 - Product Photography | C24: SG&A | D24: =D23 -> Advertising | E24: 6240 - Product Photography | F24: LENFLASH dot COM | G24: =IF(AND(G$15="Actual",ISBLANK($E$8)),SUMIFS('[1]NS Vendor Details'!$D:$D,'[1]NS Vendor Details'!$H:$H,'G&A Vendor x GL Analysis'!G$20,'[1]NS Vendor Details'!$L:$L,'G&A Vendor x GL Analysis'!$D24,'[1]NS Vendor Details'!$O:$O,'G&A Vendor x GL Analysis'!$F24,'[1]NS Vendor Details'!$N:$N,'G&A Vendor x GL Analysis'!$C24),IF(G$15="Actual",SUMIFS('[1]NS Vendor Details'!$D:$D,'[1]NS Vendor Details'!$H:$H,'G&A Vendor x GL Analysis'!G$20,'[1]NS Vendor Details'!$L:$L,'G&A Vendor x GL Analysis'!$D24,'[1]NS Vendor Details'!$O:$O,'G&A Vendor x GL Analysis'!$F24,'[1]NS Vendor Details'!$N:$N,'G&A Vendor x GL Analysis'!$C24,'[1]NS Vendor Details'!$K:$K,'G&A Vendor x GL Analysis'!$E$8),0)) -> 0 | H24: =IF(AND(H$15="Actual",ISBLANK($E$8)),SUMIFS('[1]NS Vendor Details'!$D:$D,'[1]NS Vendor Details'!$H:$H,'G&A Vendor x GL Analysis'!H$20,'[1]NS Vendor Details'!$L:$L,'G&A Vendor x GL Analysis'!$D24,'[1]NS Vendor Details'!$O:$O,'G&A Vendor x GL Analysis'!$F24,'[1]NS Vendor Details'!$N:$N,'G&A Vendor x GL Analysis'!$C24),IF(H$15="Actual",SUMIFS('[1]NS Vendor Details'!$D:$D,'[1]NS Vendor Details'!$H:$H,'G&A Vendor x GL Analysis'!H$20,'[1]NS Vendor Details'!$L:$L,'G&A Vendor x GL Analysis'!$D24,'[1]NS Vendor Details'!$O:$O,'G&A Vendor x GL Analysis'!$F24,'[1]NS Vendor Details'!$N:$N,'G&A Vendor x GL Analysis'!$C24,'[1]NS Vendor Details'!$K:$K,'G&A Vendor x GL Analysis'!$E$8),0)) -> 0 | I24: =IF(AND(I$15="Actual",ISBLANK($E$8)),SUMIFS('[1]NS Vendor Details'!$D:$D,'[1]NS Vendor Details'!$H:$H,'G&A Vendor x GL Analysis'!I$20,'[1]NS Vendor Details'!$L:$L,'G&A Vendor x GL Analysis'!$D24,'[1]NS Vendor Details'!$O:$O,'G&A Vendor x GL Analysis'!$F24,'[1]NS Vendor Details'!$N:$N,'G&A Vendor x GL Analysis'!$C24),IF(I$15="Actual",SUMIFS('[1]NS Vendor Details'!$D:$D,'[1]NS Vendor Details'!$H:$H,'G&A Vendor x GL Analysis'!I$20,'[1]NS Vendor Details'!$L:$L,'G&A Vendor x GL Analysis'!$D24,'[1]NS Vendor Details'!$O:$O,'G&A Vendor x GL Analysis'!$F24,'[1]NS Vendor Details'!$N:$N,'G&A Vendor x GL Analysis'!$C24,'[1]NS Vendor Details'!$K:$K,'G&A Vendor x GL Analysis'!$E$8),0)) -> 0 | J24: =IF(AND(J$15="Actual",ISBLANK($E$8)),SUMIFS('[1]NS Vendor Details'!$D:$D,'[1]NS Vendor Details'!$H:$H,'G&A Vendor x GL Analysis'!J$20,'[1]NS Vendor Details'!$L:$L,'G&A Vendor x GL Analysis'!$D24,'[1]NS Vendor Details'!$O:$O,'G&A Vendor x GL Analysis'!$F24,'[1]NS Vendor Details'!$N:$N,'G&A Vendor x GL Analysis'!$C24),IF(J$15="Actual",SUMIFS('[1]NS Vendor Details'!$D:$D,'[1]NS Vendor Details'!$H:$H,'G&A Vendor x GL Analysis'!J$20,'[1]NS Vendor Details'!$L:$L,'G&A Vendor x GL Analysis'!$D24,'[1]NS Vendor Details'!$O:$O,'G&A Vendor x GL Analysis'!$F24,'[1]NS Vendor Details'!$N:$N,'G&A Vendor x GL Analysis'!$C24,'[1]NS Vendor Details'!$K:$K,'G&A Vendor x GL Analysis'!$E$8),0)) -> 0 | K24: =IF(AND(K$15="Actual",ISBLANK($E$8)),SUMIFS('[1]NS Vendor Details'!$D:$D,'[1]NS Vendor Details'!$H:$H,'G&A Vendor x GL Analysis'!K$20,'[1]NS Vendor Details'!$L:$L,'G&A Vendor x GL Analysis'!$D24,'[1]NS Vendor Details'!$O:$O,'G&A Vendor x GL Analysis'!$F24,'[1]NS Vendor Details'!$N:$N,'G&A Vendor x GL Analysis'!$C24),IF(K$15="Actual",SUMIFS('[1]NS Vendor Details'!$D:$D,'[1]NS Vendor Details'!$H:$H,'G&A Vendor x GL Analysis'!K$20,'[1]NS Vendor Details'!$L:$L,'G&A Vendor x GL Analysis'!$D24,'[1]NS Vendor Details'!$O:$O,'G&A Vendor x GL Analysis'!$F24,'[1]NS Vendor Details'!$N:$N,'G&A Vendor x GL Analysis'!$C24,'[1]NS Vendor Details'!$K:$K,'G&A Vendor x GL Analysis'!$E$8),0)) -> 13010 | L24: =IF(AND(L$15="Actual",ISBLANK($E$8)),SUMIFS('[1]NS Vendor Details'!$D:$D,'[1]NS Vendor Details'!$H:$H,'G&A Vendor x GL Analysis'!L$20,'[1]NS Vendor Details'!$L:$L,'G&A Vendor x GL Analysis'!$D24,'[1]NS Vendor Details'!$O:$O,'G&A Vendor x GL Analysis'!$F24,'[1]NS Vendor Details'!$N:$N,'G&A Vendor x GL Analysis'!$C24),IF(L$15="Actual",SUMIFS('[1]NS Vendor Details'!$D:$D,'[1]NS Vendor Details'!$H:$H,'G&A Vendor x GL Analysis'!L$20,'[1]NS Vendor Details'!$L:$L,'G&A Vendor x GL Analysis'!$D24,'[1]NS Vendor Details'!$O:$O,'G&A Vendor x GL Analysis'!$F24,'[1]NS Vendor Details'!$N:$N,'G&A Vendor x GL Analysis'!$C24,'[1]NS Vendor Details'!$K:$K,'G&A Vendor x GL Analysis'!$E$8),0)) -> 9835 | M24: =IF(AND(M$15="Actual",ISBLANK($E$8)),SUMIFS('[1]NS Vendor Details'!$D:$D,'[1]NS Vendor Details'!$H:$H,'G&A Vendor x GL Analysis'!M$20,'[1]NS Vendor Details'!$L:$L,'G&A Vendor x GL Analysis'!$D24,'[1]NS Vendor Details'!$O:$O,'G&A Vendor x GL Analysis'!$F24,'[1]NS Vendor Details'!$N:$N,'G&A Vendor x GL Analysis'!$C24),IF(M$15="Actual",SUMIFS('[1]NS Vendor Details'!$D:$D,'[1]NS Vendor Details'!$H:$H,'G&A Vendor x GL Analysis'!M$20,'[1]NS Vendor Details'!$L:$L,'G&A Vendor x GL Analysis'!$D24,'[1]NS Vendor Details'!$O:$O,'G&A Vendor x GL Analysis'!$F24,'[1]NS Vendor Details'!$N:$N,'G&A Vendor x GL Analysis'!$C24,'[1]NS Vendor Details'!$K:$K,'G&A Vendor x GL Analysis'!$E$8),0)) -> 4230 | N24: =IF(AND(N$15="Actual",ISBLANK($E$8)),SUMIFS('[1]NS Vendor Details'!$D:$D,'[1]NS Vendor Details'!$H:$H,'G&A Vendor x GL Analysis'!N$20,'[1]NS Vendor Details'!$L:$L,'G&A Vendor x GL Analysis'!$D24,'[1]NS Vendor Details'!$O:$O,'G&A Vendor x GL Analysis'!$F24,'[1]NS Vendor Details'!$N:$N,'G&A Vendor x GL Analysis'!$C24),IF(N$15="Actual",SUMIFS('[1]NS Vendor Details'!$D:$D,'[1]NS Vendor Details'!$H:$H,'G&A Vendor x GL Analysis'!N$20,'[1]NS Vendor Details'!$L:$L,'G&A Vendor x GL Analysis'!$D24,'[1]NS Vendor Details'!$O:$O,'G&A Vendor x GL Analysis'!$F24,'[1]NS Vendor Details'!$N:$N,'G&A Vendor x GL Analysis'!$C24,'[1]NS Vendor Details'!$K:$K,'G&A Vendor x GL Analysis'!$E$8),0)) -> 0 | ... R24: =IF(AND(R$15="Actual",ISBLANK($E$8)),SUMIFS('[1]NS Vendor Details'!$D:$D,'[1]NS Vendor Details'!$H:$H,'G&A Vendor x GL Analysis'!R$20,'[1]NS Vendor Details'!$L:$L,'G&A Vendor x GL Analysis'!$D24,'[1]NS Vendor Details'!$O:$O,'G&A Vendor x GL Analysis'!$F24,'[1]NS Vendor Details'!$N:$N,'G&A Vendor x GL Analysis'!$C24),IF(R$15="Actual",SUMIFS('[1]NS Vendor Details'!$D:$D,'[1]NS Vendor Details'!$H:$H,'G&A Vendor x GL Analysis'!R$20,'[1]NS Vendor Details'!$L:$L,'G&A Vendor x GL Analysis'!$D24,'[1]NS Vendor Details'!$O:$O,'G&A Vendor x GL Analysis'!$F24,'[1]NS Vendor Details'!$N:$N,'G&A Vendor x GL Analysis'!$C24,'[1]NS Vendor Details'!$K:$K,'G&A Vendor x GL Analysis'!$E$8),0)) -> 6850 | S24: =IF(AND(S$15="Actual",ISBLANK($E$8)),SUMIFS('[1]NS Vendor Details'!$D:$D,'[1]NS Vendor Details'!$H:$H,'G&A Vendor x GL Analysis'!S$20,'[1]NS Vendor Details'!$L:$L,'G&A Vendor x GL Analysis'!$D24,'[1]NS Vendor Details'!$O:$O,'G&A Vendor x GL Analysis'!$F24,'[1]NS Vendor Details'!$N:$N,'G&A Vendor x GL Analysis'!$C24,'[1]NS Vendor Details'!$I:$I,'G&A Vendor x GL Analysis'!$E24),IF(S$15="Actual",SUMIFS('[1]NS Vendor Details'!$D:$D,'[1]NS Vendor Details'!$H:$H,'G&A Vendor x GL Analysis'!S$20,'[1]NS Vendor Details'!$L:$L,'G&A Vendor x GL Analysis'!$D24,'[1]NS Vendor Details'!$O:$O,'G&A Vendor x GL Analysis'!$F24,'[1]NS Vendor Details'!$N:$N,'G&A Vendor x GL Analysis'!$C24,'[1]NS Vendor Details'!$K:$K,'G&A Vendor x GL Analysis'!$E$8,'[1]NS Vendor Details'!$I:$I,'G&A Vendor x GL Analysis'!$E24),0)) -> 0 | T24: =IF(AND(T$15="Actual",ISBLANK($E$8)),SUMIFS('[1]NS Vendor Details'!$D:$D,'[1]NS Vendor Details'!$H:$H,'G&A Vendor x GL Analysis'!T$20,'[1]NS Vendor Details'!$L:$L,'G&A Vendor x GL Analysis'!$D24,'[1]NS Vendor Details'!$O:$O,'G&A Vendor x GL Analysis'!$F24,'[1]NS Vendor Details'!$N:$N,'G&A Vendor x GL Analysis'!$C24,'[1]NS Vendor Details'!$I:$I,'G&A Vendor x GL Analysis'!$E24),IF(T$15="Actual",SUMIFS('[1]NS Vendor Details'!$D:$D,'[1]NS Vendor Details'!$H:$H,'G&A Vendor x GL Analysis'!T$20,'[1]NS Vendor Details'!$L:$L,'G&A Vendor x GL Analysis'!$D24,'[1]NS Vendor Details'!$O:$O,'G&A Vendor x GL Analysis'!$F24,'[1]NS Vendor Details'!$N:$N,'G&A Vendor x GL Analysis'!$C24,'[1]NS Vendor Details'!$K:$K,'G&A Vendor x GL Analysis'!$E$8,'[1]NS Vendor Details'!$I:$I,'G&A Vendor x GL Analysis'!$E24),0)) -> 3855 | U24: =IF(AND(U$15="Actual",ISBLANK($E$8)),SUMIFS('[1]NS Vendor Details'!$D:$D,'[1]NS Vendor Details'!$H:$H,'G&A Vendor x GL Analysis'!U$20,'[1]NS Vendor Details'!$L:$L,'G&A Vendor x GL Analysis'!$D24,'[1]NS Vendor Details'!$O:$O,'G&A Vendor x GL Analysis'!$F24,'[1]NS Vendor Details'!$N:$N,'G&A Vendor x GL Analysis'!$C24,'[1]NS Vendor Details'!$I:$I,'G&A Vendor x GL Analysis'!$E24),IF(U$15="Actual",SUMIFS('[1]NS Vendor Details'!$D:$D,'[1]NS Vendor Details'!$H:$H,'G&A Vendor x GL Analysis'!U$20,'[1]NS Vendor Details'!$L:$L,'G&A Vendor x GL Analysis'!$D24,'[1]NS Vendor Details'!$O:$O,'G&A Vendor x GL Analysis'!$F24,'[1]NS Vendor Details'!$N:$N,'G&A Vendor x GL Analysis'!$C24,'[1]NS Vendor Details'!$K:$K,'G&A Vendor x GL Analysis'!$E$8,'[1]NS Vendor Details'!$I:$I,'G&A Vendor x GL Analysis'!$E24),0)) -> 1270 | V24: =IF(AND(V$15="Actual",ISBLANK($E$8)),SUMIFS('[1]NS Vendor Details'!$D:$D,'[1]NS Vendor Details'!$H:$H,'G&A Vendor x GL Analysis'!V$20,'[1]NS Vendor Details'!$L:$L,'G&A Vendor x GL Analysis'!$D24,'[1]NS Vendor Details'!$O:$O,'G&A Vendor x GL Analysis'!$F24,'[1]NS Vendor Details'!$N:$N,'G&A Vendor x GL Analysis'!$C24,'[1]NS Vendor Details'!$I:$I,'G&A Vendor x GL Analysis'!$E24),IF(V$15="Actual",SUMIFS('[1]NS Vendor Details'!$D:$D,'[1]NS Vendor Details'!$H:$H,'G&A Vendor x GL Analysis'!V$20,'[1]NS Vendor Details'!$L:$L,'G&A Vendor x GL Analysis'!$D24,'[1]NS Vendor Details'!$O:$O,'G&A Vendor x GL Analysis'!$F24,'[1]NS Vendor Details'!$N:$N,'G&A Vendor x GL Analysis'!$C24,'[1]NS Vendor Details'!$K:$K,'G&A Vendor x GL Analysis'!$E$8,'[1]NS Vendor Details'!$I:$I,'G&A Vendor x GL Analysis'!$E24),0)) -> 0 | W24: =IF(AND(W$15="Actual",ISBLANK($E$8)),SUMIFS('[1]NS Vendor Details'!$D:$D,'[1]NS Vendor Details'!$H:$H,'G&A Vendor x GL Analysis'!W$20,'[1]NS Vendor Details'!$L:$L,'G&A Vendor x GL Analysis'!$D24,'[1]NS Vendor Details'!$O:$O,'G&A Vendor x GL Analysis'!$F24,'[1]NS Vendor Details'!$N:$N,'G&A Vendor x GL Analysis'!$C24,'[1]NS Vendor Details'!$I:$I,'G&A Vendor x GL Analysis'!$E24),IF(W$15="Actual",SUMIFS('[1]NS Vendor Details'!$D:$D,'[1]NS Vendor Details'!$H:$H,'G&A Vendor x GL Analysis'!W$20,'[1]NS Vendor Details'!$L:$L,'G&A Vendor x GL Analysis'!$D24,'[1]NS Vendor Details'!$O:$O,'G&A Vendor x GL Analysis'!$F24,'[1]NS Vendor Details'!$N:$N,'G&A Vendor x GL Analysis'!$C24,'[1]NS Vendor Details'!$K:$K,'G&A Vendor x GL Analysis'!$E$8,'[1]NS Vendor Details'!$I:$I,'G&A Vendor x GL Analysis'!$E24),0)) -> 0 | X24: =IF(AND(X$15="Actual",ISBLANK($E$8)),SUMIFS('[1]NS Vendor Details'!$D:$D,'[1]NS Vendor Details'!$H:$H,'G&A Vendor x GL Analysis'!X$20,'[1]NS Vendor Details'!$L:$L,'G&A Vendor x GL Analysis'!$D24,'[1]NS Vendor Details'!$O:$O,'G&A Vendor x GL Analysis'!$F24,'[1]NS Vendor Details'!$N:$N,'G&A Vendor x GL Analysis'!$C24,'[1]NS Vendor Details'!$I:$I,'G&A Vendor x GL Analysis'!$E24),IF(X$15="Actual",SUMIFS('[1]NS Vendor Details'!$D:$D,'[1]NS Vendor Details'!$H:$H,'G&A Vendor x GL Analysis'!X$20,'[1]NS Vendor Details'!$L:$L,'G&A Vendor x GL Analysis'!$D24,'[1]NS Vendor Details'!$O:$O,'G&A Vendor x GL Analysis'!$F24,'[1]NS Vendor Details'!$N:$N,'G&A Vendor x GL Analysis'!$C24,'[1]NS Vendor Details'!$K:$K,'G&A Vendor x GL Analysis'!$E$8,'[1]NS Vendor Details'!$I:$I,'G&A Vendor x GL Analysis'!$E24),0)) -> 0 | Y24: =IF(AND(Y$15="Actual",ISBLANK($E$8)),SUMIFS('[1]NS Vendor Details'!$D:$D,'[1]NS Vendor Details'!$H:$H,'G&A Vendor x GL Analysis'!Y$20,'[1]NS Vendor Details'!$L:$L,'G&A Vendor x GL Analysis'!$D24,'[1]NS Vendor Details'!$O:$O,'G&A Vendor x GL Analysis'!$F24,'[1]NS Vendor Details'!$N:$N,'G&A Vendor x GL Analysis'!$C24,'[1]NS Vendor Details'!$I:$I,'G&A Vendor x GL Analysis'!$E24),IF(Y$15="Actual",SUMIFS('[1]NS Vendor Details'!$D:$D,'[1]NS Vendor Details'!$H:$H,'G&A Vendor x GL Analysis'!Y$20,'[1]NS Vendor Details'!$L:$L,'G&A Vendor x GL Analysis'!$D24,'[1]NS Vendor Details'!$O:$O,'G&A Vendor x GL Analysis'!$F24,'[1]NS Vendor Details'!$N:$N,'G&A Vendor x GL Analysis'!$C24,'[1]NS Vendor Details'!$K:$K,'G&A Vendor x GL Analysis'!$E$8,'[1]NS Vendor Details'!$I:$I,'G&A Vendor x GL Analysis'!$E24),0)) -> 0 | Z24: =IF(AND(Z$15="Actual",ISBLANK($E$8)),SUMIFS('[1]NS Vendor Details'!$D:$D,'[1]NS Vendor Details'!$H:$H,'G&A Vendor x GL Analysis'!Z$20,'[1]NS Vendor Details'!$L:$L,'G&A Vendor x GL Analysis'!$D24,'[1]NS Vendor Details'!$O:$O,'G&A Vendor x GL Analysis'!$F24,'[1]NS Vendor Details'!$N:$N,'G&A Vendor x GL Analysis'!$C24,'[1]NS Vendor Details'!$I:$I,'G&A Vendor x GL Analysis'!$E24),IF(Z$15="Actual",SUMIFS('[1]NS Vendor Details'!$D:$D,'[1]NS Vendor Details'!$H:$H,'G&A Vendor x GL Analysis'!Z$20,'[1]NS Vendor Details'!$L:$L,'G&A Vendor x GL Analysis'!$D24,'[1]NS Vendor Details'!$O:$O,'G&A Vendor x GL Analysis'!$F24,'[1]NS Vendor Details'!$N:$N,'G&A Vendor x GL Analysis'!$C24,'[1]NS Vendor Details'!$K:$K,'G&A Vendor x GL Analysis'!$E$8,'[1]NS Vendor Details'!$I:$I,'G&A Vendor x GL Analysis'!$E24),0)) -> 23250 | ... AD24: =IF(AND(AD$15="Actual",ISBLANK($E$8)),SUMIFS('[1]NS Vendor Details'!$D:$D,'[1]NS Vendor Details'!$H:$H,'G&A Vendor x GL Analysis'!AD$20,'[1]NS Vendor Details'!$L:$L,'G&A Vendor x GL Analysis'!$D24,'[1]NS Vendor Details'!$O:$O,'G&A Vendor x GL Analysis'!$F24,'[1]NS Vendor Details'!$N:$N,'G&A Vendor x GL Analysis'!$C24,'[1]NS Vendor Details'!$I:$I,'G&A Vendor x GL Analysis'!$E24),IF(AD$15="Actual",SUMIFS('[1]NS Vendor Details'!$D:$D,'[1]NS Vendor Details'!$H:$H,'G&A Vendor x GL Analysis'!AD$20,'[1]NS Vendor Details'!$L:$L,'G&A Vendor x GL Analysis'!$D24,'[1]NS Vendor Details'!$O:$O,'G&A Vendor x GL Analysis'!$F24,'[1]NS Vendor Details'!$N:$N,'G&A Vendor x GL Analysis'!$C24,'[1]NS Vendor Details'!$K:$K,'G&A Vendor x GL Analysis'!$E$8,'[1]NS Vendor Details'!$I:$I,'G&A Vendor x GL Analysis'!$E24),0)) -> 0 | AF24: =ABS(S24)+ABS(T24)+ABS(U24)+ABS(V24)+ABS(W24)+ABS(X24)+ABS(Y24)+ABS(Z24)+ABS(AA24)+ABS(AB24)+ABS(AC24)+ABS(AD24) -> 28375
A25: =D25&E25 -> Advertising6240 - Product Photography | C25: SG&A | D25: =D24 -> Advertising | E25: 6240 - Product Photography | F25: [No Vendor] | G25: =IF(AND(G$15="Actual",ISBLANK($E$8)),SUMIFS('[1]NS Vendor Details'!$D:$D,'[1]NS Vendor Details'!$H:$H,'G&A Vendor x GL Analysis'!G$20,'[1]NS Vendor Details'!$L:$L,'G&A Vendor x GL Analysis'!$D25,'[1]NS Vendor Details'!$O:$O,'G&A Vendor x GL Analysis'!$F25,'[1]NS Vendor Details'!$N:$N,'G&A Vendor x GL Analysis'!$C25),IF(G$15="Actual",SUMIFS('[1]NS Vendor Details'!$D:$D,'[1]NS Vendor Details'!$H:$H,'G&A Vendor x GL Analysis'!G$20,'[1]NS Vendor Details'!$L:$L,'G&A Vendor x GL Analysis'!$D25,'[1]NS Vendor Details'!$O:$O,'G&A Vendor x GL Analysis'!$F25,'[1]NS Vendor Details'!$N:$N,'G&A Vendor x GL Analysis'!$C25,'[1]NS Vendor Details'!$K:$K,'G&A Vendor x GL Analysis'!$E$8),0)) -> -19852.71 | H25: =IF(AND(H$15="Actual",ISBLANK($E$8)),SUMIFS('[1]NS Vendor Details'!$D:$D,'[1]NS Vendor Details'!$H:$H,'G&A Vendor x GL Analysis'!H$20,'[1]NS Vendor Details'!$L:$L,'G&A Vendor x GL Analysis'!$D25,'[1]NS Vendor Details'!$O:$O,'G&A Vendor x GL Analysis'!$F25,'[1]NS Vendor Details'!$N:$N,'G&A Vendor x GL Analysis'!$C25),IF(H$15="Actual",SUMIFS('[1]NS Vendor Details'!$D:$D,'[1]NS Vendor Details'!$H:$H,'G&A Vendor x GL Analysis'!H$20,'[1]NS Vendor Details'!$L:$L,'G&A Vendor x GL Analysis'!$D25,'[1]NS Vendor Details'!$O:$O,'G&A Vendor x GL Analysis'!$F25,'[1]NS Vendor Details'!$N:$N,'G&A Vendor x GL Analysis'!$C25,'[1]NS Vendor Details'!$K:$K,'G&A Vendor x GL Analysis'!$E$8),0)) -> 895.77 | I25: =IF(AND(I$15="Actual",ISBLANK($E$8)),SUMIFS('[1]NS Vendor Details'!$D:$D,'[1]NS Vendor Details'!$H:$H,'G&A Vendor x GL Analysis'!I$20,'[1]NS Vendor Details'!$L:$L,'G&A Vendor x GL Analysis'!$D25,'[1]NS Vendor Details'!$O:$O,'G&A Vendor x GL Analysis'!$F25,'[1]NS Vendor Details'!$N:$N,'G&A Vendor x GL Analysis'!$C25),IF(I$15="Actual",SUMIFS('[1]NS Vendor Details'!$D:$D,'[1]NS Vendor Details'!$H:$H,'G&A Vendor x GL Analysis'!I$20,'[1]NS Vendor Details'!$L:$L,'G&A Vendor x GL Analysis'!$D25,'[1]NS Vendor Details'!$O:$O,'G&A Vendor x GL Analysis'!$F25,'[1]NS Vendor Details'!$N:$N,'G&A Vendor x GL Analysis'!$C25,'[1]NS Vendor Details'!$K:$K,'G&A Vendor x GL Analysis'!$E$8),0)) -> 47270.03 | J25: =IF(AND(J$15="Actual",ISBLANK($E$8)),SUMIFS('[1]NS Vendor Details'!$D:$D,'[1]NS Vendor Details'!$H:$H,'G&A Vendor x GL Analysis'!J$20,'[1]NS Vendor Details'!$L:$L,'G&A Vendor x GL Analysis'!$D25,'[1]NS Vendor Details'!$O:$O,'G&A Vendor x GL Analysis'!$F25,'[1]NS Vendor Details'!$N:$N,'G&A Vendor x GL Analysis'!$C25),IF(J$15="Actual",SUMIFS('[1]NS Vendor Details'!$D:$D,'[1]NS Vendor Details'!$H:$H,'G&A Vendor x GL Analysis'!J$20,'[1]NS Vendor Details'!$L:$L,'G&A Vendor x GL Analysis'!$D25,'[1]NS Vendor Details'!$O:$O,'G&A Vendor x GL Analysis'!$F25,'[1]NS Vendor Details'!$N:$N,'G&A Vendor x GL Analysis'!$C25,'[1]NS Vendor Details'!$K:$K,'G&A Vendor x GL Analysis'!$E$8),0)) -> 37784.42 | K25: =IF(AND(K$15="Actual",ISBLANK($E$8)),SUMIFS('[1]NS Vendor Details'!$D:$D,'[1]NS Vendor Details'!$H:$H,'G&A Vendor x GL Analysis'!K$20,'[1]NS Vendor Details'!$L:$L,'G&A Vendor x GL Analysis'!$D25,'[1]NS Vendor Details'!$O:$O,'G&A Vendor x GL Analysis'!$F25,'[1]NS Vendor Details'!$N:$N,'G&A Vendor x GL Analysis'!$C25),IF(K$15="Actual",SUMIFS('[1]NS Vendor Details'!$D:$D,'[1]NS Vendor Details'!$H:$H,'G&A Vendor x GL Analysis'!K$20,'[1]NS Vendor Details'!$L:$L,'G&A Vendor x GL Analysis'!$D25,'[1]NS Vendor Details'!$O:$O,'G&A Vendor x GL Analysis'!$F25,'[1]NS Vendor Details'!$N:$N,'G&A Vendor x GL Analysis'!$C25,'[1]NS Vendor Details'!$K:$K,'G&A Vendor x GL Analysis'!$E$8),0)) -> 37718.04 | L25: =IF(AND(L$15="Actual",ISBLANK($E$8)),SUMIFS('[1]NS Vendor Details'!$D:$D,'[1]NS Vendor Details'!$H:$H,'G&A Vendor x GL Analysis'!L$20,'[1]NS Vendor Details'!$L:$L,'G&A Vendor x GL Analysis'!$D25,'[1]NS Vendor Details'!$O:$O,'G&A Vendor x GL Analysis'!$F25,'[1]NS Vendor Details'!$N:$N,'G&A Vendor x GL Analysis'!$C25),IF(L$15="Actual",SUMIFS('[1]NS Vendor Details'!$D:$D,'[1]NS Vendor Details'!$H:$H,'G&A Vendor x GL Analysis'!L$20,'[1]NS Vendor Details'!$L:$L,'G&A Vendor x GL Analysis'!$D25,'[1]NS Vendor Details'!$O:$O,'G&A Vendor x GL Analysis'!$F25,'[1]NS Vendor Details'!$N:$N,'G&A Vendor x GL Analysis'!$C25,'[1]NS Vendor Details'!$K:$K,'G&A Vendor x GL Analysis'!$E$8),0)) -> 40369.25 | M25: =IF(AND(M$15="Actual",ISBLANK($E$8)),SUMIFS('[1]NS Vendor Details'!$D:$D,'[1]NS Vendor Details'!$H:$H,'G&A Vendor x GL Analysis'!M$20,'[1]NS Vendor Details'!$L:$L,'G&A Vendor x GL Analysis'!$D25,'[1]NS Vendor Details'!$O:$O,'G&A Vendor x GL Analysis'!$F25,'[1]NS Vendor Details'!$N:$N,'G&A Vendor x GL Analysis'!$C25),IF(M$15="Actual",SUMIFS('[1]NS Vendor Details'!$D:$D,'[1]NS Vendor Details'!$H:$H,'G&A Vendor x GL Analysis'!M$20,'[1]NS Vendor Details'!$L:$L,'G&A Vendor x GL Analysis'!$D25,'[1]NS Vendor Details'!$O:$O,'G&A Vendor x GL Analysis'!$F25,'[1]NS Vendor Details'!$N:$N,'G&A Vendor x GL Analysis'!$C25,'[1]NS Vendor Details'!$K:$K,'G&A Vendor x GL Analysis'!$E$8),0)) -> 50892.76 | N25: =IF(AND(N$15="Actual",ISBLANK($E$8)),SUMIFS('[1]NS Vendor Details'!$D:$D,'[1]NS Vendor Details'!$H:$H,'G&A Vendor x GL Analysis'!N$20,'[1]NS Vendor Details'!$L:$L,'G&A Vendor x GL Analysis'!$D25,'[1]NS Vendor Details'!$O:$O,'G&A Vendor x GL Analysis'!$F25,'[1]NS Vendor Details'!$N:$N,'G&A Vendor x GL Analysis'!$C25),IF(N$15="Actual",SUMIFS('[1]NS Vendor Details'!$D:$D,'[1]NS Vendor Details'!$H:$H,'G&A Vendor x GL Analysis'!N$20,'[1]NS Vendor Details'!$L:$L,'G&A Vendor x GL Analysis'!$D25,'[1]NS Vendor Details'!$O:$O,'G&A Vendor x GL Analysis'!$F25,'[1]NS Vendor Details'!$N:$N,'G&A Vendor x GL Analysis'!$C25,'[1]NS Vendor Details'!$K:$K,'G&A Vendor x GL Analysis'!$E$8),0)) -> 54358.52 | ... R25: =IF(AND(R$15="Actual",ISBLANK($E$8)),SUMIFS('[1]NS Vendor Details'!$D:$D,'[1]NS Vendor Details'!$H:$H,'G&A Vendor x GL Analysis'!R$20,'[1]NS Vendor Details'!$L:$L,'G&A Vendor x GL Analysis'!$D25,'[1]NS Vendor Details'!$O:$O,'G&A Vendor x GL Analysis'!$F25,'[1]NS Vendor Details'!$N:$N,'G&A Vendor x GL Analysis'!$C25),IF(R$15="Actual",SUMIFS('[1]NS Vendor Details'!$D:$D,'[1]NS Vendor Details'!$H:$H,'G&A Vendor x GL Analysis'!R$20,'[1]NS Vendor Details'!$L:$L,'G&A Vendor x GL Analysis'!$D25,'[1]NS Vendor Details'!$O:$O,'G&A Vendor x GL Analysis'!$F25,'[1]NS Vendor Details'!$N:$N,'G&A Vendor x GL Analysis'!$C25,'[1]NS Vendor Details'!$K:$K,'G&A Vendor x GL Analysis'!$E$8),0)) -> 37431.61 | S25: =IF(AND(S$15="Actual",ISBLANK($E$8)),SUMIFS('[1]NS Vendor Details'!$D:$D,'[1]NS Vendor Details'!$H:$H,'G&A Vendor x GL Analysis'!S$20,'[1]NS Vendor Details'!$L:$L,'G&A Vendor x GL Analysis'!$D25,'[1]NS Vendor Details'!$O:$O,'G&A Vendor x GL Analysis'!$F25,'[1]NS Vendor Details'!$N:$N,'G&A Vendor x GL Analysis'!$C25,'[1]NS Vendor Details'!$I:$I,'G&A Vendor x GL Analysis'!$E25),IF(S$15="Actual",SUMIFS('[1]NS Vendor Details'!$D:$D,'[1]NS Vendor Details'!$H:$H,'G&A Vendor x GL Analysis'!S$20,'[1]NS Vendor Details'!$L:$L,'G&A Vendor x GL Analysis'!$D25,'[1]NS Vendor Details'!$O:$O,'G&A Vendor x GL Analysis'!$F25,'[1]NS Vendor Details'!$N:$N,'G&A Vendor x GL Analysis'!$C25,'[1]NS Vendor Details'!$K:$K,'G&A Vendor x GL Analysis'!$E$8,'[1]NS Vendor Details'!$I:$I,'G&A Vendor x GL Analysis'!$E25),0)) -> 0 | T25: =IF(AND(T$15="Actual",ISBLANK($E$8)),SUMIFS('[1]NS Vendor Details'!$D:$D,'[1]NS Vendor Details'!$H:$H,'G&A Vendor x GL Analysis'!T$20,'[1]NS Vendor Details'!$L:$L,'G&A Vendor x GL Analysis'!$D25,'[1]NS Vendor Details'!$O:$O,'G&A Vendor x GL Analysis'!$F25,'[1]NS Vendor Details'!$N:$N,'G&A Vendor x GL Analysis'!$C25,'[1]NS Vendor Details'!$I:$I,'G&A Vendor x GL Analysis'!$E25),IF(T$15="Actual",SUMIFS('[1]NS Vendor Details'!$D:$D,'[1]NS Vendor Details'!$H:$H,'G&A Vendor x GL Analysis'!T$20,'[1]NS Vendor Details'!$L:$L,'G&A Vendor x GL Analysis'!$D25,'[1]NS Vendor Details'!$O:$O,'G&A Vendor x GL Analysis'!$F25,'[1]NS Vendor Details'!$N:$N,'G&A Vendor x GL Analysis'!$C25,'[1]NS Vendor Details'!$K:$K,'G&A Vendor x GL Analysis'!$E$8,'[1]NS Vendor Details'!$I:$I,'G&A Vendor x GL Analysis'!$E25),0)) -> 0 | U25: =IF(AND(U$15="Actual",ISBLANK($E$8)),SUMIFS('[1]NS Vendor Details'!$D:$D,'[1]NS Vendor Details'!$H:$H,'G&A Vendor x GL Analysis'!U$20,'[1]NS Vendor Details'!$L:$L,'G&A Vendor x GL Analysis'!$D25,'[1]NS Vendor Details'!$O:$O,'G&A Vendor x GL Analysis'!$F25,'[1]NS Vendor Details'!$N:$N,'G&A Vendor x GL Analysis'!$C25,'[1]NS Vendor Details'!$I:$I,'G&A Vendor x GL Analysis'!$E25),IF(U$15="Actual",SUMIFS('[1]NS Vendor Details'!$D:$D,'[1]NS Vendor Details'!$H:$H,'G&A Vendor x GL Analysis'!U$20,'[1]NS Vendor Details'!$L:$L,'G&A Vendor x GL Analysis'!$D25,'[1]NS Vendor Details'!$O:$O,'G&A Vendor x GL Analysis'!$F25,'[1]NS Vendor Details'!$N:$N,'G&A Vendor x GL Analysis'!$C25,'[1]NS Vendor Details'!$K:$K,'G&A Vendor x GL Analysis'!$E$8,'[1]NS Vendor Details'!$I:$I,'G&A Vendor x GL Analysis'!$E25),0)) -> 50000 | V25: =IF(AND(V$15="Actual",ISBLANK($E$8)),SUMIFS('[1]NS Vendor Details'!$D:$D,'[1]NS Vendor Details'!$H:$H,'G&A Vendor x GL Analysis'!V$20,'[1]NS Vendor Details'!$L:$L,'G&A Vendor x GL Analysis'!$D25,'[1]NS Vendor Details'!$O:$O,'G&A Vendor x GL Analysis'!$F25,'[1]NS Vendor Details'!$N:$N,'G&A Vendor x GL Analysis'!$C25,'[1]NS Vendor Details'!$I:$I,'G&A Vendor x GL Analysis'!$E25),IF(V$15="Actual",SUMIFS('[1]NS Vendor Details'!$D:$D,'[1]NS Vendor Details'!$H:$H,'G&A Vendor x GL Analysis'!V$20,'[1]NS Vendor Details'!$L:$L,'G&A Vendor x GL Analysis'!$D25,'[1]NS Vendor Details'!$O:$O,'G&A Vendor x GL Analysis'!$F25,'[1]NS Vendor Details'!$N:$N,'G&A Vendor x GL Analysis'!$C25,'[1]NS Vendor Details'!$K:$K,'G&A Vendor x GL Analysis'!$E$8,'[1]NS Vendor Details'!$I:$I,'G&A Vendor x GL Analysis'!$E25),0)) -> 0 | W25: =IF(AND(W$15="Actual",ISBLANK($E$8)),SUMIFS('[1]NS Vendor Details'!$D:$D,'[1]NS Vendor Details'!$H:$H,'G&A Vendor x GL Analysis'!W$20,'[1]NS Vendor Details'!$L:$L,'G&A Vendor x GL Analysis'!$D25,'[1]NS Vendor Details'!$O:$O,'G&A Vendor x GL Analysis'!$F25,'[1]NS Vendor Details'!$N:$N,'G&A Vendor x GL Analysis'!$C25,'[1]NS Vendor Details'!$I:$I,'G&A Vendor x GL Analysis'!$E25),IF(W$15="Actual",SUMIFS('[1]NS Vendor Details'!$D:$D,'[1]NS Vendor Details'!$H:$H,'G&A Vendor x GL Analysis'!W$20,'[1]NS Vendor Details'!$L:$L,'G&A Vendor x GL Analysis'!$D25,'[1]NS Vendor Details'!$O:$O,'G&A Vendor x GL Analysis'!$F25,'[1]NS Vendor Details'!$N:$N,'G&A Vendor x GL Analysis'!$C25,'[1]NS Vendor Details'!$K:$K,'G&A Vendor x GL Analysis'!$E$8,'[1]NS Vendor Details'!$I:$I,'G&A Vendor x GL Analysis'!$E25),0)) -> 0 | X25: =IF(AND(X$15="Actual",ISBLANK($E$8)),SUMIFS('[1]NS Vendor Details'!$D:$D,'[1]NS Vendor Details'!$H:$H,'G&A Vendor x GL Analysis'!X$20,'[1]NS Vendor Details'!$L:$L,'G&A Vendor x GL Analysis'!$D25,'[1]NS Vendor Details'!$O:$O,'G&A Vendor x GL Analysis'!$F25,'[1]NS Vendor Details'!$N:$N,'G&A Vendor x GL Analysis'!$C25,'[1]NS Vendor Details'!$I:$I,'G&A Vendor x GL Analysis'!$E25),IF(X$15="Actual",SUMIFS('[1]NS Vendor Details'!$D:$D,'[1]NS Vendor Details'!$H:$H,'G&A Vendor x GL Analysis'!X$20,'[1]NS Vendor Details'!$L:$L,'G&A Vendor x GL Analysis'!$D25,'[1]NS Vendor Details'!$O:$O,'G&A Vendor x GL Analysis'!$F25,'[1]NS Vendor Details'!$N:$N,'G&A Vendor x GL Analysis'!$C25,'[1]NS Vendor Details'!$K:$K,'G&A Vendor x GL Analysis'!$E$8,'[1]NS Vendor Details'!$I:$I,'G&A Vendor x GL Analysis'!$E25),0)) -> 0 | Y25: =IF(AND(Y$15="Actual",ISBLANK($E$8)),SUMIFS('[1]NS Vendor Details'!$D:$D,'[1]NS Vendor Details'!$H:$H,'G&A Vendor x GL Analysis'!Y$20,'[1]NS Vendor Details'!$L:$L,'G&A Vendor x GL Analysis'!$D25,'[1]NS Vendor Details'!$O:$O,'G&A Vendor x GL Analysis'!$F25,'[1]NS Vendor Details'!$N:$N,'G&A Vendor x GL Analysis'!$C25,'[1]NS Vendor Details'!$I:$I,'G&A Vendor x GL Analysis'!$E25),IF(Y$15="Actual",SUMIFS('[1]NS Vendor Details'!$D:$D,'[1]NS Vendor Details'!$H:$H,'G&A Vendor x GL Analysis'!Y$20,'[1]NS Vendor Details'!$L:$L,'G&A Vendor x GL Analysis'!$D25,'[1]NS Vendor Details'!$O:$O,'G&A Vendor x GL Analysis'!$F25,'[1]NS Vendor Details'!$N:$N,'G&A Vendor x GL Analysis'!$C25,'[1]NS Vendor Details'!$K:$K,'G&A Vendor x GL Analysis'!$E$8,'[1]NS Vendor Details'!$I:$I,'G&A Vendor x GL Analysis'!$E25),0)) -> 0 | Z25: =IF(AND(Z$15="Actual",ISBLANK($E$8)),SUMIFS('[1]NS Vendor Details'!$D:$D,'[1]NS Vendor Details'!$H:$H,'G&A Vendor x GL Analysis'!Z$20,'[1]NS Vendor Details'!$L:$L,'G&A Vendor x GL Analysis'!$D25,'[1]NS Vendor Details'!$O:$O,'G&A Vendor x GL Analysis'!$F25,'[1]NS Vendor Details'!$N:$N,'G&A Vendor x GL Analysis'!$C25,'[1]NS Vendor Details'!$I:$I,'G&A Vendor x GL Analysis'!$E25),IF(Z$15="Actual",SUMIFS('[1]NS Vendor Details'!$D:$D,'[1]NS Vendor Details'!$H:$H,'G&A Vendor x GL Analysis'!Z$20,'[1]NS Vendor Details'!$L:$L,'G&A Vendor x GL Analysis'!$D25,'[1]NS Vendor Details'!$O:$O,'G&A Vendor x GL Analysis'!$F25,'[1]NS Vendor Details'!$N:$N,'G&A Vendor x GL Analysis'!$C25,'[1]NS Vendor Details'!$K:$K,'G&A Vendor x GL Analysis'!$E$8,'[1]NS Vendor Details'!$I:$I,'G&A Vendor x GL Analysis'!$E25),0)) -> 0 | ... AD25: =IF(AND(AD$15="Actual",ISBLANK($E$8)),SUMIFS('[1]NS Vendor Details'!$D:$D,'[1]NS Vendor Details'!$H:$H,'G&A Vendor x GL Analysis'!AD$20,'[1]NS Vendor Details'!$L:$L,'G&A Vendor x GL Analysis'!$D25,'[1]NS Vendor Details'!$O:$O,'G&A Vendor x GL Analysis'!$F25,'[1]NS Vendor Details'!$N:$N,'G&A Vendor x GL Analysis'!$C25,'[1]NS Vendor Details'!$I:$I,'G&A Vendor x GL Analysis'!$E25),IF(AD$15="Actual",SUMIFS('[1]NS Vendor Details'!$D:$D,'[1]NS Vendor Details'!$H:$H,'G&A Vendor x GL Analysis'!AD$20,'[1]NS Vendor Details'!$L:$L,'G&A Vendor x GL Analysis'!$D25,'[1]NS Vendor Details'!$O:$O,'G&A Vendor x GL Analysis'!$F25,'[1]NS Vendor Details'!$N:$N,'G&A Vendor x GL Analysis'!$C25,'[1]NS Vendor Details'!$K:$K,'G&A Vendor x GL Analysis'!$E$8,'[1]NS Vendor Details'!$I:$I,'G&A Vendor x GL Analysis'!$E25),0)) -> 0 | AF25: =ABS(S25)+ABS(T25)+ABS(U25)+ABS(V25)+ABS(W25)+ABS(X25)+ABS(Y25)+ABS(Z25)+ABS(AA25)+ABS(AB25)+ABS(AC25)+ABS(AD25) -> 50000
A26: =D26&E26 -> Advertising6282 - Royalty Expense | C26: SG&A | D26: =D25 -> Advertising | E26: 6282 - Royalty Expense | F26: Monte Carlo Country Club | G26: =IF(AND(G$15="Actual",ISBLANK($E$8)),SUMIFS('[1]NS Vendor Details'!$D:$D,'[1]NS Vendor Details'!$H:$H,'G&A Vendor x GL Analysis'!G$20,'[1]NS Vendor Details'!$L:$L,'G&A Vendor x GL Analysis'!$D26,'[1]NS Vendor Details'!$O:$O,'G&A Vendor x GL Analysis'!$F26,'[1]NS Vendor Details'!$N:$N,'G&A Vendor x GL Analysis'!$C26),IF(G$15="Actual",SUMIFS('[1]NS Vendor Details'!$D:$D,'[1]NS Vendor Details'!$H:$H,'G&A Vendor x GL Analysis'!G$20,'[1]NS Vendor Details'!$L:$L,'G&A Vendor x GL Analysis'!$D26,'[1]NS Vendor Details'!$O:$O,'G&A Vendor x GL Analysis'!$F26,'[1]NS Vendor Details'!$N:$N,'G&A Vendor x GL Analysis'!$C26,'[1]NS Vendor Details'!$K:$K,'G&A Vendor x GL Analysis'!$E$8),0)) -> 0 | H26: =IF(AND(H$15="Actual",ISBLANK($E$8)),SUMIFS('[1]NS Vendor Details'!$D:$D,'[1]NS Vendor Details'!$H:$H,'G&A Vendor x GL Analysis'!H$20,'[1]NS Vendor Details'!$L:$L,'G&A Vendor x GL Analysis'!$D26,'[1]NS Vendor Details'!$O:$O,'G&A Vendor x GL Analysis'!$F26,'[1]NS Vendor Details'!$N:$N,'G&A Vendor x GL Analysis'!$C26),IF(H$15="Actual",SUMIFS('[1]NS Vendor Details'!$D:$D,'[1]NS Vendor Details'!$H:$H,'G&A Vendor x GL Analysis'!H$20,'[1]NS Vendor Details'!$L:$L,'G&A Vendor x GL Analysis'!$D26,'[1]NS Vendor Details'!$O:$O,'G&A Vendor x GL Analysis'!$F26,'[1]NS Vendor Details'!$N:$N,'G&A Vendor x GL Analysis'!$C26,'[1]NS Vendor Details'!$K:$K,'G&A Vendor x GL Analysis'!$E$8),0)) -> 0 | I26: =IF(AND(I$15="Actual",ISBLANK($E$8)),SUMIFS('[1]NS Vendor Details'!$D:$D,'[1]NS Vendor Details'!$H:$H,'G&A Vendor x GL Analysis'!I$20,'[1]NS Vendor Details'!$L:$L,'G&A Vendor x GL Analysis'!$D26,'[1]NS Vendor Details'!$O:$O,'G&A Vendor x GL Analysis'!$F26,'[1]NS Vendor Details'!$N:$N,'G&A Vendor x GL Analysis'!$C26),IF(I$15="Actual",SUMIFS('[1]NS Vendor Details'!$D:$D,'[1]NS Vendor Details'!$H:$H,'G&A Vendor x GL Analysis'!I$20,'[1]NS Vendor Details'!$L:$L,'G&A Vendor x GL Analysis'!$D26,'[1]NS Vendor Details'!$O:$O,'G&A Vendor x GL Analysis'!$F26,'[1]NS Vendor Details'!$N:$N,'G&A Vendor x GL Analysis'!$C26,'[1]NS Vendor Details'!$K:$K,'G&A Vendor x GL Analysis'!$E$8),0)) -> 0 | J26: =IF(AND(J$15="Actual",ISBLANK($E$8)),SUMIFS('[1]NS Vendor Details'!$D:$D,'[1]NS Vendor Details'!$H:$H,'G&A Vendor x GL Analysis'!J$20,'[1]NS Vendor Details'!$L:$L,'G&A Vendor x GL Analysis'!$D26,'[1]NS Vendor Details'!$O:$O,'G&A Vendor x GL Analysis'!$F26,'[1]NS Vendor Details'!$N:$N,'G&A Vendor x GL Analysis'!$C26),IF(J$15="Actual",SUMIFS('[1]NS Vendor Details'!$D:$D,'[1]NS Vendor Details'!$H:$H,'G&A Vendor x GL Analysis'!J$20,'[1]NS Vendor Details'!$L:$L,'G&A Vendor x GL Analysis'!$D26,'[1]NS Vendor Details'!$O:$O,'G&A Vendor x GL Analysis'!$F26,'[1]NS Vendor Details'!$N:$N,'G&A Vendor x GL Analysis'!$C26,'[1]NS Vendor Details'!$K:$K,'G&A Vendor x GL Analysis'!$E$8),0)) -> 0 | K26: =IF(AND(K$15="Actual",ISBLANK($E$8)),SUMIFS('[1]NS Vendor Details'!$D:$D,'[1]NS Vendor Details'!$H:$H,'G&A Vendor x GL Analysis'!K$20,'[1]NS Vendor Details'!$L:$L,'G&A Vendor x GL Analysis'!$D26,'[1]NS Vendor Details'!$O:$O,'G&A Vendor x GL Analysis'!$F26,'[1]NS Vendor Details'!$N:$N,'G&A Vendor x GL Analysis'!$C26),IF(K$15="Actual",SUMIFS('[1]NS Vendor Details'!$D:$D,'[1]NS Vendor Details'!$H:$H,'G&A Vendor x GL Analysis'!K$20,'[1]NS Vendor Details'!$L:$L,'G&A Vendor x GL Analysis'!$D26,'[1]NS Vendor Details'!$O:$O,'G&A Vendor x GL Analysis'!$F26,'[1]NS Vendor Details'!$N:$N,'G&A Vendor x GL Analysis'!$C26,'[1]NS Vendor Details'!$K:$K,'G&A Vendor x GL Analysis'!$E$8),0)) -> 16267.2 | L26: =IF(AND(L$15="Actual",ISBLANK($E$8)),SUMIFS('[1]NS Vendor Details'!$D:$D,'[1]NS Vendor Details'!$H:$H,'G&A Vendor x GL Analysis'!L$20,'[1]NS Vendor Details'!$L:$L,'G&A Vendor x GL Analysis'!$D26,'[1]NS Vendor Details'!$O:$O,'G&A Vendor x GL Analysis'!$F26,'[1]NS Vendor Details'!$N:$N,'G&A Vendor x GL Analysis'!$C26),IF(L$15="Actual",SUMIFS('[1]NS Vendor Details'!$D:$D,'[1]NS Vendor Details'!$H:$H,'G&A Vendor x GL Analysis'!L$20,'[1]NS Vendor Details'!$L:$L,'G&A Vendor x GL Analysis'!$D26,'[1]NS Vendor Details'!$O:$O,'G&A Vendor x GL Analysis'!$F26,'[1]NS Vendor Details'!$N:$N,'G&A Vendor x GL Analysis'!$C26,'[1]NS Vendor Details'!$K:$K,'G&A Vendor x GL Analysis'!$E$8),0)) -> 0 | M26: =IF(AND(M$15="Actual",ISBLANK($E$8)),SUMIFS('[1]NS Vendor Details'!$D:$D,'[1]NS Vendor Details'!$H:$H,'G&A Vendor x GL Analysis'!M$20,'[1]NS Vendor Details'!$L:$L,'G&A Vendor x GL Analysis'!$D26,'[1]NS Vendor Details'!$O:$O,'G&A Vendor x GL Analysis'!$F26,'[1]NS Vendor Details'!$N:$N,'G&A Vendor x GL Analysis'!$C26),IF(M$15="Actual",SUMIFS('[1]NS Vendor Details'!$D:$D,'[1]NS Vendor Details'!$H:$H,'G&A Vendor x GL Analysis'!M$20,'[1]NS Vendor Details'!$L:$L,'G&A Vendor x GL Analysis'!$D26,'[1]NS Vendor Details'!$O:$O,'G&A Vendor x GL Analysis'!$F26,'[1]NS Vendor Details'!$N:$N,'G&A Vendor x GL Analysis'!$C26,'[1]NS Vendor Details'!$K:$K,'G&A Vendor x GL Analysis'!$E$8),0)) -> 0 | N26: =IF(AND(N$15="Actual",ISBLANK($E$8)),SUMIFS('[1]NS Vendor Details'!$D:$D,'[1]NS Vendor Details'!$H:$H,'G&A Vendor x GL Analysis'!N$20,'[1]NS Vendor Details'!$L:$L,'G&A Vendor x GL Analysis'!$D26,'[1]NS Vendor Details'!$O:$O,'G&A Vendor x GL Analysis'!$F26,'[1]NS Vendor Details'!$N:$N,'G&A Vendor x GL Analysis'!$C26),IF(N$15="Actual",SUMIFS('[1]NS Vendor Details'!$D:$D,'[1]NS Vendor Details'!$H:$H,'G&A Vendor x GL Analysis'!N$20,'[1]NS Vendor Details'!$L:$L,'G&A Vendor x GL Analysis'!$D26,'[1]NS Vendor Details'!$O:$O,'G&A Vendor x GL Analysis'!$F26,'[1]NS Vendor Details'!$N:$N,'G&A Vendor x GL Analysis'!$C26,'[1]NS Vendor Details'!$K:$K,'G&A Vendor x GL Analysis'!$E$8),0)) -> 0 | ... R26: =IF(AND(R$15="Actual",ISBLANK($E$8)),SUMIFS('[1]NS Vendor Details'!$D:$D,'[1]NS Vendor Details'!$H:$H,'G&A Vendor x GL Analysis'!R$20,'[1]NS Vendor Details'!$L:$L,'G&A Vendor x GL Analysis'!$D26,'[1]NS Vendor Details'!$O:$O,'G&A Vendor x GL Analysis'!$F26,'[1]NS Vendor Details'!$N:$N,'G&A Vendor x GL Analysis'!$C26),IF(R$15="Actual",SUMIFS('[1]NS Vendor Details'!$D:$D,'[1]NS Vendor Details'!$H:$H,'G&A Vendor x GL Analysis'!R$20,'[1]NS Vendor Details'!$L:$L,'G&A Vendor x GL Analysis'!$D26,'[1]NS Vendor Details'!$O:$O,'G&A Vendor x GL Analysis'!$F26,'[1]NS Vendor Details'!$N:$N,'G&A Vendor x GL Analysis'!$C26,'[1]NS Vendor Details'!$K:$K,'G&A Vendor x GL Analysis'!$E$8),0)) -> 0 | S26: =IF(AND(S$15="Actual",ISBLANK($E$8)),SUMIFS('[1]NS Vendor Details'!$D:$D,'[1]NS Vendor Details'!$H:$H,'G&A Vendor x GL Analysis'!S$20,'[1]NS Vendor Details'!$L:$L,'G&A Vendor x GL Analysis'!$D26,'[1]NS Vendor Details'!$O:$O,'G&A Vendor x GL Analysis'!$F26,'[1]NS Vendor Details'!$N:$N,'G&A Vendor x GL Analysis'!$C26,'[1]NS Vendor Details'!$I:$I,'G&A Vendor x GL Analysis'!$E26),IF(S$15="Actual",SUMIFS('[1]NS Vendor Details'!$D:$D,'[1]NS Vendor Details'!$H:$H,'G&A Vendor x GL Analysis'!S$20,'[1]NS Vendor Details'!$L:$L,'G&A Vendor x GL Analysis'!$D26,'[1]NS Vendor Details'!$O:$O,'G&A Vendor x GL Analysis'!$F26,'[1]NS Vendor Details'!$N:$N,'G&A Vendor x GL Analysis'!$C26,'[1]NS Vendor Details'!$K:$K,'G&A Vendor x GL Analysis'!$E$8,'[1]NS Vendor Details'!$I:$I,'G&A Vendor x GL Analysis'!$E26),0)) -> 0 | T26: =IF(AND(T$15="Actual",ISBLANK($E$8)),SUMIFS('[1]NS Vendor Details'!$D:$D,'[1]NS Vendor Details'!$H:$H,'G&A Vendor x GL Analysis'!T$20,'[1]NS Vendor Details'!$L:$L,'G&A Vendor x GL Analysis'!$D26,'[1]NS Vendor Details'!$O:$O,'G&A Vendor x GL Analysis'!$F26,'[1]NS Vendor Details'!$N:$N,'G&A Vendor x GL Analysis'!$C26,'[1]NS Vendor Details'!$I:$I,'G&A Vendor x GL Analysis'!$E26),IF(T$15="Actual",SUMIFS('[1]NS Vendor Details'!$D:$D,'[1]NS Vendor Details'!$H:$H,'G&A Vendor x GL Analysis'!T$20,'[1]NS Vendor Details'!$L:$L,'G&A Vendor x GL Analysis'!$D26,'[1]NS Vendor Details'!$O:$O,'G&A Vendor x GL Analysis'!$F26,'[1]NS Vendor Details'!$N:$N,'G&A Vendor x GL Analysis'!$C26,'[1]NS Vendor Details'!$K:$K,'G&A Vendor x GL Analysis'!$E$8,'[1]NS Vendor Details'!$I:$I,'G&A Vendor x GL Analysis'!$E26),0)) -> 20718.4 | U26: =IF(AND(U$15="Actual",ISBLANK($E$8)),SUMIFS('[1]NS Vendor Details'!$D:$D,'[1]NS Vendor Details'!$H:$H,'G&A Vendor x GL Analysis'!U$20,'[1]NS Vendor Details'!$L:$L,'G&A Vendor x GL Analysis'!$D26,'[1]NS Vendor Details'!$O:$O,'G&A Vendor x GL Analysis'!$F26,'[1]NS Vendor Details'!$N:$N,'G&A Vendor x GL Analysis'!$C26,'[1]NS Vendor Details'!$I:$I,'G&A Vendor x GL Analysis'!$E26),IF(U$15="Actual",SUMIFS('[1]NS Vendor Details'!$D:$D,'[1]NS Vendor Details'!$H:$H,'G&A Vendor x GL Analysis'!U$20,'[1]NS Vendor Details'!$L:$L,'G&A Vendor x GL Analysis'!$D26,'[1]NS Vendor Details'!$O:$O,'G&A Vendor x GL Analysis'!$F26,'[1]NS Vendor Details'!$N:$N,'G&A Vendor x GL Analysis'!$C26,'[1]NS Vendor Details'!$K:$K,'G&A Vendor x GL Analysis'!$E$8,'[1]NS Vendor Details'!$I:$I,'G&A Vendor x GL Analysis'!$E26),0)) -> 0 | V26: =IF(AND(V$15="Actual",ISBLANK($E$8)),SUMIFS('[1]NS Vendor Details'!$D:$D,'[1]NS Vendor Details'!$H:$H,'G&A Vendor x GL Analysis'!V$20,'[1]NS Vendor Details'!$L:$L,'G&A Vendor x GL Analysis'!$D26,'[1]NS Vendor Details'!$O:$O,'G&A Vendor x GL Analysis'!$F26,'[1]NS Vendor Details'!$N:$N,'G&A Vendor x GL Analysis'!$C26,'[1]NS Vendor Details'!$I:$I,'G&A Vendor x GL Analysis'!$E26),IF(V$15="Actual",SUMIFS('[1]NS Vendor Details'!$D:$D,'[1]NS Vendor Details'!$H:$H,'G&A Vendor x GL Analysis'!V$20,'[1]NS Vendor Details'!$L:$L,'G&A Vendor x GL Analysis'!$D26,'[1]NS Vendor Details'!$O:$O,'G&A Vendor x GL Analysis'!$F26,'[1]NS Vendor Details'!$N:$N,'G&A Vendor x GL Analysis'!$C26,'[1]NS Vendor Details'!$K:$K,'G&A Vendor x GL Analysis'!$E$8,'[1]NS Vendor Details'!$I:$I,'G&A Vendor x GL Analysis'!$E26),0)) -> 0 | W26: =IF(AND(W$15="Actual",ISBLANK($E$8)),SUMIFS('[1]NS Vendor Details'!$D:$D,'[1]NS Vendor Details'!$H:$H,'G&A Vendor x GL Analysis'!W$20,'[1]NS Vendor Details'!$L:$L,'G&A Vendor x GL Analysis'!$D26,'[1]NS Vendor Details'!$O:$O,'G&A Vendor x GL Analysis'!$F26,'[1]NS Vendor Details'!$N:$N,'G&A Vendor x GL Analysis'!$C26,'[1]NS Vendor Details'!$I:$I,'G&A Vendor x GL Analysis'!$E26),IF(W$15="Actual",SUMIFS('[1]NS Vendor Details'!$D:$D,'[1]NS Vendor Details'!$H:$H,'G&A Vendor x GL Analysis'!W$20,'[1]NS Vendor Details'!$L:$L,'G&A Vendor x GL Analysis'!$D26,'[1]NS Vendor Details'!$O:$O,'G&A Vendor x GL Analysis'!$F26,'[1]NS Vendor Details'!$N:$N,'G&A Vendor x GL Analysis'!$C26,'[1]NS Vendor Details'!$K:$K,'G&A Vendor x GL Analysis'!$E$8,'[1]NS Vendor Details'!$I:$I,'G&A Vendor x GL Analysis'!$E26),0)) -> 0 | X26: =IF(AND(X$15="Actual",ISBLANK($E$8)),SUMIFS('[1]NS Vendor Details'!$D:$D,'[1]NS Vendor Details'!$H:$H,'G&A Vendor x GL Analysis'!X$20,'[1]NS Vendor Details'!$L:$L,'G&A Vendor x GL Analysis'!$D26,'[1]NS Vendor Details'!$O:$O,'G&A Vendor x GL Analysis'!$F26,'[1]NS Vendor Details'!$N:$N,'G&A Vendor x GL Analysis'!$C26,'[1]NS Vendor Details'!$I:$I,'G&A Vendor x GL Analysis'!$E26),IF(X$15="Actual",SUMIFS('[1]NS Vendor Details'!$D:$D,'[1]NS Vendor Details'!$H:$H,'G&A Vendor x GL Analysis'!X$20,'[1]NS Vendor Details'!$L:$L,'G&A Vendor x GL Analysis'!$D26,'[1]NS Vendor Details'!$O:$O,'G&A Vendor x GL Analysis'!$F26,'[1]NS Vendor Details'!$N:$N,'G&A Vendor x GL Analysis'!$C26,'[1]NS Vendor Details'!$K:$K,'G&A Vendor x GL Analysis'!$E$8,'[1]NS Vendor Details'!$I:$I,'G&A Vendor x GL Analysis'!$E26),0)) -> 0 | Y26: =IF(AND(Y$15="Actual",ISBLANK($E$8)),SUMIFS('[1]NS Vendor Details'!$D:$D,'[1]NS Vendor Details'!$H:$H,'G&A Vendor x GL Analysis'!Y$20,'[1]NS Vendor Details'!$L:$L,'G&A Vendor x GL Analysis'!$D26,'[1]NS Vendor Details'!$O:$O,'G&A Vendor x GL Analysis'!$F26,'[1]NS Vendor Details'!$N:$N,'G&A Vendor x GL Analysis'!$C26,'[1]NS Vendor Details'!$I:$I,'G&A Vendor x GL Analysis'!$E26),IF(Y$15="Actual",SUMIFS('[1]NS Vendor Details'!$D:$D,'[1]NS Vendor Details'!$H:$H,'G&A Vendor x GL Analysis'!Y$20,'[1]NS Vendor Details'!$L:$L,'G&A Vendor x GL Analysis'!$D26,'[1]NS Vendor Details'!$O:$O,'G&A Vendor x GL Analysis'!$F26,'[1]NS Vendor Details'!$N:$N,'G&A Vendor x GL Analysis'!$C26,'[1]NS Vendor Details'!$K:$K,'G&A Vendor x GL Analysis'!$E$8,'[1]NS Vendor Details'!$I:$I,'G&A Vendor x GL Analysis'!$E26),0)) -> 0 | Z26: =IF(AND(Z$15="Actual",ISBLANK($E$8)),SUMIFS('[1]NS Vendor Details'!$D:$D,'[1]NS Vendor Details'!$H:$H,'G&A Vendor x GL Analysis'!Z$20,'[1]NS Vendor Details'!$L:$L,'G&A Vendor x GL Analysis'!$D26,'[1]NS Vendor Details'!$O:$O,'G&A Vendor x GL Analysis'!$F26,'[1]NS Vendor Details'!$N:$N,'G&A Vendor x GL Analysis'!$C26,'[1]NS Vendor Details'!$I:$I,'G&A Vendor x GL Analysis'!$E26),IF(Z$15="Actual",SUMIFS('[1]NS Vendor Details'!$D:$D,'[1]NS Vendor Details'!$H:$H,'G&A Vendor x GL Analysis'!Z$20,'[1]NS Vendor Details'!$L:$L,'G&A Vendor x GL Analysis'!$D26,'[1]NS Vendor Details'!$O:$O,'G&A Vendor x GL Analysis'!$F26,'[1]NS Vendor Details'!$N:$N,'G&A Vendor x GL Analysis'!$C26,'[1]NS Vendor Details'!$K:$K,'G&A Vendor x GL Analysis'!$E$8,'[1]NS Vendor Details'!$I:$I,'G&A Vendor x GL Analysis'!$E26),0)) -> 0 | ... AD26: =IF(AND(AD$15="Actual",ISBLANK($E$8)),SUMIFS('[1]NS Vendor Details'!$D:$D,'[1]NS Vendor Details'!$H:$H,'G&A Vendor x GL Analysis'!AD$20,'[1]NS Vendor Details'!$L:$L,'G&A Vendor x GL Analysis'!$D26,'[1]NS Vendor Details'!$O:$O,'G&A Vendor x GL Analysis'!$F26,'[1]NS Vendor Details'!$N:$N,'G&A Vendor x GL Analysis'!$C26,'[1]NS Vendor Details'!$I:$I,'G&A Vendor x GL Analysis'!$E26),IF(AD$15="Actual",SUMIFS('[1]NS Vendor Details'!$D:$D,'[1]NS Vendor Details'!$H:$H,'G&A Vendor x GL Analysis'!AD$20,'[1]NS Vendor Details'!$L:$L,'G&A Vendor x GL Analysis'!$D26,'[1]NS Vendor Details'!$O:$O,'G&A Vendor x GL Analysis'!$F26,'[1]NS Vendor Details'!$N:$N,'G&A Vendor x GL Analysis'!$C26,'[1]NS Vendor Details'!$K:$K,'G&A Vendor x GL Analysis'!$E$8,'[1]NS Vendor Details'!$I:$I,'G&A Vendor x GL Analysis'!$E26),0)) -> 0 | AF26: =ABS(S26)+ABS(T26)+ABS(U26)+ABS(V26)+ABS(W26)+ABS(X26)+ABS(Y26)+ABS(Z26)+ABS(AA26)+ABS(AB26)+ABS(AC26)+ABS(AD26) -> 20718.4
A27: =D27&E27 -> Advertising6282 - Royalty Expense | C27: SG&A | D27: =D26 -> Advertising | E27: 6282 - Royalty Expense | F27: [No Vendor] | G27: =IF(AND(G$15="Actual",ISBLANK($E$8)),SUMIFS('[1]NS Vendor Details'!$D:$D,'[1]NS Vendor Details'!$H:$H,'G&A Vendor x GL Analysis'!G$20,'[1]NS Vendor Details'!$L:$L,'G&A Vendor x GL Analysis'!$D27,'[1]NS Vendor Details'!$O:$O,'G&A Vendor x GL Analysis'!$F27,'[1]NS Vendor Details'!$N:$N,'G&A Vendor x GL Analysis'!$C27),IF(G$15="Actual",SUMIFS('[1]NS Vendor Details'!$D:$D,'[1]NS Vendor Details'!$H:$H,'G&A Vendor x GL Analysis'!G$20,'[1]NS Vendor Details'!$L:$L,'G&A Vendor x GL Analysis'!$D27,'[1]NS Vendor Details'!$O:$O,'G&A Vendor x GL Analysis'!$F27,'[1]NS Vendor Details'!$N:$N,'G&A Vendor x GL Analysis'!$C27,'[1]NS Vendor Details'!$K:$K,'G&A Vendor x GL Analysis'!$E$8),0)) -> -19852.71 | H27: =IF(AND(H$15="Actual",ISBLANK($E$8)),SUMIFS('[1]NS Vendor Details'!$D:$D,'[1]NS Vendor Details'!$H:$H,'G&A Vendor x GL Analysis'!H$20,'[1]NS Vendor Details'!$L:$L,'G&A Vendor x GL Analysis'!$D27,'[1]NS Vendor Details'!$O:$O,'G&A Vendor x GL Analysis'!$F27,'[1]NS Vendor Details'!$N:$N,'G&A Vendor x GL Analysis'!$C27),IF(H$15="Actual",SUMIFS('[1]NS Vendor Details'!$D:$D,'[1]NS Vendor Details'!$H:$H,'G&A Vendor x GL Analysis'!H$20,'[1]NS Vendor Details'!$L:$L,'G&A Vendor x GL Analysis'!$D27,'[1]NS Vendor Details'!$O:$O,'G&A Vendor x GL Analysis'!$F27,'[1]NS Vendor Details'!$N:$N,'G&A Vendor x GL Analysis'!$C27,'[1]NS Vendor Details'!$K:$K,'G&A Vendor x GL Analysis'!$E$8),0)) -> 895.77 | I27: =IF(AND(I$15="Actual",ISBLANK($E$8)),SUMIFS('[1]NS Vendor Details'!$D:$D,'[1]NS Vendor Details'!$H:$H,'G&A Vendor x GL Analysis'!I$20,'[1]NS Vendor Details'!$L:$L,'G&A Vendor x GL Analysis'!$D27,'[1]NS Vendor Details'!$O:$O,'G&A Vendor x GL Analysis'!$F27,'[1]NS Vendor Details'!$N:$N,'G&A Vendor x GL Analysis'!$C27),IF(I$15="Actual",SUMIFS('[1]NS Vendor Details'!$D:$D,'[1]NS Vendor Details'!$H:$H,'G&A Vendor x GL Analysis'!I$20,'[1]NS Vendor Details'!$L:$L,'G&A Vendor x GL Analysis'!$D27,'[1]NS Vendor Details'!$O:$O,'G&A Vendor x GL Analysis'!$F27,'[1]NS Vendor Details'!$N:$N,'G&A Vendor x GL Analysis'!$C27,'[1]NS Vendor Details'!$K:$K,'G&A Vendor x GL Analysis'!$E$8),0)) -> 47270.03 | J27: =IF(AND(J$15="Actual",ISBLANK($E$8)),SUMIFS('[1]NS Vendor Details'!$D:$D,'[1]NS Vendor Details'!$H:$H,'G&A Vendor x GL Analysis'!J$20,'[1]NS Vendor Details'!$L:$L,'G&A Vendor x GL Analysis'!$D27,'[1]NS Vendor Details'!$O:$O,'G&A Vendor x GL Analysis'!$F27,'[1]NS Vendor Details'!$N:$N,'G&A Vendor x GL Analysis'!$C27),IF(J$15="Actual",SUMIFS('[1]NS Vendor Details'!$D:$D,'[1]NS Vendor Details'!$H:$H,'G&A Vendor x GL Analysis'!J$20,'[1]NS Vendor Details'!$L:$L,'G&A Vendor x GL Analysis'!$D27,'[1]NS Vendor Details'!$O:$O,'G&A Vendor x GL Analysis'!$F27,'[1]NS Vendor Details'!$N:$N,'G&A Vendor x GL Analysis'!$C27,'[1]NS Vendor Details'!$K:$K,'G&A Vendor x GL Analysis'!$E$8),0)) -> 37784.42 | K27: =IF(AND(K$15="Actual",ISBLANK($E$8)),SUMIFS('[1]NS Vendor Details'!$D:$D,'[1]NS Vendor Details'!$H:$H,'G&A Vendor x GL Analysis'!K$20,'[1]NS Vendor Details'!$L:$L,'G&A Vendor x GL Analysis'!$D27,'[1]NS Vendor Details'!$O:$O,'G&A Vendor x GL Analysis'!$F27,'[1]NS Vendor Details'!$N:$N,'G&A Vendor x GL Analysis'!$C27),IF(K$15="Actual",SUMIFS('[1]NS Vendor Details'!$D:$D,'[1]NS Vendor Details'!$H:$H,'G&A Vendor x GL Analysis'!K$20,'[1]NS Vendor Details'!$L:$L,'G&A Vendor x GL Analysis'!$D27,'[1]NS Vendor Details'!$O:$O,'G&A Vendor x GL Analysis'!$F27,'[1]NS Vendor Details'!$N:$N,'G&A Vendor x GL Analysis'!$C27,'[1]NS Vendor Details'!$K:$K,'G&A Vendor x GL Analysis'!$E$8),0)) -> 37718.04 | L27: =IF(AND(L$15="Actual",ISBLANK($E$8)),SUMIFS('[1]NS Vendor Details'!$D:$D,'[1]NS Vendor Details'!$H:$H,'G&A Vendor x GL Analysis'!L$20,'[1]NS Vendor Details'!$L:$L,'G&A Vendor x GL Analysis'!$D27,'[1]NS Vendor Details'!$O:$O,'G&A Vendor x GL Analysis'!$F27,'[1]NS Vendor Details'!$N:$N,'G&A Vendor x GL Analysis'!$C27),IF(L$15="Actual",SUMIFS('[1]NS Vendor Details'!$D:$D,'[1]NS Vendor Details'!$H:$H,'G&A Vendor x GL Analysis'!L$20,'[1]NS Vendor Details'!$L:$L,'G&A Vendor x GL Analysis'!$D27,'[1]NS Vendor Details'!$O:$O,'G&A Vendor x GL Analysis'!$F27,'[1]NS Vendor Details'!$N:$N,'G&A Vendor x GL Analysis'!$C27,'[1]NS Vendor Details'!$K:$K,'G&A Vendor x GL Analysis'!$E$8),0)) -> 40369.25 | M27: =IF(AND(M$15="Actual",ISBLANK($E$8)),SUMIFS('[1]NS Vendor Details'!$D:$D,'[1]NS Vendor Details'!$H:$H,'G&A Vendor x GL Analysis'!M$20,'[1]NS Vendor Details'!$L:$L,'G&A Vendor x GL Analysis'!$D27,'[1]NS Vendor Details'!$O:$O,'G&A Vendor x GL Analysis'!$F27,'[1]NS Vendor Details'!$N:$N,'G&A Vendor x GL Analysis'!$C27),IF(M$15="Actual",SUMIFS('[1]NS Vendor Details'!$D:$D,'[1]NS Vendor Details'!$H:$H,'G&A Vendor x GL Analysis'!M$20,'[1]NS Vendor Details'!$L:$L,'G&A Vendor x GL Analysis'!$D27,'[1]NS Vendor Details'!$O:$O,'G&A Vendor x GL Analysis'!$F27,'[1]NS Vendor Details'!$N:$N,'G&A Vendor x GL Analysis'!$C27,'[1]NS Vendor Details'!$K:$K,'G&A Vendor x GL Analysis'!$E$8),0)) -> 50892.76 | N27: =IF(AND(N$15="Actual",ISBLANK($E$8)),SUMIFS('[1]NS Vendor Details'!$D:$D,'[1]NS Vendor Details'!$H:$H,'G&A Vendor x GL Analysis'!N$20,'[1]NS Vendor Details'!$L:$L,'G&A Vendor x GL Analysis'!$D27,'[1]NS Vendor Details'!$O:$O,'G&A Vendor x GL Analysis'!$F27,'[1]NS Vendor Details'!$N:$N,'G&A Vendor x GL Analysis'!$C27),IF(N$15="Actual",SUMIFS('[1]NS Vendor Details'!$D:$D,'[1]NS Vendor Details'!$H:$H,'G&A Vendor x GL Analysis'!N$20,'[1]NS Vendor Details'!$L:$L,'G&A Vendor x GL Analysis'!$D27,'[1]NS Vendor Details'!$O:$O,'G&A Vendor x GL Analysis'!$F27,'[1]NS Vendor Details'!$N:$N,'G&A Vendor x GL Analysis'!$C27,'[1]NS Vendor Details'!$K:$K,'G&A Vendor x GL Analysis'!$E$8),0)) -> 54358.52 | ... R27: =IF(AND(R$15="Actual",ISBLANK($E$8)),SUMIFS('[1]NS Vendor Details'!$D:$D,'[1]NS Vendor Details'!$H:$H,'G&A Vendor x GL Analysis'!R$20,'[1]NS Vendor Details'!$L:$L,'G&A Vendor x GL Analysis'!$D27,'[1]NS Vendor Details'!$O:$O,'G&A Vendor x GL Analysis'!$F27,'[1]NS Vendor Details'!$N:$N,'G&A Vendor x GL Analysis'!$C27),IF(R$15="Actual",SUMIFS('[1]NS Vendor Details'!$D:$D,'[1]NS Vendor Details'!$H:$H,'G&A Vendor x GL Analysis'!R$20,'[1]NS Vendor Details'!$L:$L,'G&A Vendor x GL Analysis'!$D27,'[1]NS Vendor Details'!$O:$O,'G&A Vendor x GL Analysis'!$F27,'[1]NS Vendor Details'!$N:$N,'G&A Vendor x GL Analysis'!$C27,'[1]NS Vendor Details'!$K:$K,'G&A Vendor x GL Analysis'!$E$8),0)) -> 37431.61 | S27: =IF(AND(S$15="Actual",ISBLANK($E$8)),SUMIFS('[1]NS Vendor Details'!$D:$D,'[1]NS Vendor Details'!$H:$H,'G&A Vendor x GL Analysis'!S$20,'[1]NS Vendor Details'!$L:$L,'G&A Vendor x GL Analysis'!$D27,'[1]NS Vendor Details'!$O:$O,'G&A Vendor x GL Analysis'!$F27,'[1]NS Vendor Details'!$N:$N,'G&A Vendor x GL Analysis'!$C27,'[1]NS Vendor Details'!$I:$I,'G&A Vendor x GL Analysis'!$E27),IF(S$15="Actual",SUMIFS('[1]NS Vendor Details'!$D:$D,'[1]NS Vendor Details'!$H:$H,'G&A Vendor x GL Analysis'!S$20,'[1]NS Vendor Details'!$L:$L,'G&A Vendor x GL Analysis'!$D27,'[1]NS Vendor Details'!$O:$O,'G&A Vendor x GL Analysis'!$F27,'[1]NS Vendor Details'!$N:$N,'G&A Vendor x GL Analysis'!$C27,'[1]NS Vendor Details'!$K:$K,'G&A Vendor x GL Analysis'!$E$8,'[1]NS Vendor Details'!$I:$I,'G&A Vendor x GL Analysis'!$E27),0)) -> 0 | T27: =IF(AND(T$15="Actual",ISBLANK($E$8)),SUMIFS('[1]NS Vendor Details'!$D:$D,'[1]NS Vendor Details'!$H:$H,'G&A Vendor x GL Analysis'!T$20,'[1]NS Vendor Details'!$L:$L,'G&A Vendor x GL Analysis'!$D27,'[1]NS Vendor Details'!$O:$O,'G&A Vendor x GL Analysis'!$F27,'[1]NS Vendor Details'!$N:$N,'G&A Vendor x GL Analysis'!$C27,'[1]NS Vendor Details'!$I:$I,'G&A Vendor x GL Analysis'!$E27),IF(T$15="Actual",SUMIFS('[1]NS Vendor Details'!$D:$D,'[1]NS Vendor Details'!$H:$H,'G&A Vendor x GL Analysis'!T$20,'[1]NS Vendor Details'!$L:$L,'G&A Vendor x GL Analysis'!$D27,'[1]NS Vendor Details'!$O:$O,'G&A Vendor x GL Analysis'!$F27,'[1]NS Vendor Details'!$N:$N,'G&A Vendor x GL Analysis'!$C27,'[1]NS Vendor Details'!$K:$K,'G&A Vendor x GL Analysis'!$E$8,'[1]NS Vendor Details'!$I:$I,'G&A Vendor x GL Analysis'!$E27),0)) -> -20826 | U27: =IF(AND(U$15="Actual",ISBLANK($E$8)),SUMIFS('[1]NS Vendor Details'!$D:$D,'[1]NS Vendor Details'!$H:$H,'G&A Vendor x GL Analysis'!U$20,'[1]NS Vendor Details'!$L:$L,'G&A Vendor x GL Analysis'!$D27,'[1]NS Vendor Details'!$O:$O,'G&A Vendor x GL Analysis'!$F27,'[1]NS Vendor Details'!$N:$N,'G&A Vendor x GL Analysis'!$C27,'[1]NS Vendor Details'!$I:$I,'G&A Vendor x GL Analysis'!$E27),IF(U$15="Actual",SUMIFS('[1]NS Vendor Details'!$D:$D,'[1]NS Vendor Details'!$H:$H,'G&A Vendor x GL Analysis'!U$20,'[1]NS Vendor Details'!$L:$L,'G&A Vendor x GL Analysis'!$D27,'[1]NS Vendor Details'!$O:$O,'G&A Vendor x GL Analysis'!$F27,'[1]NS Vendor Details'!$N:$N,'G&A Vendor x GL Analysis'!$C27,'[1]NS Vendor Details'!$K:$K,'G&A Vendor x GL Analysis'!$E$8,'[1]NS Vendor Details'!$I:$I,'G&A Vendor x GL Analysis'!$E27),0)) -> 0 | V27: =IF(AND(V$15="Actual",ISBLANK($E$8)),SUMIFS('[1]NS Vendor Details'!$D:$D,'[1]NS Vendor Details'!$H:$H,'G&A Vendor x GL Analysis'!V$20,'[1]NS Vendor Details'!$L:$L,'G&A Vendor x GL Analysis'!$D27,'[1]NS Vendor Details'!$O:$O,'G&A Vendor x GL Analysis'!$F27,'[1]NS Vendor Details'!$N:$N,'G&A Vendor x GL Analysis'!$C27,'[1]NS Vendor Details'!$I:$I,'G&A Vendor x GL Analysis'!$E27),IF(V$15="Actual",SUMIFS('[1]NS Vendor Details'!$D:$D,'[1]NS Vendor Details'!$H:$H,'G&A Vendor x GL Analysis'!V$20,'[1]NS Vendor Details'!$L:$L,'G&A Vendor x GL Analysis'!$D27,'[1]NS Vendor Details'!$O:$O,'G&A Vendor x GL Analysis'!$F27,'[1]NS Vendor Details'!$N:$N,'G&A Vendor x GL Analysis'!$C27,'[1]NS Vendor Details'!$K:$K,'G&A Vendor x GL Analysis'!$E$8,'[1]NS Vendor Details'!$I:$I,'G&A Vendor x GL Analysis'!$E27),0)) -> 0 | W27: =IF(AND(W$15="Actual",ISBLANK($E$8)),SUMIFS('[1]NS Vendor Details'!$D:$D,'[1]NS Vendor Details'!$H:$H,'G&A Vendor x GL Analysis'!W$20,'[1]NS Vendor Details'!$L:$L,'G&A Vendor x GL Analysis'!$D27,'[1]NS Vendor Details'!$O:$O,'G&A Vendor x GL Analysis'!$F27,'[1]NS Vendor Details'!$N:$N,'G&A Vendor x GL Analysis'!$C27,'[1]NS Vendor Details'!$I:$I,'G&A Vendor x GL Analysis'!$E27),IF(W$15="Actual",SUMIFS('[1]NS Vendor Details'!$D:$D,'[1]NS Vendor Details'!$H:$H,'G&A Vendor x GL Analysis'!W$20,'[1]NS Vendor Details'!$L:$L,'G&A Vendor x GL Analysis'!$D27,'[1]NS Vendor Details'!$O:$O,'G&A Vendor x GL Analysis'!$F27,'[1]NS Vendor Details'!$N:$N,'G&A Vendor x GL Analysis'!$C27,'[1]NS Vendor Details'!$K:$K,'G&A Vendor x GL Analysis'!$E$8,'[1]NS Vendor Details'!$I:$I,'G&A Vendor x GL Analysis'!$E27),0)) -> 0 | X27: =IF(AND(X$15="Actual",ISBLANK($E$8)),SUMIFS('[1]NS Vendor Details'!$D:$D,'[1]NS Vendor Details'!$H:$H,'G&A Vendor x GL Analysis'!X$20,'[1]NS Vendor Details'!$L:$L,'G&A Vendor x GL Analysis'!$D27,'[1]NS Vendor Details'!$O:$O,'G&A Vendor x GL Analysis'!$F27,'[1]NS Vendor Details'!$N:$N,'G&A Vendor x GL Analysis'!$C27,'[1]NS Vendor Details'!$I:$I,'G&A Vendor x GL Analysis'!$E27),IF(X$15="Actual",SUMIFS('[1]NS Vendor Details'!$D:$D,'[1]NS Vendor Details'!$H:$H,'G&A Vendor x GL Analysis'!X$20,'[1]NS Vendor Details'!$L:$L,'G&A Vendor x GL Analysis'!$D27,'[1]NS Vendor Details'!$O:$O,'G&A Vendor x GL Analysis'!$F27,'[1]NS Vendor Details'!$N:$N,'G&A Vendor x GL Analysis'!$C27,'[1]NS Vendor Details'!$K:$K,'G&A Vendor x GL Analysis'!$E$8,'[1]NS Vendor Details'!$I:$I,'G&A Vendor x GL Analysis'!$E27),0)) -> 0 | Y27: =IF(AND(Y$15="Actual",ISBLANK($E$8)),SUMIFS('[1]NS Vendor Details'!$D:$D,'[1]NS Vendor Details'!$H:$H,'G&A Vendor x GL Analysis'!Y$20,'[1]NS Vendor Details'!$L:$L,'G&A Vendor x GL Analysis'!$D27,'[1]NS Vendor Details'!$O:$O,'G&A Vendor x GL Analysis'!$F27,'[1]NS Vendor Details'!$N:$N,'G&A Vendor x GL Analysis'!$C27,'[1]NS Vendor Details'!$I:$I,'G&A Vendor x GL Analysis'!$E27),IF(Y$15="Actual",SUMIFS('[1]NS Vendor Details'!$D:$D,'[1]NS Vendor Details'!$H:$H,'G&A Vendor x GL Analysis'!Y$20,'[1]NS Vendor Details'!$L:$L,'G&A Vendor x GL Analysis'!$D27,'[1]NS Vendor Details'!$O:$O,'G&A Vendor x GL Analysis'!$F27,'[1]NS Vendor Details'!$N:$N,'G&A Vendor x GL Analysis'!$C27,'[1]NS Vendor Details'!$K:$K,'G&A Vendor x GL Analysis'!$E$8,'[1]NS Vendor Details'!$I:$I,'G&A Vendor x GL Analysis'!$E27),0)) -> 0 | Z27: =IF(AND(Z$15="Actual",ISBLANK($E$8)),SUMIFS('[1]NS Vendor Details'!$D:$D,'[1]NS Vendor Details'!$H:$H,'G&A Vendor x GL Analysis'!Z$20,'[1]NS Vendor Details'!$L:$L,'G&A Vendor x GL Analysis'!$D27,'[1]NS Vendor Details'!$O:$O,'G&A Vendor x GL Analysis'!$F27,'[1]NS Vendor Details'!$N:$N,'G&A Vendor x GL Analysis'!$C27,'[1]NS Vendor Details'!$I:$I,'G&A Vendor x GL Analysis'!$E27),IF(Z$15="Actual",SUMIFS('[1]NS Vendor Details'!$D:$D,'[1]NS Vendor Details'!$H:$H,'G&A Vendor x GL Analysis'!Z$20,'[1]NS Vendor Details'!$L:$L,'G&A Vendor x GL Analysis'!$D27,'[1]NS Vendor Details'!$O:$O,'G&A Vendor x GL Analysis'!$F27,'[1]NS Vendor Details'!$N:$N,'G&A Vendor x GL Analysis'!$C27,'[1]NS Vendor Details'!$K:$K,'G&A Vendor x GL Analysis'!$E$8,'[1]NS Vendor Details'!$I:$I,'G&A Vendor x GL Analysis'!$E27),0)) -> 0 | ... AD27: =IF(AND(AD$15="Actual",ISBLANK($E$8)),SUMIFS('[1]NS Vendor Details'!$D:$D,'[1]NS Vendor Details'!$H:$H,'G&A Vendor x GL Analysis'!AD$20,'[1]NS Vendor Details'!$L:$L,'G&A Vendor x GL Analysis'!$D27,'[1]NS Vendor Details'!$O:$O,'G&A Vendor x GL Analysis'!$F27,'[1]NS Vendor Details'!$N:$N,'G&A Vendor x GL Analysis'!$C27,'[1]NS Vendor Details'!$I:$I,'G&A Vendor x GL Analysis'!$E27),IF(AD$15="Actual",SUMIFS('[1]NS Vendor Details'!$D:$D,'[1]NS Vendor Details'!$H:$H,'G&A Vendor x GL Analysis'!AD$20,'[1]NS Vendor Details'!$L:$L,'G&A Vendor x GL Analysis'!$D27,'[1]NS Vendor Details'!$O:$O,'G&A Vendor x GL Analysis'!$F27,'[1]NS Vendor Details'!$N:$N,'G&A Vendor x GL Analysis'!$C27,'[1]NS Vendor Details'!$K:$K,'G&A Vendor x GL Analysis'!$E$8,'[1]NS Vendor Details'!$I:$I,'G&A Vendor x GL Analysis'!$E27),0)) -> 0 | AF27: =ABS(S27)+ABS(T27)+ABS(U27)+ABS(V27)+ABS(W27)+ABS(X27)+ABS(Y27)+ABS(Z27)+ABS(AA27)+ABS(AB27)+ABS(AC27)+ABS(AD27) -> 20826
A28: =D28&E28 -> Advertising6287 - Events | C28: SG&A | D28: =D27 -> Advertising | E28: 6287 - Events | F28: [No Vendor] | G28: =IF(AND(G$15="Actual",ISBLANK($E$8)),SUMIFS('[1]NS Vendor Details'!$D:$D,'[1]NS Vendor Details'!$H:$H,'G&A Vendor x GL Analysis'!G$20,'[1]NS Vendor Details'!$L:$L,'G&A Vendor x GL Analysis'!$D28,'[1]NS Vendor Details'!$O:$O,'G&A Vendor x GL Analysis'!$F28,'[1]NS Vendor Details'!$N:$N,'G&A Vendor x GL Analysis'!$C28),IF(G$15="Actual",SUMIFS('[1]NS Vendor Details'!$D:$D,'[1]NS Vendor Details'!$H:$H,'G&A Vendor x GL Analysis'!G$20,'[1]NS Vendor Details'!$L:$L,'G&A Vendor x GL Analysis'!$D28,'[1]NS Vendor Details'!$O:$O,'G&A Vendor x GL Analysis'!$F28,'[1]NS Vendor Details'!$N:$N,'G&A Vendor x GL Analysis'!$C28,'[1]NS Vendor Details'!$K:$K,'G&A Vendor x GL Analysis'!$E$8),0)) -> -19852.71 | H28: =IF(AND(H$15="Actual",ISBLANK($E$8)),SUMIFS('[1]NS Vendor Details'!$D:$D,'[1]NS Vendor Details'!$H:$H,'G&A Vendor x GL Analysis'!H$20,'[1]NS Vendor Details'!$L:$L,'G&A Vendor x GL Analysis'!$D28,'[1]NS Vendor Details'!$O:$O,'G&A Vendor x GL Analysis'!$F28,'[1]NS Vendor Details'!$N:$N,'G&A Vendor x GL Analysis'!$C28),IF(H$15="Actual",SUMIFS('[1]NS Vendor Details'!$D:$D,'[1]NS Vendor Details'!$H:$H,'G&A Vendor x GL Analysis'!H$20,'[1]NS Vendor Details'!$L:$L,'G&A Vendor x GL Analysis'!$D28,'[1]NS Vendor Details'!$O:$O,'G&A Vendor x GL Analysis'!$F28,'[1]NS Vendor Details'!$N:$N,'G&A Vendor x GL Analysis'!$C28,'[1]NS Vendor Details'!$K:$K,'G&A Vendor x GL Analysis'!$E$8),0)) -> 895.77 | I28: =IF(AND(I$15="Actual",ISBLANK($E$8)),SUMIFS('[1]NS Vendor Details'!$D:$D,'[1]NS Vendor Details'!$H:$H,'G&A Vendor x GL Analysis'!I$20,'[1]NS Vendor Details'!$L:$L,'G&A Vendor x GL Analysis'!$D28,'[1]NS Vendor Details'!$O:$O,'G&A Vendor x GL Analysis'!$F28,'[1]NS Vendor Details'!$N:$N,'G&A Vendor x GL Analysis'!$C28),IF(I$15="Actual",SUMIFS('[1]NS Vendor Details'!$D:$D,'[1]NS Vendor Details'!$H:$H,'G&A Vendor x GL Analysis'!I$20,'[1]NS Vendor Details'!$L:$L,'G&A Vendor x GL Analysis'!$D28,'[1]NS Vendor Details'!$O:$O,'G&A Vendor x GL Analysis'!$F28,'[1]NS Vendor Details'!$N:$N,'G&A Vendor x GL Analysis'!$C28,'[1]NS Vendor Details'!$K:$K,'G&A Vendor x GL Analysis'!$E$8),0)) -> 47270.03 | J28: =IF(AND(J$15="Actual",ISBLANK($E$8)),SUMIFS('[1]NS Vendor Details'!$D:$D,'[1]NS Vendor Details'!$H:$H,'G&A Vendor x GL Analysis'!J$20,'[1]NS Vendor Details'!$L:$L,'G&A Vendor x GL Analysis'!$D28,'[1]NS Vendor Details'!$O:$O,'G&A Vendor x GL Analysis'!$F28,'[1]NS Vendor Details'!$N:$N,'G&A Vendor x GL Analysis'!$C28),IF(J$15="Actual",SUMIFS('[1]NS Vendor Details'!$D:$D,'[1]NS Vendor Details'!$H:$H,'G&A Vendor x GL Analysis'!J$20,'[1]NS Vendor Details'!$L:$L,'G&A Vendor x GL Analysis'!$D28,'[1]NS Vendor Details'!$O:$O,'G&A Vendor x GL Analysis'!$F28,'[1]NS Vendor Details'!$N:$N,'G&A Vendor x GL Analysis'!$C28,'[1]NS Vendor Details'!$K:$K,'G&A Vendor x GL Analysis'!$E$8),0)) -> 37784.42 | K28: =IF(AND(K$15="Actual",ISBLANK($E$8)),SUMIFS('[1]NS Vendor Details'!$D:$D,'[1]NS Vendor Details'!$H:$H,'G&A Vendor x GL Analysis'!K$20,'[1]NS Vendor Details'!$L:$L,'G&A Vendor x GL Analysis'!$D28,'[1]NS Vendor Details'!$O:$O,'G&A Vendor x GL Analysis'!$F28,'[1]NS Vendor Details'!$N:$N,'G&A Vendor x GL Analysis'!$C28),IF(K$15="Actual",SUMIFS('[1]NS Vendor Details'!$D:$D,'[1]NS Vendor Details'!$H:$H,'G&A Vendor x GL Analysis'!K$20,'[1]NS Vendor Details'!$L:$L,'G&A Vendor x GL Analysis'!$D28,'[1]NS Vendor Details'!$O:$O,'G&A Vendor x GL Analysis'!$F28,'[1]NS Vendor Details'!$N:$N,'G&A Vendor x GL Analysis'!$C28,'[1]NS Vendor Details'!$K:$K,'G&A Vendor x GL Analysis'!$E$8),0)) -> 37718.04 | L28: =IF(AND(L$15="Actual",ISBLANK($E$8)),SUMIFS('[1]NS Vendor Details'!$D:$D,'[1]NS Vendor Details'!$H:$H,'G&A Vendor x GL Analysis'!L$20,'[1]NS Vendor Details'!$L:$L,'G&A Vendor x GL Analysis'!$D28,'[1]NS Vendor Details'!$O:$O,'G&A Vendor x GL Analysis'!$F28,'[1]NS Vendor Details'!$N:$N,'G&A Vendor x GL Analysis'!$C28),IF(L$15="Actual",SUMIFS('[1]NS Vendor Details'!$D:$D,'[1]NS Vendor Details'!$H:$H,'G&A Vendor x GL Analysis'!L$20,'[1]NS Vendor Details'!$L:$L,'G&A Vendor x GL Analysis'!$D28,'[1]NS Vendor Details'!$O:$O,'G&A Vendor x GL Analysis'!$F28,'[1]NS Vendor Details'!$N:$N,'G&A Vendor x GL Analysis'!$C28,'[1]NS Vendor Details'!$K:$K,'G&A Vendor x GL Analysis'!$E$8),0)) -> 40369.25 | M28: =IF(AND(M$15="Actual",ISBLANK($E$8)),SUMIFS('[1]NS Vendor Details'!$D:$D,'[1]NS Vendor Details'!$H:$H,'G&A Vendor x GL Analysis'!M$20,'[1]NS Vendor Details'!$L:$L,'G&A Vendor x GL Analysis'!$D28,'[1]NS Vendor Details'!$O:$O,'G&A Vendor x GL Analysis'!$F28,'[1]NS Vendor Details'!$N:$N,'G&A Vendor x GL Analysis'!$C28),IF(M$15="Actual",SUMIFS('[1]NS Vendor Details'!$D:$D,'[1]NS Vendor Details'!$H:$H,'G&A Vendor x GL Analysis'!M$20,'[1]NS Vendor Details'!$L:$L,'G&A Vendor x GL Analysis'!$D28,'[1]NS Vendor Details'!$O:$O,'G&A Vendor x GL Analysis'!$F28,'[1]NS Vendor Details'!$N:$N,'G&A Vendor x GL Analysis'!$C28,'[1]NS Vendor Details'!$K:$K,'G&A Vendor x GL Analysis'!$E$8),0)) -> 50892.76 | N28: =IF(AND(N$15="Actual",ISBLANK($E$8)),SUMIFS('[1]NS Vendor Details'!$D:$D,'[1]NS Vendor Details'!$H:$H,'G&A Vendor x GL Analysis'!N$20,'[1]NS Vendor Details'!$L:$L,'G&A Vendor x GL Analysis'!$D28,'[1]NS Vendor Details'!$O:$O,'G&A Vendor x GL Analysis'!$F28,'[1]NS Vendor Details'!$N:$N,'G&A Vendor x GL Analysis'!$C28),IF(N$15="Actual",SUMIFS('[1]NS Vendor Details'!$D:$D,'[1]NS Vendor Details'!$H:$H,'G&A Vendor x GL Analysis'!N$20,'[1]NS Vendor Details'!$L:$L,'G&A Vendor x GL Analysis'!$D28,'[1]NS Vendor Details'!$O:$O,'G&A Vendor x GL Analysis'!$F28,'[1]NS Vendor Details'!$N:$N,'G&A Vendor x GL Analysis'!$C28,'[1]NS Vendor Details'!$K:$K,'G&A Vendor x GL Analysis'!$E$8),0)) -> 54358.52 | ... R28: =IF(AND(R$15="Actual",ISBLANK($E$8)),SUMIFS('[1]NS Vendor Details'!$D:$D,'[1]NS Vendor Details'!$H:$H,'G&A Vendor x GL Analysis'!R$20,'[1]NS Vendor Details'!$L:$L,'G&A Vendor x GL Analysis'!$D28,'[1]NS Vendor Details'!$O:$O,'G&A Vendor x GL Analysis'!$F28,'[1]NS Vendor Details'!$N:$N,'G&A Vendor x GL Analysis'!$C28),IF(R$15="Actual",SUMIFS('[1]NS Vendor Details'!$D:$D,'[1]NS Vendor Details'!$H:$H,'G&A Vendor x GL Analysis'!R$20,'[1]NS Vendor Details'!$L:$L,'G&A Vendor x GL Analysis'!$D28,'[1]NS Vendor Details'!$O:$O,'G&A Vendor x GL Analysis'!$F28,'[1]NS Vendor Details'!$N:$N,'G&A Vendor x GL Analysis'!$C28,'[1]NS Vendor Details'!$K:$K,'G&A Vendor x GL Analysis'!$E$8),0)) -> 37431.61 | S28: =IF(AND(S$15="Actual",ISBLANK($E$8)),SUMIFS('[1]NS Vendor Details'!$D:$D,'[1]NS Vendor Details'!$H:$H,'G&A Vendor x GL Analysis'!S$20,'[1]NS Vendor Details'!$L:$L,'G&A Vendor x GL Analysis'!$D28,'[1]NS Vendor Details'!$O:$O,'G&A Vendor x GL Analysis'!$F28,'[1]NS Vendor Details'!$N:$N,'G&A Vendor x GL Analysis'!$C28,'[1]NS Vendor Details'!$I:$I,'G&A Vendor x GL Analysis'!$E28),IF(S$15="Actual",SUMIFS('[1]NS Vendor Details'!$D:$D,'[1]NS Vendor Details'!$H:$H,'G&A Vendor x GL Analysis'!S$20,'[1]NS Vendor Details'!$L:$L,'G&A Vendor x GL Analysis'!$D28,'[1]NS Vendor Details'!$O:$O,'G&A Vendor x GL Analysis'!$F28,'[1]NS Vendor Details'!$N:$N,'G&A Vendor x GL Analysis'!$C28,'[1]NS Vendor Details'!$K:$K,'G&A Vendor x GL Analysis'!$E$8,'[1]NS Vendor Details'!$I:$I,'G&A Vendor x GL Analysis'!$E28),0)) -> 0 | T28: =IF(AND(T$15="Actual",ISBLANK($E$8)),SUMIFS('[1]NS Vendor Details'!$D:$D,'[1]NS Vendor Details'!$H:$H,'G&A Vendor x GL Analysis'!T$20,'[1]NS Vendor Details'!$L:$L,'G&A Vendor x GL Analysis'!$D28,'[1]NS Vendor Details'!$O:$O,'G&A Vendor x GL Analysis'!$F28,'[1]NS Vendor Details'!$N:$N,'G&A Vendor x GL Analysis'!$C28,'[1]NS Vendor Details'!$I:$I,'G&A Vendor x GL Analysis'!$E28),IF(T$15="Actual",SUMIFS('[1]NS Vendor Details'!$D:$D,'[1]NS Vendor Details'!$H:$H,'G&A Vendor x GL Analysis'!T$20,'[1]NS Vendor Details'!$L:$L,'G&A Vendor x GL Analysis'!$D28,'[1]NS Vendor Details'!$O:$O,'G&A Vendor x GL Analysis'!$F28,'[1]NS Vendor Details'!$N:$N,'G&A Vendor x GL Analysis'!$C28,'[1]NS Vendor Details'!$K:$K,'G&A Vendor x GL Analysis'!$E$8,'[1]NS Vendor Details'!$I:$I,'G&A Vendor x GL Analysis'!$E28),0)) -> 0 | U28: =IF(AND(U$15="Actual",ISBLANK($E$8)),SUMIFS('[1]NS Vendor Details'!$D:$D,'[1]NS Vendor Details'!$H:$H,'G&A Vendor x GL Analysis'!U$20,'[1]NS Vendor Details'!$L:$L,'G&A Vendor x GL Analysis'!$D28,'[1]NS Vendor Details'!$O:$O,'G&A Vendor x GL Analysis'!$F28,'[1]NS Vendor Details'!$N:$N,'G&A Vendor x GL Analysis'!$C28,'[1]NS Vendor Details'!$I:$I,'G&A Vendor x GL Analysis'!$E28),IF(U$15="Actual",SUMIFS('[1]NS Vendor Details'!$D:$D,'[1]NS Vendor Details'!$H:$H,'G&A Vendor x GL Analysis'!U$20,'[1]NS Vendor Details'!$L:$L,'G&A Vendor x GL Analysis'!$D28,'[1]NS Vendor Details'!$O:$O,'G&A Vendor x GL Analysis'!$F28,'[1]NS Vendor Details'!$N:$N,'G&A Vendor x GL Analysis'!$C28,'[1]NS Vendor Details'!$K:$K,'G&A Vendor x GL Analysis'!$E$8,'[1]NS Vendor Details'!$I:$I,'G&A Vendor x GL Analysis'!$E28),0)) -> 0 | V28: =IF(AND(V$15="Actual",ISBLANK($E$8)),SUMIFS('[1]NS Vendor Details'!$D:$D,'[1]NS Vendor Details'!$H:$H,'G&A Vendor x GL Analysis'!V$20,'[1]NS Vendor Details'!$L:$L,'G&A Vendor x GL Analysis'!$D28,'[1]NS Vendor Details'!$O:$O,'G&A Vendor x GL Analysis'!$F28,'[1]NS Vendor Details'!$N:$N,'G&A Vendor x GL Analysis'!$C28,'[1]NS Vendor Details'!$I:$I,'G&A Vendor x GL Analysis'!$E28),IF(V$15="Actual",SUMIFS('[1]NS Vendor Details'!$D:$D,'[1]NS Vendor Details'!$H:$H,'G&A Vendor x GL Analysis'!V$20,'[1]NS Vendor Details'!$L:$L,'G&A Vendor x GL Analysis'!$D28,'[1]NS Vendor Details'!$O:$O,'G&A Vendor x GL Analysis'!$F28,'[1]NS Vendor Details'!$N:$N,'G&A Vendor x GL Analysis'!$C28,'[1]NS Vendor Details'!$K:$K,'G&A Vendor x GL Analysis'!$E$8,'[1]NS Vendor Details'!$I:$I,'G&A Vendor x GL Analysis'!$E28),0)) -> 0 | W28: =IF(AND(W$15="Actual",ISBLANK($E$8)),SUMIFS('[1]NS Vendor Details'!$D:$D,'[1]NS Vendor Details'!$H:$H,'G&A Vendor x GL Analysis'!W$20,'[1]NS Vendor Details'!$L:$L,'G&A Vendor x GL Analysis'!$D28,'[1]NS Vendor Details'!$O:$O,'G&A Vendor x GL Analysis'!$F28,'[1]NS Vendor Details'!$N:$N,'G&A Vendor x GL Analysis'!$C28,'[1]NS Vendor Details'!$I:$I,'G&A Vendor x GL Analysis'!$E28),IF(W$15="Actual",SUMIFS('[1]NS Vendor Details'!$D:$D,'[1]NS Vendor Details'!$H:$H,'G&A Vendor x GL Analysis'!W$20,'[1]NS Vendor Details'!$L:$L,'G&A Vendor x GL Analysis'!$D28,'[1]NS Vendor Details'!$O:$O,'G&A Vendor x GL Analysis'!$F28,'[1]NS Vendor Details'!$N:$N,'G&A Vendor x GL Analysis'!$C28,'[1]NS Vendor Details'!$K:$K,'G&A Vendor x GL Analysis'!$E$8,'[1]NS Vendor Details'!$I:$I,'G&A Vendor x GL Analysis'!$E28),0)) -> 0 | X28: =IF(AND(X$15="Actual",ISBLANK($E$8)),SUMIFS('[1]NS Vendor Details'!$D:$D,'[1]NS Vendor Details'!$H:$H,'G&A Vendor x GL Analysis'!X$20,'[1]NS Vendor Details'!$L:$L,'G&A Vendor x GL Analysis'!$D28,'[1]NS Vendor Details'!$O:$O,'G&A Vendor x GL Analysis'!$F28,'[1]NS Vendor Details'!$N:$N,'G&A Vendor x GL Analysis'!$C28,'[1]NS Vendor Details'!$I:$I,'G&A Vendor x GL Analysis'!$E28),IF(X$15="Actual",SUMIFS('[1]NS Vendor Details'!$D:$D,'[1]NS Vendor Details'!$H:$H,'G&A Vendor x GL Analysis'!X$20,'[1]NS Vendor Details'!$L:$L,'G&A Vendor x GL Analysis'!$D28,'[1]NS Vendor Details'!$O:$O,'G&A Vendor x GL Analysis'!$F28,'[1]NS Vendor Details'!$N:$N,'G&A Vendor x GL Analysis'!$C28,'[1]NS Vendor Details'!$K:$K,'G&A Vendor x GL Analysis'!$E$8,'[1]NS Vendor Details'!$I:$I,'G&A Vendor x GL Analysis'!$E28),0)) -> 0 | Y28: =IF(AND(Y$15="Actual",ISBLANK($E$8)),SUMIFS('[1]NS Vendor Details'!$D:$D,'[1]NS Vendor Details'!$H:$H,'G&A Vendor x GL Analysis'!Y$20,'[1]NS Vendor Details'!$L:$L,'G&A Vendor x GL Analysis'!$D28,'[1]NS Vendor Details'!$O:$O,'G&A Vendor x GL Analysis'!$F28,'[1]NS Vendor Details'!$N:$N,'G&A Vendor x GL Analysis'!$C28,'[1]NS Vendor Details'!$I:$I,'G&A Vendor x GL Analysis'!$E28),IF(Y$15="Actual",SUMIFS('[1]NS Vendor Details'!$D:$D,'[1]NS Vendor Details'!$H:$H,'G&A Vendor x GL Analysis'!Y$20,'[1]NS Vendor Details'!$L:$L,'G&A Vendor x GL Analysis'!$D28,'[1]NS Vendor Details'!$O:$O,'G&A Vendor x GL Analysis'!$F28,'[1]NS Vendor Details'!$N:$N,'G&A Vendor x GL Analysis'!$C28,'[1]NS Vendor Details'!$K:$K,'G&A Vendor x GL Analysis'!$E$8,'[1]NS Vendor Details'!$I:$I,'G&A Vendor x GL Analysis'!$E28),0)) -> 0 | Z28: =IF(AND(Z$15="Actual",ISBLANK($E$8)),SUMIFS('[1]NS Vendor Details'!$D:$D,'[1]NS Vendor Details'!$H:$H,'G&A Vendor x GL Analysis'!Z$20,'[1]NS Vendor Details'!$L:$L,'G&A Vendor x GL Analysis'!$D28,'[1]NS Vendor Details'!$O:$O,'G&A Vendor x GL Analysis'!$F28,'[1]NS Vendor Details'!$N:$N,'G&A Vendor x GL Analysis'!$C28,'[1]NS Vendor Details'!$I:$I,'G&A Vendor x GL Analysis'!$E28),IF(Z$15="Actual",SUMIFS('[1]NS Vendor Details'!$D:$D,'[1]NS Vendor Details'!$H:$H,'G&A Vendor x GL Analysis'!Z$20,'[1]NS Vendor Details'!$L:$L,'G&A Vendor x GL Analysis'!$D28,'[1]NS Vendor Details'!$O:$O,'G&A Vendor x GL Analysis'!$F28,'[1]NS Vendor Details'!$N:$N,'G&A Vendor x GL Analysis'!$C28,'[1]NS Vendor Details'!$K:$K,'G&A Vendor x GL Analysis'!$E$8,'[1]NS Vendor Details'!$I:$I,'G&A Vendor x GL Analysis'!$E28),0)) -> 0 | ... AD28: =IF(AND(AD$15="Actual",ISBLANK($E$8)),SUMIFS('[1]NS Vendor Details'!$D:$D,'[1]NS Vendor Details'!$H:$H,'G&A Vendor x GL Analysis'!AD$20,'[1]NS Vendor Details'!$L:$L,'G&A Vendor x GL Analysis'!$D28,'[1]NS Vendor Details'!$O:$O,'G&A Vendor x GL Analysis'!$F28,'[1]NS Vendor Details'!$N:$N,'G&A Vendor x GL Analysis'!$C28,'[1]NS Vendor Details'!$I:$I,'G&A Vendor x GL Analysis'!$E28),IF(AD$15="Actual",SUMIFS('[1]NS Vendor Details'!$D:$D,'[1]NS Vendor Details'!$H:$H,'G&A Vendor x GL Analysis'!AD$20,'[1]NS Vendor Details'!$L:$L,'G&A Vendor x GL Analysis'!$D28,'[1]NS Vendor Details'!$O:$O,'G&A Vendor x GL Analysis'!$F28,'[1]NS Vendor Details'!$N:$N,'G&A Vendor x GL Analysis'!$C28,'[1]NS Vendor Details'!$K:$K,'G&A Vendor x GL Analysis'!$E$8,'[1]NS Vendor Details'!$I:$I,'G&A Vendor x GL Analysis'!$E28),0)) -> 0 | AF28: =ABS(S28)+ABS(T28)+ABS(U28)+ABS(V28)+ABS(W28)+ABS(X28)+ABS(Y28)+ABS(Z28)+ABS(AA28)+ABS(AB28)+ABS(AC28)+ABS(AD28) -> 33579.69
A29: =D29&E29 -> Advertising6284 - Advertising | C29: SG&A | D29: =D28 -> Advertising | E29: 6284 - Advertising | F29: [No Vendor] | G29: =IF(AND(G$15="Actual",ISBLANK($E$8)),SUMIFS('[1]NS Vendor Details'!$D:$D,'[1]NS Vendor Details'!$H:$H,'G&A Vendor x GL Analysis'!G$20,'[1]NS Vendor Details'!$L:$L,'G&A Vendor x GL Analysis'!$D29,'[1]NS Vendor Details'!$O:$O,'G&A Vendor x GL Analysis'!$F29,'[1]NS Vendor Details'!$N:$N,'G&A Vendor x GL Analysis'!$C29),IF(G$15="Actual",SUMIFS('[1]NS Vendor Details'!$D:$D,'[1]NS Vendor Details'!$H:$H,'G&A Vendor x GL Analysis'!G$20,'[1]NS Vendor Details'!$L:$L,'G&A Vendor x GL Analysis'!$D29,'[1]NS Vendor Details'!$O:$O,'G&A Vendor x GL Analysis'!$F29,'[1]NS Vendor Details'!$N:$N,'G&A Vendor x GL Analysis'!$C29,'[1]NS Vendor Details'!$K:$K,'G&A Vendor x GL Analysis'!$E$8),0)) -> -19852.71 | H29: =IF(AND(H$15="Actual",ISBLANK($E$8)),SUMIFS('[1]NS Vendor Details'!$D:$D,'[1]NS Vendor Details'!$H:$H,'G&A Vendor x GL Analysis'!H$20,'[1]NS Vendor Details'!$L:$L,'G&A Vendor x GL Analysis'!$D29,'[1]NS Vendor Details'!$O:$O,'G&A Vendor x GL Analysis'!$F29,'[1]NS Vendor Details'!$N:$N,'G&A Vendor x GL Analysis'!$C29),IF(H$15="Actual",SUMIFS('[1]NS Vendor Details'!$D:$D,'[1]NS Vendor Details'!$H:$H,'G&A Vendor x GL Analysis'!H$20,'[1]NS Vendor Details'!$L:$L,'G&A Vendor x GL Analysis'!$D29,'[1]NS Vendor Details'!$O:$O,'G&A Vendor x GL Analysis'!$F29,'[1]NS Vendor Details'!$N:$N,'G&A Vendor x GL Analysis'!$C29,'[1]NS Vendor Details'!$K:$K,'G&A Vendor x GL Analysis'!$E$8),0)) -> 895.77 | I29: =IF(AND(I$15="Actual",ISBLANK($E$8)),SUMIFS('[1]NS Vendor Details'!$D:$D,'[1]NS Vendor Details'!$H:$H,'G&A Vendor x GL Analysis'!I$20,'[1]NS Vendor Details'!$L:$L,'G&A Vendor x GL Analysis'!$D29,'[1]NS Vendor Details'!$O:$O,'G&A Vendor x GL Analysis'!$F29,'[1]NS Vendor Details'!$N:$N,'G&A Vendor x GL Analysis'!$C29),IF(I$15="Actual",SUMIFS('[1]NS Vendor Details'!$D:$D,'[1]NS Vendor Details'!$H:$H,'G&A Vendor x GL Analysis'!I$20,'[1]NS Vendor Details'!$L:$L,'G&A Vendor x GL Analysis'!$D29,'[1]NS Vendor Details'!$O:$O,'G&A Vendor x GL Analysis'!$F29,'[1]NS Vendor Details'!$N:$N,'G&A Vendor x GL Analysis'!$C29,'[1]NS Vendor Details'!$K:$K,'G&A Vendor x GL Analysis'!$E$8),0)) -> 47270.03 | J29: =IF(AND(J$15="Actual",ISBLANK($E$8)),SUMIFS('[1]NS Vendor Details'!$D:$D,'[1]NS Vendor Details'!$H:$H,'G&A Vendor x GL Analysis'!J$20,'[1]NS Vendor Details'!$L:$L,'G&A Vendor x GL Analysis'!$D29,'[1]NS Vendor Details'!$O:$O,'G&A Vendor x GL Analysis'!$F29,'[1]NS Vendor Details'!$N:$N,'G&A Vendor x GL Analysis'!$C29),IF(J$15="Actual",SUMIFS('[1]NS Vendor Details'!$D:$D,'[1]NS Vendor Details'!$H:$H,'G&A Vendor x GL Analysis'!J$20,'[1]NS Vendor Details'!$L:$L,'G&A Vendor x GL Analysis'!$D29,'[1]NS Vendor Details'!$O:$O,'G&A Vendor x GL Analysis'!$F29,'[1]NS Vendor Details'!$N:$N,'G&A Vendor x GL Analysis'!$C29,'[1]NS Vendor Details'!$K:$K,'G&A Vendor x GL Analysis'!$E$8),0)) -> 37784.42 | K29: =IF(AND(K$15="Actual",ISBLANK($E$8)),SUMIFS('[1]NS Vendor Details'!$D:$D,'[1]NS Vendor Details'!$H:$H,'G&A Vendor x GL Analysis'!K$20,'[1]NS Vendor Details'!$L:$L,'G&A Vendor x GL Analysis'!$D29,'[1]NS Vendor Details'!$O:$O,'G&A Vendor x GL Analysis'!$F29,'[1]NS Vendor Details'!$N:$N,'G&A Vendor x GL Analysis'!$C29),IF(K$15="Actual",SUMIFS('[1]NS Vendor Details'!$D:$D,'[1]NS Vendor Details'!$H:$H,'G&A Vendor x GL Analysis'!K$20,'[1]NS Vendor Details'!$L:$L,'G&A Vendor x GL Analysis'!$D29,'[1]NS Vendor Details'!$O:$O,'G&A Vendor x GL Analysis'!$F29,'[1]NS Vendor Details'!$N:$N,'G&A Vendor x GL Analysis'!$C29,'[1]NS Vendor Details'!$K:$K,'G&A Vendor x GL Analysis'!$E$8),0)) -> 37718.04 | L29: =IF(AND(L$15="Actual",ISBLANK($E$8)),SUMIFS('[1]NS Vendor Details'!$D:$D,'[1]NS Vendor Details'!$H:$H,'G&A Vendor x GL Analysis'!L$20,'[1]NS Vendor Details'!$L:$L,'G&A Vendor x GL Analysis'!$D29,'[1]NS Vendor Details'!$O:$O,'G&A Vendor x GL Analysis'!$F29,'[1]NS Vendor Details'!$N:$N,'G&A Vendor x GL Analysis'!$C29),IF(L$15="Actual",SUMIFS('[1]NS Vendor Details'!$D:$D,'[1]NS Vendor Details'!$H:$H,'G&A Vendor x GL Analysis'!L$20,'[1]NS Vendor Details'!$L:$L,'G&A Vendor x GL Analysis'!$D29,'[1]NS Vendor Details'!$O:$O,'G&A Vendor x GL Analysis'!$F29,'[1]NS Vendor Details'!$N:$N,'G&A Vendor x GL Analysis'!$C29,'[1]NS Vendor Details'!$K:$K,'G&A Vendor x GL Analysis'!$E$8),0)) -> 40369.25 | M29: =IF(AND(M$15="Actual",ISBLANK($E$8)),SUMIFS('[1]NS Vendor Details'!$D:$D,'[1]NS Vendor Details'!$H:$H,'G&A Vendor x GL Analysis'!M$20,'[1]NS Vendor Details'!$L:$L,'G&A Vendor x GL Analysis'!$D29,'[1]NS Vendor Details'!$O:$O,'G&A Vendor x GL Analysis'!$F29,'[1]NS Vendor Details'!$N:$N,'G&A Vendor x GL Analysis'!$C29),IF(M$15="Actual",SUMIFS('[1]NS Vendor Details'!$D:$D,'[1]NS Vendor Details'!$H:$H,'G&A Vendor x GL Analysis'!M$20,'[1]NS Vendor Details'!$L:$L,'G&A Vendor x GL Analysis'!$D29,'[1]NS Vendor Details'!$O:$O,'G&A Vendor x GL Analysis'!$F29,'[1]NS Vendor Details'!$N:$N,'G&A Vendor x GL Analysis'!$C29,'[1]NS Vendor Details'!$K:$K,'G&A Vendor x GL Analysis'!$E$8),0)) -> 50892.76 | N29: =IF(AND(N$15="Actual",ISBLANK($E$8)),SUMIFS('[1]NS Vendor Details'!$D:$D,'[1]NS Vendor Details'!$H:$H,'G&A Vendor x GL Analysis'!N$20,'[1]NS Vendor Details'!$L:$L,'G&A Vendor x GL Analysis'!$D29,'[1]NS Vendor Details'!$O:$O,'G&A Vendor x GL Analysis'!$F29,'[1]NS Vendor Details'!$N:$N,'G&A Vendor x GL Analysis'!$C29),IF(N$15="Actual",SUMIFS('[1]NS Vendor Details'!$D:$D,'[1]NS Vendor Details'!$H:$H,'G&A Vendor x GL Analysis'!N$20,'[1]NS Vendor Details'!$L:$L,'G&A Vendor x GL Analysis'!$D29,'[1]NS Vendor Details'!$O:$O,'G&A Vendor x GL Analysis'!$F29,'[1]NS Vendor Details'!$N:$N,'G&A Vendor x GL Analysis'!$C29,'[1]NS Vendor Details'!$K:$K,'G&A Vendor x GL Analysis'!$E$8),0)) -> 54358.52 | ... R29: =IF(AND(R$15="Actual",ISBLANK($E$8)),SUMIFS('[1]NS Vendor Details'!$D:$D,'[1]NS Vendor Details'!$H:$H,'G&A Vendor x GL Analysis'!R$20,'[1]NS Vendor Details'!$L:$L,'G&A Vendor x GL Analysis'!$D29,'[1]NS Vendor Details'!$O:$O,'G&A Vendor x GL Analysis'!$F29,'[1]NS Vendor Details'!$N:$N,'G&A Vendor x GL Analysis'!$C29),IF(R$15="Actual",SUMIFS('[1]NS Vendor Details'!$D:$D,'[1]NS Vendor Details'!$H:$H,'G&A Vendor x GL Analysis'!R$20,'[1]NS Vendor Details'!$L:$L,'G&A Vendor x GL Analysis'!$D29,'[1]NS Vendor Details'!$O:$O,'G&A Vendor x GL Analysis'!$F29,'[1]NS Vendor Details'!$N:$N,'G&A Vendor x GL Analysis'!$C29,'[1]NS Vendor Details'!$K:$K,'G&A Vendor x GL Analysis'!$E$8),0)) -> 37431.61 | S29: =IF(AND(S$15="Actual",ISBLANK($E$8)),SUMIFS('[1]NS Vendor Details'!$D:$D,'[1]NS Vendor Details'!$H:$H,'G&A Vendor x GL Analysis'!S$20,'[1]NS Vendor Details'!$L:$L,'G&A Vendor x GL Analysis'!$D29,'[1]NS Vendor Details'!$O:$O,'G&A Vendor x GL Analysis'!$F29,'[1]NS Vendor Details'!$N:$N,'G&A Vendor x GL Analysis'!$C29,'[1]NS Vendor Details'!$I:$I,'G&A Vendor x GL Analysis'!$E29),IF(S$15="Actual",SUMIFS('[1]NS Vendor Details'!$D:$D,'[1]NS Vendor Details'!$H:$H,'G&A Vendor x GL Analysis'!S$20,'[1]NS Vendor Details'!$L:$L,'G&A Vendor x GL Analysis'!$D29,'[1]NS Vendor Details'!$O:$O,'G&A Vendor x GL Analysis'!$F29,'[1]NS Vendor Details'!$N:$N,'G&A Vendor x GL Analysis'!$C29,'[1]NS Vendor Details'!$K:$K,'G&A Vendor x GL Analysis'!$E$8,'[1]NS Vendor Details'!$I:$I,'G&A Vendor x GL Analysis'!$E29),0)) -> 1666.67 | T29: =IF(AND(T$15="Actual",ISBLANK($E$8)),SUMIFS('[1]NS Vendor Details'!$D:$D,'[1]NS Vendor Details'!$H:$H,'G&A Vendor x GL Analysis'!T$20,'[1]NS Vendor Details'!$L:$L,'G&A Vendor x GL Analysis'!$D29,'[1]NS Vendor Details'!$O:$O,'G&A Vendor x GL Analysis'!$F29,'[1]NS Vendor Details'!$N:$N,'G&A Vendor x GL Analysis'!$C29,'[1]NS Vendor Details'!$I:$I,'G&A Vendor x GL Analysis'!$E29),IF(T$15="Actual",SUMIFS('[1]NS Vendor Details'!$D:$D,'[1]NS Vendor Details'!$H:$H,'G&A Vendor x GL Analysis'!T$20,'[1]NS Vendor Details'!$L:$L,'G&A Vendor x GL Analysis'!$D29,'[1]NS Vendor Details'!$O:$O,'G&A Vendor x GL Analysis'!$F29,'[1]NS Vendor Details'!$N:$N,'G&A Vendor x GL Analysis'!$C29,'[1]NS Vendor Details'!$K:$K,'G&A Vendor x GL Analysis'!$E$8,'[1]NS Vendor Details'!$I:$I,'G&A Vendor x GL Analysis'!$E29),0)) -> 1666.66 | U29: =IF(AND(U$15="Actual",ISBLANK($E$8)),SUMIFS('[1]NS Vendor Details'!$D:$D,'[1]NS Vendor Details'!$H:$H,'G&A Vendor x GL Analysis'!U$20,'[1]NS Vendor Details'!$L:$L,'G&A Vendor x GL Analysis'!$D29,'[1]NS Vendor Details'!$O:$O,'G&A Vendor x GL Analysis'!$F29,'[1]NS Vendor Details'!$N:$N,'G&A Vendor x GL Analysis'!$C29,'[1]NS Vendor Details'!$I:$I,'G&A Vendor x GL Analysis'!$E29),IF(U$15="Actual",SUMIFS('[1]NS Vendor Details'!$D:$D,'[1]NS Vendor Details'!$H:$H,'G&A Vendor x GL Analysis'!U$20,'[1]NS Vendor Details'!$L:$L,'G&A Vendor x GL Analysis'!$D29,'[1]NS Vendor Details'!$O:$O,'G&A Vendor x GL Analysis'!$F29,'[1]NS Vendor Details'!$N:$N,'G&A Vendor x GL Analysis'!$C29,'[1]NS Vendor Details'!$K:$K,'G&A Vendor x GL Analysis'!$E$8,'[1]NS Vendor Details'!$I:$I,'G&A Vendor x GL Analysis'!$E29),0)) -> 0 | V29: =IF(AND(V$15="Actual",ISBLANK($E$8)),SUMIFS('[1]NS Vendor Details'!$D:$D,'[1]NS Vendor Details'!$H:$H,'G&A Vendor x GL Analysis'!V$20,'[1]NS Vendor Details'!$L:$L,'G&A Vendor x GL Analysis'!$D29,'[1]NS Vendor Details'!$O:$O,'G&A Vendor x GL Analysis'!$F29,'[1]NS Vendor Details'!$N:$N,'G&A Vendor x GL Analysis'!$C29,'[1]NS Vendor Details'!$I:$I,'G&A Vendor x GL Analysis'!$E29),IF(V$15="Actual",SUMIFS('[1]NS Vendor Details'!$D:$D,'[1]NS Vendor Details'!$H:$H,'G&A Vendor x GL Analysis'!V$20,'[1]NS Vendor Details'!$L:$L,'G&A Vendor x GL Analysis'!$D29,'[1]NS Vendor Details'!$O:$O,'G&A Vendor x GL Analysis'!$F29,'[1]NS Vendor Details'!$N:$N,'G&A Vendor x GL Analysis'!$C29,'[1]NS Vendor Details'!$K:$K,'G&A Vendor x GL Analysis'!$E$8,'[1]NS Vendor Details'!$I:$I,'G&A Vendor x GL Analysis'!$E29),0)) -> 0 | W29: =IF(AND(W$15="Actual",ISBLANK($E$8)),SUMIFS('[1]NS Vendor Details'!$D:$D,'[1]NS Vendor Details'!$H:$H,'G&A Vendor x GL Analysis'!W$20,'[1]NS Vendor Details'!$L:$L,'G&A Vendor x GL Analysis'!$D29,'[1]NS Vendor Details'!$O:$O,'G&A Vendor x GL Analysis'!$F29,'[1]NS Vendor Details'!$N:$N,'G&A Vendor x GL Analysis'!$C29,'[1]NS Vendor Details'!$I:$I,'G&A Vendor x GL Analysis'!$E29),IF(W$15="Actual",SUMIFS('[1]NS Vendor Details'!$D:$D,'[1]NS Vendor Details'!$H:$H,'G&A Vendor x GL Analysis'!W$20,'[1]NS Vendor Details'!$L:$L,'G&A Vendor x GL Analysis'!$D29,'[1]NS Vendor Details'!$O:$O,'G&A Vendor x GL Analysis'!$F29,'[1]NS Vendor Details'!$N:$N,'G&A Vendor x GL Analysis'!$C29,'[1]NS Vendor Details'!$K:$K,'G&A Vendor x GL Analysis'!$E$8,'[1]NS Vendor Details'!$I:$I,'G&A Vendor x GL Analysis'!$E29),0)) -> 3333.33 | X29: =IF(AND(X$15="Actual",ISBLANK($E$8)),SUMIFS('[1]NS Vendor Details'!$D:$D,'[1]NS Vendor Details'!$H:$H,'G&A Vendor x GL Analysis'!X$20,'[1]NS Vendor Details'!$L:$L,'G&A Vendor x GL Analysis'!$D29,'[1]NS Vendor Details'!$O:$O,'G&A Vendor x GL Analysis'!$F29,'[1]NS Vendor Details'!$N:$N,'G&A Vendor x GL Analysis'!$C29,'[1]NS Vendor Details'!$I:$I,'G&A Vendor x GL Analysis'!$E29),IF(X$15="Actual",SUMIFS('[1]NS Vendor Details'!$D:$D,'[1]NS Vendor Details'!$H:$H,'G&A Vendor x GL Analysis'!X$20,'[1]NS Vendor Details'!$L:$L,'G&A Vendor x GL Analysis'!$D29,'[1]NS Vendor Details'!$O:$O,'G&A Vendor x GL Analysis'!$F29,'[1]NS Vendor Details'!$N:$N,'G&A Vendor x GL Analysis'!$C29,'[1]NS Vendor Details'!$K:$K,'G&A Vendor x GL Analysis'!$E$8,'[1]NS Vendor Details'!$I:$I,'G&A Vendor x GL Analysis'!$E29),0)) -> 2500.01 | Y29: =IF(AND(Y$15="Actual",ISBLANK($E$8)),SUMIFS('[1]NS Vendor Details'!$D:$D,'[1]NS Vendor Details'!$H:$H,'G&A Vendor x GL Analysis'!Y$20,'[1]NS Vendor Details'!$L:$L,'G&A Vendor x GL Analysis'!$D29,'[1]NS Vendor Details'!$O:$O,'G&A Vendor x GL Analysis'!$F29,'[1]NS Vendor Details'!$N:$N,'G&A Vendor x GL Analysis'!$C29,'[1]NS Vendor Details'!$I:$I,'G&A Vendor x GL Analysis'!$E29),IF(Y$15="Actual",SUMIFS('[1]NS Vendor Details'!$D:$D,'[1]NS Vendor Details'!$H:$H,'G&A Vendor x GL Analysis'!Y$20,'[1]NS Vendor Details'!$L:$L,'G&A Vendor x GL Analysis'!$D29,'[1]NS Vendor Details'!$O:$O,'G&A Vendor x GL Analysis'!$F29,'[1]NS Vendor Details'!$N:$N,'G&A Vendor x GL Analysis'!$C29,'[1]NS Vendor Details'!$K:$K,'G&A Vendor x GL Analysis'!$E$8,'[1]NS Vendor Details'!$I:$I,'G&A Vendor x GL Analysis'!$E29),0)) -> 4166.67 | Z29: =IF(AND(Z$15="Actual",ISBLANK($E$8)),SUMIFS('[1]NS Vendor Details'!$D:$D,'[1]NS Vendor Details'!$H:$H,'G&A Vendor x GL Analysis'!Z$20,'[1]NS Vendor Details'!$L:$L,'G&A Vendor x GL Analysis'!$D29,'[1]NS Vendor Details'!$O:$O,'G&A Vendor x GL Analysis'!$F29,'[1]NS Vendor Details'!$N:$N,'G&A Vendor x GL Analysis'!$C29,'[1]NS Vendor Details'!$I:$I,'G&A Vendor x GL Analysis'!$E29),IF(Z$15="Actual",SUMIFS('[1]NS Vendor Details'!$D:$D,'[1]NS Vendor Details'!$H:$H,'G&A Vendor x GL Analysis'!Z$20,'[1]NS Vendor Details'!$L:$L,'G&A Vendor x GL Analysis'!$D29,'[1]NS Vendor Details'!$O:$O,'G&A Vendor x GL Analysis'!$F29,'[1]NS Vendor Details'!$N:$N,'G&A Vendor x GL Analysis'!$C29,'[1]NS Vendor Details'!$K:$K,'G&A Vendor x GL Analysis'!$E$8,'[1]NS Vendor Details'!$I:$I,'G&A Vendor x GL Analysis'!$E29),0)) -> 4166.66 | ... AD29: =IF(AND(AD$15="Actual",ISBLANK($E$8)),SUMIFS('[1]NS Vendor Details'!$D:$D,'[1]NS Vendor Details'!$H:$H,'G&A Vendor x GL Analysis'!AD$20,'[1]NS Vendor Details'!$L:$L,'G&A Vendor x GL Analysis'!$D29,'[1]NS Vendor Details'!$O:$O,'G&A Vendor x GL Analysis'!$F29,'[1]NS Vendor Details'!$N:$N,'G&A Vendor x GL Analysis'!$C29,'[1]NS Vendor Details'!$I:$I,'G&A Vendor x GL Analysis'!$E29),IF(AD$15="Actual",SUMIFS('[1]NS Vendor Details'!$D:$D,'[1]NS Vendor Details'!$H:$H,'G&A Vendor x GL Analysis'!AD$20,'[1]NS Vendor Details'!$L:$L,'G&A Vendor x GL Analysis'!$D29,'[1]NS Vendor Details'!$O:$O,'G&A Vendor x GL Analysis'!$F29,'[1]NS Vendor Details'!$N:$N,'G&A Vendor x GL Analysis'!$C29,'[1]NS Vendor Details'!$K:$K,'G&A Vendor x GL Analysis'!$E$8,'[1]NS Vendor Details'!$I:$I,'G&A Vendor x GL Analysis'!$E29),0)) -> 0 | AF29: =ABS(S29)+ABS(T29)+ABS(U29)+ABS(V29)+ABS(W29)+ABS(X29)+ABS(Y29)+ABS(Z29)+ABS(AA29)+ABS(AB29)+ABS(AC29)+ABS(AD29) -> 20833.34
A30: =D30&E30 -> Advertising6285 - SEM Brand Marketing | C30: SG&A | D30: =D29 -> Advertising | E30: 6285 - SEM Brand Marketing | F30: Google | G30: =IF(AND(G$15="Actual",ISBLANK($E$8)),SUMIFS('[1]NS Vendor Details'!$D:$D,'[1]NS Vendor Details'!$H:$H,'G&A Vendor x GL Analysis'!G$20,'[1]NS Vendor Details'!$L:$L,'G&A Vendor x GL Analysis'!$D30,'[1]NS Vendor Details'!$O:$O,'G&A Vendor x GL Analysis'!$F30,'[1]NS Vendor Details'!$N:$N,'G&A Vendor x GL Analysis'!$C30),IF(G$15="Actual",SUMIFS('[1]NS Vendor Details'!$D:$D,'[1]NS Vendor Details'!$H:$H,'G&A Vendor x GL Analysis'!G$20,'[1]NS Vendor Details'!$L:$L,'G&A Vendor x GL Analysis'!$D30,'[1]NS Vendor Details'!$O:$O,'G&A Vendor x GL Analysis'!$F30,'[1]NS Vendor Details'!$N:$N,'G&A Vendor x GL Analysis'!$C30,'[1]NS Vendor Details'!$K:$K,'G&A Vendor x GL Analysis'!$E$8),0)) -> 0 | H30: =IF(AND(H$15="Actual",ISBLANK($E$8)),SUMIFS('[1]NS Vendor Details'!$D:$D,'[1]NS Vendor Details'!$H:$H,'G&A Vendor x GL Analysis'!H$20,'[1]NS Vendor Details'!$L:$L,'G&A Vendor x GL Analysis'!$D30,'[1]NS Vendor Details'!$O:$O,'G&A Vendor x GL Analysis'!$F30,'[1]NS Vendor Details'!$N:$N,'G&A Vendor x GL Analysis'!$C30),IF(H$15="Actual",SUMIFS('[1]NS Vendor Details'!$D:$D,'[1]NS Vendor Details'!$H:$H,'G&A Vendor x GL Analysis'!H$20,'[1]NS Vendor Details'!$L:$L,'G&A Vendor x GL Analysis'!$D30,'[1]NS Vendor Details'!$O:$O,'G&A Vendor x GL Analysis'!$F30,'[1]NS Vendor Details'!$N:$N,'G&A Vendor x GL Analysis'!$C30,'[1]NS Vendor Details'!$K:$K,'G&A Vendor x GL Analysis'!$E$8),0)) -> 0 | I30: =IF(AND(I$15="Actual",ISBLANK($E$8)),SUMIFS('[1]NS Vendor Details'!$D:$D,'[1]NS Vendor Details'!$H:$H,'G&A Vendor x GL Analysis'!I$20,'[1]NS Vendor Details'!$L:$L,'G&A Vendor x GL Analysis'!$D30,'[1]NS Vendor Details'!$O:$O,'G&A Vendor x GL Analysis'!$F30,'[1]NS Vendor Details'!$N:$N,'G&A Vendor x GL Analysis'!$C30),IF(I$15="Actual",SUMIFS('[1]NS Vendor Details'!$D:$D,'[1]NS Vendor Details'!$H:$H,'G&A Vendor x GL Analysis'!I$20,'[1]NS Vendor Details'!$L:$L,'G&A Vendor x GL Analysis'!$D30,'[1]NS Vendor Details'!$O:$O,'G&A Vendor x GL Analysis'!$F30,'[1]NS Vendor Details'!$N:$N,'G&A Vendor x GL Analysis'!$C30,'[1]NS Vendor Details'!$K:$K,'G&A Vendor x GL Analysis'!$E$8),0)) -> 0 | J30: =IF(AND(J$15="Actual",ISBLANK($E$8)),SUMIFS('[1]NS Vendor Details'!$D:$D,'[1]NS Vendor Details'!$H:$H,'G&A Vendor x GL Analysis'!J$20,'[1]NS Vendor Details'!$L:$L,'G&A Vendor x GL Analysis'!$D30,'[1]NS Vendor Details'!$O:$O,'G&A Vendor x GL Analysis'!$F30,'[1]NS Vendor Details'!$N:$N,'G&A Vendor x GL Analysis'!$C30),IF(J$15="Actual",SUMIFS('[1]NS Vendor Details'!$D:$D,'[1]NS Vendor Details'!$H:$H,'G&A Vendor x GL Analysis'!J$20,'[1]NS Vendor Details'!$L:$L,'G&A Vendor x GL Analysis'!$D30,'[1]NS Vendor Details'!$O:$O,'G&A Vendor x GL Analysis'!$F30,'[1]NS Vendor Details'!$N:$N,'G&A Vendor x GL Analysis'!$C30,'[1]NS Vendor Details'!$K:$K,'G&A Vendor x GL Analysis'!$E$8),0)) -> 0 | K30: =IF(AND(K$15="Actual",ISBLANK($E$8)),SUMIFS('[1]NS Vendor Details'!$D:$D,'[1]NS Vendor Details'!$H:$H,'G&A Vendor x GL Analysis'!K$20,'[1]NS Vendor Details'!$L:$L,'G&A Vendor x GL Analysis'!$D30,'[1]NS Vendor Details'!$O:$O,'G&A Vendor x GL Analysis'!$F30,'[1]NS Vendor Details'!$N:$N,'G&A Vendor x GL Analysis'!$C30),IF(K$15="Actual",SUMIFS('[1]NS Vendor Details'!$D:$D,'[1]NS Vendor Details'!$H:$H,'G&A Vendor x GL Analysis'!K$20,'[1]NS Vendor Details'!$L:$L,'G&A Vendor x GL Analysis'!$D30,'[1]NS Vendor Details'!$O:$O,'G&A Vendor x GL Analysis'!$F30,'[1]NS Vendor Details'!$N:$N,'G&A Vendor x GL Analysis'!$C30,'[1]NS Vendor Details'!$K:$K,'G&A Vendor x GL Analysis'!$E$8),0)) -> 0 | L30: =IF(AND(L$15="Actual",ISBLANK($E$8)),SUMIFS('[1]NS Vendor Details'!$D:$D,'[1]NS Vendor Details'!$H:$H,'G&A Vendor x GL Analysis'!L$20,'[1]NS Vendor Details'!$L:$L,'G&A Vendor x GL Analysis'!$D30,'[1]NS Vendor Details'!$O:$O,'G&A Vendor x GL Analysis'!$F30,'[1]NS Vendor Details'!$N:$N,'G&A Vendor x GL Analysis'!$C30),IF(L$15="Actual",SUMIFS('[1]NS Vendor Details'!$D:$D,'[1]NS Vendor Details'!$H:$H,'G&A Vendor x GL Analysis'!L$20,'[1]NS Vendor Details'!$L:$L,'G&A Vendor x GL Analysis'!$D30,'[1]NS Vendor Details'!$O:$O,'G&A Vendor x GL Analysis'!$F30,'[1]NS Vendor Details'!$N:$N,'G&A Vendor x GL Analysis'!$C30,'[1]NS Vendor Details'!$K:$K,'G&A Vendor x GL Analysis'!$E$8),0)) -> 0 | M30: =IF(AND(M$15="Actual",ISBLANK($E$8)),SUMIFS('[1]NS Vendor Details'!$D:$D,'[1]NS Vendor Details'!$H:$H,'G&A Vendor x GL Analysis'!M$20,'[1]NS Vendor Details'!$L:$L,'G&A Vendor x GL Analysis'!$D30,'[1]NS Vendor Details'!$O:$O,'G&A Vendor x GL Analysis'!$F30,'[1]NS Vendor Details'!$N:$N,'G&A Vendor x GL Analysis'!$C30),IF(M$15="Actual",SUMIFS('[1]NS Vendor Details'!$D:$D,'[1]NS Vendor Details'!$H:$H,'G&A Vendor x GL Analysis'!M$20,'[1]NS Vendor Details'!$L:$L,'G&A Vendor x GL Analysis'!$D30,'[1]NS Vendor Details'!$O:$O,'G&A Vendor x GL Analysis'!$F30,'[1]NS Vendor Details'!$N:$N,'G&A Vendor x GL Analysis'!$C30,'[1]NS Vendor Details'!$K:$K,'G&A Vendor x GL Analysis'!$E$8),0)) -> 0 | N30: =IF(AND(N$15="Actual",ISBLANK($E$8)),SUMIFS('[1]NS Vendor Details'!$D:$D,'[1]NS Vendor Details'!$H:$H,'G&A Vendor x GL Analysis'!N$20,'[1]NS Vendor Details'!$L:$L,'G&A Vendor x GL Analysis'!$D30,'[1]NS Vendor Details'!$O:$O,'G&A Vendor x GL Analysis'!$F30,'[1]NS Vendor Details'!$N:$N,'G&A Vendor x GL Analysis'!$C30),IF(N$15="Actual",SUMIFS('[1]NS Vendor Details'!$D:$D,'[1]NS Vendor Details'!$H:$H,'G&A Vendor x GL Analysis'!N$20,'[1]NS Vendor Details'!$L:$L,'G&A Vendor x GL Analysis'!$D30,'[1]NS Vendor Details'!$O:$O,'G&A Vendor x GL Analysis'!$F30,'[1]NS Vendor Details'!$N:$N,'G&A Vendor x GL Analysis'!$C30,'[1]NS Vendor Details'!$K:$K,'G&A Vendor x GL Analysis'!$E$8),0)) -> 0 | ... R30: =IF(AND(R$15="Actual",ISBLANK($E$8)),SUMIFS('[1]NS Vendor Details'!$D:$D,'[1]NS Vendor Details'!$H:$H,'G&A Vendor x GL Analysis'!R$20,'[1]NS Vendor Details'!$L:$L,'G&A Vendor x GL Analysis'!$D30,'[1]NS Vendor Details'!$O:$O,'G&A Vendor x GL Analysis'!$F30,'[1]NS Vendor Details'!$N:$N,'G&A Vendor x GL Analysis'!$C30),IF(R$15="Actual",SUMIFS('[1]NS Vendor Details'!$D:$D,'[1]NS Vendor Details'!$H:$H,'G&A Vendor x GL Analysis'!R$20,'[1]NS Vendor Details'!$L:$L,'G&A Vendor x GL Analysis'!$D30,'[1]NS Vendor Details'!$O:$O,'G&A Vendor x GL Analysis'!$F30,'[1]NS Vendor Details'!$N:$N,'G&A Vendor x GL Analysis'!$C30,'[1]NS Vendor Details'!$K:$K,'G&A Vendor x GL Analysis'!$E$8),0)) -> 0 | S30: =IF(AND(S$15="Actual",ISBLANK($E$8)),SUMIFS('[1]NS Vendor Details'!$D:$D,'[1]NS Vendor Details'!$H:$H,'G&A Vendor x GL Analysis'!S$20,'[1]NS Vendor Details'!$L:$L,'G&A Vendor x GL Analysis'!$D30,'[1]NS Vendor Details'!$O:$O,'G&A Vendor x GL Analysis'!$F30,'[1]NS Vendor Details'!$N:$N,'G&A Vendor x GL Analysis'!$C30,'[1]NS Vendor Details'!$I:$I,'G&A Vendor x GL Analysis'!$E30),IF(S$15="Actual",SUMIFS('[1]NS Vendor Details'!$D:$D,'[1]NS Vendor Details'!$H:$H,'G&A Vendor x GL Analysis'!S$20,'[1]NS Vendor Details'!$L:$L,'G&A Vendor x GL Analysis'!$D30,'[1]NS Vendor Details'!$O:$O,'G&A Vendor x GL Analysis'!$F30,'[1]NS Vendor Details'!$N:$N,'G&A Vendor x GL Analysis'!$C30,'[1]NS Vendor Details'!$K:$K,'G&A Vendor x GL Analysis'!$E$8,'[1]NS Vendor Details'!$I:$I,'G&A Vendor x GL Analysis'!$E30),0)) -> 52909.75 | T30: =IF(AND(T$15="Actual",ISBLANK($E$8)),SUMIFS('[1]NS Vendor Details'!$D:$D,'[1]NS Vendor Details'!$H:$H,'G&A Vendor x GL Analysis'!T$20,'[1]NS Vendor Details'!$L:$L,'G&A Vendor x GL Analysis'!$D30,'[1]NS Vendor Details'!$O:$O,'G&A Vendor x GL Analysis'!$F30,'[1]NS Vendor Details'!$N:$N,'G&A Vendor x GL Analysis'!$C30,'[1]NS Vendor Details'!$I:$I,'G&A Vendor x GL Analysis'!$E30),IF(T$15="Actual",SUMIFS('[1]NS Vendor Details'!$D:$D,'[1]NS Vendor Details'!$H:$H,'G&A Vendor x GL Analysis'!T$20,'[1]NS Vendor Details'!$L:$L,'G&A Vendor x GL Analysis'!$D30,'[1]NS Vendor Details'!$O:$O,'G&A Vendor x GL Analysis'!$F30,'[1]NS Vendor Details'!$N:$N,'G&A Vendor x GL Analysis'!$C30,'[1]NS Vendor Details'!$K:$K,'G&A Vendor x GL Analysis'!$E$8,'[1]NS Vendor Details'!$I:$I,'G&A Vendor x GL Analysis'!$E30),0)) -> 12846.03 | U30: =IF(AND(U$15="Actual",ISBLANK($E$8)),SUMIFS('[1]NS Vendor Details'!$D:$D,'[1]NS Vendor Details'!$H:$H,'G&A Vendor x GL Analysis'!U$20,'[1]NS Vendor Details'!$L:$L,'G&A Vendor x GL Analysis'!$D30,'[1]NS Vendor Details'!$O:$O,'G&A Vendor x GL Analysis'!$F30,'[1]NS Vendor Details'!$N:$N,'G&A Vendor x GL Analysis'!$C30,'[1]NS Vendor Details'!$I:$I,'G&A Vendor x GL Analysis'!$E30),IF(U$15="Actual",SUMIFS('[1]NS Vendor Details'!$D:$D,'[1]NS Vendor Details'!$H:$H,'G&A Vendor x GL Analysis'!U$20,'[1]NS Vendor Details'!$L:$L,'G&A Vendor x GL Analysis'!$D30,'[1]NS Vendor Details'!$O:$O,'G&A Vendor x GL Analysis'!$F30,'[1]NS Vendor Details'!$N:$N,'G&A Vendor x GL Analysis'!$C30,'[1]NS Vendor Details'!$K:$K,'G&A Vendor x GL Analysis'!$E$8,'[1]NS Vendor Details'!$I:$I,'G&A Vendor x GL Analysis'!$E30),0)) -> 22779.69 | V30: =IF(AND(V$15="Actual",ISBLANK($E$8)),SUMIFS('[1]NS Vendor Details'!$D:$D,'[1]NS Vendor Details'!$H:$H,'G&A Vendor x GL Analysis'!V$20,'[1]NS Vendor Details'!$L:$L,'G&A Vendor x GL Analysis'!$D30,'[1]NS Vendor Details'!$O:$O,'G&A Vendor x GL Analysis'!$F30,'[1]NS Vendor Details'!$N:$N,'G&A Vendor x GL Analysis'!$C30,'[1]NS Vendor Details'!$I:$I,'G&A Vendor x GL Analysis'!$E30),IF(V$15="Actual",SUMIFS('[1]NS Vendor Details'!$D:$D,'[1]NS Vendor Details'!$H:$H,'G&A Vendor x GL Analysis'!V$20,'[1]NS Vendor Details'!$L:$L,'G&A Vendor x GL Analysis'!$D30,'[1]NS Vendor Details'!$O:$O,'G&A Vendor x GL Analysis'!$F30,'[1]NS Vendor Details'!$N:$N,'G&A Vendor x GL Analysis'!$C30,'[1]NS Vendor Details'!$K:$K,'G&A Vendor x GL Analysis'!$E$8,'[1]NS Vendor Details'!$I:$I,'G&A Vendor x GL Analysis'!$E30),0)) -> 12363.11 | W30: =IF(AND(W$15="Actual",ISBLANK($E$8)),SUMIFS('[1]NS Vendor Details'!$D:$D,'[1]NS Vendor Details'!$H:$H,'G&A Vendor x GL Analysis'!W$20,'[1]NS Vendor Details'!$L:$L,'G&A Vendor x GL Analysis'!$D30,'[1]NS Vendor Details'!$O:$O,'G&A Vendor x GL Analysis'!$F30,'[1]NS Vendor Details'!$N:$N,'G&A Vendor x GL Analysis'!$C30,'[1]NS Vendor Details'!$I:$I,'G&A Vendor x GL Analysis'!$E30),IF(W$15="Actual",SUMIFS('[1]NS Vendor Details'!$D:$D,'[1]NS Vendor Details'!$H:$H,'G&A Vendor x GL Analysis'!W$20,'[1]NS Vendor Details'!$L:$L,'G&A Vendor x GL Analysis'!$D30,'[1]NS Vendor Details'!$O:$O,'G&A Vendor x GL Analysis'!$F30,'[1]NS Vendor Details'!$N:$N,'G&A Vendor x GL Analysis'!$C30,'[1]NS Vendor Details'!$K:$K,'G&A Vendor x GL Analysis'!$E$8,'[1]NS Vendor Details'!$I:$I,'G&A Vendor x GL Analysis'!$E30),0)) -> 10850.15 | X30: =IF(AND(X$15="Actual",ISBLANK($E$8)),SUMIFS('[1]NS Vendor Details'!$D:$D,'[1]NS Vendor Details'!$H:$H,'G&A Vendor x GL Analysis'!X$20,'[1]NS Vendor Details'!$L:$L,'G&A Vendor x GL Analysis'!$D30,'[1]NS Vendor Details'!$O:$O,'G&A Vendor x GL Analysis'!$F30,'[1]NS Vendor Details'!$N:$N,'G&A Vendor x GL Analysis'!$C30,'[1]NS Vendor Details'!$I:$I,'G&A Vendor x GL Analysis'!$E30),IF(X$15="Actual",SUMIFS('[1]NS Vendor Details'!$D:$D,'[1]NS Vendor Details'!$H:$H,'G&A Vendor x GL Analysis'!X$20,'[1]NS Vendor Details'!$L:$L,'G&A Vendor x GL Analysis'!$D30,'[1]NS Vendor Details'!$O:$O,'G&A Vendor x GL Analysis'!$F30,'[1]NS Vendor Details'!$N:$N,'G&A Vendor x GL Analysis'!$C30,'[1]NS Vendor Details'!$K:$K,'G&A Vendor x GL Analysis'!$E$8,'[1]NS Vendor Details'!$I:$I,'G&A Vendor x GL Analysis'!$E30),0)) -> 9524.9 | Y30: =IF(AND(Y$15="Actual",ISBLANK($E$8)),SUMIFS('[1]NS Vendor Details'!$D:$D,'[1]NS Vendor Details'!$H:$H,'G&A Vendor x GL Analysis'!Y$20,'[1]NS Vendor Details'!$L:$L,'G&A Vendor x GL Analysis'!$D30,'[1]NS Vendor Details'!$O:$O,'G&A Vendor x GL Analysis'!$F30,'[1]NS Vendor Details'!$N:$N,'G&A Vendor x GL Analysis'!$C30,'[1]NS Vendor Details'!$I:$I,'G&A Vendor x GL Analysis'!$E30),IF(Y$15="Actual",SUMIFS('[1]NS Vendor Details'!$D:$D,'[1]NS Vendor Details'!$H:$H,'G&A Vendor x GL Analysis'!Y$20,'[1]NS Vendor Details'!$L:$L,'G&A Vendor x GL Analysis'!$D30,'[1]NS Vendor Details'!$O:$O,'G&A Vendor x GL Analysis'!$F30,'[1]NS Vendor Details'!$N:$N,'G&A Vendor x GL Analysis'!$C30,'[1]NS Vendor Details'!$K:$K,'G&A Vendor x GL Analysis'!$E$8,'[1]NS Vendor Details'!$I:$I,'G&A Vendor x GL Analysis'!$E30),0)) -> 9059.06 | Z30: =IF(AND(Z$15="Actual",ISBLANK($E$8)),SUMIFS('[1]NS Vendor Details'!$D:$D,'[1]NS Vendor Details'!$H:$H,'G&A Vendor x GL Analysis'!Z$20,'[1]NS Vendor Details'!$L:$L,'G&A Vendor x GL Analysis'!$D30,'[1]NS Vendor Details'!$O:$O,'G&A Vendor x GL Analysis'!$F30,'[1]NS Vendor Details'!$N:$N,'G&A Vendor x GL Analysis'!$C30,'[1]NS Vendor Details'!$I:$I,'G&A Vendor x GL Analysis'!$E30),IF(Z$15="Actual",SUMIFS('[1]NS Vendor Details'!$D:$D,'[1]NS Vendor Details'!$H:$H,'G&A Vendor x GL Analysis'!Z$20,'[1]NS Vendor Details'!$L:$L,'G&A Vendor x GL Analysis'!$D30,'[1]NS Vendor Details'!$O:$O,'G&A Vendor x GL Analysis'!$F30,'[1]NS Vendor Details'!$N:$N,'G&A Vendor x GL Analysis'!$C30,'[1]NS Vendor Details'!$K:$K,'G&A Vendor x GL Analysis'!$E$8,'[1]NS Vendor Details'!$I:$I,'G&A Vendor x GL Analysis'!$E30),0)) -> 13596.89 | ... AD30: =IF(AND(AD$15="Actual",ISBLANK($E$8)),SUMIFS('[1]NS Vendor Details'!$D:$D,'[1]NS Vendor Details'!$H:$H,'G&A Vendor x GL Analysis'!AD$20,'[1]NS Vendor Details'!$L:$L,'G&A Vendor x GL Analysis'!$D30,'[1]NS Vendor Details'!$O:$O,'G&A Vendor x GL Analysis'!$F30,'[1]NS Vendor Details'!$N:$N,'G&A Vendor x GL Analysis'!$C30,'[1]NS Vendor Details'!$I:$I,'G&A Vendor x GL Analysis'!$E30),IF(AD$15="Actual",SUMIFS('[1]NS Vendor Details'!$D:$D,'[1]NS Vendor Details'!$H:$H,'G&A Vendor x GL Analysis'!AD$20,'[1]NS Vendor Details'!$L:$L,'G&A Vendor x GL Analysis'!$D30,'[1]NS Vendor Details'!$O:$O,'G&A Vendor x GL Analysis'!$F30,'[1]NS Vendor Details'!$N:$N,'G&A Vendor x GL Analysis'!$C30,'[1]NS Vendor Details'!$K:$K,'G&A Vendor x GL Analysis'!$E$8,'[1]NS Vendor Details'!$I:$I,'G&A Vendor x GL Analysis'!$E30),0)) -> 0 | AF30: =ABS(S30)+ABS(T30)+ABS(U30)+ABS(V30)+ABS(W30)+ABS(X30)+ABS(Y30)+ABS(Z30)+ABS(AA30)+ABS(AB30)+ABS(AC30)+ABS(AD30) -> 143929.58
A31: =D31&E31 -> Advertising6288 - Model | C31: SG&A | D31: =D30 -> Advertising | E31: 6288 - Model | F31: Que Management, Inc | G31: =IF(AND(G$15="Actual",ISBLANK($E$8)),SUMIFS('[1]NS Vendor Details'!$D:$D,'[1]NS Vendor Details'!$H:$H,'G&A Vendor x GL Analysis'!G$20,'[1]NS Vendor Details'!$L:$L,'G&A Vendor x GL Analysis'!$D31,'[1]NS Vendor Details'!$O:$O,'G&A Vendor x GL Analysis'!$F31,'[1]NS Vendor Details'!$N:$N,'G&A Vendor x GL Analysis'!$C31),IF(G$15="Actual",SUMIFS('[1]NS Vendor Details'!$D:$D,'[1]NS Vendor Details'!$H:$H,'G&A Vendor x GL Analysis'!G$20,'[1]NS Vendor Details'!$L:$L,'G&A Vendor x GL Analysis'!$D31,'[1]NS Vendor Details'!$O:$O,'G&A Vendor x GL Analysis'!$F31,'[1]NS Vendor Details'!$N:$N,'G&A Vendor x GL Analysis'!$C31,'[1]NS Vendor Details'!$K:$K,'G&A Vendor x GL Analysis'!$E$8),0)) -> 0 | H31: =IF(AND(H$15="Actual",ISBLANK($E$8)),SUMIFS('[1]NS Vendor Details'!$D:$D,'[1]NS Vendor Details'!$H:$H,'G&A Vendor x GL Analysis'!H$20,'[1]NS Vendor Details'!$L:$L,'G&A Vendor x GL Analysis'!$D31,'[1]NS Vendor Details'!$O:$O,'G&A Vendor x GL Analysis'!$F31,'[1]NS Vendor Details'!$N:$N,'G&A Vendor x GL Analysis'!$C31),IF(H$15="Actual",SUMIFS('[1]NS Vendor Details'!$D:$D,'[1]NS Vendor Details'!$H:$H,'G&A Vendor x GL Analysis'!H$20,'[1]NS Vendor Details'!$L:$L,'G&A Vendor x GL Analysis'!$D31,'[1]NS Vendor Details'!$O:$O,'G&A Vendor x GL Analysis'!$F31,'[1]NS Vendor Details'!$N:$N,'G&A Vendor x GL Analysis'!$C31,'[1]NS Vendor Details'!$K:$K,'G&A Vendor x GL Analysis'!$E$8),0)) -> 0 | I31: =IF(AND(I$15="Actual",ISBLANK($E$8)),SUMIFS('[1]NS Vendor Details'!$D:$D,'[1]NS Vendor Details'!$H:$H,'G&A Vendor x GL Analysis'!I$20,'[1]NS Vendor Details'!$L:$L,'G&A Vendor x GL Analysis'!$D31,'[1]NS Vendor Details'!$O:$O,'G&A Vendor x GL Analysis'!$F31,'[1]NS Vendor Details'!$N:$N,'G&A Vendor x GL Analysis'!$C31),IF(I$15="Actual",SUMIFS('[1]NS Vendor Details'!$D:$D,'[1]NS Vendor Details'!$H:$H,'G&A Vendor x GL Analysis'!I$20,'[1]NS Vendor Details'!$L:$L,'G&A Vendor x GL Analysis'!$D31,'[1]NS Vendor Details'!$O:$O,'G&A Vendor x GL Analysis'!$F31,'[1]NS Vendor Details'!$N:$N,'G&A Vendor x GL Analysis'!$C31,'[1]NS Vendor Details'!$K:$K,'G&A Vendor x GL Analysis'!$E$8),0)) -> 0 | J31: =IF(AND(J$15="Actual",ISBLANK($E$8)),SUMIFS('[1]NS Vendor Details'!$D:$D,'[1]NS Vendor Details'!$H:$H,'G&A Vendor x GL Analysis'!J$20,'[1]NS Vendor Details'!$L:$L,'G&A Vendor x GL Analysis'!$D31,'[1]NS Vendor Details'!$O:$O,'G&A Vendor x GL Analysis'!$F31,'[1]NS Vendor Details'!$N:$N,'G&A Vendor x GL Analysis'!$C31),IF(J$15="Actual",SUMIFS('[1]NS Vendor Details'!$D:$D,'[1]NS Vendor Details'!$H:$H,'G&A Vendor x GL Analysis'!J$20,'[1]NS Vendor Details'!$L:$L,'G&A Vendor x GL Analysis'!$D31,'[1]NS Vendor Details'!$O:$O,'G&A Vendor x GL Analysis'!$F31,'[1]NS Vendor Details'!$N:$N,'G&A Vendor x GL Analysis'!$C31,'[1]NS Vendor Details'!$K:$K,'G&A Vendor x GL Analysis'!$E$8),0)) -> 0 | K31: =IF(AND(K$15="Actual",ISBLANK($E$8)),SUMIFS('[1]NS Vendor Details'!$D:$D,'[1]NS Vendor Details'!$H:$H,'G&A Vendor x GL Analysis'!K$20,'[1]NS Vendor Details'!$L:$L,'G&A Vendor x GL Analysis'!$D31,'[1]NS Vendor Details'!$O:$O,'G&A Vendor x GL Analysis'!$F31,'[1]NS Vendor Details'!$N:$N,'G&A Vendor x GL Analysis'!$C31),IF(K$15="Actual",SUMIFS('[1]NS Vendor Details'!$D:$D,'[1]NS Vendor Details'!$H:$H,'G&A Vendor x GL Analysis'!K$20,'[1]NS Vendor Details'!$L:$L,'G&A Vendor x GL Analysis'!$D31,'[1]NS Vendor Details'!$O:$O,'G&A Vendor x GL Analysis'!$F31,'[1]NS Vendor Details'!$N:$N,'G&A Vendor x GL Analysis'!$C31,'[1]NS Vendor Details'!$K:$K,'G&A Vendor x GL Analysis'!$E$8),0)) -> 0 | L31: =IF(AND(L$15="Actual",ISBLANK($E$8)),SUMIFS('[1]NS Vendor Details'!$D:$D,'[1]NS Vendor Details'!$H:$H,'G&A Vendor x GL Analysis'!L$20,'[1]NS Vendor Details'!$L:$L,'G&A Vendor x GL Analysis'!$D31,'[1]NS Vendor Details'!$O:$O,'G&A Vendor x GL Analysis'!$F31,'[1]NS Vendor Details'!$N:$N,'G&A Vendor x GL Analysis'!$C31),IF(L$15="Actual",SUMIFS('[1]NS Vendor Details'!$D:$D,'[1]NS Vendor Details'!$H:$H,'G&A Vendor x GL Analysis'!L$20,'[1]NS Vendor Details'!$L:$L,'G&A Vendor x GL Analysis'!$D31,'[1]NS Vendor Details'!$O:$O,'G&A Vendor x GL Analysis'!$F31,'[1]NS Vendor Details'!$N:$N,'G&A Vendor x GL Analysis'!$C31,'[1]NS Vendor Details'!$K:$K,'G&A Vendor x GL Analysis'!$E$8),0)) -> 0 | M31: =IF(AND(M$15="Actual",ISBLANK($E$8)),SUMIFS('[1]NS Vendor Details'!$D:$D,'[1]NS Vendor Details'!$H:$H,'G&A Vendor x GL Analysis'!M$20,'[1]NS Vendor Details'!$L:$L,'G&A Vendor x GL Analysis'!$D31,'[1]NS Vendor Details'!$O:$O,'G&A Vendor x GL Analysis'!$F31,'[1]NS Vendor Details'!$N:$N,'G&A Vendor x GL Analysis'!$C31),IF(M$15="Actual",SUMIFS('[1]NS Vendor Details'!$D:$D,'[1]NS Vendor Details'!$H:$H,'G&A Vendor x GL Analysis'!M$20,'[1]NS Vendor Details'!$L:$L,'G&A Vendor x GL Analysis'!$D31,'[1]NS Vendor Details'!$O:$O,'G&A Vendor x GL Analysis'!$F31,'[1]NS Vendor Details'!$N:$N,'G&A Vendor x GL Analysis'!$C31,'[1]NS Vendor Details'!$K:$K,'G&A Vendor x GL Analysis'!$E$8),0)) -> 0 | N31: =IF(AND(N$15="Actual",ISBLANK($E$8)),SUMIFS('[1]NS Vendor Details'!$D:$D,'[1]NS Vendor Details'!$H:$H,'G&A Vendor x GL Analysis'!N$20,'[1]NS Vendor Details'!$L:$L,'G&A Vendor x GL Analysis'!$D31,'[1]NS Vendor Details'!$O:$O,'G&A Vendor x GL Analysis'!$F31,'[1]NS Vendor Details'!$N:$N,'G&A Vendor x GL Analysis'!$C31),IF(N$15="Actual",SUMIFS('[1]NS Vendor Details'!$D:$D,'[1]NS Vendor Details'!$H:$H,'G&A Vendor x GL Analysis'!N$20,'[1]NS Vendor Details'!$L:$L,'G&A Vendor x GL Analysis'!$D31,'[1]NS Vendor Details'!$O:$O,'G&A Vendor x GL Analysis'!$F31,'[1]NS Vendor Details'!$N:$N,'G&A Vendor x GL Analysis'!$C31,'[1]NS Vendor Details'!$K:$K,'G&A Vendor x GL Analysis'!$E$8),0)) -> 0 | ... R31: =IF(AND(R$15="Actual",ISBLANK($E$8)),SUMIFS('[1]NS Vendor Details'!$D:$D,'[1]NS Vendor Details'!$H:$H,'G&A Vendor x GL Analysis'!R$20,'[1]NS Vendor Details'!$L:$L,'G&A Vendor x GL Analysis'!$D31,'[1]NS Vendor Details'!$O:$O,'G&A Vendor x GL Analysis'!$F31,'[1]NS Vendor Details'!$N:$N,'G&A Vendor x GL Analysis'!$C31),IF(R$15="Actual",SUMIFS('[1]NS Vendor Details'!$D:$D,'[1]NS Vendor Details'!$H:$H,'G&A Vendor x GL Analysis'!R$20,'[1]NS Vendor Details'!$L:$L,'G&A Vendor x GL Analysis'!$D31,'[1]NS Vendor Details'!$O:$O,'G&A Vendor x GL Analysis'!$F31,'[1]NS Vendor Details'!$N:$N,'G&A Vendor x GL Analysis'!$C31,'[1]NS Vendor Details'!$K:$K,'G&A Vendor x GL Analysis'!$E$8),0)) -> 2880 | S31: =IF(AND(S$15="Actual",ISBLANK($E$8)),SUMIFS('[1]NS Vendor Details'!$D:$D,'[1]NS Vendor Details'!$H:$H,'G&A Vendor x GL Analysis'!S$20,'[1]NS Vendor Details'!$L:$L,'G&A Vendor x GL Analysis'!$D31,'[1]NS Vendor Details'!$O:$O,'G&A Vendor x GL Analysis'!$F31,'[1]NS Vendor Details'!$N:$N,'G&A Vendor x GL Analysis'!$C31,'[1]NS Vendor Details'!$I:$I,'G&A Vendor x GL Analysis'!$E31),IF(S$15="Actual",SUMIFS('[1]NS Vendor Details'!$D:$D,'[1]NS Vendor Details'!$H:$H,'G&A Vendor x GL Analysis'!S$20,'[1]NS Vendor Details'!$L:$L,'G&A Vendor x GL Analysis'!$D31,'[1]NS Vendor Details'!$O:$O,'G&A Vendor x GL Analysis'!$F31,'[1]NS Vendor Details'!$N:$N,'G&A Vendor x GL Analysis'!$C31,'[1]NS Vendor Details'!$K:$K,'G&A Vendor x GL Analysis'!$E$8,'[1]NS Vendor Details'!$I:$I,'G&A Vendor x GL Analysis'!$E31),0)) -> 1440 | T31: =IF(AND(T$15="Actual",ISBLANK($E$8)),SUMIFS('[1]NS Vendor Details'!$D:$D,'[1]NS Vendor Details'!$H:$H,'G&A Vendor x GL Analysis'!T$20,'[1]NS Vendor Details'!$L:$L,'G&A Vendor x GL Analysis'!$D31,'[1]NS Vendor Details'!$O:$O,'G&A Vendor x GL Analysis'!$F31,'[1]NS Vendor Details'!$N:$N,'G&A Vendor x GL Analysis'!$C31,'[1]NS Vendor Details'!$I:$I,'G&A Vendor x GL Analysis'!$E31),IF(T$15="Actual",SUMIFS('[1]NS Vendor Details'!$D:$D,'[1]NS Vendor Details'!$H:$H,'G&A Vendor x GL Analysis'!T$20,'[1]NS Vendor Details'!$L:$L,'G&A Vendor x GL Analysis'!$D31,'[1]NS Vendor Details'!$O:$O,'G&A Vendor x GL Analysis'!$F31,'[1]NS Vendor Details'!$N:$N,'G&A Vendor x GL Analysis'!$C31,'[1]NS Vendor Details'!$K:$K,'G&A Vendor x GL Analysis'!$E$8,'[1]NS Vendor Details'!$I:$I,'G&A Vendor x GL Analysis'!$E31),0)) -> 0 | U31: =IF(AND(U$15="Actual",ISBLANK($E$8)),SUMIFS('[1]NS Vendor Details'!$D:$D,'[1]NS Vendor Details'!$H:$H,'G&A Vendor x GL Analysis'!U$20,'[1]NS Vendor Details'!$L:$L,'G&A Vendor x GL Analysis'!$D31,'[1]NS Vendor Details'!$O:$O,'G&A Vendor x GL Analysis'!$F31,'[1]NS Vendor Details'!$N:$N,'G&A Vendor x GL Analysis'!$C31,'[1]NS Vendor Details'!$I:$I,'G&A Vendor x GL Analysis'!$E31),IF(U$15="Actual",SUMIFS('[1]NS Vendor Details'!$D:$D,'[1]NS Vendor Details'!$H:$H,'G&A Vendor x GL Analysis'!U$20,'[1]NS Vendor Details'!$L:$L,'G&A Vendor x GL Analysis'!$D31,'[1]NS Vendor Details'!$O:$O,'G&A Vendor x GL Analysis'!$F31,'[1]NS Vendor Details'!$N:$N,'G&A Vendor x GL Analysis'!$C31,'[1]NS Vendor Details'!$K:$K,'G&A Vendor x GL Analysis'!$E$8,'[1]NS Vendor Details'!$I:$I,'G&A Vendor x GL Analysis'!$E31),0)) -> 0 | V31: =IF(AND(V$15="Actual",ISBLANK($E$8)),SUMIFS('[1]NS Vendor Details'!$D:$D,'[1]NS Vendor Details'!$H:$H,'G&A Vendor x GL Analysis'!V$20,'[1]NS Vendor Details'!$L:$L,'G&A Vendor x GL Analysis'!$D31,'[1]NS Vendor Details'!$O:$O,'G&A Vendor x GL Analysis'!$F31,'[1]NS Vendor Details'!$N:$N,'G&A Vendor x GL Analysis'!$C31,'[1]NS Vendor Details'!$I:$I,'G&A Vendor x GL Analysis'!$E31),IF(V$15="Actual",SUMIFS('[1]NS Vendor Details'!$D:$D,'[1]NS Vendor Details'!$H:$H,'G&A Vendor x GL Analysis'!V$20,'[1]NS Vendor Details'!$L:$L,'G&A Vendor x GL Analysis'!$D31,'[1]NS Vendor Details'!$O:$O,'G&A Vendor x GL Analysis'!$F31,'[1]NS Vendor Details'!$N:$N,'G&A Vendor x GL Analysis'!$C31,'[1]NS Vendor Details'!$K:$K,'G&A Vendor x GL Analysis'!$E$8,'[1]NS Vendor Details'!$I:$I,'G&A Vendor x GL Analysis'!$E31),0)) -> 0 | W31: =IF(AND(W$15="Actual",ISBLANK($E$8)),SUMIFS('[1]NS Vendor Details'!$D:$D,'[1]NS Vendor Details'!$H:$H,'G&A Vendor x GL Analysis'!W$20,'[1]NS Vendor Details'!$L:$L,'G&A Vendor x GL Analysis'!$D31,'[1]NS Vendor Details'!$O:$O,'G&A Vendor x GL Analysis'!$F31,'[1]NS Vendor Details'!$N:$N,'G&A Vendor x GL Analysis'!$C31,'[1]NS Vendor Details'!$I:$I,'G&A Vendor x GL Analysis'!$E31),IF(W$15="Actual",SUMIFS('[1]NS Vendor Details'!$D:$D,'[1]NS Vendor Details'!$H:$H,'G&A Vendor x GL Analysis'!W$20,'[1]NS Vendor Details'!$L:$L,'G&A Vendor x GL Analysis'!$D31,'[1]NS Vendor Details'!$O:$O,'G&A Vendor x GL Analysis'!$F31,'[1]NS Vendor Details'!$N:$N,'G&A Vendor x GL Analysis'!$C31,'[1]NS Vendor Details'!$K:$K,'G&A Vendor x GL Analysis'!$E$8,'[1]NS Vendor Details'!$I:$I,'G&A Vendor x GL Analysis'!$E31),0)) -> 0 | X31: =IF(AND(X$15="Actual",ISBLANK($E$8)),SUMIFS('[1]NS Vendor Details'!$D:$D,'[1]NS Vendor Details'!$H:$H,'G&A Vendor x GL Analysis'!X$20,'[1]NS Vendor Details'!$L:$L,'G&A Vendor x GL Analysis'!$D31,'[1]NS Vendor Details'!$O:$O,'G&A Vendor x GL Analysis'!$F31,'[1]NS Vendor Details'!$N:$N,'G&A Vendor x GL Analysis'!$C31,'[1]NS Vendor Details'!$I:$I,'G&A Vendor x GL Analysis'!$E31),IF(X$15="Actual",SUMIFS('[1]NS Vendor Details'!$D:$D,'[1]NS Vendor Details'!$H:$H,'G&A Vendor x GL Analysis'!X$20,'[1]NS Vendor Details'!$L:$L,'G&A Vendor x GL Analysis'!$D31,'[1]NS Vendor Details'!$O:$O,'G&A Vendor x GL Analysis'!$F31,'[1]NS Vendor Details'!$N:$N,'G&A Vendor x GL Analysis'!$C31,'[1]NS Vendor Details'!$K:$K,'G&A Vendor x GL Analysis'!$E$8,'[1]NS Vendor Details'!$I:$I,'G&A Vendor x GL Analysis'!$E31),0)) -> 1800 | Y31: =IF(AND(Y$15="Actual",ISBLANK($E$8)),SUMIFS('[1]NS Vendor Details'!$D:$D,'[1]NS Vendor Details'!$H:$H,'G&A Vendor x GL Analysis'!Y$20,'[1]NS Vendor Details'!$L:$L,'G&A Vendor x GL Analysis'!$D31,'[1]NS Vendor Details'!$O:$O,'G&A Vendor x GL Analysis'!$F31,'[1]NS Vendor Details'!$N:$N,'G&A Vendor x GL Analysis'!$C31,'[1]NS Vendor Details'!$I:$I,'G&A Vendor x GL Analysis'!$E31),IF(Y$15="Actual",SUMIFS('[1]NS Vendor Details'!$D:$D,'[1]NS Vendor Details'!$H:$H,'G&A Vendor x GL Analysis'!Y$20,'[1]NS Vendor Details'!$L:$L,'G&A Vendor x GL Analysis'!$D31,'[1]NS Vendor Details'!$O:$O,'G&A Vendor x GL Analysis'!$F31,'[1]NS Vendor Details'!$N:$N,'G&A Vendor x GL Analysis'!$C31,'[1]NS Vendor Details'!$K:$K,'G&A Vendor x GL Analysis'!$E$8,'[1]NS Vendor Details'!$I:$I,'G&A Vendor x GL Analysis'!$E31),0)) -> 1800 | Z31: =IF(AND(Z$15="Actual",ISBLANK($E$8)),SUMIFS('[1]NS Vendor Details'!$D:$D,'[1]NS Vendor Details'!$H:$H,'G&A Vendor x GL Analysis'!Z$20,'[1]NS Vendor Details'!$L:$L,'G&A Vendor x GL Analysis'!$D31,'[1]NS Vendor Details'!$O:$O,'G&A Vendor x GL Analysis'!$F31,'[1]NS Vendor Details'!$N:$N,'G&A Vendor x GL Analysis'!$C31,'[1]NS Vendor Details'!$I:$I,'G&A Vendor x GL Analysis'!$E31),IF(Z$15="Actual",SUMIFS('[1]NS Vendor Details'!$D:$D,'[1]NS Vendor Details'!$H:$H,'G&A Vendor x GL Analysis'!Z$20,'[1]NS Vendor Details'!$L:$L,'G&A Vendor x GL Analysis'!$D31,'[1]NS Vendor Details'!$O:$O,'G&A Vendor x GL Analysis'!$F31,'[1]NS Vendor Details'!$N:$N,'G&A Vendor x GL Analysis'!$C31,'[1]NS Vendor Details'!$K:$K,'G&A Vendor x GL Analysis'!$E$8,'[1]NS Vendor Details'!$I:$I,'G&A Vendor x GL Analysis'!$E31),0)) -> 0 | ... AD31: =IF(AND(AD$15="Actual",ISBLANK($E$8)),SUMIFS('[1]NS Vendor Details'!$D:$D,'[1]NS Vendor Details'!$H:$H,'G&A Vendor x GL Analysis'!AD$20,'[1]NS Vendor Details'!$L:$L,'G&A Vendor x GL Analysis'!$D31,'[1]NS Vendor Details'!$O:$O,'G&A Vendor x GL Analysis'!$F31,'[1]NS Vendor Details'!$N:$N,'G&A Vendor x GL Analysis'!$C31,'[1]NS Vendor Details'!$I:$I,'G&A Vendor x GL Analysis'!$E31),IF(AD$15="Actual",SUMIFS('[1]NS Vendor Details'!$D:$D,'[1]NS Vendor Details'!$H:$H,'G&A Vendor x GL Analysis'!AD$20,'[1]NS Vendor Details'!$L:$L,'G&A Vendor x GL Analysis'!$D31,'[1]NS Vendor Details'!$O:$O,'G&A Vendor x GL Analysis'!$F31,'[1]NS Vendor Details'!$N:$N,'G&A Vendor x GL Analysis'!$C31,'[1]NS Vendor Details'!$K:$K,'G&A Vendor x GL Analysis'!$E$8,'[1]NS Vendor Details'!$I:$I,'G&A Vendor x GL Analysis'!$E31),0)) -> 0 | AF31: =ABS(S31)+ABS(T31)+ABS(U31)+ABS(V31)+ABS(W31)+ABS(X31)+ABS(Y31)+ABS(Z31)+ABS(AA31)+ABS(AB31)+ABS(AC31)+ABS(AD31) -> 5040
A32: =D32&E32 -> Advertising6288 - Model | C32: SG&A | D32: =D31 -> Advertising | E32: 6288 - Model | F32: State Artist Management | G32: =IF(AND(G$15="Actual",ISBLANK($E$8)),SUMIFS('[1]NS Vendor Details'!$D:$D,'[1]NS Vendor Details'!$H:$H,'G&A Vendor x GL Analysis'!G$20,'[1]NS Vendor Details'!$L:$L,'G&A Vendor x GL Analysis'!$D32,'[1]NS Vendor Details'!$O:$O,'G&A Vendor x GL Analysis'!$F32,'[1]NS Vendor Details'!$N:$N,'G&A Vendor x GL Analysis'!$C32),IF(G$15="Actual",SUMIFS('[1]NS Vendor Details'!$D:$D,'[1]NS Vendor Details'!$H:$H,'G&A Vendor x GL Analysis'!G$20,'[1]NS Vendor Details'!$L:$L,'G&A Vendor x GL Analysis'!$D32,'[1]NS Vendor Details'!$O:$O,'G&A Vendor x GL Analysis'!$F32,'[1]NS Vendor Details'!$N:$N,'G&A Vendor x GL Analysis'!$C32,'[1]NS Vendor Details'!$K:$K,'G&A Vendor x GL Analysis'!$E$8),0)) -> 2625 | H32: =IF(AND(H$15="Actual",ISBLANK($E$8)),SUMIFS('[1]NS Vendor Details'!$D:$D,'[1]NS Vendor Details'!$H:$H,'G&A Vendor x GL Analysis'!H$20,'[1]NS Vendor Details'!$L:$L,'G&A Vendor x GL Analysis'!$D32,'[1]NS Vendor Details'!$O:$O,'G&A Vendor x GL Analysis'!$F32,'[1]NS Vendor Details'!$N:$N,'G&A Vendor x GL Analysis'!$C32),IF(H$15="Actual",SUMIFS('[1]NS Vendor Details'!$D:$D,'[1]NS Vendor Details'!$H:$H,'G&A Vendor x GL Analysis'!H$20,'[1]NS Vendor Details'!$L:$L,'G&A Vendor x GL Analysis'!$D32,'[1]NS Vendor Details'!$O:$O,'G&A Vendor x GL Analysis'!$F32,'[1]NS Vendor Details'!$N:$N,'G&A Vendor x GL Analysis'!$C32,'[1]NS Vendor Details'!$K:$K,'G&A Vendor x GL Analysis'!$E$8),0)) -> 0 | I32: =IF(AND(I$15="Actual",ISBLANK($E$8)),SUMIFS('[1]NS Vendor Details'!$D:$D,'[1]NS Vendor Details'!$H:$H,'G&A Vendor x GL Analysis'!I$20,'[1]NS Vendor Details'!$L:$L,'G&A Vendor x GL Analysis'!$D32,'[1]NS Vendor Details'!$O:$O,'G&A Vendor x GL Analysis'!$F32,'[1]NS Vendor Details'!$N:$N,'G&A Vendor x GL Analysis'!$C32),IF(I$15="Actual",SUMIFS('[1]NS Vendor Details'!$D:$D,'[1]NS Vendor Details'!$H:$H,'G&A Vendor x GL Analysis'!I$20,'[1]NS Vendor Details'!$L:$L,'G&A Vendor x GL Analysis'!$D32,'[1]NS Vendor Details'!$O:$O,'G&A Vendor x GL Analysis'!$F32,'[1]NS Vendor Details'!$N:$N,'G&A Vendor x GL Analysis'!$C32,'[1]NS Vendor Details'!$K:$K,'G&A Vendor x GL Analysis'!$E$8),0)) -> 2100 | J32: =IF(AND(J$15="Actual",ISBLANK($E$8)),SUMIFS('[1]NS Vendor Details'!$D:$D,'[1]NS Vendor Details'!$H:$H,'G&A Vendor x GL Analysis'!J$20,'[1]NS Vendor Details'!$L:$L,'G&A Vendor x GL Analysis'!$D32,'[1]NS Vendor Details'!$O:$O,'G&A Vendor x GL Analysis'!$F32,'[1]NS Vendor Details'!$N:$N,'G&A Vendor x GL Analysis'!$C32),IF(J$15="Actual",SUMIFS('[1]NS Vendor Details'!$D:$D,'[1]NS Vendor Details'!$H:$H,'G&A Vendor x GL Analysis'!J$20,'[1]NS Vendor Details'!$L:$L,'G&A Vendor x GL Analysis'!$D32,'[1]NS Vendor Details'!$O:$O,'G&A Vendor x GL Analysis'!$F32,'[1]NS Vendor Details'!$N:$N,'G&A Vendor x GL Analysis'!$C32,'[1]NS Vendor Details'!$K:$K,'G&A Vendor x GL Analysis'!$E$8),0)) -> 540 | K32: =IF(AND(K$15="Actual",ISBLANK($E$8)),SUMIFS('[1]NS Vendor Details'!$D:$D,'[1]NS Vendor Details'!$H:$H,'G&A Vendor x GL Analysis'!K$20,'[1]NS Vendor Details'!$L:$L,'G&A Vendor x GL Analysis'!$D32,'[1]NS Vendor Details'!$O:$O,'G&A Vendor x GL Analysis'!$F32,'[1]NS Vendor Details'!$N:$N,'G&A Vendor x GL Analysis'!$C32),IF(K$15="Actual",SUMIFS('[1]NS Vendor Details'!$D:$D,'[1]NS Vendor Details'!$H:$H,'G&A Vendor x GL Analysis'!K$20,'[1]NS Vendor Details'!$L:$L,'G&A Vendor x GL Analysis'!$D32,'[1]NS Vendor Details'!$O:$O,'G&A Vendor x GL Analysis'!$F32,'[1]NS Vendor Details'!$N:$N,'G&A Vendor x GL Analysis'!$C32,'[1]NS Vendor Details'!$K:$K,'G&A Vendor x GL Analysis'!$E$8),0)) -> 2400 | L32: =IF(AND(L$15="Actual",ISBLANK($E$8)),SUMIFS('[1]NS Vendor Details'!$D:$D,'[1]NS Vendor Details'!$H:$H,'G&A Vendor x GL Analysis'!L$20,'[1]NS Vendor Details'!$L:$L,'G&A Vendor x GL Analysis'!$D32,'[1]NS Vendor Details'!$O:$O,'G&A Vendor x GL Analysis'!$F32,'[1]NS Vendor Details'!$N:$N,'G&A Vendor x GL Analysis'!$C32),IF(L$15="Actual",SUMIFS('[1]NS Vendor Details'!$D:$D,'[1]NS Vendor Details'!$H:$H,'G&A Vendor x GL Analysis'!L$20,'[1]NS Vendor Details'!$L:$L,'G&A Vendor x GL Analysis'!$D32,'[1]NS Vendor Details'!$O:$O,'G&A Vendor x GL Analysis'!$F32,'[1]NS Vendor Details'!$N:$N,'G&A Vendor x GL Analysis'!$C32,'[1]NS Vendor Details'!$K:$K,'G&A Vendor x GL Analysis'!$E$8),0)) -> 6780 | M32: =IF(AND(M$15="Actual",ISBLANK($E$8)),SUMIFS('[1]NS Vendor Details'!$D:$D,'[1]NS Vendor Details'!$H:$H,'G&A Vendor x GL Analysis'!M$20,'[1]NS Vendor Details'!$L:$L,'G&A Vendor x GL Analysis'!$D32,'[1]NS Vendor Details'!$O:$O,'G&A Vendor x GL Analysis'!$F32,'[1]NS Vendor Details'!$N:$N,'G&A Vendor x GL Analysis'!$C32),IF(M$15="Actual",SUMIFS('[1]NS Vendor Details'!$D:$D,'[1]NS Vendor Details'!$H:$H,'G&A Vendor x GL Analysis'!M$20,'[1]NS Vendor Details'!$L:$L,'G&A Vendor x GL Analysis'!$D32,'[1]NS Vendor Details'!$O:$O,'G&A Vendor x GL Analysis'!$F32,'[1]NS Vendor Details'!$N:$N,'G&A Vendor x GL Analysis'!$C32,'[1]NS Vendor Details'!$K:$K,'G&A Vendor x GL Analysis'!$E$8),0)) -> 4680 | N32: =IF(AND(N$15="Actual",ISBLANK($E$8)),SUMIFS('[1]NS Vendor Details'!$D:$D,'[1]NS Vendor Details'!$H:$H,'G&A Vendor x GL Analysis'!N$20,'[1]NS Vendor Details'!$L:$L,'G&A Vendor x GL Analysis'!$D32,'[1]NS Vendor Details'!$O:$O,'G&A Vendor x GL Analysis'!$F32,'[1]NS Vendor Details'!$N:$N,'G&A Vendor x GL Analysis'!$C32),IF(N$15="Actual",SUMIFS('[1]NS Vendor Details'!$D:$D,'[1]NS Vendor Details'!$H:$H,'G&A Vendor x GL Analysis'!N$20,'[1]NS Vendor Details'!$L:$L,'G&A Vendor x GL Analysis'!$D32,'[1]NS Vendor Details'!$O:$O,'G&A Vendor x GL Analysis'!$F32,'[1]NS Vendor Details'!$N:$N,'G&A Vendor x GL Analysis'!$C32,'[1]NS Vendor Details'!$K:$K,'G&A Vendor x GL Analysis'!$E$8),0)) -> 3900 | ... R32: =IF(AND(R$15="Actual",ISBLANK($E$8)),SUMIFS('[1]NS Vendor Details'!$D:$D,'[1]NS Vendor Details'!$H:$H,'G&A Vendor x GL Analysis'!R$20,'[1]NS Vendor Details'!$L:$L,'G&A Vendor x GL Analysis'!$D32,'[1]NS Vendor Details'!$O:$O,'G&A Vendor x GL Analysis'!$F32,'[1]NS Vendor Details'!$N:$N,'G&A Vendor x GL Analysis'!$C32),IF(R$15="Actual",SUMIFS('[1]NS Vendor Details'!$D:$D,'[1]NS Vendor Details'!$H:$H,'G&A Vendor x GL Analysis'!R$20,'[1]NS Vendor Details'!$L:$L,'G&A Vendor x GL Analysis'!$D32,'[1]NS Vendor Details'!$O:$O,'G&A Vendor x GL Analysis'!$F32,'[1]NS Vendor Details'!$N:$N,'G&A Vendor x GL Analysis'!$C32,'[1]NS Vendor Details'!$K:$K,'G&A Vendor x GL Analysis'!$E$8),0)) -> 4860 | S32: =IF(AND(S$15="Actual",ISBLANK($E$8)),SUMIFS('[1]NS Vendor Details'!$D:$D,'[1]NS Vendor Details'!$H:$H,'G&A Vendor x GL Analysis'!S$20,'[1]NS Vendor Details'!$L:$L,'G&A Vendor x GL Analysis'!$D32,'[1]NS Vendor Details'!$O:$O,'G&A Vendor x GL Analysis'!$F32,'[1]NS Vendor Details'!$N:$N,'G&A Vendor x GL Analysis'!$C32,'[1]NS Vendor Details'!$I:$I,'G&A Vendor x GL Analysis'!$E32),IF(S$15="Actual",SUMIFS('[1]NS Vendor Details'!$D:$D,'[1]NS Vendor Details'!$H:$H,'G&A Vendor x GL Analysis'!S$20,'[1]NS Vendor Details'!$L:$L,'G&A Vendor x GL Analysis'!$D32,'[1]NS Vendor Details'!$O:$O,'G&A Vendor x GL Analysis'!$F32,'[1]NS Vendor Details'!$N:$N,'G&A Vendor x GL Analysis'!$C32,'[1]NS Vendor Details'!$K:$K,'G&A Vendor x GL Analysis'!$E$8,'[1]NS Vendor Details'!$I:$I,'G&A Vendor x GL Analysis'!$E32),0)) -> 3840 | T32: =IF(AND(T$15="Actual",ISBLANK($E$8)),SUMIFS('[1]NS Vendor Details'!$D:$D,'[1]NS Vendor Details'!$H:$H,'G&A Vendor x GL Analysis'!T$20,'[1]NS Vendor Details'!$L:$L,'G&A Vendor x GL Analysis'!$D32,'[1]NS Vendor Details'!$O:$O,'G&A Vendor x GL Analysis'!$F32,'[1]NS Vendor Details'!$N:$N,'G&A Vendor x GL Analysis'!$C32,'[1]NS Vendor Details'!$I:$I,'G&A Vendor x GL Analysis'!$E32),IF(T$15="Actual",SUMIFS('[1]NS Vendor Details'!$D:$D,'[1]NS Vendor Details'!$H:$H,'G&A Vendor x GL Analysis'!T$20,'[1]NS Vendor Details'!$L:$L,'G&A Vendor x GL Analysis'!$D32,'[1]NS Vendor Details'!$O:$O,'G&A Vendor x GL Analysis'!$F32,'[1]NS Vendor Details'!$N:$N,'G&A Vendor x GL Analysis'!$C32,'[1]NS Vendor Details'!$K:$K,'G&A Vendor x GL Analysis'!$E$8,'[1]NS Vendor Details'!$I:$I,'G&A Vendor x GL Analysis'!$E32),0)) -> 1500 | U32: =IF(AND(U$15="Actual",ISBLANK($E$8)),SUMIFS('[1]NS Vendor Details'!$D:$D,'[1]NS Vendor Details'!$H:$H,'G&A Vendor x GL Analysis'!U$20,'[1]NS Vendor Details'!$L:$L,'G&A Vendor x GL Analysis'!$D32,'[1]NS Vendor Details'!$O:$O,'G&A Vendor x GL Analysis'!$F32,'[1]NS Vendor Details'!$N:$N,'G&A Vendor x GL Analysis'!$C32,'[1]NS Vendor Details'!$I:$I,'G&A Vendor x GL Analysis'!$E32),IF(U$15="Actual",SUMIFS('[1]NS Vendor Details'!$D:$D,'[1]NS Vendor Details'!$H:$H,'G&A Vendor x GL Analysis'!U$20,'[1]NS Vendor Details'!$L:$L,'G&A Vendor x GL Analysis'!$D32,'[1]NS Vendor Details'!$O:$O,'G&A Vendor x GL Analysis'!$F32,'[1]NS Vendor Details'!$N:$N,'G&A Vendor x GL Analysis'!$C32,'[1]NS Vendor Details'!$K:$K,'G&A Vendor x GL Analysis'!$E$8,'[1]NS Vendor Details'!$I:$I,'G&A Vendor x GL Analysis'!$E32),0)) -> 840 | V32: =IF(AND(V$15="Actual",ISBLANK($E$8)),SUMIFS('[1]NS Vendor Details'!$D:$D,'[1]NS Vendor Details'!$H:$H,'G&A Vendor x GL Analysis'!V$20,'[1]NS Vendor Details'!$L:$L,'G&A Vendor x GL Analysis'!$D32,'[1]NS Vendor Details'!$O:$O,'G&A Vendor x GL Analysis'!$F32,'[1]NS Vendor Details'!$N:$N,'G&A Vendor x GL Analysis'!$C32,'[1]NS Vendor Details'!$I:$I,'G&A Vendor x GL Analysis'!$E32),IF(V$15="Actual",SUMIFS('[1]NS Vendor Details'!$D:$D,'[1]NS Vendor Details'!$H:$H,'G&A Vendor x GL Analysis'!V$20,'[1]NS Vendor Details'!$L:$L,'G&A Vendor x GL Analysis'!$D32,'[1]NS Vendor Details'!$O:$O,'G&A Vendor x GL Analysis'!$F32,'[1]NS Vendor Details'!$N:$N,'G&A Vendor x GL Analysis'!$C32,'[1]NS Vendor Details'!$K:$K,'G&A Vendor x GL Analysis'!$E$8,'[1]NS Vendor Details'!$I:$I,'G&A Vendor x GL Analysis'!$E32),0)) -> 330 | W32: =IF(AND(W$15="Actual",ISBLANK($E$8)),SUMIFS('[1]NS Vendor Details'!$D:$D,'[1]NS Vendor Details'!$H:$H,'G&A Vendor x GL Analysis'!W$20,'[1]NS Vendor Details'!$L:$L,'G&A Vendor x GL Analysis'!$D32,'[1]NS Vendor Details'!$O:$O,'G&A Vendor x GL Analysis'!$F32,'[1]NS Vendor Details'!$N:$N,'G&A Vendor x GL Analysis'!$C32,'[1]NS Vendor Details'!$I:$I,'G&A Vendor x GL Analysis'!$E32),IF(W$15="Actual",SUMIFS('[1]NS Vendor Details'!$D:$D,'[1]NS Vendor Details'!$H:$H,'G&A Vendor x GL Analysis'!W$20,'[1]NS Vendor Details'!$L:$L,'G&A Vendor x GL Analysis'!$D32,'[1]NS Vendor Details'!$O:$O,'G&A Vendor x GL Analysis'!$F32,'[1]NS Vendor Details'!$N:$N,'G&A Vendor x GL Analysis'!$C32,'[1]NS Vendor Details'!$K:$K,'G&A Vendor x GL Analysis'!$E$8,'[1]NS Vendor Details'!$I:$I,'G&A Vendor x GL Analysis'!$E32),0)) -> 4980 | X32: =IF(AND(X$15="Actual",ISBLANK($E$8)),SUMIFS('[1]NS Vendor Details'!$D:$D,'[1]NS Vendor Details'!$H:$H,'G&A Vendor x GL Analysis'!X$20,'[1]NS Vendor Details'!$L:$L,'G&A Vendor x GL Analysis'!$D32,'[1]NS Vendor Details'!$O:$O,'G&A Vendor x GL Analysis'!$F32,'[1]NS Vendor Details'!$N:$N,'G&A Vendor x GL Analysis'!$C32,'[1]NS Vendor Details'!$I:$I,'G&A Vendor x GL Analysis'!$E32),IF(X$15="Actual",SUMIFS('[1]NS Vendor Details'!$D:$D,'[1]NS Vendor Details'!$H:$H,'G&A Vendor x GL Analysis'!X$20,'[1]NS Vendor Details'!$L:$L,'G&A Vendor x GL Analysis'!$D32,'[1]NS Vendor Details'!$O:$O,'G&A Vendor x GL Analysis'!$F32,'[1]NS Vendor Details'!$N:$N,'G&A Vendor x GL Analysis'!$C32,'[1]NS Vendor Details'!$K:$K,'G&A Vendor x GL Analysis'!$E$8,'[1]NS Vendor Details'!$I:$I,'G&A Vendor x GL Analysis'!$E32),0)) -> 1980 | Y32: =IF(AND(Y$15="Actual",ISBLANK($E$8)),SUMIFS('[1]NS Vendor Details'!$D:$D,'[1]NS Vendor Details'!$H:$H,'G&A Vendor x GL Analysis'!Y$20,'[1]NS Vendor Details'!$L:$L,'G&A Vendor x GL Analysis'!$D32,'[1]NS Vendor Details'!$O:$O,'G&A Vendor x GL Analysis'!$F32,'[1]NS Vendor Details'!$N:$N,'G&A Vendor x GL Analysis'!$C32,'[1]NS Vendor Details'!$I:$I,'G&A Vendor x GL Analysis'!$E32),IF(Y$15="Actual",SUMIFS('[1]NS Vendor Details'!$D:$D,'[1]NS Vendor Details'!$H:$H,'G&A Vendor x GL Analysis'!Y$20,'[1]NS Vendor Details'!$L:$L,'G&A Vendor x GL Analysis'!$D32,'[1]NS Vendor Details'!$O:$O,'G&A Vendor x GL Analysis'!$F32,'[1]NS Vendor Details'!$N:$N,'G&A Vendor x GL Analysis'!$C32,'[1]NS Vendor Details'!$K:$K,'G&A Vendor x GL Analysis'!$E$8,'[1]NS Vendor Details'!$I:$I,'G&A Vendor x GL Analysis'!$E32),0)) -> 3150 | Z32: =IF(AND(Z$15="Actual",ISBLANK($E$8)),SUMIFS('[1]NS Vendor Details'!$D:$D,'[1]NS Vendor Details'!$H:$H,'G&A Vendor x GL Analysis'!Z$20,'[1]NS Vendor Details'!$L:$L,'G&A Vendor x GL Analysis'!$D32,'[1]NS Vendor Details'!$O:$O,'G&A Vendor x GL Analysis'!$F32,'[1]NS Vendor Details'!$N:$N,'G&A Vendor x GL Analysis'!$C32,'[1]NS Vendor Details'!$I:$I,'G&A Vendor x GL Analysis'!$E32),IF(Z$15="Actual",SUMIFS('[1]NS Vendor Details'!$D:$D,'[1]NS Vendor Details'!$H:$H,'G&A Vendor x GL Analysis'!Z$20,'[1]NS Vendor Details'!$L:$L,'G&A Vendor x GL Analysis'!$D32,'[1]NS Vendor Details'!$O:$O,'G&A Vendor x GL Analysis'!$F32,'[1]NS Vendor Details'!$N:$N,'G&A Vendor x GL Analysis'!$C32,'[1]NS Vendor Details'!$K:$K,'G&A Vendor x GL Analysis'!$E$8,'[1]NS Vendor Details'!$I:$I,'G&A Vendor x GL Analysis'!$E32),0)) -> 1485 | ... AD32: =IF(AND(AD$15="Actual",ISBLANK($E$8)),SUMIFS('[1]NS Vendor Details'!$D:$D,'[1]NS Vendor Details'!$H:$H,'G&A Vendor x GL Analysis'!AD$20,'[1]NS Vendor Details'!$L:$L,'G&A Vendor x GL Analysis'!$D32,'[1]NS Vendor Details'!$O:$O,'G&A Vendor x GL Analysis'!$F32,'[1]NS Vendor Details'!$N:$N,'G&A Vendor x GL Analysis'!$C32,'[1]NS Vendor Details'!$I:$I,'G&A Vendor x GL Analysis'!$E32),IF(AD$15="Actual",SUMIFS('[1]NS Vendor Details'!$D:$D,'[1]NS Vendor Details'!$H:$H,'G&A Vendor x GL Analysis'!AD$20,'[1]NS Vendor Details'!$L:$L,'G&A Vendor x GL Analysis'!$D32,'[1]NS Vendor Details'!$O:$O,'G&A Vendor x GL Analysis'!$F32,'[1]NS Vendor Details'!$N:$N,'G&A Vendor x GL Analysis'!$C32,'[1]NS Vendor Details'!$K:$K,'G&A Vendor x GL Analysis'!$E$8,'[1]NS Vendor Details'!$I:$I,'G&A Vendor x GL Analysis'!$E32),0)) -> 0 | AF32: =ABS(S32)+ABS(T32)+ABS(U32)+ABS(V32)+ABS(W32)+ABS(X32)+ABS(Y32)+ABS(Z32)+ABS(AA32)+ABS(AB32)+ABS(AC32)+ABS(AD32) -> 20745
A33: =D33&E33 -> Advertising6288 - Model | C33: SG&A | D33: =D32 -> Advertising | E33: 6288 - Model | F33: Women Management LLC | G33: =IF(AND(G$15="Actual",ISBLANK($E$8)),SUMIFS('[1]NS Vendor Details'!$D:$D,'[1]NS Vendor Details'!$H:$H,'G&A Vendor x GL Analysis'!G$20,'[1]NS Vendor Details'!$L:$L,'G&A Vendor x GL Analysis'!$D33,'[1]NS Vendor Details'!$O:$O,'G&A Vendor x GL Analysis'!$F33,'[1]NS Vendor Details'!$N:$N,'G&A Vendor x GL Analysis'!$C33),IF(G$15="Actual",SUMIFS('[1]NS Vendor Details'!$D:$D,'[1]NS Vendor Details'!$H:$H,'G&A Vendor x GL Analysis'!G$20,'[1]NS Vendor Details'!$L:$L,'G&A Vendor x GL Analysis'!$D33,'[1]NS Vendor Details'!$O:$O,'G&A Vendor x GL Analysis'!$F33,'[1]NS Vendor Details'!$N:$N,'G&A Vendor x GL Analysis'!$C33,'[1]NS Vendor Details'!$K:$K,'G&A Vendor x GL Analysis'!$E$8),0)) -> 0 | H33: =IF(AND(H$15="Actual",ISBLANK($E$8)),SUMIFS('[1]NS Vendor Details'!$D:$D,'[1]NS Vendor Details'!$H:$H,'G&A Vendor x GL Analysis'!H$20,'[1]NS Vendor Details'!$L:$L,'G&A Vendor x GL Analysis'!$D33,'[1]NS Vendor Details'!$O:$O,'G&A Vendor x GL Analysis'!$F33,'[1]NS Vendor Details'!$N:$N,'G&A Vendor x GL Analysis'!$C33),IF(H$15="Actual",SUMIFS('[1]NS Vendor Details'!$D:$D,'[1]NS Vendor Details'!$H:$H,'G&A Vendor x GL Analysis'!H$20,'[1]NS Vendor Details'!$L:$L,'G&A Vendor x GL Analysis'!$D33,'[1]NS Vendor Details'!$O:$O,'G&A Vendor x GL Analysis'!$F33,'[1]NS Vendor Details'!$N:$N,'G&A Vendor x GL Analysis'!$C33,'[1]NS Vendor Details'!$K:$K,'G&A Vendor x GL Analysis'!$E$8),0)) -> 0 | I33: =IF(AND(I$15="Actual",ISBLANK($E$8)),SUMIFS('[1]NS Vendor Details'!$D:$D,'[1]NS Vendor Details'!$H:$H,'G&A Vendor x GL Analysis'!I$20,'[1]NS Vendor Details'!$L:$L,'G&A Vendor x GL Analysis'!$D33,'[1]NS Vendor Details'!$O:$O,'G&A Vendor x GL Analysis'!$F33,'[1]NS Vendor Details'!$N:$N,'G&A Vendor x GL Analysis'!$C33),IF(I$15="Actual",SUMIFS('[1]NS Vendor Details'!$D:$D,'[1]NS Vendor Details'!$H:$H,'G&A Vendor x GL Analysis'!I$20,'[1]NS Vendor Details'!$L:$L,'G&A Vendor x GL Analysis'!$D33,'[1]NS Vendor Details'!$O:$O,'G&A Vendor x GL Analysis'!$F33,'[1]NS Vendor Details'!$N:$N,'G&A Vendor x GL Analysis'!$C33,'[1]NS Vendor Details'!$K:$K,'G&A Vendor x GL Analysis'!$E$8),0)) -> 0 | J33: =IF(AND(J$15="Actual",ISBLANK($E$8)),SUMIFS('[1]NS Vendor Details'!$D:$D,'[1]NS Vendor Details'!$H:$H,'G&A Vendor x GL Analysis'!J$20,'[1]NS Vendor Details'!$L:$L,'G&A Vendor x GL Analysis'!$D33,'[1]NS Vendor Details'!$O:$O,'G&A Vendor x GL Analysis'!$F33,'[1]NS Vendor Details'!$N:$N,'G&A Vendor x GL Analysis'!$C33),IF(J$15="Actual",SUMIFS('[1]NS Vendor Details'!$D:$D,'[1]NS Vendor Details'!$H:$H,'G&A Vendor x GL Analysis'!J$20,'[1]NS Vendor Details'!$L:$L,'G&A Vendor x GL Analysis'!$D33,'[1]NS Vendor Details'!$O:$O,'G&A Vendor x GL Analysis'!$F33,'[1]NS Vendor Details'!$N:$N,'G&A Vendor x GL Analysis'!$C33,'[1]NS Vendor Details'!$K:$K,'G&A Vendor x GL Analysis'!$E$8),0)) -> 0 | K33: =IF(AND(K$15="Actual",ISBLANK($E$8)),SUMIFS('[1]NS Vendor Details'!$D:$D,'[1]NS Vendor Details'!$H:$H,'G&A Vendor x GL Analysis'!K$20,'[1]NS Vendor Details'!$L:$L,'G&A Vendor x GL Analysis'!$D33,'[1]NS Vendor Details'!$O:$O,'G&A Vendor x GL Analysis'!$F33,'[1]NS Vendor Details'!$N:$N,'G&A Vendor x GL Analysis'!$C33),IF(K$15="Actual",SUMIFS('[1]NS Vendor Details'!$D:$D,'[1]NS Vendor Details'!$H:$H,'G&A Vendor x GL Analysis'!K$20,'[1]NS Vendor Details'!$L:$L,'G&A Vendor x GL Analysis'!$D33,'[1]NS Vendor Details'!$O:$O,'G&A Vendor x GL Analysis'!$F33,'[1]NS Vendor Details'!$N:$N,'G&A Vendor x GL Analysis'!$C33,'[1]NS Vendor Details'!$K:$K,'G&A Vendor x GL Analysis'!$E$8),0)) -> 0 | L33: =IF(AND(L$15="Actual",ISBLANK($E$8)),SUMIFS('[1]NS Vendor Details'!$D:$D,'[1]NS Vendor Details'!$H:$H,'G&A Vendor x GL Analysis'!L$20,'[1]NS Vendor Details'!$L:$L,'G&A Vendor x GL Analysis'!$D33,'[1]NS Vendor Details'!$O:$O,'G&A Vendor x GL Analysis'!$F33,'[1]NS Vendor Details'!$N:$N,'G&A Vendor x GL Analysis'!$C33),IF(L$15="Actual",SUMIFS('[1]NS Vendor Details'!$D:$D,'[1]NS Vendor Details'!$H:$H,'G&A Vendor x GL Analysis'!L$20,'[1]NS Vendor Details'!$L:$L,'G&A Vendor x GL Analysis'!$D33,'[1]NS Vendor Details'!$O:$O,'G&A Vendor x GL Analysis'!$F33,'[1]NS Vendor Details'!$N:$N,'G&A Vendor x GL Analysis'!$C33,'[1]NS Vendor Details'!$K:$K,'G&A Vendor x GL Analysis'!$E$8),0)) -> 0 | M33: =IF(AND(M$15="Actual",ISBLANK($E$8)),SUMIFS('[1]NS Vendor Details'!$D:$D,'[1]NS Vendor Details'!$H:$H,'G&A Vendor x GL Analysis'!M$20,'[1]NS Vendor Details'!$L:$L,'G&A Vendor x GL Analysis'!$D33,'[1]NS Vendor Details'!$O:$O,'G&A Vendor x GL Analysis'!$F33,'[1]NS Vendor Details'!$N:$N,'G&A Vendor x GL Analysis'!$C33),IF(M$15="Actual",SUMIFS('[1]NS Vendor Details'!$D:$D,'[1]NS Vendor Details'!$H:$H,'G&A Vendor x GL Analysis'!M$20,'[1]NS Vendor Details'!$L:$L,'G&A Vendor x GL Analysis'!$D33,'[1]NS Vendor Details'!$O:$O,'G&A Vendor x GL Analysis'!$F33,'[1]NS Vendor Details'!$N:$N,'G&A Vendor x GL Analysis'!$C33,'[1]NS Vendor Details'!$K:$K,'G&A Vendor x GL Analysis'!$E$8),0)) -> 0 | N33: =IF(AND(N$15="Actual",ISBLANK($E$8)),SUMIFS('[1]NS Vendor Details'!$D:$D,'[1]NS Vendor Details'!$H:$H,'G&A Vendor x GL Analysis'!N$20,'[1]NS Vendor Details'!$L:$L,'G&A Vendor x GL Analysis'!$D33,'[1]NS Vendor Details'!$O:$O,'G&A Vendor x GL Analysis'!$F33,'[1]NS Vendor Details'!$N:$N,'G&A Vendor x GL Analysis'!$C33),IF(N$15="Actual",SUMIFS('[1]NS Vendor Details'!$D:$D,'[1]NS Vendor Details'!$H:$H,'G&A Vendor x GL Analysis'!N$20,'[1]NS Vendor Details'!$L:$L,'G&A Vendor x GL Analysis'!$D33,'[1]NS Vendor Details'!$O:$O,'G&A Vendor x GL Analysis'!$F33,'[1]NS Vendor Details'!$N:$N,'G&A Vendor x GL Analysis'!$C33,'[1]NS Vendor Details'!$K:$K,'G&A Vendor x GL Analysis'!$E$8),0)) -> 0 | ... R33: =IF(AND(R$15="Actual",ISBLANK($E$8)),SUMIFS('[1]NS Vendor Details'!$D:$D,'[1]NS Vendor Details'!$H:$H,'G&A Vendor x GL Analysis'!R$20,'[1]NS Vendor Details'!$L:$L,'G&A Vendor x GL Analysis'!$D33,'[1]NS Vendor Details'!$O:$O,'G&A Vendor x GL Analysis'!$F33,'[1]NS Vendor Details'!$N:$N,'G&A Vendor x GL Analysis'!$C33),IF(R$15="Actual",SUMIFS('[1]NS Vendor Details'!$D:$D,'[1]NS Vendor Details'!$H:$H,'G&A Vendor x GL Analysis'!R$20,'[1]NS Vendor Details'!$L:$L,'G&A Vendor x GL Analysis'!$D33,'[1]NS Vendor Details'!$O:$O,'G&A Vendor x GL Analysis'!$F33,'[1]NS Vendor Details'!$N:$N,'G&A Vendor x GL Analysis'!$C33,'[1]NS Vendor Details'!$K:$K,'G&A Vendor x GL Analysis'!$E$8),0)) -> 0 | S33: =IF(AND(S$15="Actual",ISBLANK($E$8)),SUMIFS('[1]NS Vendor Details'!$D:$D,'[1]NS Vendor Details'!$H:$H,'G&A Vendor x GL Analysis'!S$20,'[1]NS Vendor Details'!$L:$L,'G&A Vendor x GL Analysis'!$D33,'[1]NS Vendor Details'!$O:$O,'G&A Vendor x GL Analysis'!$F33,'[1]NS Vendor Details'!$N:$N,'G&A Vendor x GL Analysis'!$C33,'[1]NS Vendor Details'!$I:$I,'G&A Vendor x GL Analysis'!$E33),IF(S$15="Actual",SUMIFS('[1]NS Vendor Details'!$D:$D,'[1]NS Vendor Details'!$H:$H,'G&A Vendor x GL Analysis'!S$20,'[1]NS Vendor Details'!$L:$L,'G&A Vendor x GL Analysis'!$D33,'[1]NS Vendor Details'!$O:$O,'G&A Vendor x GL Analysis'!$F33,'[1]NS Vendor Details'!$N:$N,'G&A Vendor x GL Analysis'!$C33,'[1]NS Vendor Details'!$K:$K,'G&A Vendor x GL Analysis'!$E$8,'[1]NS Vendor Details'!$I:$I,'G&A Vendor x GL Analysis'!$E33),0)) -> 720 | T33: =IF(AND(T$15="Actual",ISBLANK($E$8)),SUMIFS('[1]NS Vendor Details'!$D:$D,'[1]NS Vendor Details'!$H:$H,'G&A Vendor x GL Analysis'!T$20,'[1]NS Vendor Details'!$L:$L,'G&A Vendor x GL Analysis'!$D33,'[1]NS Vendor Details'!$O:$O,'G&A Vendor x GL Analysis'!$F33,'[1]NS Vendor Details'!$N:$N,'G&A Vendor x GL Analysis'!$C33,'[1]NS Vendor Details'!$I:$I,'G&A Vendor x GL Analysis'!$E33),IF(T$15="Actual",SUMIFS('[1]NS Vendor Details'!$D:$D,'[1]NS Vendor Details'!$H:$H,'G&A Vendor x GL Analysis'!T$20,'[1]NS Vendor Details'!$L:$L,'G&A Vendor x GL Analysis'!$D33,'[1]NS Vendor Details'!$O:$O,'G&A Vendor x GL Analysis'!$F33,'[1]NS Vendor Details'!$N:$N,'G&A Vendor x GL Analysis'!$C33,'[1]NS Vendor Details'!$K:$K,'G&A Vendor x GL Analysis'!$E$8,'[1]NS Vendor Details'!$I:$I,'G&A Vendor x GL Analysis'!$E33),0)) -> 0 | U33: =IF(AND(U$15="Actual",ISBLANK($E$8)),SUMIFS('[1]NS Vendor Details'!$D:$D,'[1]NS Vendor Details'!$H:$H,'G&A Vendor x GL Analysis'!U$20,'[1]NS Vendor Details'!$L:$L,'G&A Vendor x GL Analysis'!$D33,'[1]NS Vendor Details'!$O:$O,'G&A Vendor x GL Analysis'!$F33,'[1]NS Vendor Details'!$N:$N,'G&A Vendor x GL Analysis'!$C33,'[1]NS Vendor Details'!$I:$I,'G&A Vendor x GL Analysis'!$E33),IF(U$15="Actual",SUMIFS('[1]NS Vendor Details'!$D:$D,'[1]NS Vendor Details'!$H:$H,'G&A Vendor x GL Analysis'!U$20,'[1]NS Vendor Details'!$L:$L,'G&A Vendor x GL Analysis'!$D33,'[1]NS Vendor Details'!$O:$O,'G&A Vendor x GL Analysis'!$F33,'[1]NS Vendor Details'!$N:$N,'G&A Vendor x GL Analysis'!$C33,'[1]NS Vendor Details'!$K:$K,'G&A Vendor x GL Analysis'!$E$8,'[1]NS Vendor Details'!$I:$I,'G&A Vendor x GL Analysis'!$E33),0)) -> 0 | V33: =IF(AND(V$15="Actual",ISBLANK($E$8)),SUMIFS('[1]NS Vendor Details'!$D:$D,'[1]NS Vendor Details'!$H:$H,'G&A Vendor x GL Analysis'!V$20,'[1]NS Vendor Details'!$L:$L,'G&A Vendor x GL Analysis'!$D33,'[1]NS Vendor Details'!$O:$O,'G&A Vendor x GL Analysis'!$F33,'[1]NS Vendor Details'!$N:$N,'G&A Vendor x GL Analysis'!$C33,'[1]NS Vendor Details'!$I:$I,'G&A Vendor x GL Analysis'!$E33),IF(V$15="Actual",SUMIFS('[1]NS Vendor Details'!$D:$D,'[1]NS Vendor Details'!$H:$H,'G&A Vendor x GL Analysis'!V$20,'[1]NS Vendor Details'!$L:$L,'G&A Vendor x GL Analysis'!$D33,'[1]NS Vendor Details'!$O:$O,'G&A Vendor x GL Analysis'!$F33,'[1]NS Vendor Details'!$N:$N,'G&A Vendor x GL Analysis'!$C33,'[1]NS Vendor Details'!$K:$K,'G&A Vendor x GL Analysis'!$E$8,'[1]NS Vendor Details'!$I:$I,'G&A Vendor x GL Analysis'!$E33),0)) -> 0 | W33: =IF(AND(W$15="Actual",ISBLANK($E$8)),SUMIFS('[1]NS Vendor Details'!$D:$D,'[1]NS Vendor Details'!$H:$H,'G&A Vendor x GL Analysis'!W$20,'[1]NS Vendor Details'!$L:$L,'G&A Vendor x GL Analysis'!$D33,'[1]NS Vendor Details'!$O:$O,'G&A Vendor x GL Analysis'!$F33,'[1]NS Vendor Details'!$N:$N,'G&A Vendor x GL Analysis'!$C33,'[1]NS Vendor Details'!$I:$I,'G&A Vendor x GL Analysis'!$E33),IF(W$15="Actual",SUMIFS('[1]NS Vendor Details'!$D:$D,'[1]NS Vendor Details'!$H:$H,'G&A Vendor x GL Analysis'!W$20,'[1]NS Vendor Details'!$L:$L,'G&A Vendor x GL Analysis'!$D33,'[1]NS Vendor Details'!$O:$O,'G&A Vendor x GL Analysis'!$F33,'[1]NS Vendor Details'!$N:$N,'G&A Vendor x GL Analysis'!$C33,'[1]NS Vendor Details'!$K:$K,'G&A Vendor x GL Analysis'!$E$8,'[1]NS Vendor Details'!$I:$I,'G&A Vendor x GL Analysis'!$E33),0)) -> 0 | X33: =IF(AND(X$15="Actual",ISBLANK($E$8)),SUMIFS('[1]NS Vendor Details'!$D:$D,'[1]NS Vendor Details'!$H:$H,'G&A Vendor x GL Analysis'!X$20,'[1]NS Vendor Details'!$L:$L,'G&A Vendor x GL Analysis'!$D33,'[1]NS Vendor Details'!$O:$O,'G&A Vendor x GL Analysis'!$F33,'[1]NS Vendor Details'!$N:$N,'G&A Vendor x GL Analysis'!$C33,'[1]NS Vendor Details'!$I:$I,'G&A Vendor x GL Analysis'!$E33),IF(X$15="Actual",SUMIFS('[1]NS Vendor Details'!$D:$D,'[1]NS Vendor Details'!$H:$H,'G&A Vendor x GL Analysis'!X$20,'[1]NS Vendor Details'!$L:$L,'G&A Vendor x GL Analysis'!$D33,'[1]NS Vendor Details'!$O:$O,'G&A Vendor x GL Analysis'!$F33,'[1]NS Vendor Details'!$N:$N,'G&A Vendor x GL Analysis'!$C33,'[1]NS Vendor Details'!$K:$K,'G&A Vendor x GL Analysis'!$E$8,'[1]NS Vendor Details'!$I:$I,'G&A Vendor x GL Analysis'!$E33),0)) -> 0 | Y33: =IF(AND(Y$15="Actual",ISBLANK($E$8)),SUMIFS('[1]NS Vendor Details'!$D:$D,'[1]NS Vendor Details'!$H:$H,'G&A Vendor x GL Analysis'!Y$20,'[1]NS Vendor Details'!$L:$L,'G&A Vendor x GL Analysis'!$D33,'[1]NS Vendor Details'!$O:$O,'G&A Vendor x GL Analysis'!$F33,'[1]NS Vendor Details'!$N:$N,'G&A Vendor x GL Analysis'!$C33,'[1]NS Vendor Details'!$I:$I,'G&A Vendor x GL Analysis'!$E33),IF(Y$15="Actual",SUMIFS('[1]NS Vendor Details'!$D:$D,'[1]NS Vendor Details'!$H:$H,'G&A Vendor x GL Analysis'!Y$20,'[1]NS Vendor Details'!$L:$L,'G&A Vendor x GL Analysis'!$D33,'[1]NS Vendor Details'!$O:$O,'G&A Vendor x GL Analysis'!$F33,'[1]NS Vendor Details'!$N:$N,'G&A Vendor x GL Analysis'!$C33,'[1]NS Vendor Details'!$K:$K,'G&A Vendor x GL Analysis'!$E$8,'[1]NS Vendor Details'!$I:$I,'G&A Vendor x GL Analysis'!$E33),0)) -> 0 | Z33: =IF(AND(Z$15="Actual",ISBLANK($E$8)),SUMIFS('[1]NS Vendor Details'!$D:$D,'[1]NS Vendor Details'!$H:$H,'G&A Vendor x GL Analysis'!Z$20,'[1]NS Vendor Details'!$L:$L,'G&A Vendor x GL Analysis'!$D33,'[1]NS Vendor Details'!$O:$O,'G&A Vendor x GL Analysis'!$F33,'[1]NS Vendor Details'!$N:$N,'G&A Vendor x GL Analysis'!$C33,'[1]NS Vendor Details'!$I:$I,'G&A Vendor x GL Analysis'!$E33),IF(Z$15="Actual",SUMIFS('[1]NS Vendor Details'!$D:$D,'[1]NS Vendor Details'!$H:$H,'G&A Vendor x GL Analysis'!Z$20,'[1]NS Vendor Details'!$L:$L,'G&A Vendor x GL Analysis'!$D33,'[1]NS Vendor Details'!$O:$O,'G&A Vendor x GL Analysis'!$F33,'[1]NS Vendor Details'!$N:$N,'G&A Vendor x GL Analysis'!$C33,'[1]NS Vendor Details'!$K:$K,'G&A Vendor x GL Analysis'!$E$8,'[1]NS Vendor Details'!$I:$I,'G&A Vendor x GL Analysis'!$E33),0)) -> 0 | ... AD33: =IF(AND(AD$15="Actual",ISBLANK($E$8)),SUMIFS('[1]NS Vendor Details'!$D:$D,'[1]NS Vendor Details'!$H:$H,'G&A Vendor x GL Analysis'!AD$20,'[1]NS Vendor Details'!$L:$L,'G&A Vendor x GL Analysis'!$D33,'[1]NS Vendor Details'!$O:$O,'G&A Vendor x GL Analysis'!$F33,'[1]NS Vendor Details'!$N:$N,'G&A Vendor x GL Analysis'!$C33,'[1]NS Vendor Details'!$I:$I,'G&A Vendor x GL Analysis'!$E33),IF(AD$15="Actual",SUMIFS('[1]NS Vendor Details'!$D:$D,'[1]NS Vendor Details'!$H:$H,'G&A Vendor x GL Analysis'!AD$20,'[1]NS Vendor Details'!$L:$L,'G&A Vendor x GL Analysis'!$D33,'[1]NS Vendor Details'!$O:$O,'G&A Vendor x GL Analysis'!$F33,'[1]NS Vendor Details'!$N:$N,'G&A Vendor x GL Analysis'!$C33,'[1]NS Vendor Details'!$K:$K,'G&A Vendor x GL Analysis'!$E$8,'[1]NS Vendor Details'!$I:$I,'G&A Vendor x GL Analysis'!$E33),0)) -> 0 | AF33: =ABS(S33)+ABS(T33)+ABS(U33)+ABS(V33)+ABS(W33)+ABS(X33)+ABS(Y33)+ABS(Z33)+ABS(AA33)+ABS(AB33)+ABS(AC33)+ABS(AD33) -> 720
A34: =D34&E34 -> Advertising6288 - Model | C34: SG&A | D34: =D33 -> Advertising | E34: 6288 - Model | F34: Soul Artist Management | G34: =IF(AND(G$15="Actual",ISBLANK($E$8)),SUMIFS('[1]NS Vendor Details'!$D:$D,'[1]NS Vendor Details'!$H:$H,'G&A Vendor x GL Analysis'!G$20,'[1]NS Vendor Details'!$L:$L,'G&A Vendor x GL Analysis'!$D34,'[1]NS Vendor Details'!$O:$O,'G&A Vendor x GL Analysis'!$F34,'[1]NS Vendor Details'!$N:$N,'G&A Vendor x GL Analysis'!$C34),IF(G$15="Actual",SUMIFS('[1]NS Vendor Details'!$D:$D,'[1]NS Vendor Details'!$H:$H,'G&A Vendor x GL Analysis'!G$20,'[1]NS Vendor Details'!$L:$L,'G&A Vendor x GL Analysis'!$D34,'[1]NS Vendor Details'!$O:$O,'G&A Vendor x GL Analysis'!$F34,'[1]NS Vendor Details'!$N:$N,'G&A Vendor x GL Analysis'!$C34,'[1]NS Vendor Details'!$K:$K,'G&A Vendor x GL Analysis'!$E$8),0)) -> 0 | H34: =IF(AND(H$15="Actual",ISBLANK($E$8)),SUMIFS('[1]NS Vendor Details'!$D:$D,'[1]NS Vendor Details'!$H:$H,'G&A Vendor x GL Analysis'!H$20,'[1]NS Vendor Details'!$L:$L,'G&A Vendor x GL Analysis'!$D34,'[1]NS Vendor Details'!$O:$O,'G&A Vendor x GL Analysis'!$F34,'[1]NS Vendor Details'!$N:$N,'G&A Vendor x GL Analysis'!$C34),IF(H$15="Actual",SUMIFS('[1]NS Vendor Details'!$D:$D,'[1]NS Vendor Details'!$H:$H,'G&A Vendor x GL Analysis'!H$20,'[1]NS Vendor Details'!$L:$L,'G&A Vendor x GL Analysis'!$D34,'[1]NS Vendor Details'!$O:$O,'G&A Vendor x GL Analysis'!$F34,'[1]NS Vendor Details'!$N:$N,'G&A Vendor x GL Analysis'!$C34,'[1]NS Vendor Details'!$K:$K,'G&A Vendor x GL Analysis'!$E$8),0)) -> 0 | I34: =IF(AND(I$15="Actual",ISBLANK($E$8)),SUMIFS('[1]NS Vendor Details'!$D:$D,'[1]NS Vendor Details'!$H:$H,'G&A Vendor x GL Analysis'!I$20,'[1]NS Vendor Details'!$L:$L,'G&A Vendor x GL Analysis'!$D34,'[1]NS Vendor Details'!$O:$O,'G&A Vendor x GL Analysis'!$F34,'[1]NS Vendor Details'!$N:$N,'G&A Vendor x GL Analysis'!$C34),IF(I$15="Actual",SUMIFS('[1]NS Vendor Details'!$D:$D,'[1]NS Vendor Details'!$H:$H,'G&A Vendor x GL Analysis'!I$20,'[1]NS Vendor Details'!$L:$L,'G&A Vendor x GL Analysis'!$D34,'[1]NS Vendor Details'!$O:$O,'G&A Vendor x GL Analysis'!$F34,'[1]NS Vendor Details'!$N:$N,'G&A Vendor x GL Analysis'!$C34,'[1]NS Vendor Details'!$K:$K,'G&A Vendor x GL Analysis'!$E$8),0)) -> 0 | J34: =IF(AND(J$15="Actual",ISBLANK($E$8)),SUMIFS('[1]NS Vendor Details'!$D:$D,'[1]NS Vendor Details'!$H:$H,'G&A Vendor x GL Analysis'!J$20,'[1]NS Vendor Details'!$L:$L,'G&A Vendor x GL Analysis'!$D34,'[1]NS Vendor Details'!$O:$O,'G&A Vendor x GL Analysis'!$F34,'[1]NS Vendor Details'!$N:$N,'G&A Vendor x GL Analysis'!$C34),IF(J$15="Actual",SUMIFS('[1]NS Vendor Details'!$D:$D,'[1]NS Vendor Details'!$H:$H,'G&A Vendor x GL Analysis'!J$20,'[1]NS Vendor Details'!$L:$L,'G&A Vendor x GL Analysis'!$D34,'[1]NS Vendor Details'!$O:$O,'G&A Vendor x GL Analysis'!$F34,'[1]NS Vendor Details'!$N:$N,'G&A Vendor x GL Analysis'!$C34,'[1]NS Vendor Details'!$K:$K,'G&A Vendor x GL Analysis'!$E$8),0)) -> 0 | K34: =IF(AND(K$15="Actual",ISBLANK($E$8)),SUMIFS('[1]NS Vendor Details'!$D:$D,'[1]NS Vendor Details'!$H:$H,'G&A Vendor x GL Analysis'!K$20,'[1]NS Vendor Details'!$L:$L,'G&A Vendor x GL Analysis'!$D34,'[1]NS Vendor Details'!$O:$O,'G&A Vendor x GL Analysis'!$F34,'[1]NS Vendor Details'!$N:$N,'G&A Vendor x GL Analysis'!$C34),IF(K$15="Actual",SUMIFS('[1]NS Vendor Details'!$D:$D,'[1]NS Vendor Details'!$H:$H,'G&A Vendor x GL Analysis'!K$20,'[1]NS Vendor Details'!$L:$L,'G&A Vendor x GL Analysis'!$D34,'[1]NS Vendor Details'!$O:$O,'G&A Vendor x GL Analysis'!$F34,'[1]NS Vendor Details'!$N:$N,'G&A Vendor x GL Analysis'!$C34,'[1]NS Vendor Details'!$K:$K,'G&A Vendor x GL Analysis'!$E$8),0)) -> 0 | L34: =IF(AND(L$15="Actual",ISBLANK($E$8)),SUMIFS('[1]NS Vendor Details'!$D:$D,'[1]NS Vendor Details'!$H:$H,'G&A Vendor x GL Analysis'!L$20,'[1]NS Vendor Details'!$L:$L,'G&A Vendor x GL Analysis'!$D34,'[1]NS Vendor Details'!$O:$O,'G&A Vendor x GL Analysis'!$F34,'[1]NS Vendor Details'!$N:$N,'G&A Vendor x GL Analysis'!$C34),IF(L$15="Actual",SUMIFS('[1]NS Vendor Details'!$D:$D,'[1]NS Vendor Details'!$H:$H,'G&A Vendor x GL Analysis'!L$20,'[1]NS Vendor Details'!$L:$L,'G&A Vendor x GL Analysis'!$D34,'[1]NS Vendor Details'!$O:$O,'G&A Vendor x GL Analysis'!$F34,'[1]NS Vendor Details'!$N:$N,'G&A Vendor x GL Analysis'!$C34,'[1]NS Vendor Details'!$K:$K,'G&A Vendor x GL Analysis'!$E$8),0)) -> 4320 | M34: =IF(AND(M$15="Actual",ISBLANK($E$8)),SUMIFS('[1]NS Vendor Details'!$D:$D,'[1]NS Vendor Details'!$H:$H,'G&A Vendor x GL Analysis'!M$20,'[1]NS Vendor Details'!$L:$L,'G&A Vendor x GL Analysis'!$D34,'[1]NS Vendor Details'!$O:$O,'G&A Vendor x GL Analysis'!$F34,'[1]NS Vendor Details'!$N:$N,'G&A Vendor x GL Analysis'!$C34),IF(M$15="Actual",SUMIFS('[1]NS Vendor Details'!$D:$D,'[1]NS Vendor Details'!$H:$H,'G&A Vendor x GL Analysis'!M$20,'[1]NS Vendor Details'!$L:$L,'G&A Vendor x GL Analysis'!$D34,'[1]NS Vendor Details'!$O:$O,'G&A Vendor x GL Analysis'!$F34,'[1]NS Vendor Details'!$N:$N,'G&A Vendor x GL Analysis'!$C34,'[1]NS Vendor Details'!$K:$K,'G&A Vendor x GL Analysis'!$E$8),0)) -> 0 | N34: =IF(AND(N$15="Actual",ISBLANK($E$8)),SUMIFS('[1]NS Vendor Details'!$D:$D,'[1]NS Vendor Details'!$H:$H,'G&A Vendor x GL Analysis'!N$20,'[1]NS Vendor Details'!$L:$L,'G&A Vendor x GL Analysis'!$D34,'[1]NS Vendor Details'!$O:$O,'G&A Vendor x GL Analysis'!$F34,'[1]NS Vendor Details'!$N:$N,'G&A Vendor x GL Analysis'!$C34),IF(N$15="Actual",SUMIFS('[1]NS Vendor Details'!$D:$D,'[1]NS Vendor Details'!$H:$H,'G&A Vendor x GL Analysis'!N$20,'[1]NS Vendor Details'!$L:$L,'G&A Vendor x GL Analysis'!$D34,'[1]NS Vendor Details'!$O:$O,'G&A Vendor x GL Analysis'!$F34,'[1]NS Vendor Details'!$N:$N,'G&A Vendor x GL Analysis'!$C34,'[1]NS Vendor Details'!$K:$K,'G&A Vendor x GL Analysis'!$E$8),0)) -> 1440 | ... R34: =IF(AND(R$15="Actual",ISBLANK($E$8)),SUMIFS('[1]NS Vendor Details'!$D:$D,'[1]NS Vendor Details'!$H:$H,'G&A Vendor x GL Analysis'!R$20,'[1]NS Vendor Details'!$L:$L,'G&A Vendor x GL Analysis'!$D34,'[1]NS Vendor Details'!$O:$O,'G&A Vendor x GL Analysis'!$F34,'[1]NS Vendor Details'!$N:$N,'G&A Vendor x GL Analysis'!$C34),IF(R$15="Actual",SUMIFS('[1]NS Vendor Details'!$D:$D,'[1]NS Vendor Details'!$H:$H,'G&A Vendor x GL Analysis'!R$20,'[1]NS Vendor Details'!$L:$L,'G&A Vendor x GL Analysis'!$D34,'[1]NS Vendor Details'!$O:$O,'G&A Vendor x GL Analysis'!$F34,'[1]NS Vendor Details'!$N:$N,'G&A Vendor x GL Analysis'!$C34,'[1]NS Vendor Details'!$K:$K,'G&A Vendor x GL Analysis'!$E$8),0)) -> 2880 | S34: =IF(AND(S$15="Actual",ISBLANK($E$8)),SUMIFS('[1]NS Vendor Details'!$D:$D,'[1]NS Vendor Details'!$H:$H,'G&A Vendor x GL Analysis'!S$20,'[1]NS Vendor Details'!$L:$L,'G&A Vendor x GL Analysis'!$D34,'[1]NS Vendor Details'!$O:$O,'G&A Vendor x GL Analysis'!$F34,'[1]NS Vendor Details'!$N:$N,'G&A Vendor x GL Analysis'!$C34,'[1]NS Vendor Details'!$I:$I,'G&A Vendor x GL Analysis'!$E34),IF(S$15="Actual",SUMIFS('[1]NS Vendor Details'!$D:$D,'[1]NS Vendor Details'!$H:$H,'G&A Vendor x GL Analysis'!S$20,'[1]NS Vendor Details'!$L:$L,'G&A Vendor x GL Analysis'!$D34,'[1]NS Vendor Details'!$O:$O,'G&A Vendor x GL Analysis'!$F34,'[1]NS Vendor Details'!$N:$N,'G&A Vendor x GL Analysis'!$C34,'[1]NS Vendor Details'!$K:$K,'G&A Vendor x GL Analysis'!$E$8,'[1]NS Vendor Details'!$I:$I,'G&A Vendor x GL Analysis'!$E34),0)) -> 1440 | T34: =IF(AND(T$15="Actual",ISBLANK($E$8)),SUMIFS('[1]NS Vendor Details'!$D:$D,'[1]NS Vendor Details'!$H:$H,'G&A Vendor x GL Analysis'!T$20,'[1]NS Vendor Details'!$L:$L,'G&A Vendor x GL Analysis'!$D34,'[1]NS Vendor Details'!$O:$O,'G&A Vendor x GL Analysis'!$F34,'[1]NS Vendor Details'!$N:$N,'G&A Vendor x GL Analysis'!$C34,'[1]NS Vendor Details'!$I:$I,'G&A Vendor x GL Analysis'!$E34),IF(T$15="Actual",SUMIFS('[1]NS Vendor Details'!$D:$D,'[1]NS Vendor Details'!$H:$H,'G&A Vendor x GL Analysis'!T$20,'[1]NS Vendor Details'!$L:$L,'G&A Vendor x GL Analysis'!$D34,'[1]NS Vendor Details'!$O:$O,'G&A Vendor x GL Analysis'!$F34,'[1]NS Vendor Details'!$N:$N,'G&A Vendor x GL Analysis'!$C34,'[1]NS Vendor Details'!$K:$K,'G&A Vendor x GL Analysis'!$E$8,'[1]NS Vendor Details'!$I:$I,'G&A Vendor x GL Analysis'!$E34),0)) -> 0 | U34: =IF(AND(U$15="Actual",ISBLANK($E$8)),SUMIFS('[1]NS Vendor Details'!$D:$D,'[1]NS Vendor Details'!$H:$H,'G&A Vendor x GL Analysis'!U$20,'[1]NS Vendor Details'!$L:$L,'G&A Vendor x GL Analysis'!$D34,'[1]NS Vendor Details'!$O:$O,'G&A Vendor x GL Analysis'!$F34,'[1]NS Vendor Details'!$N:$N,'G&A Vendor x GL Analysis'!$C34,'[1]NS Vendor Details'!$I:$I,'G&A Vendor x GL Analysis'!$E34),IF(U$15="Actual",SUMIFS('[1]NS Vendor Details'!$D:$D,'[1]NS Vendor Details'!$H:$H,'G&A Vendor x GL Analysis'!U$20,'[1]NS Vendor Details'!$L:$L,'G&A Vendor x GL Analysis'!$D34,'[1]NS Vendor Details'!$O:$O,'G&A Vendor x GL Analysis'!$F34,'[1]NS Vendor Details'!$N:$N,'G&A Vendor x GL Analysis'!$C34,'[1]NS Vendor Details'!$K:$K,'G&A Vendor x GL Analysis'!$E$8,'[1]NS Vendor Details'!$I:$I,'G&A Vendor x GL Analysis'!$E34),0)) -> 0 | V34: =IF(AND(V$15="Actual",ISBLANK($E$8)),SUMIFS('[1]NS Vendor Details'!$D:$D,'[1]NS Vendor Details'!$H:$H,'G&A Vendor x GL Analysis'!V$20,'[1]NS Vendor Details'!$L:$L,'G&A Vendor x GL Analysis'!$D34,'[1]NS Vendor Details'!$O:$O,'G&A Vendor x GL Analysis'!$F34,'[1]NS Vendor Details'!$N:$N,'G&A Vendor x GL Analysis'!$C34,'[1]NS Vendor Details'!$I:$I,'G&A Vendor x GL Analysis'!$E34),IF(V$15="Actual",SUMIFS('[1]NS Vendor Details'!$D:$D,'[1]NS Vendor Details'!$H:$H,'G&A Vendor x GL Analysis'!V$20,'[1]NS Vendor Details'!$L:$L,'G&A Vendor x GL Analysis'!$D34,'[1]NS Vendor Details'!$O:$O,'G&A Vendor x GL Analysis'!$F34,'[1]NS Vendor Details'!$N:$N,'G&A Vendor x GL Analysis'!$C34,'[1]NS Vendor Details'!$K:$K,'G&A Vendor x GL Analysis'!$E$8,'[1]NS Vendor Details'!$I:$I,'G&A Vendor x GL Analysis'!$E34),0)) -> 0 | W34: =IF(AND(W$15="Actual",ISBLANK($E$8)),SUMIFS('[1]NS Vendor Details'!$D:$D,'[1]NS Vendor Details'!$H:$H,'G&A Vendor x GL Analysis'!W$20,'[1]NS Vendor Details'!$L:$L,'G&A Vendor x GL Analysis'!$D34,'[1]NS Vendor Details'!$O:$O,'G&A Vendor x GL Analysis'!$F34,'[1]NS Vendor Details'!$N:$N,'G&A Vendor x GL Analysis'!$C34,'[1]NS Vendor Details'!$I:$I,'G&A Vendor x GL Analysis'!$E34),IF(W$15="Actual",SUMIFS('[1]NS Vendor Details'!$D:$D,'[1]NS Vendor Details'!$H:$H,'G&A Vendor x GL Analysis'!W$20,'[1]NS Vendor Details'!$L:$L,'G&A Vendor x GL Analysis'!$D34,'[1]NS Vendor Details'!$O:$O,'G&A Vendor x GL Analysis'!$F34,'[1]NS Vendor Details'!$N:$N,'G&A Vendor x GL Analysis'!$C34,'[1]NS Vendor Details'!$K:$K,'G&A Vendor x GL Analysis'!$E$8,'[1]NS Vendor Details'!$I:$I,'G&A Vendor x GL Analysis'!$E34),0)) -> 0 | X34: =IF(AND(X$15="Actual",ISBLANK($E$8)),SUMIFS('[1]NS Vendor Details'!$D:$D,'[1]NS Vendor Details'!$H:$H,'G&A Vendor x GL Analysis'!X$20,'[1]NS Vendor Details'!$L:$L,'G&A Vendor x GL Analysis'!$D34,'[1]NS Vendor Details'!$O:$O,'G&A Vendor x GL Analysis'!$F34,'[1]NS Vendor Details'!$N:$N,'G&A Vendor x GL Analysis'!$C34,'[1]NS Vendor Details'!$I:$I,'G&A Vendor x GL Analysis'!$E34),IF(X$15="Actual",SUMIFS('[1]NS Vendor Details'!$D:$D,'[1]NS Vendor Details'!$H:$H,'G&A Vendor x GL Analysis'!X$20,'[1]NS Vendor Details'!$L:$L,'G&A Vendor x GL Analysis'!$D34,'[1]NS Vendor Details'!$O:$O,'G&A Vendor x GL Analysis'!$F34,'[1]NS Vendor Details'!$N:$N,'G&A Vendor x GL Analysis'!$C34,'[1]NS Vendor Details'!$K:$K,'G&A Vendor x GL Analysis'!$E$8,'[1]NS Vendor Details'!$I:$I,'G&A Vendor x GL Analysis'!$E34),0)) -> 4320 | Y34: =IF(AND(Y$15="Actual",ISBLANK($E$8)),SUMIFS('[1]NS Vendor Details'!$D:$D,'[1]NS Vendor Details'!$H:$H,'G&A Vendor x GL Analysis'!Y$20,'[1]NS Vendor Details'!$L:$L,'G&A Vendor x GL Analysis'!$D34,'[1]NS Vendor Details'!$O:$O,'G&A Vendor x GL Analysis'!$F34,'[1]NS Vendor Details'!$N:$N,'G&A Vendor x GL Analysis'!$C34,'[1]NS Vendor Details'!$I:$I,'G&A Vendor x GL Analysis'!$E34),IF(Y$15="Actual",SUMIFS('[1]NS Vendor Details'!$D:$D,'[1]NS Vendor Details'!$H:$H,'G&A Vendor x GL Analysis'!Y$20,'[1]NS Vendor Details'!$L:$L,'G&A Vendor x GL Analysis'!$D34,'[1]NS Vendor Details'!$O:$O,'G&A Vendor x GL Analysis'!$F34,'[1]NS Vendor Details'!$N:$N,'G&A Vendor x GL Analysis'!$C34,'[1]NS Vendor Details'!$K:$K,'G&A Vendor x GL Analysis'!$E$8,'[1]NS Vendor Details'!$I:$I,'G&A Vendor x GL Analysis'!$E34),0)) -> 0 | Z34: =IF(AND(Z$15="Actual",ISBLANK($E$8)),SUMIFS('[1]NS Vendor Details'!$D:$D,'[1]NS Vendor Details'!$H:$H,'G&A Vendor x GL Analysis'!Z$20,'[1]NS Vendor Details'!$L:$L,'G&A Vendor x GL Analysis'!$D34,'[1]NS Vendor Details'!$O:$O,'G&A Vendor x GL Analysis'!$F34,'[1]NS Vendor Details'!$N:$N,'G&A Vendor x GL Analysis'!$C34,'[1]NS Vendor Details'!$I:$I,'G&A Vendor x GL Analysis'!$E34),IF(Z$15="Actual",SUMIFS('[1]NS Vendor Details'!$D:$D,'[1]NS Vendor Details'!$H:$H,'G&A Vendor x GL Analysis'!Z$20,'[1]NS Vendor Details'!$L:$L,'G&A Vendor x GL Analysis'!$D34,'[1]NS Vendor Details'!$O:$O,'G&A Vendor x GL Analysis'!$F34,'[1]NS Vendor Details'!$N:$N,'G&A Vendor x GL Analysis'!$C34,'[1]NS Vendor Details'!$K:$K,'G&A Vendor x GL Analysis'!$E$8,'[1]NS Vendor Details'!$I:$I,'G&A Vendor x GL Analysis'!$E34),0)) -> 1440 | ... AD34: =IF(AND(AD$15="Actual",ISBLANK($E$8)),SUMIFS('[1]NS Vendor Details'!$D:$D,'[1]NS Vendor Details'!$H:$H,'G&A Vendor x GL Analysis'!AD$20,'[1]NS Vendor Details'!$L:$L,'G&A Vendor x GL Analysis'!$D34,'[1]NS Vendor Details'!$O:$O,'G&A Vendor x GL Analysis'!$F34,'[1]NS Vendor Details'!$N:$N,'G&A Vendor x GL Analysis'!$C34,'[1]NS Vendor Details'!$I:$I,'G&A Vendor x GL Analysis'!$E34),IF(AD$15="Actual",SUMIFS('[1]NS Vendor Details'!$D:$D,'[1]NS Vendor Details'!$H:$H,'G&A Vendor x GL Analysis'!AD$20,'[1]NS Vendor Details'!$L:$L,'G&A Vendor x GL Analysis'!$D34,'[1]NS Vendor Details'!$O:$O,'G&A Vendor x GL Analysis'!$F34,'[1]NS Vendor Details'!$N:$N,'G&A Vendor x GL Analysis'!$C34,'[1]NS Vendor Details'!$K:$K,'G&A Vendor x GL Analysis'!$E$8,'[1]NS Vendor Details'!$I:$I,'G&A Vendor x GL Analysis'!$E34),0)) -> 0 | AF34: =ABS(S34)+ABS(T34)+ABS(U34)+ABS(V34)+ABS(W34)+ABS(X34)+ABS(Y34)+ABS(Z34)+ABS(AA34)+ABS(AB34)+ABS(AC34)+ABS(AD34) -> 7200
